Workbook

Sheet B5 - Market Regime
A1: BLOQUE 5: MARKET REGIME DETECTION
A2: AI Investing Dashboard | Marango Fund
A3: Objetivo: Identificar el régimen de mercado actual (Risk-On vs Risk-Off) para ajustar posicionamiento del portfolio | V5 thresholds updated 06-Mar-2026
A5: 📊 SENTIMENT & SYSTEMIC RISK | K5: Date: 20-Mar-2026 (Updated 23-Mar)
A6: # | B6: INDICATOR | C6: CURRENT VALUE | D6: RISK-ON THRESHOLD | E6: NEUTRAL ZONE | F6: RISK-OFF THRESHOLD | G6: DIRECTION | H6: STATUS | I6: SCORE | J6: WEIGHT | K6: WEIGHTED | L6: LAST WEEK | M6: DELTA | N6: TREND
A7: 1 | B7: VIX (Volatility Index) | C7: 26.78 | D7: < 15 | E7: 15 - 22 | F7: > 35 | G7: Lower = Better | H7: =IF(C7<15,"✅ Risk-On",IF(C7<=22,"⚠️ Neutral","🔴 Risk-Off")) -> 🔴 Risk-Off | I7: =ROUND(MAX(0,MIN(100, IF(C7<=15,100, IF(C7>=35,0, 100-(C7-15)/(35-15)*100)))),0) -> 41 | J7: 0.3 | K7: =I7*J7 -> 12.3 | L7: 23.51 | M7: =IF(L7="","",C7-L7) -> 3.27 | N7: =IF(M7="","⏳ Awaiting data",IF(ABS(M7)<1,"→ Stable",IF(M7>0,"↗ Deteriorating","↘ Improving"))) -> ↗ Deteriorating
A8: 2 | B8: HY Credit Spreads (bps) | C8: 320 | D8: < 200 | E8: 200 - 400 | F8: > 600 | G8: Lower = Better | H8: =IF(C8<200,"✅ Risk-On",IF(C8<=400,"⚠️ Neutral","🔴 Risk-Off")) -> ⚠️ Neutral | I8: =ROUND(MAX(0,MIN(100, IF(C8<=200,100, IF(C8>=600,0, 100-(C8-200)/(600-200)*100)))),0) -> 70 | J8: 0.3 | K8: =I8*J8 -> 21 | L8: 317 | M8: =IF(L8="","",C8-L8) -> 3 | N8: =IF(M8="","⏳ Awaiting data",IF(ABS(M8)<10,"→ Stable",IF(M8>0,"↗ Deteriorating","↘ Improving"))) -> → Stable
A9: 3 | B9: Put/Call Ratio (Market-wide) | C9: 0.58 | D9: < 0.5 | E9: 0.5 - 1.2 | F9: > 2.0 | G9: Lower = Better | H9: =IF(C9<0.5,"✅ Risk-On",IF(C9<=1.2,"⚠️ Neutral","🔴 Risk-Off")) -> ⚠️ Neutral | I9: =ROUND(MAX(0,MIN(100, IF(C9<=0.5,100, IF(C9>=2,0, 100-(C9-0.5)/(2-0.5)*100)))),0) -> 95 | J9: 0.2 | K9: =I9*J9 -> 19 | L9: 0.58 | M9: =IF(L9="","",C9-L9) -> 0 | N9: =IF(M9="","⏳ Awaiting data",IF(ABS(M9)<0.05,"→ Stable",IF(M9>0,"↗ Deteriorating","↘ Improving"))) -> → Stable
A10: 4 | B10: Market Breadth (% > 200d MA) | C10: 0.42 | D10: > 80% | E10: 40% - 80% | F10: < 20% | G10: Higher = Better | H10: =IF(C10>0.8,"✅ Risk-On",IF(C10>=0.4,"⚠️ Neutral","🔴 Risk-Off")) -> ⚠️ Neutral | I10: =ROUND(MAX(0,MIN(100, IF(C10>=0.8,100, IF(C10<=0.2,0, (C10-0.2)/(0.8-0.2)*100)))),0) -> 37 | J10: 0.15 | K10: =I10*J10 -> 5.55 | L10: 0.48 | M10: =IF(L10="","",C10-L10) -> -0.06 | N10: =IF(M10="","⏳ Awaiting data",IF(ABS(M10)<0.02,"→ Stable",IF(M10>0,"↗ Improving","↘ Deteriorating"))) -> ↘ Deteriorating
A11: 5 | B11: VIX Term Structure (VIX/VIX3M) | C11: 1.05 | D11: < 0.85 | E11: 0.85 - 1.0 | F11: > 1.2 | G11: Lower = Better | H11: =IF(C11<0.85,"✅ Risk-On",IF(C11<=1,"⚠️ Neutral","🔴 Risk-Off")) -> 🔴 Risk-Off | I11: =ROUND(MAX(0,MIN(100, IF(C11<=0.85,100, IF(C11>=1.2,0, 100-(C11-0.85)/(1.2-0.85)*100)))),0) -> 43 | J11: 0.05 | K11: =I11*J11 -> 2.15 | L11: 1.02
B13: COMPOSITE SCORE | I13: =ROUND(SUM(K7:K11),0) -> 60 | J13: =SUM(J7:J11) -> 1 | K13: =SUM(K7:K11) -> 60
A15: ⚡ REGIME CLASSIFICATION & RECOMMENDATION
B16: Sentiment & Systemic Regime: | C16: =IF(I13>=80,"✅ CLEAR RISK-ON",IF(I13>=60,"⚠️ RISK-ON (Moderate)",IF(I13>=45,"⚖️ NEUTRAL",IF(I13>=35,"⚠️ RISK-OFF (Moderate)","🔴 CLEAR RISK-OFF")))) -> ⚠️ RISK-ON (Moderate) | F16: Score Scale (V5):
B17: Composite Score: | C17: =I13&" / 100" -> 60 / 100 | F17: ≥75: ⚠️ PRECAUCIÓN — Tomar beneficios
B18: Regime Change Probability: | C18: =IF(COUNTA(L7:L10)=0,IF(I13>=80,"🟢 LOW (<15%) — No trend data yet",IF(I13>=60,"⚠️ MODERATE (20-40%)",IF(I13>=50,"🟡 ELEVATED (40-60%)","🔴 HIGH (>60%)"))),IF(COUNTIF(N7:N10,"*Deteriorating*")>=3,"🔴 HIGH (>50%) — "&COUNTIF(N7:N10,"*Deteriorating*")&" indicators deteriorating",IF(OR(COUNTIF(N7:N10,"*Deteriorating*")>=2,AND(C7>=22,C7<=28),AND(C8>=350,C8<=450)),"🟡 ELEVATED (30-50%) — Warning signs emerging",IF(OR(COUNTIF(N7:N10,"*Deteriorating*")>=1,C7>=20),"⚠️ MODERATE (15-30%) — Watch closely","🟢 LOW (<15%) — Regime stable")))) -> 🟡 ELEVATED (30-50%) — Warning signs emerging | F18: 60-74: ✅ NORMAL — Allocation B1
B19: Leading Indicators: | C19: =IF(COUNTA(L7:L10)=0,"⏳ Fill column L (Last Week) to activate trend tracking","Deteriorating: "&COUNTIF(N7:N10,"*Deteriorating*")&" | Improving: "&COUNTIF(N7:N10,"*Improving*")&" | Stable: "&COUNTIF(N7:N10,"*Stable*")&IF(AND(C7>=22,C7<=28)," | ⚠️ VIX near trigger (25)","")&IF(AND(C8>=350,C8<=450)," | ⚠️ Spreads near trigger","")) -> Deteriorating: 2 | Improving: 0 | Stable: 2 | ⚠️ VIX near trigger (25) | F19: 45-59: 🛡️ DEFENSIVO — Subir calidad
F20: <45: 🔴 Protección + compras oportunistas
B21: PORTFOLIO POSITIONING: | C21: =IF(COUNTIF(E27:E31,"🔴 YES")>0,"🚨 OVERRIDE ACTIVO: "&IF(C82>=45,"🛡️ Score "&C82&" + Override → Cash +5%. Solo Core A+.","🔴 Score "&C82&" + Override → Máx protección. Cash 15-20%."),IF(C82>=75,"⚠️ PRECAUCIÓN: Tomar beneficios (10-15%). Cash 8-12%."&IF(E32="⚠️ WATCH"," ⚠️ 10Y Watch: solo Core A+.",""),IF(C82>=60,"✅ NORMAL: Allocation según B1. Cash 5-8%."&IF(E32="⚠️ WATCH"," ⚠️ 10Y Watch: solo Core A+.",""),IF(C82>=45,"🛡️ DEFENSIVO: Subir calidad (B1≥80). Cash 10-12%."&IF(E32="⚠️ WATCH"," ⚠️ 10Y Watch: solo Core A+.",""),IF(C82>=35,"🔴 PROTECCIÓN + 1ª compra oportunista. Cash 12-18%.","🔴🟢 MÁX PROTECCIÓN + 2ª/3ª compra. Cash 15-20%."))))) -> 🚨 OVERRIDE ACTIVO: 🔴 Score 44 + Override → Máx protección. Cash 15-20%.
C22: 10
A23: ⏱️ REGIME DURATION TRACKER | C23: 9
A24: Weeks in Current Regime: | C24: 9 | D24: =IF(C24<4,"🟢 EARLY REGIME ("&C24&" wks)",IF(C24<26,"🟡 MID REGIME ("&C24&" wks)",IF(C24<52,"⚠️ LATE REGIME ("&C24&" wks)","🔴 EXTENDED ("&C24&" wks)"))) -> 🟡 MID REGIME (9 wks) | F24: =IF(C24<4,"Opportunity window — New regime forming, conviction building",IF(C24<26,"Normal positioning — Regime mature and reliable",IF(C24<52,"Late cycle caution — Consider gradual profit-taking","Extended regime — Historically elevated reversal risk"))) -> Normal positioning — Regime mature and reliable
A25: 🚨 RISK-OFF TRIGGER ACTIONS
A26: TRIGGER | B26: CONDITION | D26: CURRENT | E26: TRIGGERED? | F26: ACTION IF TRIGGERED
A27: VIX Spike | B27: VIX > 25 | D27: 26.78 | E27: =IF(C7>25,"🔴 YES","✅ NO") -> 🔴 YES | F27: Reduce tech exposure 44% → 35%, increase hedges
A28: Credit Stress | B28: HY Spreads > 400bps | D28: 320 bps | E28: =IF(C8>400,"🔴 YES","✅ NO") -> ✅ NO | F28: Cut cyclicals, shift to investment-grade bonds
A29: Fear Extreme | B29: Put/Call > 1.2 | D29: 0.58 | E29: =IF(C9>1.2,"🔴 YES","✅ NO") -> ✅ NO | F29: Raise cash to 10-15%, pause new positions
A30: Breadth Collapse | B30: Breadth < 50% | D30: 0.42 | E30: =IF(C10<0.5,"🔴 YES","✅ NO") -> 🔴 YES | F30: Rotate to defensives (healthcare, utilities, staples)
A31: Oil Shock | B31: WTI Crude ≥ $100 | D31: 98.23 | E31: =IF(C33>=100,"🔴 YES","✅ NO") -> ✅ NO | F31: 🔴 TRIGGER: Activa Override (+5% cash). ↑Costes → ↓Márgenes → ↓Earnings. Hit rate 86%.
A32: Rate Shock | B32: 10Y Yield ≥ 4.5% | D32: 98.23 (↗ from $93.71) | E32: =IF(C35>=5,"🔴 YES",IF(C35>=4.5,"⚠️ WATCH","✅ NO")) -> ✅ NO | F32: ⚠️ ESCALONADO: 4.5-4.99% = Watch (solo Core A+). ≥5.0% = Override real. Hit rate 4.5%=57%, 5.0%=100%.
B33: WTI Crude ($/bbl) | C33: 98.23 | D33: 4.39% (⚠️ WATCH) | E33: 63.5 | F33: =IF(C33>E33,"↑ Rising","↓ Falling") -> ↑ Rising
B34: DXY Dollar Index | C34: 99.5 | D34: 1M ago: | E34: 96.5 | F34: =IF(C34>E34,"↑ Rising","↓ Falling") -> ↑ Rising
B35: US 10Y Yield (%) | C35: 4.39 | D35: 1M ago: | E35: 3.95 | F35: =IF(C35>E35,"↑ Rising","↓ Falling") -> ↑ Rising
C36: 99.5 | E36: 96.5
C37: 4.39
K38: Date: 05-Mar-2026 (Updated 06-Mar)
A39: 📊 TECHNICAL INDICATORS — S&P 500 | J39: Date: 20-Mar-2026 (Updated 23-Mar) | K39: Date: 20-Mar-2026 (Updated 23-Mar)
A40: Indicator | B40: Current Value | C40: Reference | D40: Bearish Threshold | E40: Bullish Threshold | F40: Score (0-100) | G40: Weight | H40: Wtd Score | I40: Signal | J40: Interpretation | K40: LAST WEEK | L40: DELTA | M40: TREND
A41: S&P 500 vs MA-200 | B41: 6506.48 | C41: 6806.41 | D41: -5 | E41: 3 | F41: =ROUND(IF((B41-C41)/C41*100<D41,0,IF((B41-C41)/C41*100>E41,100,((B41-C41)/C41*100-D41)/(E41-D41)*100)),0) -> 7 | G41: 0.22 | H41: =ROUND(F41*G41,1) -> 1.5 | I41: =IF(F41>=70,"✅ Bullish",IF(F41>=40,"⚠️ Neutral","🔴 Bearish")) -> 🔴 Bearish | J41: =IF(B41>C41,"Price ABOVE MA200 (+"&TEXT((B41-C41)/C41,"0.0%")&")","Price BELOW MA200 ("&TEXT((B41-C41)/C41,"0.0%")&")") -> Price BELOW MA200 (-04%) | K41: 6716.09 | L41: =IF(K41="","",B41-K41) -> -209.61 | M41: =IF(L41="","⏳ Awaiting data",IF(ABS(L41)<10,"→ Stable",IF(L41>0,"↗ Improving","↘ Deteriorating"))) -> ↘ Deteriorating
A42: S&P 500 vs MA-50 | B42: 6506.48 | C42: 6655.67 | D42: -3 | E42: 2 | F42: =ROUND(IF((B42-C42)/C42*100<D42,0,IF((B42-C42)/C42*100>E42,100,((B42-C42)/C42*100-D42)/(E42-D42)*100)),0) -> 15 | G42: 0.2 | H42: =ROUND(F42*G42,1) -> 3 | I42: =IF(F42>=70,"✅ Bullish",IF(F42>=40,"⚠️ Neutral","🔴 Bearish")) -> 🔴 Bearish | J42: =IF(B42>C42,"Price ABOVE MA50 (+"&TEXT((B42-C42)/C42,"0.0%")&")","Price BELOW MA50 ("&TEXT((B42-C42)/C42,"0.0%")&")") -> Price BELOW MA50 (-02%) | K42: 6716.09 | L42: =IF(K42="","",B42-K42) -> -209.61 | M42: =IF(L42="","⏳ Awaiting data",IF(ABS(L42)<10,"→ Stable",IF(L42>0,"↗ Improving","↘ Deteriorating"))) -> ↘ Deteriorating
A43: Golden/Death Cross | B43: 6655.67 | C43: 6806.41 | D43: MA50 < MA200 | E43: MA50 > MA200 | F43: =IF(B43<C43,0,100) -> 0 | G43: 0.1 | H43: =ROUND(F43*G43,1) -> 0 | I43: =IF(B43>C43,"✅ Golden Cross","🔴 Death Cross") -> 🔴 Death Cross | J43: =IF(B43>C43,"MA50 above MA200 — Bullish trend","MA50 below MA200 — Bearish trend") -> MA50 below MA200 — Bearish trend | K43: 6746.03 | L43: =IF(K43="","",B43-K43) -> -90.36 | M43: =IF(L43="","⏳ Awaiting data",IF(L43>0,"↗ Improving",IF(L43<0,"↘ Deteriorating","→ Stable"))) -> ↘ Deteriorating
A44: RSI (14-Day) | B44: 23.34 | C44: 50 | D44: 30 | E44: 70 | F44: =ROUND(IF(B44<D44,0,IF(B44>E44,100,IF(B44<C44,(B44-D44)/(C44-D44)*50,(B44-C44)/(E44-C44)*50+50))),0) -> 0 | G44: 0.2 | H44: =ROUND(F44*G44,1) -> 0 | I44: =IF(B44>=70,"🔴 Overbought",IF(B44<=30,"🔴 Oversold",IF(B44>=55,"✅ Bullish",IF(B44<=45,"⚠️ Weakening","⚠️ Neutral")))) -> 🔴 Oversold | J44: =IF(B44>=70,"Overbought — Reversal risk",IF(B44<=30,"Oversold — Bounce expected",IF(B44>=55,"Momentum favors bulls",IF(B44<=45,"Momentum weakening","Neutral — No clear edge")))) -> Oversold — Bounce expected | K44: 48.85 | L44: =IF(K44="","",B44-K44) -> -25.51 | M44: =IF(L44="","⏳ Awaiting data",IF(ABS(L44)<2,"→ Stable",IF(L44>0,"↗ Improving","↘ Deteriorating"))) -> ↘ Deteriorating
A45: MACD (12,26,9) | B45: -39.43 | C45: 0 | D45: -50 | E45: 50 | F45: =ROUND(IF(B45<D45,0,IF(B45>E45,100,(B45-D45)/(E45-D45)*100)),0) -> 11 | G45: 0.2 | H45: =ROUND(F45*G45,1) -> 2.2 | I45: =IF(B45>0,IF(B45>C45,"✅ Bullish","⚠️ Weakening"),IF(B45<C45,"🔴 Bearish","⚠️ Recovering")) -> 🔴 Bearish | J45: =IF(B45>0,"MACD positive — Bullish momentum","MACD negative — Bearish momentum") -> MACD negative — Bearish momentum | K45: -8.63 | L45: =IF(K45="","",B45-K45) -> -30.8 | M45: =IF(L45="","⏳ Awaiting data",IF(ABS(L45)<3,"→ Stable",IF(L45>0,"↗ Improving","↘ Deteriorating"))) -> ↘ Deteriorating
A46: CBOE Skew Index | B46: 140 | C46: 130 | D46: 155 | E46: 120 | F46: =ROUND(IF(B46>D46,0,IF(B46<E46,100,(D46-B46)/(D46-E46)*100)),0) -> 43 | G46: 0.08 | H46: =ROUND(F46*G46,1) -> 3.4 | I46: =IF(B46>=155,"🔴 Tail Risk",IF(B46>=145,"⚠️ Elevated",IF(B46<=120,"✅ Low Risk","✅ Normal"))) -> ✅ Normal | J46: =IF(B46>=155,"Extreme tail risk — Protect portfolio",IF(B46>=145,"Elevated skew — Monitor closely",IF(B46<=120,"Low tail risk — Risk-on","Normal range — No concern"))) -> Normal range — No concern | K46: 140 | L46: =IF(K46="","",B46-K46) -> 0 | M46: =IF(L46="","⏳ Awaiting data",IF(ABS(L46)<3,"→ Stable",IF(L46<0,"↗ Improving","↘ Deteriorating"))) -> → Stable
A47: TECHNICAL COMPOSITE SCORE | F47: =ROUND(SUM(H41:H46),0) -> 10 | H47: =ROUND(SUM(H41:H46),1) -> 10.1 | I47: =IF(F47>=70,"✅ Bullish",IF(F47>=45,"⚠️ Mixed","🔴 Bearish")) -> 🔴 Bearish | J47: =F47&" / 100" -> 10 / 100
A49: 🎯 TECHNICAL REGIME CLASSIFICATION
A50: Technical Regime: | C50: =IF(F47>=70,"✅ STRONG UPTREND",IF(F47>=55,"✅ UPTREND (Moderate)",IF(F47>=45,"⚠️ SIDEWAYS / CHOPPY",IF(F47>=30,"⚠️ DOWNTREND (Moderate)","🔴 STRONG DOWNTREND")))) -> 🔴 STRONG DOWNTREND | H50: Score Range | I50: Classification
A51: Implication: | C51: =IF(F47>=70,"Strong bullish technicals — Full risk-on positioning",IF(F47>=55,"Moderately bullish — Favor long positions",IF(F47>=45,"No clear trend — Reduce position sizes",IF(F47>=30,"Moderately bearish — Defensive positioning","Strong bearish technicals — Hedge / raise cash")))) -> Strong bearish technicals — Hedge / raise cash | H51: 70-100 | I51: ✅ Strong Uptrend
H52: 45-69 / 30-44 | I52: ⚠️ Sideways / ⚠️ Down
K53: Date: 20-Mar-2026 (Updated 23-Mar)
A54: 💧 LIQUIDITY MONITOR | K54: Date: 20-Mar-2026 (Updated 23-Mar)
A55: # | B55: INDICATOR | C55: CURRENT VALUE | D55: RISK-ON THRESHOLD | E55: NEUTRAL ZONE | F55: RISK-OFF THRESHOLD | G55: DIRECTION | H55: STATUS | I55: SCORE | J55: WEIGHT | K55: WEIGHTED | L55: LAST WEEK | M55: DELTA | N55: TREND
A56: 1 | B56: M2 Money Supply YoY % | C56: 0.0429 | D56: > 5% | E56: 2% - 5% | F56: < 2% | G56: Higher = Better | H56: =IF(C56>0.05,"✅ Risk-On",IF(C56>=0.02,"⚠️ Neutral","🔴 Risk-Off")) -> ⚠️ Neutral | I56: =IF(C56>0.05,ROUND(80+((C56-0.05)/0.05)*20,0),IF(C56>=0.02,ROUND(40+((C56-0.02)/0.03)*40,0),ROUND(MAX(0,(C56/0.02)*40),0))) -> 71 | J56: 0.15 | K56: =I56*J56 -> 10.65 | L56: 0.0429 | M56: =IF(L56="","",C56-L56) -> 0 | N56: =IF(M56="","⏳ Awaiting data",IF(ABS(M56)<0.002,"→ Stable",IF(M56>0,"↗ Improving","↘ Deteriorating"))) -> → Stable
A57: 2 | B57: Fed Balance Sheet ($T) | C57: 6.61 | D57: > 7.0 | E57: 6.0 - 7.0 | F57: < 6.0 | G57: Higher = Better | H57: =IF(C57>7,"✅ Risk-On",IF(C57>=6,"⚠️ Neutral","🔴 Risk-Off")) -> ⚠️ Neutral | I57: =IF(C57>7,ROUND(80+((C57-7)/1)*20,0),IF(C57>=6,ROUND(40+((C57-6)/1)*40,0),ROUND(MAX(0,(C57/6)*40),0))) -> 64 | J57: 0.1 | K57: =I57*J57 -> 6.4 | L57: 6.61 | M57: =IF(L57="","",C57-L57) -> 0 | N57: =IF(M57="","⏳ Awaiting data",IF(ABS(M57)<0.05,"→ Stable",IF(M57>0,"↗ Improving","↘ Deteriorating"))) -> → Stable
A58: 3 | B58: Fed Balance Sheet YoY % | C58: -0.028 | D58: > 0% | E58: -5% to 0% | F58: < -5% | G58: Higher = Better | H58: =IF(C58>0,"✅ Risk-On",IF(C58>=-0.05,"⚠️ Neutral","🔴 Risk-Off")) -> ⚠️ Neutral | I58: =IF(C58>0,ROUND(80+MIN((C58/0.05)*20,20),0),IF(C58>=-0.05,ROUND(40+((C58+0.05)/0.05)*40,0),ROUND(MAX(0,(C58+0.1)/0.05*40),0))) -> 58 | J58: 0.1 | K58: =I58*J58 -> 5.8 | L58: -0.028 | M58: =IF(L58="","",C58-L58) -> 0 | N58: =IF(M58="","⏳ Awaiting data",IF(ABS(M58)<0.005,"→ Stable",IF(M58>0,"↗ Improving","↘ Deteriorating"))) -> → Stable
A59: 4 | B59: Fed Funds Rate (%) | C59: 3.625 | D59: < 3% | E59: 3% - 5% | F59: > 5% | G59: Lower = Better | H59: =IF(C59<3,"✅ Risk-On",IF(C59<=5,"⚠️ Neutral","🔴 Risk-Off")) -> ⚠️ Neutral | I59: =IF(C59<3,ROUND(80+((3-C59)/3)*20,0),IF(C59<=5,ROUND(40+((5-C59)/2)*40,0),ROUND(MAX(0,(7-C59)/2*40),0))) -> 68 | J59: 0.1 | K59: =I59*J59 -> 6.8 | L59: 3.625 | M59: =IF(L59="","",C59-L59) -> 0 | N59: =IF(M59="","⏳ Awaiting data",IF(ABS(M59)<0.125,"→ Stable",IF(M59<0,"↗ Improving","↘ Deteriorating"))) -> → Stable
A60: 5 | B60: Reverse Repo Facility ($B) | C60: 6 | D60: < 200 | E60: 200 - 1000 | F60: > 1000 | G60: Lower = Better | H60: =IF(C60<200,"✅ Risk-On",IF(C60<=1000,"⚠️ Neutral","🔴 Risk-Off")) -> ✅ Risk-On | I60: =IF(C60<200,ROUND(80+((200-C60)/200)*20,0),IF(C60<=1000,ROUND(40+((1000-C60)/800)*40,0),ROUND(MAX(0,(2000-C60)/1000*40),0))) -> 99 | J60: 0.1 | K60: =I60*J60 -> 9.9 | L60: 6 | M60: =IF(L60="","",C60-L60) -> 0 | N60: =IF(M60="","⏳ Awaiting data",IF(ABS(M60)<50,"→ Stable",IF(M60<0,"↗ Improving","↘ Deteriorating"))) -> → Stable
A61: 6 | B61: Net Liquidity Index ($B) | C61: 5665 | D61: > 6000 | E61: 5000 - 6000 | F61: < 5000 | G61: Higher = Better | H61: =IF(C61>6000,"✅ Risk-On",IF(C61>=5000,"⚠️ Neutral","🔴 Risk-Off")) -> ⚠️ Neutral | I61: =IF(C61>6000,ROUND(80+((C61-6000)/1000)*20,0),IF(C61>=5000,ROUND(40+((C61-5000)/1000)*40,0),ROUND(MAX(0,(C61/5000)*40),0))) -> 67 | J61: 0.15 | K61: =I61*J61 -> 10.05 | L61: 5665 | M61: =IF(L61="","",C61-L61) -> 0 | N61: =IF(M61="","⏳ Awaiting data",IF(ABS(M61)<50,"→ Stable",IF(M61>0,"↗ Improving","↘ Deteriorating"))) -> → Stable
A62: 7 | B62: 2Y-10Y Yield Curve (%) | C62: 0.51 | D62: > 1.0% | E62: 0% - 1.0% | F62: < 0% (inverted) | G62: Higher = Better | H62: =IF(C62>1,"✅ Risk-On",IF(C62>=0,"⚠️ Neutral","🔴 Risk-Off")) -> ⚠️ Neutral | I62: =IF(C62>1,ROUND(80+MIN(((C62-1)/1)*20,20),0),IF(C62>=0,ROUND(40+(C62/1)*40,0),ROUND(MAX(0,(C62+1)/1*40),0))) -> 60 | J62: 0.1 | K62: =I62*J62 -> 6 | L62: 0.51 | M62: =IF(L62="","",C62-L62) -> 0 | N62: =IF(M62="","⏳ Awaiting data",IF(ABS(M62)<0.05,"→ Stable",IF(M62>0,"↗ Improving","↘ Deteriorating"))) -> → Stable
A63: 8 | B63: SOFR Spread (bps) | C63: 5 | D63: < 10 bps | E63: 10 - 50 bps | F63: > 50 bps | G63: Lower = Better | H63: =IF(C63<10,"✅ Risk-On",IF(C63<=50,"⚠️ Neutral","🔴 Risk-Off")) -> ✅ Risk-On | I63: =IF(C63<10,ROUND(80+((10-C63)/10)*20,0),IF(C63<=50,ROUND(40+((50-C63)/40)*40,0),ROUND(MAX(0,(100-C63)/50*40),0))) -> 90 | J63: 0 | K63: =I63*J63 -> 0 | L63: 5 | M63: =IF(L63="","",C63-L63) -> 0 | N63: =IF(M63="","⏳ Awaiting data",IF(ABS(M63)<2,"→ Stable",IF(M63<0,"↗ Improving","↘ Deteriorating"))) -> → Stable
A64: 9 | B64: DXY (Dollar Index) | C64: 99.5 | D64: < 95 | E64: 95 - 105 | F64: > 105 | G64: Lower = Better | H64: =IF(C64<95,"✅ Risk-On",IF(C64<=105,"⚠️ Neutral","🔴 Risk-Off")) -> ⚠️ Neutral | I64: =IF(C64<95,ROUND(80+((95-C64)/10)*20,0),IF(C64<=105,ROUND(40+((105-C64)/10)*40,0),ROUND(MAX(0,(115-C64)/10*40),0))) -> 62 | J64: 0.1 | K64: =I64*J64 -> 6.2 | L64: 99.5 | M64: =IF(L64="","",C64-L64) -> 0 | N64: =IF(M64="","⏳ Awaiting data",IF(ABS(M64)<0.5,"→ Stable",IF(M64<0,"↗ Improving","↘ Deteriorating"))) -> → Stable
A65: 10 | B65: Gold/SPX Ratio | C65: 0.711 | D65: < 0.4 | E65: 0.4 - 0.8 | F65: > 0.8 | G65: Lower = Better | H65: =IF(C65<0.4,"✅ Risk-On",IF(C65<=0.8,"⚠️ Neutral","🔴 Risk-Off")) -> ⚠️ Neutral | I65: =IF(C65<0.4,ROUND(80+((0.4-C65)/0.4)*20,0),IF(C65<=0.8,ROUND(40+((0.8-C65)/0.4)*40,0),ROUND(MAX(0,(1.2-C65)/0.4*40),0))) -> 49 | J65: 0.05 | K65: =I65*J65 -> 2.45 | L65: 0.746 | M65: =IF(L65="","",C65-L65) -> -0.035 | N65: =IF(M65="","⏳ Awaiting data",IF(ABS(M65)<0.02,"→ Stable",IF(M65<0,"↗ Improving","↘ Deteriorating"))) -> ↗ Improving
A66: 11 | B66: MOVE Index (Bond Vol) | C66: 109 | D66: < 60 | E66: 60 - 100 | F66: > 120 | G66: Lower = Better | H66: =IF(C66<60,"✅ Risk-On",IF(C66<=100,"⚠️ Neutral","🔴 Risk-Off")) -> 🔴 Risk-Off | I66: =ROUND(MAX(0,MIN(100, IF(C66<=60,100, IF(C66>=120,0, 100-(C66-60)/(120-60)*100)))),0) -> 18 | J66: 0.05 | K66: =I66*J66 -> 0.9 | L66: 79 | M66: =IF(L66="","",C66-L66) -> 30
B67: LIQUIDITY COMPOSITE SCORE | I67: =ROUND(SUM(K56:K66),0) -> 65 | J67: =SUM(J56:J66) -> 1 | K67: =ROUND(SUM(K56:K66),1) -> 65.2
K69: Date: 20-Mar-2026 (Updated 23-Mar)
A70: Liquidity Regime: | C70: =IF(I67>=70,"✅ LIQUIDITY EXPANSION",IF(I67>=55,"✅ MODERATE LIQUIDITY",IF(I67>=45,"⚠️ NEUTRAL LIQUIDITY",IF(I67>=30,"⚠️ TIGHTENING","🔴 LIQUIDITY CRUNCH")))) -> ✅ MODERATE LIQUIDITY | H70: Score Range | I70: Classification | K70: Date: 20-Mar-2026 (Updated 23-Mar)
A71: Implication: | C71: =IF(I67>=70,"Ample liquidity — Supports risk assets and credit expansion",IF(I67>=55,"Moderately supportive — Normal liquidity conditions",IF(I67>=45,"Mixed signals — Monitor closely for changes",IF(I67>=30,"Tightening conditions — Reduce risk exposure","Severe liquidity stress — Defensive positioning required")))) -> Moderately supportive — Normal liquidity conditions | H71: 70-100 / 55-69 | I71: ✅ Expansion / Moderate
A77: 🔗 COMBINED REGIME SCORE (MACRO + TECHNICAL + LIQUIDITY)
A78: Component | C78: Score | D78: Weight | E78: Weighted | F78: Status | I78: COMBINED REGIME
A79: 🌐 Sentiment & Systemic Score | C79: =I13 -> 60 | D79: 0.35 | E79: =ROUND(C79*D79,1) -> 21 | F79: =IF(C79>=80,"✅ Risk-On",IF(C79>=60,"⚠️ Moderate",IF(C79>=50,"⚠️ Neutral","🔴 Risk-Off"))) -> ⚠️ Moderate
A80: 📊 Technical Score | C80: =F47 -> 10 | D80: 0.35 | E80: =ROUND(C80*D80,1) -> 3.5 | F80: =IF(C80>=70,"✅ Bullish",IF(C80>=45,"⚠️ Mixed","🔴 Bearish")) -> 🔴 Bearish
A81: 💧 Liquidity Score | C81: =I67 -> 65 | D81: 0.3 | E81: =ROUND(C81*D81,1) -> 19.5 | F81: =IF(C81>=70,"✅ Expansive",IF(C81>=45,"⚠️ Neutral","🔴 Tight")) -> ⚠️ Neutral
A82: 🎯 COMBINED SCORE | C82: =ROUND(E79+E80+E81,1) -> 44 | E82: =ROUND(E79+E80+E81,1) -> 44 | F82: =C82&" / 100" -> 44 / 100 | I82: =IF(COUNTIF(E27:E31,"🔴 YES")>0,"🚨 OVERRIDE: RISK-OFF (Trigger Active)",IF(C82>=75,"✅ STRONG RISK-ON",IF(C82>=60,"✅ RISK-ON (Moderate)",IF(C82>=45,"⚠️ NEUTRAL",IF(C82>=35,"⚠️ RISK-OFF (Moderate)","🔴 STRONG RISK-OFF"))))) -> 🚨 OVERRIDE: RISK-OFF (Trigger Active)
A83: Override: | C83: =IF(COUNTIF(E27:E31,"🔴 YES")>0,"⚠️ Circuit Breaker activo — Override: "&IF(E27="🔴 YES","VIX Spike ","")&IF(E28="🔴 YES","Credit Stress ","")&IF(E29="🔴 YES","Fear Extreme ","")&IF(E30="🔴 YES","Breadth Collapse ","")&IF(E31="🔴 YES","Oil Shock ",""),IF(E32="⚠️ WATCH","⚠️ 10Y Watch activo ("&C35&"%) — Compras restringidas a Core A+","")) -> ⚠️ Circuit Breaker activo — Override: VIX Spike Breadth Collapse
A84: Action: | C84: =IF(COUNTIF(E27:E31,"🔴 YES")>0,IF(E27="🔴 YES",F27,"")&IF(AND(E27="🔴 YES",COUNTIF(E28:E31,"🔴 YES")>0)," + ","")&IF(E28="🔴 YES",F28,"")&IF(AND(E28="🔴 YES",COUNTIF(E29:E31,"🔴 YES")>0)," + ","")&IF(E29="🔴 YES",F29,"")&IF(AND(E29="🔴 YES",COUNTIF(E30:E31,"🔴 YES")>0)," + ","")&IF(E30="🔴 YES",F30,"")&IF(AND(E30="🔴 YES",E31="🔴 YES")," + ","")&IF(E31="🔴 YES",F31,""),IF(C82>=75,"Full equity exposure. Overweight growth/cyclicals.",IF(C82>=60,"Maintain equity exposure. Balanced allocation.",IF(C82>=45,"Reduce position sizes. Equal-weight sectors. Raise quality.",IF(C82>=35,"Underweight equities. Favor defensives. Add hedges.","Minimum equity exposure. Max hedging. Raise cash."))))) -> Reduce tech exposure 44% → 35%, increase hedges + Rotate to defensives (healthcare, utilities, staples)
A86: 🔀 DIVERGENCE ANALYSIS (MACRO vs TECHNICAL)
A87: Sentiment Score: | B87: =C79 -> 60 | C87: Technical Score: | D87: =C80 -> 10 | E87: Gap: | F87: =ABS(B87-D87)&" pts" -> 50 pts
A88: Divergence Status: | B88: =IF(ABS(B87-D87)<=20,"🟢 ALIGNED",IF(ABS(B87-D87)<=30,"🟡 MINOR DIVERGENCE","🔴 MAJOR DIVERGENCE")) -> 🔴 MAJOR DIVERGENCE | E88: Confidence: | F88: =IF(ABS(B87-D87)<=20,"HIGH — Macro & price agree",IF(ABS(B87-D87)<=30,"MODERATE — Some conflict","LOW — Macro and price contradict")) -> LOW — Macro and price contradict
A89: Interpretation: | B89: =IF(ABS(B87-D87)<=20,"Signals aligned — Trade with full conviction per Combined Score",IF(B87>D87,"Fundamentals OK but price weak — Macro leads? Or price warning?","Price strong but fundamentals deteriorating — Momentum? Or denial?")) -> Fundamentals OK but price weak — Macro leads? Or price warning?
A90: Risk Guidance: | B90: =IF(ABS(B87-D87)<=20,"✅ Normal positioning per Combined Score",IF(ABS(B87-D87)<=30,"⚠️ Consider modest size reduction on new positions","🔴 Reduce conviction on new adds — Wait for alignment before full sizing")) -> 🔴 Reduce conviction on new adds — Wait for alignment before full sizing
A92: What to watch for alignment: | B92: =IF(ABS(B87-D87)<=20,"N/A — Signals already aligned",IF(B87>D87,"S&P above MA-50 | RSI >55 | MACD positive → Technical catches up to Macro","VIX <20 | Spreads <300 | Breadth >65% → Macro catches up to Price")) -> S&P above MA-50 | RSI >55 | MACD positive → Technical catches up to Macro
A94: 🔄 SECTOR ROTATION SIGNALS
A95: # | B95: SECTOR | C95: BETA | D95: ⚠️ PRECAUCIÓN (≥75) | E95: ✅ NORMAL (60-74) | F95: 🛡️ DEFENSIVO (45-59) | G95: 🔴 RISK-OFF (<45) | H95: 🎯 CURRENT SIGNAL | I95: MARANGO NOTES
A96: 1 | B96: Technology | C96: High | D96: ⚠️ Trim 10% | E96: ✅ Maintain | F96: ⚠️ Trim | G96: 🔴 Underweight | H96: =IF($C$82>=75,D96,IF($C$82>=60,E96,IF($C$82>=45,F96,G96))) -> 🔴 Underweight | I96: Core: NVDA, MSFT, META. Reduce 44%→35% if Risk-Off
A97: 2 | B97: Consumer Discretionary | C97: High | D97: ⚠️ Trim 10% | E97: ✅ Maintain | F97: ⚠️ Trim | G97: 🔴 Underweight | H97: =IF($C$82>=75,D97,IF($C$82>=60,E97,IF($C$82>=45,F97,G97))) -> 🔴 Underweight | I97: AMZN, TSLA. Cyclical — sensitive to consumer confidence
A98: 3 | B98: Industrials | C98: Med-High | D98: ⚠️ Trim 15% | E98: ⚠️ Neutral | F98: ⚠️ Trim | G98: 🔴 Underweight | H98: =IF($C$82>=75,D98,IF($C$82>=60,E98,IF($C$82>=45,F98,G98))) -> 🔴 Underweight | I98: CAT, HON, GE. Tied to capex cycle & GDP growth
A99: 4 | B99: Financials | C99: Med-High | D99: ⚠️ Neutral | E99: ✅ Maintain | F99: ⚠️ Trim | G99: 🔴 Underweight | H99: =IF($C$82>=75,D99,IF($C$82>=60,E99,IF($C$82>=45,F99,G99))) -> 🔴 Underweight | I99: JPM, GS, BRK. Benefits from steeper yield curve
A100: 5 | B100: Energy | C100: Medium | D100: ⚠️ Trim 10% | E100: ⚠️ Neutral | F100: ⚠️ Neutral | G100: ⚠️ Neutral | H100: =IF($C$82>=75,D100,IF($C$82>=60,E100,IF($C$82>=45,F100,G100))) -> ⚠️ Neutral | I100: XOM, CVX. Inflation hedge, commodity-linked
A101: 6 | B101: Real Estate (REITs) | C101: Medium | D101: ⚠️ Neutral | E101: ⚠️ Neutral | F101: ⚠️ Trim | G101: 🔴 Underweight | H101: =IF($C$82>=75,D101,IF($C$82>=60,E101,IF($C$82>=45,F101,G101))) -> 🔴 Underweight | I101: Rate-sensitive. Benefits from Fed cuts & lower yields
A102: 7 | B102: Healthcare | C102: Low | D102: ✅ Overweight | E102: ⚠️ Neutral | F102: ✅ Overweight | G102: ✅ Overweight | H102: =IF($C$82>=75,D102,IF($C$82>=60,E102,IF($C$82>=45,F102,G102))) -> ✅ Overweight | I102: JNJ, UNH, LLY. Defensive — rotate INTO during stress
A103: 8 | B103: Consumer Staples | C103: Low | D103: ✅ Overweight | E103: ⚠️ Neutral | F103: ✅ Overweight | G103: ✅ Overweight | H103: =IF($C$82>=75,D103,IF($C$82>=60,E103,IF($C$82>=45,F103,G103))) -> ✅ Overweight | I103: PG, KO, PEP. Safe haven — add during Risk-Off
A104: 9 | B104: Utilities | C104: Low | D104: ✅ Overweight | E104: ⚠️ Neutral | F104: ✅ Overweight | G104: ✅ Overweight | H104: =IF($C$82>=75,D104,IF($C$82>=60,E104,IF($C$82>=45,F104,G104))) -> ✅ Overweight | I104: NEE, DUK. Bond proxy — defensive + rate sensitive
A105: 10 | B105: Small Caps (IWM) | C105: Very High | D105: 🔴 Trim 20% | E105: ⚠️ Neutral | F105: 🔴 Underweight | G105: 🔴 Avoid | H105: =IF($C$82>=75,D105,IF($C$82>=60,E105,IF($C$82>=45,F105,G105))) -> 🔴 Avoid | I105: IWM, Russell 2000. Most sensitive to liquidity & credit
A107: 🎯 CURRENT POSITIONING SUMMARY
A108: FAVOR: | B108: =IF($C$82>=75,"Healthcare, Staples, Utilities (defensivos ante toma de beneficios)",IF($C$82>=60,"Tech, Discretionary, Financials",IF($C$82>=45,"Healthcare, Staples, Utilities","Healthcare, Staples, Utilities"))) -> Healthcare, Staples, Utilities
A109: NEUTRAL: | B109: =IF($C$82>=75,"Tech, Discretionary, Cyclicals (trim 10-15%)",IF($C$82>=60,"Industrials, Energy, REITs, Healthcare, Staples, Utilities, Small Caps",IF($C$82>=45,"Industrials, Energy, Financials, Small Caps","Energy, Small Caps"))) -> Energy, Small Caps
A110: AVOID: | B110: =IF($C$82>=75,"Staples, Utilities (underperform in Risk-On)",IF($C$82>=60,"None — Balanced allocation across all sectors",IF($C$82>=45,"Tech, Discretionary, Small Caps (high beta)","Tech, Discretionary, Financials, REITs, Small Caps"))) -> Tech, Discretionary, Financials, REITs, Small Caps
A111: MARANGO: | B111: =IF($C$82>=75,"Full tech overweight (44%). Add cyclicals. Aggressive. Cash ≤4%.",IF($C$82>=60,"Maintain tech (44%). Balanced allocation. Normal risk. Cash 5-8%.",IF($C$82>=45,"Trim tech 44%→38%. Add defensives (JNJ, PG). Cash 8-10%.","Cut tech 44%→30%. Rotate to healthcare + staples. Cash 10-15%."))) -> Cut tech 44%→30%. Rotate to healthcare + staples. Cash 10-15%.

Sheet Historical Log
A1: 📊 HISTORICAL LOG — Market Regime Tracker
A2: Weekly snapshots — All regime components | Marango Fund
A3: 💡 Each Friday: Copy row 5 → paste as VALUES in next row. Update Date, Week #, and Notes. Row 5 auto-pulls current data.
A4: Date | B4: Week # | C4: VIX | D4: HY Spreads | E4: Put/Call | F4: Breadth | G4: Sentiment Score | H4: S&P 500 | I4: RSI | J4: MACD | K4: Skew | L4: Technical Score | M4: M2 YoY% | N4: Fed BS ($T) | O4: Fed Rate | P4: Yield Curve | Q4: SOFR Sprd | R4: DXY | S4: Gold/SPX | T4: Liquidity Score | U4: Combined Score | V4: Regime | W4: Triggers Active | X4: Notes
A5: 46086 | B5: 3 | C5: ='B5 - Market Regime'!C7 -> 26.78 | D5: ='B5 - Market Regime'!C8 -> 320 | E5: ='B5 - Market Regime'!C9 -> 0.58 | F5: ='B5 - Market Regime'!C10 -> 0.42 | G5: ='B5 - Market Regime'!I13 -> 60 | H5: ='B5 - Market Regime'!B41 -> 6506.48 | I5: ='B5 - Market Regime'!B44 -> 23.34 | J5: ='B5 - Market Regime'!B45 -> -39.43 | K5: ='B5 - Market Regime'!B46 -> 140 | L5: ='B5 - Market Regime'!F47 -> 10 | M5: ='B5 - Market Regime'!C56 -> 0.0429 | N5: ='B5 - Market Regime'!C57 -> 6.61 | O5: ='B5 - Market Regime'!C59 -> 3.625 | P5: ='B5 - Market Regime'!C62 -> 0.51 | Q5: ='B5 - Market Regime'!C63 -> 5 | R5: ='B5 - Market Regime'!C64 -> 99.5 | S5: ='B5 - Market Regime'!C65 -> 0.711 | T5: ='B5 - Market Regime'!I67 -> 65 | U5: ='B5 - Market Regime'!C82 -> 44 | V5: ='B5 - Market Regime'!I82 -> 🚨 OVERRIDE: RISK-OFF (Trigger Active) | W5: =IF('B5 - Market Regime'!C83="","None",'B5 - Market Regime'!C83) -> ⚠️ Circuit Breaker activo — Override: VIX Spike Breadth Collapse | X5: Week 3 — VIX spiked 26.78, S&P -3.1%, RSI oversold 23, MACD -39, MOVE 109. Iran war escalation + oil $98 near trigger. Combined 44 = RISK-OFF zone.
A6: 46079 | B6: 2 | C6: 23.51 | D6: 317 | E6: 0.58 | F6: 0.48 | G6: 67 | H6: 6716.09 | I6: 48.85 | J6: -8.63 | K6: 140 | L6: 41 | M6: 0.0429 | N6: 6.61 | O6: 3.625 | P6: 0.51 | Q6: 5 | R6: 99.5 | S6: 0.746 | T6: 67 | U6: 58 | V6: 🚨 OVERRIDE: RISK-OFF (Trigger Active) | W6: ⚠️ Circuit Breaker activo — Override: Breadth Collapse | X6: Week 2 — VIX declining, technicals weak, breadth collapsed

Sheet 📖 Indicator Guide
A1: 📖 INDICATOR GUIDE — Market Regime Detection
A2: AI Investing Dashboard | Marango Fund | Reference guide for all indicators used in Bloque 5
A3: 🌐 SENTIMENT & SYSTEMIC RISK INDICATORS (Weight in Combined Score: 35%)
A4: # | B4: INDICATOR | C4: DESCRIPTION | D4: SCORING LOGIC | E4: WEIGHT | F4: DATA SOURCE & FREQUENCY
A5: 1 | B5: VIX (Volatility Index) | C5: Mide la volatilidad implícita esperada a 30 días del S&P 500, derivada de precios de opciones. Conocido como el "índice del miedo". Un VIX bajo indica complacencia/confianza del mercado; un VIX alto indica estrés, incertidumbre o pánico. Es el indicador más reactivo del dashboard. | D5: Lineal: ≤15 → 100 (calma) ≥40 → 0 (pánico) Entre 15-40 → escala proporcional | E5: 0.3 | F5: Yahoo Finance / CBOE Diaria — Actualizar cada lunes con cierre del viernes
A6: 2 | B6: HY Credit Spreads (bps) | C6: Diferencial de rendimiento entre bonos corporativos High Yield (basura) y bonos del Tesoro. Mide el riesgo crediticio percibido en la economía. Spreads bajos = confianza crediticia, mercado sano. Spreads altos = estrés financiero, miedo a defaults. Anticipan recesiones con meses de adelanto. | D6: Lineal: ≤200 → 100 (salud) ≥600 → 0 (crisis) Entre 200-600 → escala proporcional | E6: 0.3 | F6: FRED (ICE BofA HY OAS) Semanal — Actualizar cada lunes
A7: 3 | B7: Put/Call Ratio | C7: Ratio entre volumen de opciones put (bajistas) y call (alcistas) en el mercado. Mide el sentimiento direccional de los participantes. Ratio bajo (<0.7) = exceso de optimismo (posible techo). Ratio alto (>1.2) = miedo extremo (posible suelo contrarian). Es un indicador contrarian clásico. | D7: Lineal: ≤0.5 → 100 (optimismo) ≥2.0 → 0 (pánico) Entre 0.5-2.0 → escala proporcional | E7: 0.2 | F7: CBOE / yCharts Diaria — Actualizar cada lunes
A8: 4 | B8: Market Breadth (% > 200d MA) | C8: Porcentaje de acciones del S&P 500 que cotizan por encima de su media móvil de 200 días. Mide la salud interna del mercado más allá del índice. Breadth alta (>65%) = rally amplio, saludable. Breadth baja (<40%) = mercado concentrado en pocos valores, frágil. Divergencia con el índice es señal de alerta. | D8: Lineal: ≥80% → 100 (sano) ≤20% → 0 (colapso) Entre 20-80% → escala proporcional | E8: 0.2 | F8: MacroMicro Semanal — Actualizar cada lunes Input en decimal (0.65 = 65%)
A10: 📊 TECHNICAL INDICATORS — S&P 500 (Weight in Combined Score: 35%)
A11: # | B11: INDICATOR | C11: DESCRIPTION | D11: SCORING LOGIC | E11: WEIGHT | F11: DATA SOURCE & FREQUENCY
A12: 1 | B12: S&P 500 vs MA-200 | C12: Posición del S&P 500 relativa a su media móvil de 200 días. La MA-200 es la línea divisoria clásica entre tendencia alcista y bajista a largo plazo. Por encima = bull market técnico. Por debajo = bear market técnico. La distancia porcentual mide la fuerza de la tendencia. | D12: % vs MA200: < -5% → 0 (bear fuerte) > +3% → 100 (bull fuerte) Entre -5% y +3% → proporcional | E12: 0.25 | F12: Investing.com (Technical page) Diaria — Actualizar cada lunes
A13: 2 | B13: S&P 500 vs MA-50 | C13: Posición del S&P 500 relativa a su media móvil de 50 días. Mide la tendencia de mediano plazo. Más sensible que la MA-200, captura cambios de momentum antes. Rupturas por debajo de la MA-50 suelen preceder correcciones. Útil para timing de entries/exits. | D13: % vs MA50: < -3% → 0 (débil) > +2% → 100 (fuerte) Entre -3% y +2% → proporcional | E13: 0.2 | F13: Investing.com (Technical page) Diaria — Actualizar cada lunes
A14: 3 | B14: Golden / Death Cross | C14: Señal binaria basada en el cruce de la MA-50 con la MA-200. Golden Cross (MA50 > MA200) = señal alcista de largo plazo, históricamente precede rallies sostenidos. Death Cross (MA50 < MA200) = señal bajista, precede períodos de debilidad. Cambia poco frecuentemente (cada varios meses). | D14: Binario: MA50 > MA200 → 100 (Golden) MA50 < MA200 → 0 (Death) | E14: 0.1 | F14: Calculado automáticamente Se actualiza al ingresar MA-50 y MA-200
A15: 4 | B15: RSI (14-Day) | C15: Relative Strength Index con período de 14 días. Oscilador de momentum que mide la velocidad y magnitud de los movimientos de precio (0-100). RSI > 70 = sobrecomprado (riesgo de corrección). RSI < 30 = sobrevendido (posible rebote). Entre 40-60 = zona neutral sin señal clara. | D15: Zonas: < 30 → 0 (oversold) > 70 → 100 (overbought) 30-50 → escala 0-50 50-70 → escala 50-100 | E15: 0.2 | F15: Investing.com (SPY Technical) Diaria — Actualizar cada lunes
A16: 5 | B16: MACD (12,26,9) | C16: Moving Average Convergence Divergence. Diferencia entre EMA-12 y EMA-26, con señal EMA-9. Mide momentum y dirección de tendencia. MACD positivo = momentum alcista. MACD negativo = momentum bajista. Cruces con la línea de señal generan señales de compra/venta. Es un indicador lagging (confirma, no predice). | D16: Lineal: < -50 → 0 (bear fuerte) > +50 → 100 (bull fuerte) Entre -50 y +50 → proporcional | E16: 0.2 | F16: Investing.com (SPY Technical) Diaria — Actualizar cada lunes
A17: 6 | B17: CBOE Skew Index | C17: Mide la asimetría (skew) de la distribución de retornos esperados implícita en opciones del S&P 500. Skew alto (>145) = el mercado está pagando más por protección contra caídas extremas (tail risk). Skew bajo (<120) = baja percepción de tail risk. Diferente del VIX: mide FORMA del riesgo, no NIVEL. | D17: Invertido: ≥155 → 0 (tail risk) ≤120 → 100 (bajo riesgo) Entre 120-155 → proporcional | E17: 0.05 | F17: MacroMicro / CBOE Semanal (retraso ~1 semana)
A19: 💧 LIQUIDITY MONITOR (Weight in Combined Score: 30%)
A20: # | B20: INDICATOR | C20: DESCRIPTION | D20: SCORING LOGIC | E20: WEIGHT | F20: DATA SOURCE & FREQUENCY
A21: 1 | B21: M2 Money Supply YoY % | C21: Crecimiento interanual de la masa monetaria M2 (efectivo + depósitos + money markets). M2 creciendo = más dinero circulando en la economía, favorable para activos de riesgo. M2 contrayéndose = liquidez drenando del sistema, historícamente precede debilidad en equities. El indicador de liquidez más amplio. | D21: Lineal: >5% → 80-100 2-5% → 40-80 <2% → 0-40 Input en decimal (0.046 = 4.6%) | E21: 0.15 | F21: FRED (M2SL series) Mensual (retraso ~4 semanas)
A22: 2 | B22: Fed Balance Sheet ($T) | C22: Tamaño total del balance de la Reserva Federal en trillones de dólares. Incluye bonos del Tesoro y MBS. Balance creciente (QE) = inyección de liquidez, positivo para mercados. Balance reduciéndose (QT) = drena liquidez. El balance pasó de $4T pre-COVID a $9T en 2022, ahora ~$6.6T. | D22: Lineal: >$7T → 80-100 $6-7T → 40-80 <$6T → 0-40 | E22: 0.1 | F22: Fed H.4.1 Release / FRED (WALCL) Semanal — Publicado jueves
A23: 3 | B23: Fed Balance Sheet YoY % | C23: Cambio interanual del balance de la Fed. Complementa el nivel absoluto mostrando la DIRECCIÓN. YoY positivo = expansión neta (favorable). YoY negativo = contracción neta (QT activo). Actualmente en ~-2.6% indicando que QT continúa pero a ritmo moderado. | D23: Lineal: >0% → 80-100 -5% a 0% → 40-80 <-5% → 0-40 Input en decimal (-0.026 = -2.6%) | E23: 0.1 | F23: Calculado: Fed BS actual / Fed BS hace 1 año FRED (WALCL) — Semanal
A24: 4 | B24: Fed Funds Rate (%) | C24: Tasa de interés objetivo de la Fed para préstamos interbancarios overnight. Es la herramienta principal de política monetaria. Tasas bajas (<3%) = política acomodaticia, favorable para riesgo. Tasas altas (>5%) = política restrictiva, frena la economía. Se mueve en incrementos de 25bps. | D24: Invertido: <3% → 80-100 (acomodaticia) 3-5% → 40-80 (neutral) >5% → 0-40 (restrictiva) | E24: 0.1 | F24: Federal Reserve (FOMC Statement) Cada 6 semanas (8 reuniones/año)
A25: 5 | B25: Reverse Repo Facility ($B) | C25: Dinero que instituciones financieras depositan en la Fed overnight a cambio de colateral. RRP alto (>$1T) = exceso de liquidez estacionada fuera del sistema (no circula). RRP bajo (<$200B) = liquidez fluyendo hacia mercados y economía. El drenaje de RRP en 2023-24 fue un motor clave del rally. | D25: Invertido: <$200B → 80-100 (circulando) $200-1000B → 40-80 >$1000B → 0-40 (estancada) | E25: 0.1 | F25: FRED (RRPONTSYD) Diaria — Actualizar semanal
A26: 6 | B26: Net Liquidity Index ($B) | C26: Fórmula: Fed Balance Sheet - TGA (Treasury General Account) - Reverse Repo. Mide la liquidez EFECTIVA disponible en el sistema financiero. Es el indicador más directo de “cuánto dinero puede fluir a activos”. Correlación históricamente alta con el S&P 500. >$6T es expansivo, <$5T es restrictivo. | D26: Lineal: >$6000B → 80-100 $5000-6000B → 40-80 <$5000B → 0-40 | E26: 0.15 | F26: Calculado: Fed BS - TGA - RRP Fed H.4.1 + Treasury DTS — Semanal
A27: 7 | B27: 2Y-10Y Yield Curve (%) | C27: Diferencia entre el rendimiento del bono del Tesoro a 10 años y el de 2 años. Es el indicador de recesión más estudiado en la historia. Curva positiva (>0) = economía sana, expectativas de crecimiento. Curva invertida (<0) = históricamente ha precedido TODAS las recesiones de EE.UU. desde 1970 con 12-18 meses de anticipación. Recientemente se desinvirtió tras la mayor inversión desde los 80s. | D27: Lineal: >1.0% → 80-100 (sano) 0-1.0% → 40-80 (neutral) <0% → 0-40 (invertido/peligro) | E27: 0.1 | F27: FRED (T10Y2Y) Diaria — Actualizar cada lunes fred.stlouisfed.org/series/T10Y2Y
A28: 8 | B28: SOFR Spread (bps) | C28: Diferencia entre el SOFR (Secured Overnight Financing Rate) y la tasa target de la Fed. Reemplaza al TED Spread (discontinuado en 2022 por eliminación de LIBOR). Mide estrés en el mercado de repos/funding interbancario. Spread cercano a cero = mercado de funding funcionando con normalidad. Spread elevado (>50bps) = estrés de liquidez, bancos reluctantes a prestar. | D28: Lineal invertido: <10bps → 80-100 (normal) 10-50bps → 40-80 (algo de estrés) >50bps → 0-40 (estrés severo) | E28: 0.05 | F28: NY Fed / FRED (SOFR) Diaria — Actualizar cada lunes fred.stlouisfed.org/series/SOFR Calcular: SOFR - Fed Funds Target
A29: 9 | B29: DXY (Dollar Index) | C29: Índice que mide la fortaleza del dólar frente a una cesta de 6 divisas principales (EUR 57.6%, JPY 13.6%, GBP 11.9%, CAD 9.1%, SEK 4.2%, CHF 3.6%). Un dólar fuerte (DXY alto) = condiciones financieras más restrictivas globalmente, presión sobre commodities y mercados emergentes. Un dólar débil = más liquidez global, favorable para activos de riesgo. | D29: Invertido: <95 → 80-100 (débil, favorable) 95-105 → 40-80 (neutral) >105 → 0-40 (fuerte, restrictivo) | E29: 0.1 | F29: Yahoo Finance / Investing.com Diaria — Actualizar cada lunes finance.yahoo.com/quote/DX-Y.NYB/
A30: 10 | B30: Gold/SPX Ratio | C30: Ratio entre el precio del oro ($/oz) y el nivel del S&P 500. Mide el 'flight to safety' relativo. Ratio alto (>0.8) = inversores prefiriendo refugio sobre riesgo, señal de estrés. Ratio bajo (<0.4) = confianza plena en equities. La dirección del ratio es tan importante como su nivel: ratio creciente indica deterioro de confianza incluso si equities no han caído. | D30: Invertido: <0.4 → 80-100 (risk-on) 0.4-0.8 → 40-80 (neutral) >0.8 → 0-40 (flight to safety) | E30: 0.05 | F30: Calculado: Gold Price / S&P 500 Gold: fortune.com (daily) SPX: Dashboard value Semanal — Actualizar cada lunes
A32: 🚨 CIRCUIT BREAKER TRIGGERS (Override System)
B33: Concepto: | C33: Si CUALQUIER trigger se activa, el Combined Score se ANULA automáticamente y el modelo fuerza modo RISK-OFF independientemente del score. Son condiciones extremas donde el análisis cuantitativo normal pierde fiabilidad. Cada trigger tiene una acción defensiva específica asociada.
A35: # | B35: TRIGGER | C35: DESCRIPTION & RATIONALE | D35: THRESHOLD | F35: DEFENSIVE ACTION
A36: 1 | B36: VIX Spike | C36: VIX por encima de 25 indica estrés significativo. A este nivel, las opciones de protección están caras y el mercado espera movimientos diarios >1.5%. Historícamente, VIX sostenido >25 coincide con correcciones de 5-15%. | D36: VIX > 25 | F36: Reducir tech exposure 44%→35%, aumentar hedges
A37: 2 | B37: Credit Stress | C37: HY Spreads >400bps señalan que el mercado de crédito está priciando riesgo de default significativo. Los spreads lideran a equities: cuando el crédito se estresa primero, equities suelen seguir con 2-4 semanas de retraso. | D37: HY Spreads > 400bps | F37: Cortar cíclicos, rotar a bonos investment-grade
A38: 3 | B38: Fear Extreme | C38: Put/Call >1.2 indica que se están comprando 1.2 puts por cada call. Miedo extremo en el mercado de opciones. Puede ser señal contrarian a mediano plazo (suelos), pero a corto plazo indica que la venta puede continuar. | D38: Put/Call > 1.2 | F38: Subir cash a 10-15%, pausar nuevas posiciones
A39: 4 | B39: Breadth Collapse | C39: Menos del 50% de acciones sobre su MA-200 indica que la mayoría del mercado está en bear market aunque el índice pueda no reflejarlo (concentración en mega-caps). Señal de debilidad estructural que precede caídas más amplias. | D39: Breadth < 50% | F39: Rotar a defensivos (healthcare, utilities, staples)
A41: 🎯 COMBINED REGIME SCORE — Methodology
B42: Cómo se calcula: | C42: Combined Score = (Sentiment × 35%) + (Technical × 35%) + (Liquidity × 30%). Cada pilar tiene su propio score 0-100. Sentiment: 4 indicadores. Technical: 6 indicadores. Liquidity: 10 indicadores (V4, expandido desde 6 en V3). El resultado es un score único 0-100. Si algún Circuit Breaker está activo, el score se anula y se fuerza RISK-OFF.
B44: Escala de régimen (V5): | C44: Interpretación y posicionamiento sugerido:
B45: 75-100: ⚠️ PRECAUCIÓN — Tomar beneficios | C45: Euforia = peligro. Tomar beneficios parciales (10-15%). Reducir cíclicos. Cash 8-12%. Backtest: avg S&P 1M fwd = -3.8% en este rango.
B46: 60-74: ✅ NORMAL — Allocation estándar | C46: Zona cómoda. Allocation según B1 Financial Scoring. Mantener posiciones. Cash 5-8%.
B47: 45-59: 🛡️ DEFENSIVO — Subir calidad | C47: Trim high-beta y cíclicos. Rotar a quality (B1 Score ≥80). Subir defensivos. Cash 10-12%. Override añade +5%.
B48: 35-44: 🔴 PROTECCIÓN + 1ª compra (25%) | C48: Reducir exposición general. PERO reservar 15% para 1ª compra oportunista en Core A+ (B1 Score ≥85 + Upside >15%). Cash 12-18%.
B49: <35: 🔴🟢 MÁX PROTECCIÓN + 2ª/3ª compra | C49: Máxima protección del portfolio base. Cash 15-20%. PERO ejecutar 2ª y 3ª compras oportunistas (total 50% de la reserva) en B1 Score ≥80 + Upside >10%. Backtest: avg S&P 1M fwd = +4.4%.
B51: 🚨 OVERRIDE: | C51: 6 triggers reales: VIX>25, HY>400, P/C>1.2, Breadth<50%, WTI≥$100, 10Y≥5%. Si 1+ activo → Override (+5% cash, solo Core A+). Además 10Y 4.5-4.99% = Watch informativo (restringe compras sin subir cash).
A53: 🔀 DIVERGENCE ANALYSIS — Macro vs Technical
B54: Concepto: | C54: Compara el Sentiment Score (fundamentales/macro) con el Technical Score (price action). Cuando ambos están alineados, la convicción es alta. Cuando divergen, alguno de los dos está "equivocado" y hay que actuar con cautela hasta que converjan.
B56: Gap ≤ 20 pts: | C56: 🟢 ALIGNED — Macro y precio de acuerdo. Operar con convicción plena según el Combined Score. Confianza ALTA.
B57: Gap 21-30 pts: | C57: 🟡 MINOR DIVERGENCE — Algo de conflicto entre señales. Considerar reducción modesta de posiciones nuevas. Confianza MODERADA.
B58: Gap > 30 pts: | C58: 🔴 MAJOR DIVERGENCE — Macro y precio contradicen. Reducir convicción en nuevas posiciones. Esperar alineación antes de sizing completo. Confianza BAJA.
B60: Si Macro > Technical: | C60: Fundamentales OK pero precio débil. ¿Macro lidera y precio alcanzará? ¿O precio advierte deterioro que aún no se refleja en macro? Vigilar: S&P sobre MA-50, RSI >55, MACD positivo para confirmar que Technical converge.
B61: Si Technical > Macro: | C61: Precio fuerte pero fundamentales deteriorando. ¿Momentum puro? ¿O negación del mercado? Vigilar: VIX <20, Spreads <300, Breadth >65% para confirmar que Macro converge.
A63: ⏱️ REGIME DURATION TRACKER
B64: Concepto: | C64: Cuenta las semanas que el régimen actual se ha mantenido sin cambio. Los regímenes de mercado tienen ciclos: se forman, maduran, y eventualmente revierten. La duración ayuda a calibrar el riesgo de reversión y ajustar la convicción.
B66: 0-3 semanas: 🟢 EARLY REGIME | C66: Régimen recién establecido. Ventana de oportunidad. Convicción aún en construcción.
B67: 4-25 semanas: 🟡 MID REGIME | C67: Régimen maduro y confiable. Posicionamiento normal según el score.
B68: 26-51 sem: ⚠️ LATE | 52+: 🔴 EXTENDED | C68: Late: Cautela, considerar toma de ganancias gradual. Extended: Riesgo de reversión históricamente elevado.
A70: 🎯 ÁRBOL DE DECISIÓN RÁPIDA — ¿Qué hago hoy?
A72: PASO 1: | B72: ¿Hay Override activo? (VIX>25, HY>400, P/C>1.2, BR<50%, WTI≥$100, 10Y≥5%)
B73: → SÍ: Subir cash +5% sobre nivel de régimen. Solo comprar Core A+ (B1≥85). Ir a Paso 2.
B74: → NO pero 10Y 4.5-4.99%: Cash sin cambio, pero restringir compras a Core A+. Ir a Paso 2.
B75: → NO: Ir directamente a Paso 2.
A76: PASO 2: | B76: ¿Dónde está el Combined Score?
B77: ≥75 → ⚠️ PRECAUCIÓN. Tomar beneficios parciales (10-15%). Cash 8-12%. NO abrir posiciones nuevas. | C77: Backtest: avg 1M fwd = -3.8%
B78: 60-74 → ✅ NORMAL. Seguir allocation de B1. Mantener posiciones. Cash 5-8%. | C78: Zona óptima del modelo
B79: 45-59 → 🛡️ DEFENSIVO. Trim high-beta. Solo comprar B1≥80. Cash 10-12%. | C79: Subir calidad, reducir beta
B80: 35-44 → 🔴 PROTECCIÓN + 1ª compra oportunista (25%). Cash 12-18%. Solo Core A+ (B1≥85 + Upside>15%). | C80: Proteger primero, comprar después
B81: <35 → 🔴🟢 MÁX PROTECCIÓN + 2ª/3ª compra (50%). Cash 15-20%. B1≥80 + Upside>10%. | C81: Backtest: avg 1M fwd = +4.4%
A83: PASO 3: | B83: ¿Divergencia Macro vs Technical > 30 pts?
B84: → SÍ: Reducir sizing de posiciones nuevas al 50%. Esperar convergencia antes de full size.
B85: → NO: Operar con convicción plena según Paso 2.

Sheet 📋 Sources
A1: 📋 DATA SOURCES — Market Regime Dashboard
A2: AI Investing Dashboard | Marango Fund | All data sources for Bloque 5 with URLs and update frequencies
A3: Last Updated: 24-Feb-2026
A5: 📊 SENTIMENT & SYSTEMIC RISK INDICATORS
A6: # | B6: Indicator | C6: Primary Source | D6: URL | E6: Frequency | F6: Notes / Lag
A7: 1 | B7: VIX (Volatility Index) | C7: CBOE / Investing.com | D7: cboe.com/tradable-products/vix investing.com/indices/volatility-s-p-500-historical-data | E7: Daily (close) | F7: Actualizar cada lunes con cierre del viernes
A8: 2 | B8: HY Credit Spreads (bps) | C8: FRED (ICE BofA HY OAS) | D8: fred.stlouisfed.org/series/BAMLH0A0HYM2 | E8: Daily (close) | F8: FRED publica con 1 día de retraso
A9: 3 | B9: Put/Call Ratio | C9: yCharts (CBOE Equity P/C) | D9: ycharts.com/indicators/cboe_equity_put_call_ratio | E9: Daily | F9: Usar Equity Put/Call, no Total
A10: 4 | B10: Market Breadth (% > 200d MA) | C10: StreetStats / MacroMicro | D10: streetstats.finance/markets/breadth-momentum/SP500 macromicro.me/series/22718/sp-500-200ma-breadth | E10: Daily (EOD) | F10: Input en decimal (0.678 = 67.8%)
A12: 5 | B12: VIX Term Structure (VIX/VIX3M) | C12: CBOE / VIX Central | D12: cboe.com/tradable-products/vix/term-structure/ vixcentral.com | E12: Daily | F12: Ratio VIX spot / VIX3M. >1.0 = backwardation (stress). <0.85 = contango (calm). V5 new.
A13: 📈 TECHNICAL INDICATORS — S&P 500
A14: # | B14: Indicator | C14: Primary Source | D14: URL | E14: Frequency | F14: Notes / Lag
A15: 1 | B15: S&P 500 Close Price | C15: FRED / Yahoo Finance | D15: fred.stlouisfed.org/series/SP500 finance.yahoo.com/quote/%5EGSPC/ | E15: Daily (close) | F15: FRED actualiza ~7PM CST mismo día
A16: 2 | B16: S&P 500 MA-200 / MA-50 | C16: Investing.com (Technical) | D16: investing.com/indices/us-spx-500-technical | E16: Daily | F16: Usar Simple Moving Average, no EMA
A17: 3 | B17: Golden / Death Cross | C17: Calculado automáticamente | D17: N/A — Se actualiza al ingresar MA-50 y MA-200 | E17: Auto | F17: MA50 vs MA200 en celdas B53/C53
A18: 4 | B18: RSI (14-Day) | C18: Investing.com (S&P 500) | D18: investing.com/indices/us-spx-500-technical | E18: Daily | F18: Usar RSI del índice S&P 500, no SPY ETF
A19: 5 | B19: MACD (12,26,9) | C19: Investing.com (S&P 500) | D19: investing.com/indices/us-spx-500-technical | E19: Daily | F19: Valor del MACD line (no signal ni histogram)
A20: 6 | B20: CBOE Skew Index | C20: MacroMicro / CBOE | D20: macromicro.me/series/4407/cboe-skew cboe.com/us/indices/dashboard/skew/ | E20: Weekly | F20: ⚠️ Retraso ~2 semanas en MacroMicro
A22: 💧 LIQUIDITY MONITOR
A23: # | B23: Indicator | C23: Primary Source | D23: URL | E23: Frequency | F23: Notes / Lag
A24: 1 | B24: M2 Money Supply YoY % | C24: FRED (M2SL series) | D24: fred.stlouisfed.org/series/M2SL | E24: Monthly | F24: ⚠️ Retraso ~4 semanas. Input decimal (0.046 = 4.6%)
A25: 2 | B25: Fed Balance Sheet ($T) | C25: Fed H.4.1 / FRED (WALCL) | D25: federalreserve.gov/releases/h41/current/ fred.stlouisfed.org/series/WALCL | E25: Weekly (Thu) | F25: Publicado jueves ~4:30PM ET. Usar Total Assets.
A26: 3 | B26: Fed Balance Sheet YoY % | C26: FRED (WALCL) | D26: fred.stlouisfed.org/series/WALCL | E26: Weekly | F26: Calculado: BS actual / BS hace 1 año. Input decimal.
A27: 4 | B27: Fed Funds Rate (%) | C27: Federal Reserve (FOMC) | D27: federalreserve.gov/newsevents/pressreleases.htm | E27: ~6 weeks | F27: Solo cambia en reuniones FOMC (8x/año). Usar midpoint.
A28: 5 | B28: Reverse Repo Facility ($B) | C28: FRED (RRPONTSYD) | D28: fred.stlouisfed.org/series/RRPONTSYD | E28: Daily | F28: ON RRP cerca de cero desde Jan 2026 (~$6B)
A29: 6 | B29: Net Liquidity Index ($B) | C29: Calculado | D29: fiscaldata.treasury.gov/datasets/daily-treasury-statement/ | E29: Weekly | F29: Fórmula: Fed BS − TGA − RRP. TGA del Daily Treasury Statement.
A30: 7 | B30: 2Y-10Y Yield Curve (%) | C30: FRED (T10Y2Y series) | D30: fred.stlouisfed.org/series/T10Y2Y | E30: Daily | F30: Spread 10Y-2Y. Positivo = normal, negativo = invertido.
A31: 8 | B31: SOFR Spread (bps) | C31: NY Fed / FRED (SOFR) | D31: fred.stlouisfed.org/series/SOFR | E31: Daily | F31: Calcular: (SOFR - Fed Funds Target midpoint) × 100. Reemplaza TED Spread.
A32: 9 | B32: DXY (Dollar Index) | C32: Yahoo Finance / Investing.com | D32: finance.yahoo.com/quote/DX-Y.NYB/ investing.com/indices/usdollar | E32: Daily (close) | F32: Actualizar cada lunes con cierre del viernes
A33: 10 | B33: Gold/SPX Ratio | C33: Calculado | D33: fortune.com (gold price daily) + SPX from dashboard | E33: Weekly | F33: Fórmula: Gold Price ($/oz) ÷ S&P 500 level. Input con 3 decimales.
A35: 11 | B35: MOVE Index (Bond Vol) | C35: Yahoo Finance / ICE BofAML | D35: finance.yahoo.com/quote/%5EMOVE/ investing.com/indices/ice-bofaml-move-historical-data | E35: Daily (close) | F35: <60 Risk-On, 60-100 Neutral, >120 Risk-Off. "VIX of bonds". V5 new.
A36: 🔄 ALTERNATIVE & BACKUP SOURCES
A37: # | B37: Indicator | C37: Backup Source | D37: URL | E37: When to Use | F37: Notes
A38: 1 | B38: VIX | C38: Yahoo Finance (^VIX) | D38: finance.yahoo.com/quote/%5EVIX/ | E38: Si CBOE no disponible | F38: Historical data también disponible
A39: 2 | B39: HY Spreads | C39: Trading Economics | D39: tradingeconomics.com/united-states/bofa-merrill-lynch-us-high-yield-option-adjusted-spread-fed-data.html | E39: Para dato rápido | F39: Muestra % (2.86% = 286 bps)
A40: 3 | B40: Put/Call Ratio | C40: MacroMicro (Total P/C) | D40: macromicro.me/charts/449/us-cboe-options-put-call-ratio | E40: Si yCharts no disponible | F40: Total ratio, no solo Equity
A41: 4 | B41: Market Breadth | C41: Investing.com (S5TH) | D41: investing.com/indices/sp-500-stocks-above-200-day-average | E41: Si StreetStats no disponible | F41: Datos históricos disponibles
A42: 5 | B42: S&P 500 Technicals | C42: TipRanks / Barchart | D42: tipranks.com/etf/spy/technical-analysis barchart.com/etfs-funds/quotes/SPY/technical-analysis | E42: Cross-check RSI/MACD | F42: SPY como proxy del S&P 500
A43: 6 | B43: Fed Balance Sheet | C43: American Action Forum | D43: americanactionforum.org/insight/tracker-the-federal-reserves-balance-sheet/ | E43: Resumen visual semanal | F43: Tracker actualizado semanalmente
A45: ⚠️ DATA LAG & REFRESH SCHEDULE
A46: 🟢 | B46: Refresh: Every Monday AM | C46: VIX, HY Spreads, Put/Call, S&P 500, RSI, MACD, RRP, DXY, SOFR Spread, 2Y-10Y Yield Curve, Gold/SPX
A47: 🟡 | B47: Refresh: Every Thursday PM / Friday AM | C47: Fed Balance Sheet, Fed BS YoY, Net Liquidity, CBOE Skew
A48: 🔴 | B48: Refresh: When new data released | C48: M2 Money Supply (~monthly, 4wk lag) | Fed Funds Rate (~6wk FOMC cycle)
A50: 📝 WEEKLY UPDATE WORKFLOW
A51: 1️⃣ | B51: Move current values to 'Last Week' column (L) | C51: Sentiment (L7:L10), Technical (K55:K60), Liquidity (L67:L76)
A52: 2️⃣ | B52: Update 'Current Value' cells with new data | C52: Sentiment (C7:C10), Technical (B55:B60, C55:C56), Liquidity (C67:C76)
A53: 3️⃣ | B53: Update date labels in dashboard | C53: K5, J53, K69, A35
A54: 4️⃣ | B54: Update 'Weeks in Current Regime' (C22) | C54: Increment +1 if regime unchanged, reset to 0 if changed
A55: 5️⃣ | B55: Snapshot Historical Log | C55: Copy row 5 of Historical Log → paste as VALUES in next row

Sheet 📊 Backtest
A1: 📊 HISTORICAL BACKTEST — Market Regime Model Validation
A2: AI Investing Dashboard | Marango Fund | Backtest of V5 scoring methodology across 25 key market dates (2015-2026)
A3: V5 Accuracy: 92% (22/24) + 2 partial | 0 false negatives in any crisis | V5 thresholds recalculated 06-Mar-2026
A5: # | B5: Date | C5: Market Event | D5: S&P 500 | E5: VIX | F5: 🌐 Sentiment | G5: 📊 Technical | H5: 💧 Liquidity | I5: 🎯 Combined | J5: Model Regime | K5: Expected Regime | L5: Match? | M5: Triggers Active | N5: S&P 1M Fwd
A6: 1 | B6: 43847 | C6: Pre-COVID Bull Peak | D6: 3329.62 | E6: 12.1 | F6: 87.6 | G6: 93.3 | H6: 69.3 | I6: 84.1 | J6: Clear Risk-On | K6: Risk-On | L6: ✅ | M6: None | N6: 0.02
A7: 2 | B7: 43889 | C7: COVID Fear Begins | D7: 2954.22 | E7: 40.11 | F7: 22.6 | G7: 19.2 | H7: 69.5 | I7: 35.5 | J7: Risk-Off (Moderate) | K7: Deteriorating | L7: ✅ | M7: VIX>25, HY>400, P/C>1.2, BR<50% | N7: -0.125
A8: 3 | B8: 43913 | C8: COVID Crash Bottom | D8: 2237.4 | E8: 61.59 | F8: 2.6 | G8: 15 | H8: 76.1 | I8: 29 | J8: Clear Risk-Off | K8: Clear Risk-Off | L8: ✅ | M8: VIX>25, HY>400, P/C>1.2, BR<50% | N8: 0.128
A9: 4 | B9: 43990 | C9: V-Shape Recovery | D9: 3232.39 | E9: 24.52 | F9: 53.2 | G9: 88.5 | H9: 99.7 | I9: 79.5 | J9: Risk-On (Moderate) | K9: Risk-On (Moderate) | L9: ✅ | M9: HY>400 | N9: 0.018
A10: 5 | B10: 44564 | C10: Rate Hike Fears Begin | D10: 4796.56 | E10: 16.6 | F10: 84.3 | G10: 85 | H10: 81.5 | I10: 83.7 | J10: Clear Risk-On | K10: Deteriorating | L10: ⚠️ | M10: None | N10: -0.053
A11: 6 | B11: 44725 | C11: Bear Market Confirmed | D11: 3749.63 | E11: 34.02 | F11: 18.9 | G11: 4.3 | H11: 69.6 | I11: 29 | J11: Clear Risk-Off | K11: Risk-Off | L11: ✅ | M11: VIX>25, HY>400, BR<50% | N11: -0.022
A12: 7 | B12: 44846 | C12: Bear Market Bottom | D12: 3577.03 | E12: 32.02 | F12: 17.5 | G12: 5 | H12: 57.9 | I12: 25.2 | J12: Clear Risk-Off | K12: Clear Risk-Off | L12: ✅ | M12: VIX>25, HY>400, P/C>1.2, BR<50% | N12: 0.08
A13: 8 | B13: 44928 | C13: 2023 Recovery Start | D13: 3824.14 | E13: 21.67 | F13: 54.5 | G13: 21.1 | H13: 47.2 | I13: 40.6 | J13: Risk-Off (Moderate) | K13: Neutral → Risk-On | L13: ✅ | M13: HY>400 | N13: 0.062
A14: 9 | B14: 45226 | C14: 10% Correction Low | D14: 4117.37 | E14: 21.27 | F14: 48.1 | G14: 18.1 | H14: 48.2 | I14: 37.6 | J14: Risk-Off (Moderate) | K14: Risk-Off (Moderate) | L14: ✅ | M14: HY>400, BR<50% | N14: 0.089
A15: 10 | B15: 45299 | C15: AI Bull Run Starts | D15: 4763.54 | E15: 13.35 | F15: 86.3 | G15: 95 | H15: 54.8 | I15: 79.9 | J15: Risk-On (Moderate) | K15: Risk-On | L15: ✅ | M15: None | N15: 0.016
A16: 11 | B16: 45509 | C16: VIX Spike / Yen Carry Unwind | D16: 5186.33 | E16: 38.57 | F16: 35.7 | G16: 35 | H16: 49 | I16: 39.4 | J16: Risk-Off (Moderate) | K16: Risk-Off (Brief) | L16: ✅ | M16: VIX>25, P/C>1.2 | N16: 0.023
A17: 12 | B17: 45754 | C17: Tariff Crisis | D17: 5062.25 | E17: 46.98 | F17: 17.4 | G17: 2.9 | H17: 57.5 | I17: 24.4 | J17: Clear Risk-Off | K17: Risk-Off | L17: ✅ | M17: VIX>25, HY>400, P/C>1.2, BR<50% | N17: 0.094
... A29: 24 | B29: 44526 | C29: Omicron Variant Shock | D29: 4594.62 | E29: 28.62 | F29: 37.8 | G29: 68 | H29: 85 | I29: 62.5 | J29: Risk-On (Moderate) | K29: Risk-On (Moderate) | L29: ✅ | M29: VIX>25 | N29: 0.043
A30: — | B30: 46079 | C30: Current (Baseline) | D30: 6946.13 | E30: 17.93 | F30: 84.1 | G30: 60 | H30: 70 | I30: 71.4 | J30: Risk-On (Moderate) | K30: Risk-On (Moderate) | L30: 📌 | M30: None | N30: N/A
A32: 🎯 MODEL VALIDATION SUMMARY
A34: Metric | B34: Value | C34: Rating | E34: KEY FINDINGS
A35: Overall Accuracy | B35: 92% (22/24) | C35: ⭐⭐⭐⭐⭐ | E35: 1 | F35: V5 correctly identified ALL 12 risk-off events across 11 years (China 2015, Brexit, Q4 2018, COVID, SVB, 2022 Bear, Tariff Crisis). Zero false negatives.
A36: Risk-Off Detection | B36: 100% (12/12) | C36: ⭐⭐⭐⭐⭐ | E36: 2 | F36: Risk-Off detection remains perfect at 100% (12/12). VIX ceiling tightening (25→22) improved early-stage detection without adding false positives.
A37: Risk-On Detection | B37: 100% (10/10) | C37: ⭐⭐⭐⭐⭐ | E37: 3 | F37: V-Shape Recovery (Jun 2020) now correctly classified as Risk-On (Moderate) instead of Clear Risk-On — matches expected regime perfectly.
A38: Transition Detection | B38: 0% (0/2) + 2 partial | C38: ⭐⭐ | E38: 4 | F38: Neutral zone expansion (45-59) did not reclassify Jan 2023 (40.6) but tighter VIX scoring pushes marginal events further from boundary, improving separation.
A39: False Negatives (Crisis) | B39: 0 | C39: ✅ Perfect | E39: 5 | F39: MOVE Index and VIX Term Structure added as V5 indicators — no historical data for backtest recalculation, but forward model includes both.
A40: Avg Risk-Off Score | B40: 32.1 / 100 | C40: Clear signal | E40: 6 | F40: Trump Rally 2016, Repo Crisis 2019, Omicron 2021 all correctly maintained as Risk-On under V5 — no regression on non-crisis events.
A41: Avg Risk-On Score | B41: 74.8 / 100 | C41: Clear signal | E41: 7 | F41: Combined score separation improved: Risk-On avg 74.8 vs Risk-Off avg 32.1 (42.7pt gap). Cleaner signal than V4 (43.1pt gap at 75.5 vs 32.4).
A43: ⚠️ KNOWN LIMITATIONS | E43: 🛠️ SUGGESTED THRESHOLD ADJUSTMENTS
A44: 1. Lagging in early-stage deterioration | E44: # | F44: Adjustment | G44: Status
A45: Jan 2022: Score was 83.7 (Risk-On) one month before -20% decline | E45: 1 | F45: Add yield curve (2Y-10Y) indicator | G45: ✅ DONE (V4)
A46: Model relies on realized indicators, not forward-looking ones | E46: 2 | F46: Increase CBOE Skew weight: 5% → 8% (reduce MA-200 25% → 22%) | G46: ✅ DONE (V5)
E47: 3 | F47: Lower VIX neutral ceiling: 25 → 22 (scoring formula) | G47: ✅ DONE (V5)
A48: 2. Transition detection is weakest area | E48: 4 | F48: Widen Neutral zone: 50-59 → 45-59 (regime classification) | G48: ✅ DONE (V5)
A49: Jan 2023: Model said Risk-Off (40.6) when market was about to rally +6% | E49: 5 | F49: Add MOVE Index (bond vol) to Liquidity pillar — Weight 5% (from SOFR 5%→0%) | G49: ✅ DONE (V5)
A50: Jan 2019: Model said Risk-Off (32) when Fed was pivoting — same lagging pattern confirmed | E50: 6 | F50: Add VIX Term Structure (VIX/VIX3M) to Sentiment — Weight 5% (from Put/Call 20%→15%) | G50: ✅ DONE (V5)
A51: Technical score stays depressed until price recovers above MAs — by design, model is conservative | E51: 📝 V5 ADJUSTMENT RATIONALE
A52: Consider: Is it better to be late but safe, or early but risky? | E52: # | F52: Change | G52: Backtest Evidence
E53: 1 | F53: Skew 5%→8%: Elevated Skew (>150) preceded Jan 2022 bear (-20%). Higher weight penalizes complacency earlier. | G53: Jan 2022 case: Skew ~152 but only 5% weight = negligible drag. At 8%, score drops ~2pts → triggers earlier warning.
A54: 📝 METHODOLOGY | E54: 2 | F54: VIX ceiling 25→22: VIX >22 historically precedes further vol spikes. Makes model more sensitive to rising fear. | G54: V-Shape Recovery (VIX 24.5): V4 scored 62, V5 scores 52. Correctly reclassifies from Clear Risk-On to Risk-On (Moderate). 7/12 crisis events had VIX 21-28 in early stages.
A55: All scores recalculated using V5 methodology: VIX ceiling 22 (range 35), Skew 8%/MA200 22%, Neutral 45-59. MOVE & VIX TS not backfilled (no historical data). Backtest covers 25 events (2015-2026). | E55: 3 | F55: Neutral zone 50-59→45-59: Transition zone (40-65) showed 5/7 events rallied +3-8% in 1 month. Avoids false Risk-Off calls at bottoms. | G55: Jan 2023 (40.6): model still says Risk-Off, but wider Neutral would catch scores 45-49. Brexit (42.0): stays Risk-Off. No false reclassification.
A56: Indicator values sourced from FRED, Yahoo Finance, CBOE, and Investing.com historical data | E56: 4 | F56: MOVE Index + VIX Term Structure: Added as V5 forward indicators. No historical backfill possible, but improve real-time regime detection. | G56: MOVE <60 = low bond vol (Risk-On). VIX/VIX3M >1.0 = backwardation (Risk-Off). Both capture regime shifts not visible in equity-only indicators.
A57: Some values are approximations where exact daily data was unavailable (marked where applicable)

Sheet 🔗 B1↔B5 Bridge
A1: 🔗 BLOQUE 1 ↔ BLOQUE 5 — REGIME-ADJUSTED ALLOCATION BRIDGE
A2: AI Investing Dashboard | Marango Fund | Market Regime modulates B1 position sizing and sector rotation
A3: Regime data from B5 - Market Regime | Company scores from Bloque 1 - Financial Scoring V3 | Updated: 23-Mar-2026
A5: 🎯 CURRENT MARKET REGIME (from B5)
A7: Combined Score | B7: 44 | D7: Regime Zone | E7: Score | F7: Cash % | G7: Action on B1 Portfolio | H7: Buy Filter | I7: Sell Filter | J7: Sector Tilt
A8: Regime | B8: 🚨 RISK-OFF (Override: VIX Spike + Breadth Collapse) | D8: ⚠️ PRECAUCIÓN | E8: ≥75 | F8: 8-12% | G8: Tomar beneficios 10-15%. Reducir cíclicos. | H8: Solo Core A+ | I8: Upside <0% o Score <70 | J8: Reducir Growth
A9: Sentiment | B9: 60 | D9: ✅ NORMAL | E9: 60-74 | F9: 5-8% | G9: Allocation según B1 Financial Scoring | H9: Per B1 signals | I9: Per B1 signals | J9: Balanced
A10: Technical | B10: 10 | D10: → ACTUAL ← | E10: 45-59 | F10: 10-12% | G10: Subir calidad. Solo B1 Score≥80. | H10: Score≥80 + Upside>10% | I10: Score<70 o Avoid band | J10: Defensivo / Quality
A11: Liquidity | B11: 65 | D11: 🔴 PROTECCIÓN + 1ª compra | E11: 35-44 | F11: 12-18% | G11: Reducir bulk + 1ª compra oportunista (25%) | H11: B1≥85 + Upside>15% | I11: Todo Avoid + Upside<-20% | J11: Healthcare/Staples
A12: Circuit Breaker | B12: 🚨 VIX Spike + Breadth Collapse ACTIVE | D12: 🔴🟢 MÁX + 2ª/3ª compra | E12: <35 | F12: 15-20% | G12: Máx protección + compras oportunistas (50%) | H12: B1≥80 + Upside>10% | I12: Solo mantener quality | J12: Max Defensivo
A13: Date | B13: 46086 | D13: 🚨 Override (VIX/HY/PC/BR/WTI) | E13: Cualquier | F13: +5% sobre nivel | G13: Añadir 5% cash. VIX>25, HY>400, P/C>1.2, BR<50%, WTI≥$100 | H13: Solo Core A+ | I13: Trim non-Core | J13: Max Defensivo
D14: ⚠️ 10Y Watch (4.5-4.99%) | E14: Cualquier | F14: Sin cambio | G14: No sube cash. Solo restringe compras a Core A+. | H14: Solo Core A+ (B1≥85) | I14: Per régimen base | J14: 10Y≥5% → Override real
A16: 📊 REGIME-FILTERED ACTIONABLE PICKS (Current: Neutral + Override)
A18: ✅ BUY / ACCUMULATE (Score ≥80 + Upside >10% + Core A/A+ band)
A19: Ticker | B19: Company | C19: Sector | D19: B1 Score | E19: Band | F19: Upside % | G19: B1 Signal | H19: Regime Action | I19: Size | J19: Rationale
A20: NVDA | B20: NVIDIA Corp | C20: Info Tech | D20: 92 | E20: 🟢 Core A+ | F20: 0.315 | G20: 🚀 STRONG BUY | H20: ✅ ACCUMULATE | I20: 6-8% | J20: Top score + high upside. Buy on dips.
A21: META | B21: Meta Platforms | C21: Comm. Svc. | D21: 88 | E21: 🟢 Core A+ | F21: 0.275 | G21: 🚀 STRONG BUY | H21: ✅ ACCUMULATE | I21: 4-6% | J21: Strong fundamentals + momentum.
A22: MSFT | B22: Microsoft Corp | C22: Info Tech | D22: 82 | E22: 🔵 Core A | F22: 0.484 | G22: ✅ BUY | H22: ✅ ACCUMULATE | I22: 2-4% | J22: Highest upside in Core. AI tailwind.
A23: GOOGL | B23: Alphabet Inc | C23: Comm. Svc. | D23: 88 | E23: 🟡 Satélite | F23: 0.121 | G23: ✅ BUY | H23: ✅ ACCUMULATE | I23: 2-4% | J23: Score 88 + positive upside. Quality name.
A25: ⚠️ HOLD / REDUCE SIZE (Override active → trim non-Core positions)
A26: Ticker | B26: Company | C26: Sector | D26: B1 Score | E26: Band | F26: Upside % | G26: B1 Signal | H26: Regime Action | I26: Size | J26: Rationale
A27: UNH | B27: UnitedHealth Group | C27: Health Care | D27: 76 | E27: 🔵 Core A | F27: 0.471 | G27: ⚠️ HOLD | H27: ⚠️ HOLD (defensive) | I27: 2-4% | J27: Core A but HC sector = defensive hedge.
A28: AVGO | B28: Broadcom Inc | C28: Info Tech | D28: 75 | E28: 🔵 Core A | F28: 0.501 | G28: ✅ BUY | H28: ⚠️ HOLD (trim to min) | I28: 0.02 | J28: High upside but score borderline. Trim.
A29: BRK.B | B29: Berkshire Hathaway | C29: Financials | D29: 82 | E29: 🟡 Satélite | F29: 0.052 | G29: 🚀 STRONG BUY | H29: ⚠️ HOLD (safe haven) | I29: 2-4% | J29: Cash-rich. Natural hedge in volatility.
A30: JPM | B30: JPMorgan Chase | C30: Financials | D30: 84 | E30: ⚪ Opcional | F30: -0.03 | G30: 🚀 STRONG BUY | H30: ⚠️ REDUCE | I30: 0-2% | J30: Score high but Opcional band + negative upside.
A31: PG | B31: Procter & Gamble | C31: Cons. Staples | D31: 83 | E31: ⚪ Opcional | F31: -0.062 | G31: ⚠️ HOLD | H31: ⚠️ HOLD (defensive) | I31: 1-2% | J31: Overvalued but defensive. Keep small.
A32: LLY | B32: Eli Lilly & Co | C32: Health Care | D32: 86 | E32: ⚪ Opcional | F32: -0.129 | G32: ✅ BUY | H32: ⚠️ REDUCE | I32: 0-1% | J32: Great company, overvalued. Wait for pullback.
A34: 🔴 SELL / AVOID (Score <70 OR Upside <-15% OR Avoid band + Override active)
A35: Ticker | B35: Company | C35: Sector | D35: B1 Score | E35: Band | F35: Upside % | G35: B1 Signal | H35: Regime Action | I35: Size | J35: Rationale
A36: FCX | B36: Freeport-McMoRan | C36: Materials | D36: 84 | E36: 🔴 Avoid | F36: -0.551 | G36: 🟠 REDUCE | H36: 🔴 SELL | I36: 0 | J36: -55% upside. Cyclical in risk-off. Exit.
A37: CAT | B37: Caterpillar Inc | C37: Industrials | D37: 87 | E37: ⚪ Opcional | F37: -0.162 | G37: ✅ BUY | H37: 🔴 SELL | I37: 0 | J37: Cyclical + -16% upside. Override active.
A38: WMT | B38: Walmart Inc | C38: Cons. Staples | D38: 69 | E38: 🔴 Avoid | F38: -0.512 | G38: ⚠️ HOLD | H38: 🔴 SELL | I38: 0 | J38: -51% overvalued. Low score. Exit.
A39: COST | B39: Costco Wholesale | C39: Cons. Staples | D39: 63 | E39: 🔴 Avoid | F39: -0.351 | G39: 🔴 SELL | H39: 🔴 SELL | I39: 0 | J39: -35% overvalued. Avoid band. Exit.
A40: TXN | B40: Texas Instruments | C40: Info Tech | D40: 56 | E40: 🔴 Avoid | F40: 0.03 | G40: 🔴 SELL | H40: 🔴 SELL | I40: 0 | J40: Lowest score. No upside. Exit.
A41: PLD | B41: Prologis Inc | C41: Real Estate | D41: 59 | E41: 🔴 Avoid | F41: -0.066 | G41: 🔴 SELL | H41: 🔴 SELL | I41: 0 | J41: Weak score + negative upside. Exit.
A43: 📈 COMPRAS OPORTUNISTAS ESCALONADAS (solo en Risk-Off)
A44: Priority | B44: Ticker | C44: Company | D44: B1 Score | E44: Upside % | F44: Current Band | G44: Why Contrarian Buy
A45: 1st | B45: NVDA | C45: NVIDIA Corp | D45: 92 | E45: 0.315 | F45: 🟢 Core A+ | G45: Best score in universe + 31% upside. First buy in panic.
A46: 2nd | B46: META | C46: Meta Platforms | D46: 88 | E46: 0.275 | F46: 🟢 Core A+ | G46: Core A+ with 28% upside. Strong FCF protects in downturns.
A47: 3rd | B47: MSFT | C47: Microsoft Corp | D47: 82 | E47: 0.484 | F47: 🔵 Core A | G47: 48% upside — most undervalued Core name. Cloud + AI moat.
A48: 4th | B48: AMZN | C48: Amazon.com Inc | D48: 74 | E48: 0.212 | F48: 🟡 Satélite | G48: 21% upside. Score improving. AWS + retail recovery.
A49: 5th | B49: UNH | C49: UnitedHealth Group | D49: 76 | E49: 0.471 | F49: 🔵 Core A | G49: 47% upside + defensive healthcare. Best Risk-Off hedge.
A51: 💼 PORTFOLIO ALLOCATION SUMMARY (Regime-Adjusted)
A53: Category | B53: B1 Normal % | C53: Regime-Adj % | D53: Delta | E53: Names
A54: 🟢 Core A+ (Buy) | B54: 10-14% | C54: 10-14% | D54: → maintain | E54: NVDA, META
A55: 🔵 Core A (Buy/Hold) | B55: 12-20% | C55: 8-14% | D55: ↓ reduced | E55: MSFT, GOOGL, UNH, AVGO
A56: 🟡 Satélite (Hold) | B56: 6-12% | C56: 4-8% | D56: ↓ reduced | E56: BRK.B, AMZN, AMT
A57: ⚪ Opcional (Trim) | B57: 15-25% | C57: 5-10% | D57: ↓↓ heavy trim | E57: JPM, PG, LLY, V, AAPL...
A58: 🔴 Avoid (Exit) | B58: 0 | C58: 0 | D58: → exit all | E58: FCX, WMT, COST, TXN, PLD...
A59: 💵 Cash + Hedges | B59: 0.05 | C59: 13-17% | D59: ↑↑ +8-12% | E59: Neutral(8-12%) + Override(+5%)
A61: 📝 METODOLOGÍA — MODELO HÍBRIDO ESCALONADO
A62: FILOSOFÍA: La base del portfolio es PRO-CÍCLICA (proteger en Risk-Off, exponerse en Risk-On). Pero se reserva un 15-20% para COMPRAS OPORTUNISTAS escalonadas cuando el mercado entra en pánico (Score <44). Backtest: las compras en Clear Risk-Off generan +4.4% avg en 1 mes.
A63: REGLA DE ORO: Proteger PRIMERO (subir cash, trim non-Core), comprar DESPUÉS (solo si hay cash disponible y solo en Core A+ con B1 Score≥85 y Upside>15%). Nunca sacrificar protección por oportunismo.
A64: COMPRAS ESCALONADAS: 1ª compra (25% de reserva) a Score 35-44 | 2ª compra (25%) a Score <35 | 3ª compra (50% restante) a Score <25 o VIX>40. Siempre en 3 tranches, nunca all-in.
A65: OVERRIDE: Cuando hay Circuit Breaker activo, se añade +5% cash sobre el nivel del régimen. Solo se compra Core A+ independientemente del score. El Override protege contra la falsa seguridad de un score "bueno" con estrés puntual extremo.
A66: ACTUALIZAR cuando: (1) B5 cambia de zona, (2) B1 scores actualizan post-earnings, (3) Circuit Breaker se activa/desactiva. Este puente NO reemplaza el B1 Rebalancing — añade un overlay macro.
A68: 🛡️ PLAN DE ACCIÓN CARTERA REAL — RÉGIMEN DEFENSIVO + TT Watch (06-Mar-2026)
A69: Score 57.8 (Defensivo) + TT informativo | Cash actual: 5% | Cash objetivo: 10-12% | Liberar ~€1.1M | Compras: solo Core A+
A71: # | B71: Ticker | C71: Peso actual | D71: Acción | E71: % a vender | F71: € liberados | G71: Cash acum % | H71: B1 Score | I71: Upside | J71: Rationale
A72: 1 | B72: LLY | C72: 0.027 | D72: 🔴 VENDER 100% | E72: 1 | F72: 496005 | G72: 0.077 | H72: 86 | I72: -0.129 | J72: Opcional band + Upside -12.9%. Sobrevalor extremo.
A73: 2 | B73: TSLA | C73: 0.021 | D73: 🔴 REDUCIR 50% | E73: 0.5 | F73: 199934 | G73: 0.087 | H73: N/A | I73: N/A | J73: Sin B1. High-beta Cons Disc. Máximo riesgo en defensivo.
A74: 3 | B74: PLTR | C74: 0.013 | D74: 🔴 REDUCIR 50% | E74: 0.5 | F74: 125090 | G74: 0.094 | H74: N/A | I74: N/A | J74: Sin B1. Momentum sin fundamentales. Vulnerable en corrección.
A75: 4 | B75: V | C75: 0.056 | D75: ⚠️ REDUCIR 25% | E75: 0.25 | F75: 262169 | G75: ✅ 10.8% | H75: 83 | I75: -0.004 | J75: ✅ TARGET. Opcional band, Upside -0.4%. Mantener 75% como defensivo.
A76: 5 | B76: RMS | C76: 0.03 | D76: ⚠️ REDUCIR 20% | E76: 0.2 | F76: 110010 | G76: 0.114 | H76: N/A | I76: N/A | J76: Opcional si quieres margen extra. Lujo cíclico sin B1.
A78: ⚠️ Triple Tightening activo → NO sube cash, pero RESTRINGE compras a solo Core A+ (B1≥85, Upside>15%). Si VIX cruza 25 o HY cruza 400, se activa Override real.
A83: ✅ NO TOCAR — MANTENER POSICIONES COMPLETAS
A84: Ticker | B84: Peso | C84: Band / Sector | D84: Rationale
A85: NVDA | B85: 0.034 | C85: 🟢 Core A+ | B1=92 | D85: TOP pick. Upside +31.5%. No tocar.
A86: META | B86: 0.041 | C86: 🟢 Core A+ | B1=88 | D86: Upside +27.5%. FCF protege.
A87: MSFT | B87: 0.063 | C87: 🔵 Core A | B1=82 | D87: Mayor upside cartera (+48.4%). Cloud + AI.
A88: BN | B88: 0.057 | C88: Financials (sin B1) | D88: Asset manager diversificado. Defensivo.
A89: SPGI | B89: 0.05 | C89: Financials (sin B1) | D89: Data/Analytics. Modelo resiliente.
A90: MCO | B90: 0.039 | C90: Financials (sin B1) | D90: Duopolio con SPGI. Ingresos recurrentes.
A91: MA | B91: 0.035 | C91: Financials (sin B1) | D91: Payments = defensivo en recesión.
A92: OR | B92: 0.038 | C92: Cons Staples (sin B1) | D92: L'Oréal. Defensivo por naturaleza.
A93: SYK | B93: 0.03 | C93: Healthcare (sin B1) | D93: Stryker. Defensivo + crecimiento.
A94: ISRG | B94: 0.021 | C94: Healthcare (sin B1) | D94: Intuitive Surgical. Moat + secular.
A95: IDXX | B95: 0.021 | C95: Healthcare (sin B1) | D95: IDEXX. Nicho defensivo.
