Workbook
Name GP_BY_Sectors: 'Generic Parameters'!$A$260:$A$270
Name GP_BY_T: 'Generic Parameters'!$B$260:$M$270
Name GP_CR_Sectors: 'Generic Parameters'!$A$120:$A$130
Name GP_CR_T: 'Generic Parameters'!$B$120:$M$130
Name GP_CX_Sectors: 'Generic Parameters'!$A$176:$A$186
Name GP_CX_T: 'Generic Parameters'!$B$176:$M$186
Name GP_DY_Sectors: 'Generic Parameters'!$A$232:$A$242
Name GP_DY_T: 'Generic Parameters'!$B$232:$M$242
Name GP_EG_Sectors: 'Generic Parameters'!$A$78:$A$88
Name GP_EG_T: 'Generic Parameters'!$B$78:$M$88
Name GP_EV_Sectors: 'Generic Parameters'!$A$204:$A$214
Name GP_EV_T: 'Generic Parameters'!$B$204:$M$214
Name GP_FM_Sectors: 'Generic Parameters'!$A$148:$A$158
Name GP_FM_T: 'Generic Parameters'!$B$148:$M$158
Name GP_FN_Sectors: 'Generic Parameters'!$A$162:$A$172
Name GP_FN_T: 'Generic Parameters'!$B$162:$M$172
Name GP_IC_Sectors: 'Generic Parameters'!$A$134:$A$144
Name GP_IC_T: 'Generic Parameters'!$B$134:$M$144
Name GP_ND_Sectors: 'Generic Parameters'!$A$106:$A$116
Name GP_ND_T: 'Generic Parameters'!$B$106:$M$116
Name GP_NM_Sectors: 'Generic Parameters'!$A$50:$A$60
Name GP_NM_T: 'Generic Parameters'!$B$50:$M$60
Name GP_OL_Sectors: 'Generic Parameters'!$A$92:$A$102
Name GP_OL_T: 'Generic Parameters'!$B$92:$M$102
Name GP_PE_Sectors: 'Generic Parameters'!$A$190:$A$200
Name GP_PE_T: 'Generic Parameters'!$B$190:$M$200
Name GP_PF_Sectors: 'Generic Parameters'!$A$218:$A$228
Name GP_PF_T: 'Generic Parameters'!$B$218:$M$228
Name GP_PR_Sectors: 'Generic Parameters'!$A$246:$A$256
Name GP_PR_T: 'Generic Parameters'!$B$246:$M$256
Name GP_RG_Sectors: 'Generic Parameters'!$A$64:$A$74
Name GP_RG_T: 'Generic Parameters'!$B$64:$M$74
Name GP_ROE_Sectors: 'Generic Parameters'!$A$22:$A$32
Name GP_ROE_T: 'Generic Parameters'!$B$22:$M$32
Name GP_ROIC_Sectors: 'Generic Parameters'!$A$36:$A$46
Name GP_ROIC_T: 'Generic Parameters'!$B$36:$M$46
Name GP_W_P1: 'Generic Parameters'!$B$6:$B$16
Name GP_W_P2: 'Generic Parameters'!$C$6:$C$16
Name GP_W_P3: 'Generic Parameters'!$D$6:$D$16
Name GP_W_P4: 'Generic Parameters'!$E$6:$E$16
Name GP_W_P5: 'Generic Parameters'!$F$6:$F$16
Name GP_W_P6: 'Generic Parameters'!$G$6:$G$16
Name GP_Weights_Sectors: 'Generic Parameters'!$A$6:$A$16
Name SP_AT_Sectors: #REF!
Name SP_AT_T: #REF!
Name SP_CC_Sectors: #REF!
Name SP_CC_T: #REF!
Name SP_CR_Sectors: #REF!
Name SP_CR_T: #REF!
Name SP_DSO_Sectors: #REF!
Name SP_DSO_T: #REF!
Name SP_FCF_Sectors: #REF!
Name SP_FCF_T: #REF!
Name SP_GM_Sectors: #REF!
Name SP_GM_T: #REF!
Name SP_IC_Sectors: #REF!
Name SP_IC_T: #REF!
Name SP_ND_Sectors: #REF!
Name SP_ND_T: #REF!
Name SP_OL_Sectors: #REF!

Sheet Generic Scoring
A1: GENERIC EQUITY SCORING MODEL | V1: SECTOR-ADJUSTED SCORING ENGINE | AN1: PILLAR SCORES | AT1: FINAL | AU1: -0.018 | AY1: VALUATION
A2: Cols D-U: Manual inputs | Cols V-AM: Auto-scored | Cols AN-AS: Pillar aggregation | Col AT: Final | AZ2: Consenso/Morningstar | BA2: DCF Simplified | BD2: MOMENTUM / TECHNICAL | BG2: MOMENTUM SCORING | BJ2: P7 | BK2: COMBINED SCORE (F40/V20/M25/TQ15)
A3: Company | B3: GICS Sector | C3: ROE (%) | D3: ROIC (%) | E3: Net Margin (%) | F3: Rev Gr 3Y (%) | G3: EPS Gr 3Y (%) | H3: Op Lev (x) | I3: ND/EBITDA | J3: Curr Ratio | K3: Int Cov (x) | L3: FCF Mar (%) | M3: FCF/NI (x) | N3: Capex/Rev (%) | O3: Fwd P/E | P3: EV/EBITDA | Q3: P/FCF | R3: Div Yield (%) | S3: Payout (%) | T3: Buyback (%) | U3: S.ROE | V3: S.ROIC | W3: S.NM | X3: S.RevGr | Y3: S.EPSGr | Z3: S.OpLev | AA3: S.Debt | AB3: S.CR | AC3: S.IC | AD3: S.FCFm | AE3: S.FCFni | AF3: S.Capex | AG3: S.PE | AH3: S.EVEB | AI3: S.PFCF | AJ3: S.DivY | AK3: S.Payout | AL3: S.Buyb | AM3: P1.Adj | AN3: P2.Adj | AO3: P3.Adj | AP3: P4.Adj | AQ3: P5.Val | AR3: P6.Adj | AS3: SA SCORE | AT3: ROIC 5Y Trend | AU3: Margin Stability | AV3: FCF Consistency | AW3: Trend Quality | AX3: Ticker | AY3: Current Price 🔄 | AZ3: Fair Value | BA3: DCF Fair Value | BB3: Upside % | BD3: Price/SMA200 (%) | BE3: RSI 14 | BF3: Mom 6M (%) | BG3: S.SMA | BH3: S.RSI | BI3: S.Mom | BJ3: P7.Mom | BK3: FVM Score | BL3: FVM Band | BM3: SIGNAL
A4: NVIDIA Corp | B4: Information Technology | C4: 0.9 | D4: 0.75 | E4: 0.55 | F4: 0.94 | G4: 1.2 | H4: 2.1 | I4: -1.5 | J4: 4.2 | K4: 50 | L4: 0.31 | M4: 1.15 | N4: 0.04 | O4: 32 | P4: 28 | Q4: 40 | R4: 0.0003 | S4: 0.01 | T4: 0.01 | U4: =IF(OR($B4="",C4=""),"",IF(ISERROR(MATCH($B4,GP_ROE_Sectors,0)),0,IF(C4>=INDEX(GP_ROE_T,MATCH($B4,GP_ROE_Sectors,0),1),INDEX(GP_ROE_T,MATCH($B4,GP_ROE_Sectors,0),2),IF(C4>=INDEX(GP_ROE_T,MATCH($B4,GP_ROE_Sectors,0),3),INDEX(GP_ROE_T,MATCH($B4,GP_ROE_Sectors,0),4),IF(C4>=INDEX(GP_ROE_T,MATCH($B4,GP_ROE_Sectors,0),5),INDEX(GP_ROE_T,MATCH($B4,GP_ROE_Sectors,0),6),IF(C4>=INDEX(GP_ROE_T,MATCH($B4,GP_ROE_Sectors,0),7),INDEX(GP_ROE_T,MATCH($B4,GP_ROE_Sectors,0),8),IF(C4>=INDEX(GP_ROE_T,MATCH($B4,GP_ROE_Sectors,0),9),INDEX(GP_ROE_T,MATCH($B4,GP_ROE_Sectors,0),10),IF(C4>=INDEX(GP_ROE_T,MATCH($B4,GP_ROE_Sectors,0),11),INDEX(GP_ROE_T,MATCH($B4,GP_ROE_Sectors,0),12),0)))))))) -> 100 | V4: =IF(OR($B4="",D4=""),"",IF(ISERROR(MATCH($B4,GP_ROIC_Sectors,0)),0,IF(D4>=INDEX(GP_ROIC_T,MATCH($B4,GP_ROIC_Sectors,0),1),INDEX(GP_ROIC_T,MATCH($B4,GP_ROIC_Sectors,0),2),IF(D4>=INDEX(GP_ROIC_T,MATCH($B4,GP_ROIC_Sectors,0),3),INDEX(GP_ROIC_T,MATCH($B4,GP_ROIC_Sectors,0),4),IF(D4>=INDEX(GP_ROIC_T,MATCH($B4,GP_ROIC_Sectors,0),5),INDEX(GP_ROIC_T,MATCH($B4,GP_ROIC_Sectors,0),6),IF(D4>=INDEX(GP_ROIC_T,MATCH($B4,GP_ROIC_Sectors,0),7),INDEX(GP_ROIC_T,MATCH($B4,GP_ROIC_Sectors,0),8),IF(D4>=INDEX(GP_ROIC_T,MATCH($B4,GP_ROIC_Sectors,0),9),INDEX(GP_ROIC_T,MATCH($B4,GP_ROIC_Sectors,0),10),IF(D4>=INDEX(GP_ROIC_T,MATCH($B4,GP_ROIC_Sectors,0),11),INDEX(GP_ROIC_T,MATCH($B4,GP_ROIC_Sectors,0),12),0)))))))) -> 100 | W4: =IF(OR($B4="",E4=""),"",IF(ISERROR(MATCH($B4,GP_NM_Sectors,0)),0,IF(E4>=INDEX(GP_NM_T,MATCH($B4,GP_NM_Sectors,0),1),INDEX(GP_NM_T,MATCH($B4,GP_NM_Sectors,0),2),IF(E4>=INDEX(GP_NM_T,MATCH($B4,GP_NM_Sectors,0),3),INDEX(GP_NM_T,MATCH($B4,GP_NM_Sectors,0),4),IF(E4>=INDEX(GP_NM_T,MATCH($B4,GP_NM_Sectors,0),5),INDEX(GP_NM_T,MATCH($B4,GP_NM_Sectors,0),6),IF(E4>=INDEX(GP_NM_T,MATCH($B4,GP_NM_Sectors,0),7),INDEX(GP_NM_T,MATCH($B4,GP_NM_Sectors,0),8),IF(E4>=INDEX(GP_NM_T,MATCH($B4,GP_NM_Sectors,0),9),INDEX(GP_NM_T,MATCH($B4,GP_NM_Sectors,0),10),IF(E4>=INDEX(GP_NM_T,MATCH($B4,GP_NM_Sectors,0),11),INDEX(GP_NM_T,MATCH($B4,GP_NM_Sectors,0),12),0)))))))) -> 100 | X4: =IF(OR($B4="",F4=""),"",IF(ISERROR(MATCH($B4,GP_RG_Sectors,0)),0,IF(F4>=INDEX(GP_RG_T,MATCH($B4,GP_RG_Sectors,0),1),INDEX(GP_RG_T,MATCH($B4,GP_RG_Sectors,0),2),IF(F4>=INDEX(GP_RG_T,MATCH($B4,GP_RG_Sectors,0),3),INDEX(GP_RG_T,MATCH($B4,GP_RG_Sectors,0),4),IF(F4>=INDEX(GP_RG_T,MATCH($B4,GP_RG_Sectors,0),5),INDEX(GP_RG_T,MATCH($B4,GP_RG_Sectors,0),6),IF(F4>=INDEX(GP_RG_T,MATCH($B4,GP_RG_Sectors,0),7),INDEX(GP_RG_T,MATCH($B4,GP_RG_Sectors,0),8),IF(F4>=INDEX(GP_RG_T,MATCH($B4,GP_RG_Sectors,0),9),INDEX(GP_RG_T,MATCH($B4,GP_RG_Sectors,0),10),IF(F4>=INDEX(GP_RG_T,MATCH($B4,GP_RG_Sectors,0),11),INDEX(GP_RG_T,MATCH($B4,GP_RG_Sectors,0),12),0)))))))) -> 100 | Y4: =IF(OR($B4="",G4=""),"",IF(ISERROR(MATCH($B4,GP_EG_Sectors,0)),0,IF(G4>=INDEX(GP_EG_T,MATCH($B4,GP_EG_Sectors,0),1),INDEX(GP_EG_T,MATCH($B4,GP_EG_Sectors,0),2),IF(G4>=INDEX(GP_EG_T,MATCH($B4,GP_EG_Sectors,0),3),INDEX(GP_EG_T,MATCH($B4,GP_EG_Sectors,0),4),IF(G4>=INDEX(GP_EG_T,MATCH($B4,GP_EG_Sectors,0),5),INDEX(GP_EG_T,MATCH($B4,GP_EG_Sectors,0),6),IF(G4>=INDEX(GP_EG_T,MATCH($B4,GP_EG_Sectors,0),7),INDEX(GP_EG_T,MATCH($B4,GP_EG_Sectors,0),8),IF(G4>=INDEX(GP_EG_T,MATCH($B4,GP_EG_Sectors,0),9),INDEX(GP_EG_T,MATCH($B4,GP_EG_Sectors,0),10),IF(G4>=INDEX(GP_EG_T,MATCH($B4,GP_EG_Sectors,0),11),INDEX(GP_EG_T,MATCH($B4,GP_EG_Sectors,0),12),0)))))))) -> 100 | Z4: =IF(OR($B4="",H4=""),"",IF(ISERROR(MATCH($B4,GP_OL_Sectors,0)),0,IF(H4>=INDEX(GP_OL_T,MATCH($B4,GP_OL_Sectors,0),1),INDEX(GP_OL_T,MATCH($B4,GP_OL_Sectors,0),2),IF(H4>=INDEX(GP_OL_T,MATCH($B4,GP_OL_Sectors,0),3),INDEX(GP_OL_T,MATCH($B4,GP_OL_Sectors,0),4),IF(H4>=INDEX(GP_OL_T,MATCH($B4,GP_OL_Sectors,0),5),INDEX(GP_OL_T,MATCH($B4,GP_OL_Sectors,0),6),IF(H4>=INDEX(GP_OL_T,MATCH($B4,GP_OL_Sectors,0),7),INDEX(GP_OL_T,MATCH($B4,GP_OL_Sectors,0),8),IF(H4>=INDEX(GP_OL_T,MATCH($B4,GP_OL_Sectors,0),9),INDEX(GP_OL_T,MATCH($B4,GP_OL_Sectors,0),10),IF(H4>=INDEX(GP_OL_T,MATCH($B4,GP_OL_Sectors,0),11),INDEX(GP_OL_T,MATCH($B4,GP_OL_Sectors,0),12),0)))))))) -> 100 | AA4: =IF(OR($B4="",I4=""),"",IF(ISERROR(MATCH($B4,GP_ND_Sectors,0)),0,IF(I4<=INDEX(GP_ND_T,MATCH($B4,GP_ND_Sectors,0),1),INDEX(GP_ND_T,MATCH($B4,GP_ND_Sectors,0),2),IF(I4<=INDEX(GP_ND_T,MATCH($B4,GP_ND_Sectors,0),3),INDEX(GP_ND_T,MATCH($B4,GP_ND_Sectors,0),4),IF(I4<=INDEX(GP_ND_T,MATCH($B4,GP_ND_Sectors,0),5),INDEX(GP_ND_T,MATCH($B4,GP_ND_Sectors,0),6),IF(I4<=INDEX(GP_ND_T,MATCH($B4,GP_ND_Sectors,0),7),INDEX(GP_ND_T,MATCH($B4,GP_ND_Sectors,0),8),IF(I4<=INDEX(GP_ND_T,MATCH($B4,GP_ND_Sectors,0),9),INDEX(GP_ND_T,MATCH($B4,GP_ND_Sectors,0),10),IF(I4<=INDEX(GP_ND_T,MATCH($B4,GP_ND_Sectors,0),11),INDEX(GP_ND_T,MATCH($B4,GP_ND_Sectors,0),12),0)))))))) -> 100 | AB4: =IF(OR($B4="",J4=""),"",IF(ISERROR(MATCH($B4,GP_CR_Sectors,0)),0,IF(J4>=INDEX(GP_CR_T,MATCH($B4,GP_CR_Sectors,0),1),INDEX(GP_CR_T,MATCH($B4,GP_CR_Sectors,0),2),IF(J4>=INDEX(GP_CR_T,MATCH($B4,GP_CR_Sectors,0),3),INDEX(GP_CR_T,MATCH($B4,GP_CR_Sectors,0),4),IF(J4>=INDEX(GP_CR_T,MATCH($B4,GP_CR_Sectors,0),5),INDEX(GP_CR_T,MATCH($B4,GP_CR_Sectors,0),6),IF(J4>=INDEX(GP_CR_T,MATCH($B4,GP_CR_Sectors,0),7),INDEX(GP_CR_T,MATCH($B4,GP_CR_Sectors,0),8),IF(J4>=INDEX(GP_CR_T,MATCH($B4,GP_CR_Sectors,0),9),INDEX(GP_CR_T,MATCH($B4,GP_CR_Sectors,0),10),IF(J4>=INDEX(GP_CR_T,MATCH($B4,GP_CR_Sectors,0),11),INDEX(GP_CR_T,MATCH($B4,GP_CR_Sectors,0),12),0)))))))) -> 100 | AC4: =IF(OR($B4="",K4=""),"",IF(ISERROR(MATCH($B4,GP_IC_Sectors,0)),0,IF(K4>=INDEX(GP_IC_T,MATCH($B4,GP_IC_Sectors,0),1),INDEX(GP_IC_T,MATCH($B4,GP_IC_Sectors,0),2),IF(K4>=INDEX(GP_IC_T,MATCH($B4,GP_IC_Sectors,0),3),INDEX(GP_IC_T,MATCH($B4,GP_IC_Sectors,0),4),IF(K4>=INDEX(GP_IC_T,MATCH($B4,GP_IC_Sectors,0),5),INDEX(GP_IC_T,MATCH($B4,GP_IC_Sectors,0),6),IF(K4>=INDEX(GP_IC_T,MATCH($B4,GP_IC_Sectors,0),7),INDEX(GP_IC_T,MATCH($B4,GP_IC_Sectors,0),8),IF(K4>=INDEX(GP_IC_T,MATCH($B4,GP_IC_Sectors,0),9),INDEX(GP_IC_T,MATCH($B4,GP_IC_Sectors,0),10),IF(K4>=INDEX(GP_IC_T,MATCH($B4,GP_IC_Sectors,0),11),INDEX(GP_IC_T,MATCH($B4,GP_IC_Sectors,0),12),0)))))))) -> 100 | AD4: =IF(OR($B4="",L4=""),"",IF(ISERROR(MATCH($B4,GP_FM_Sectors,0)),0,IF(L4>=INDEX(GP_FM_T,MATCH($B4,GP_FM_Sectors,0),1),INDEX(GP_FM_T,MATCH($B4,GP_FM_Sectors,0),2),IF(L4>=INDEX(GP_FM_T,MATCH($B4,GP_FM_Sectors,0),3),INDEX(GP_FM_T,MATCH($B4,GP_FM_Sectors,0),4),IF(L4>=INDEX(GP_FM_T,MATCH($B4,GP_FM_Sectors,0),5),INDEX(GP_FM_T,MATCH($B4,GP_FM_Sectors,0),6),IF(L4>=INDEX(GP_FM_T,MATCH($B4,GP_FM_Sectors,0),7),INDEX(GP_FM_T,MATCH($B4,GP_FM_Sectors,0),8),IF(L4>=INDEX(GP_FM_T,MATCH($B4,GP_FM_Sectors,0),9),INDEX(GP_FM_T,MATCH($B4,GP_FM_Sectors,0),10),IF(L4>=INDEX(GP_FM_T,MATCH($B4,GP_FM_Sectors,0),11),INDEX(GP_FM_T,MATCH($B4,GP_FM_Sectors,0),12),0)))))))) -> 100 | AE4: =IF(OR($B4="",M4=""),"",IF(ISERROR(MATCH($B4,GP_FN_Sectors,0)),0,IF(M4>=INDEX(GP_FN_T,MATCH($B4,GP_FN_Sectors,0),1),INDEX(GP_FN_T,MATCH($B4,GP_FN_Sectors,0),2),IF(M4>=INDEX(GP_FN_T,MATCH($B4,GP_FN_Sectors,0),3),INDEX(GP_FN_T,MATCH($B4,GP_FN_Sectors,0),4),IF(M4>=INDEX(GP_FN_T,MATCH($B4,GP_FN_Sectors,0),5),INDEX(GP_FN_T,MATCH($B4,GP_FN_Sectors,0),6),IF(M4>=INDEX(GP_FN_T,MATCH($B4,GP_FN_Sectors,0),7),INDEX(GP_FN_T,MATCH($B4,GP_FN_Sectors,0),8),IF(M4>=INDEX(GP_FN_T,MATCH($B4,GP_FN_Sectors,0),9),INDEX(GP_FN_T,MATCH($B4,GP_FN_Sectors,0),10),IF(M4>=INDEX(GP_FN_T,MATCH($B4,GP_FN_Sectors,0),11),INDEX(GP_FN_T,MATCH($B4,GP_FN_Sectors,0),12),0)))))))) -> 88 | AF4: =IF(OR($B4="",N4=""),"",IF(ISERROR(MATCH($B4,GP_CX_Sectors,0)),0,IF(N4<=INDEX(GP_CX_T,MATCH($B4,GP_CX_Sectors,0),1),INDEX(GP_CX_T,MATCH($B4,GP_CX_Sectors,0),2),IF(N4<=INDEX(GP_CX_T,MATCH($B4,GP_CX_Sectors,0),3),INDEX(GP_CX_T,MATCH($B4,GP_CX_Sectors,0),4),IF(N4<=INDEX(GP_CX_T,MATCH($B4,GP_CX_Sectors,0),5),INDEX(GP_CX_T,MATCH($B4,GP_CX_Sectors,0),6),IF(N4<=INDEX(GP_CX_T,MATCH($B4,GP_CX_Sectors,0),7),INDEX(GP_CX_T,MATCH($B4,GP_CX_Sectors,0),8),IF(N4<=INDEX(GP_CX_T,MATCH($B4,GP_CX_Sectors,0),9),INDEX(GP_CX_T,MATCH($B4,GP_CX_Sectors,0),10),IF(N4<=INDEX(GP_CX_T,MATCH($B4,GP_CX_Sectors,0),11),INDEX(GP_CX_T,MATCH($B4,GP_CX_Sectors,0),12),0)))))))) -> 85 | AG4: =IF(OR($B4="",O4=""),"",IF(ISERROR(MATCH($B4,GP_PE_Sectors,0)),0,IF(O4<=INDEX(GP_PE_T,MATCH($B4,GP_PE_Sectors,0),1),INDEX(GP_PE_T,MATCH($B4,GP_PE_Sectors,0),2),IF(O4<=INDEX(GP_PE_T,MATCH($B4,GP_PE_Sectors,0),3),INDEX(GP_PE_T,MATCH($B4,GP_PE_Sectors,0),4),IF(O4<=INDEX(GP_PE_T,MATCH($B4,GP_PE_Sectors,0),5),INDEX(GP_PE_T,MATCH($B4,GP_PE_Sectors,0),6),IF(O4<=INDEX(GP_PE_T,MATCH($B4,GP_PE_Sectors,0),7),INDEX(GP_PE_T,MATCH($B4,GP_PE_Sectors,0),8),IF(O4<=INDEX(GP_PE_T,MATCH($B4,GP_PE_Sectors,0),9),INDEX(GP_PE_T,MATCH($B4,GP_PE_Sectors,0),10),IF(O4<=INDEX(GP_PE_T,MATCH($B4,GP_PE_Sectors,0),11),INDEX(GP_PE_T,MATCH($B4,GP_PE_Sectors,0),12),0)))))))) -> 48 | AH4: =IF(OR($B4="",P4=""),"",IF(ISERROR(MATCH($B4,GP_EV_Sectors,0)),0,IF(P4<=INDEX(GP_EV_T,MATCH($B4,GP_EV_Sectors,0),1),INDEX(GP_EV_T,MATCH($B4,GP_EV_Sectors,0),2),IF(P4<=INDEX(GP_EV_T,MATCH($B4,GP_EV_Sectors,0),3),INDEX(GP_EV_T,MATCH($B4,GP_EV_Sectors,0),4),IF(P4<=INDEX(GP_EV_T,MATCH($B4,GP_EV_Sectors,0),5),INDEX(GP_EV_T,MATCH($B4,GP_EV_Sectors,0),6),IF(P4<=INDEX(GP_EV_T,MATCH($B4,GP_EV_Sectors,0),7),INDEX(GP_EV_T,MATCH($B4,GP_EV_Sectors,0),8),IF(P4<=INDEX(GP_EV_T,MATCH($B4,GP_EV_Sectors,0),9),INDEX(GP_EV_T,MATCH($B4,GP_EV_Sectors,0),10),IF(P4<=INDEX(GP_EV_T,MATCH($B4,GP_EV_Sectors,0),11),INDEX(GP_EV_T,MATCH($B4,GP_EV_Sectors,0),12),0)))))))) -> 48 | AI4: =IF(OR($B4="",Q4=""),"",IF(ISERROR(MATCH($B4,GP_PF_Sectors,0)),0,IF(Q4<=INDEX(GP_PF_T,MATCH($B4,GP_PF_Sectors,0),1),INDEX(GP_PF_T,MATCH($B4,GP_PF_Sectors,0),2),IF(Q4<=INDEX(GP_PF_T,MATCH($B4,GP_PF_Sectors,0),3),INDEX(GP_PF_T,MATCH($B4,GP_PF_Sectors,0),4),IF(Q4<=INDEX(GP_PF_T,MATCH($B4,GP_PF_Sectors,0),5),INDEX(GP_PF_T,MATCH($B4,GP_PF_Sectors,0),6),IF(Q4<=INDEX(GP_PF_T,MATCH($B4,GP_PF_Sectors,0),7),INDEX(GP_PF_T,MATCH($B4,GP_PF_Sectors,0),8),IF(Q4<=INDEX(GP_PF_T,MATCH($B4,GP_PF_Sectors,0),9),INDEX(GP_PF_T,MATCH($B4,GP_PF_Sectors,0),10),IF(Q4<=INDEX(GP_PF_T,MATCH($B4,GP_PF_Sectors,0),11),INDEX(GP_PF_T,MATCH($B4,GP_PF_Sectors,0),12),0)))))))) -> 48 | AJ4: =IF(OR($B4="",R4=""),"",IF(ISERROR(MATCH($B4,GP_DY_Sectors,0)),0,IF(R4>=INDEX(GP_DY_T,MATCH($B4,GP_DY_Sectors,0),1),INDEX(GP_DY_T,MATCH($B4,GP_DY_Sectors,0),2),IF(R4>=INDEX(GP_DY_T,MATCH($B4,GP_DY_Sectors,0),3),INDEX(GP_DY_T,MATCH($B4,GP_DY_Sectors,0),4),IF(R4>=INDEX(GP_DY_T,MATCH($B4,GP_DY_Sectors,0),5),INDEX(GP_DY_T,MATCH($B4,GP_DY_Sectors,0),6),IF(R4>=INDEX(GP_DY_T,MATCH($B4,GP_DY_Sectors,0),7),INDEX(GP_DY_T,MATCH($B4,GP_DY_Sectors,0),8),IF(R4>=INDEX(GP_DY_T,MATCH($B4,GP_DY_Sectors,0),9),INDEX(GP_DY_T,MATCH($B4,GP_DY_Sectors,0),10),IF(R4>=INDEX(GP_DY_T,MATCH($B4,GP_DY_Sectors,0),11),INDEX(GP_DY_T,MATCH($B4,GP_DY_Sectors,0),12),0)))))))) -> 5 | AK4: =IF(OR($B4="",S4=""),"",IF(ISERROR(MATCH($B4,GP_PR_Sectors,0)),0,IF(S4>=INDEX(GP_PR_T,MATCH($B4,GP_PR_Sectors,0),1),INDEX(GP_PR_T,MATCH($B4,GP_PR_Sectors,0),2),IF(S4>=INDEX(GP_PR_T,MATCH($B4,GP_PR_Sectors,0),3),INDEX(GP_PR_T,MATCH($B4,GP_PR_Sectors,0),4),IF(S4>=INDEX(GP_PR_T,MATCH($B4,GP_PR_Sectors,0),5),INDEX(GP_PR_T,MATCH($B4,GP_PR_Sectors,0),6),IF(S4>=INDEX(GP_PR_T,MATCH($B4,GP_PR_Sectors,0),7),INDEX(GP_PR_T,MATCH($B4,GP_PR_Sectors,0),8),IF(S4>=INDEX(GP_PR_T,MATCH($B4,GP_PR_Sectors,0),9),INDEX(GP_PR_T,MATCH($B4,GP_PR_Sectors,0),10),IF(S4>=INDEX(GP_PR_T,MATCH($B4,GP_PR_Sectors,0),11),INDEX(GP_PR_T,MATCH($B4,GP_PR_Sectors,0),12),0)))))))) -> 0 | AL4: =IF(OR($B4="",T4=""),"",IF(ISERROR(MATCH($B4,GP_BY_Sectors,0)),0,IF(T4>=INDEX(GP_BY_T,MATCH($B4,GP_BY_Sectors,0),1),INDEX(GP_BY_T,MATCH($B4,GP_BY_Sectors,0),2),IF(T4>=INDEX(GP_BY_T,MATCH($B4,GP_BY_Sectors,0),3),INDEX(GP_BY_T,MATCH($B4,GP_BY_Sectors,0),4),IF(T4>=INDEX(GP_BY_T,MATCH($B4,GP_BY_Sectors,0),5),INDEX(GP_BY_T,MATCH($B4,GP_BY_Sectors,0),6),IF(T4>=INDEX(GP_BY_T,MATCH($B4,GP_BY_Sectors,0),7),INDEX(GP_BY_T,MATCH($B4,GP_BY_Sectors,0),8),IF(T4>=INDEX(GP_BY_T,MATCH($B4,GP_BY_Sectors,0),9),INDEX(GP_BY_T,MATCH($B4,GP_BY_Sectors,0),10),IF(T4>=INDEX(GP_BY_T,MATCH($B4,GP_BY_Sectors,0),11),INDEX(GP_BY_T,MATCH($B4,GP_BY_Sectors,0),12),0)))))))) -> 50 | AM4: =IF($B4="","",U4*0.35+V4*0.35+W4*0.3) -> 100 | AN4: =IF($B4="","",X4*0.4+Y4*0.35+Z4*0.25) -> 100 | AO4: =IF($B4="","",AA4*0.35+AB4*0.3+AC4*0.35) -> 100 | AP4: =IF($B4="","",AD4*0.4+AE4*0.35+AF4*0.25) -> 92.05 | AQ4: =IF($B4="","",AG4*0.35+AH4*0.35+AI4*0.3) -> 48 | AR4: =IF($B4="","",AJ4*0.45+AK4*0.2+AL4*0.35) -> 19.75 | AS4: =IF($B4="","",MIN(100,MAX(0,ROUND(AM4*INDEX(GP_W_P1,MATCH($B4,GP_Weights_Sectors,0))+AN4*INDEX(GP_W_P2,MATCH($B4,GP_Weights_Sectors,0))+AO4*INDEX(GP_W_P3,MATCH($B4,GP_Weights_Sectors,0))+AP4*INDEX(GP_W_P4,MATCH($B4,GP_Weights_Sectors,0))+AQ4*INDEX(GP_W_P5,MATCH($B4,GP_Weights_Sectors,0))+AR4*INDEX(GP_W_P6,MATCH($B4,GP_Weights_Sectors,0)),0)))) -> 83 | AT4: 3 | AU4: 3 | AV4: 4 | AW4: =MAX(-10,MIN(10,AT4+AU4+AV4)) -> 10 | AX4: #VALUE! | AY4: {=_FV(AX4,"PRECIO")} -> 171.24 | AZ4: 240 | BA4: =IFERROR(INDEX('DCF Simplified'!$Y$4:$Y$38,MATCH(A4,'DCF Simplified'!$A$4:$A$38,0)),"") -> 69.398445 | BB4: =IF(OR(AY4="",AZ4=""),"",(AZ4-AY4)/AY4) -> 0.4015417 | BD4: 0.12 | BE4: 62 | BF4: 0.35 | BG4: =IF(BD4>0.1,100,IF(BD4>0.05,80,IF(BD4>0,65,IF(BD4>-0.05,45,IF(BD4>-0.1,25,10))))) -> 100 | BH4: =IF(AND(BE4>=40,BE4<=60),70,IF(AND(BE4>60,BE4<=70),85,IF(BE4>70,50,IF(AND(BE4>=30,BE4<40),55,40)))) -> 85 | BI4: =IF(BF4>0.2,100,IF(BF4>0.1,80,IF(BF4>0,65,IF(BF4>-0.1,45,IF(BF4>-0.2,25,10))))) -> 100 | BJ4: =ROUND(BG4*0.4+BH4*0.25+BI4*0.35,1) -> 96.3 | BK4: =IF(OR(AS4="",AQ4="",BJ4=""),"",ROUND(AS4*0.4+MAX(15,MIN(90,AQ4))*0.2+BJ4*0.25+MIN(100,MAX(0,AW4*10))*0.15,0)) -> 82 | BL4: =IF(BK4="","",IF(BK4>=85,"🟢 STRONG",IF(BK4>=70,"🟡 FAVORABLE",IF(BK4>=55,"⚪ NEUTRAL",IF(BK4>=40,"🟠 WEAK","🔴 AVOID"))))) -> 🟡 FAVORABLE | BM4: =IF(BK4="","",IF(AND(BK4>=75,BJ4>=70,AW4>=6),"🚀 STRONG BUY",IF(AND(BK4>=65,BJ4>=55),"✅ BUY",IF(BK4>=55,"⚠️ HOLD",IF(OR(BK4<45,AND(BJ4<35,AW4<3)),"🔴 SELL","🟠 UNDERWEIGHT"))))) -> 🚀 STRONG BUY
A5: Johnson & Johnson | B5: Health Care | C5: 0.22 | D5: 0.18 | E5: 0.18 | F5: 0.04 | G5: 0.03 | H5: 0.9 | I5: 1.2 | J5: 1.3 | K5: 8 | L5: 0.16 | M5: 0.95 | N5: 0.05 | O5: 16 | P5: 12 | Q5: 20 | R5: 0.032 | S5: 0.48 | T5: 0.02 | U5: =IF(OR($B5="",C5=""),"",IF(ISERROR(MATCH($B5,GP_ROE_Sectors,0)),0,IF(C5>=INDEX(GP_ROE_T,MATCH($B5,GP_ROE_Sectors,0),1),INDEX(GP_ROE_T,MATCH($B5,GP_ROE_Sectors,0),2),IF(C5>=INDEX(GP_ROE_T,MATCH($B5,GP_ROE_Sectors,0),3),INDEX(GP_ROE_T,MATCH($B5,GP_ROE_Sectors,0),4),IF(C5>=INDEX(GP_ROE_T,MATCH($B5,GP_ROE_Sectors,0),5),INDEX(GP_ROE_T,MATCH($B5,GP_ROE_Sectors,0),6),IF(C5>=INDEX(GP_ROE_T,MATCH($B5,GP_ROE_Sectors,0),7),INDEX(GP_ROE_T,MATCH($B5,GP_ROE_Sectors,0),8),IF(C5>=INDEX(GP_ROE_T,MATCH($B5,GP_ROE_Sectors,0),9),INDEX(GP_ROE_T,MATCH($B5,GP_ROE_Sectors,0),10),IF(C5>=INDEX(GP_ROE_T,MATCH($B5,GP_ROE_Sectors,0),11),INDEX(GP_ROE_T,MATCH($B5,GP_ROE_Sectors,0),12),0)))))))) -> 88 | V5: =IF(OR($B5="",D5=""),"",IF(ISERROR(MATCH($B5,GP_ROIC_Sectors,0)),0,IF(D5>=INDEX(GP_ROIC_T,MATCH($B5,GP_ROIC_Sectors,0),1),INDEX(GP_ROIC_T,MATCH($B5,GP_ROIC_Sectors,0),2),IF(D5>=INDEX(GP_ROIC_T,MATCH($B5,GP_ROIC_Sectors,0),3),INDEX(GP_ROIC_T,MATCH($B5,GP_ROIC_Sectors,0),4),IF(D5>=INDEX(GP_ROIC_T,MATCH($B5,GP_ROIC_Sectors,0),5),INDEX(GP_ROIC_T,MATCH($B5,GP_ROIC_Sectors,0),6),IF(D5>=INDEX(GP_ROIC_T,MATCH($B5,GP_ROIC_Sectors,0),7),INDEX(GP_ROIC_T,MATCH($B5,GP_ROIC_Sectors,0),8),IF(D5>=INDEX(GP_ROIC_T,MATCH($B5,GP_ROIC_Sectors,0),9),INDEX(GP_ROIC_T,MATCH($B5,GP_ROIC_Sectors,0),10),IF(D5>=INDEX(GP_ROIC_T,MATCH($B5,GP_ROIC_Sectors,0),11),INDEX(GP_ROIC_T,MATCH($B5,GP_ROIC_Sectors,0),12),0)))))))) -> 88 | W5: =IF(OR($B5="",E5=""),"",IF(ISERROR(MATCH($B5,GP_NM_Sectors,0)),0,IF(E5>=INDEX(GP_NM_T,MATCH($B5,GP_NM_Sectors,0),1),INDEX(GP_NM_T,MATCH($B5,GP_NM_Sectors,0),2),IF(E5>=INDEX(GP_NM_T,MATCH($B5,GP_NM_Sectors,0),3),INDEX(GP_NM_T,MATCH($B5,GP_NM_Sectors,0),4),IF(E5>=INDEX(GP_NM_T,MATCH($B5,GP_NM_Sectors,0),5),INDEX(GP_NM_T,MATCH($B5,GP_NM_Sectors,0),6),IF(E5>=INDEX(GP_NM_T,MATCH($B5,GP_NM_Sectors,0),7),INDEX(GP_NM_T,MATCH($B5,GP_NM_Sectors,0),8),IF(E5>=INDEX(GP_NM_T,MATCH($B5,GP_NM_Sectors,0),9),INDEX(GP_NM_T,MATCH($B5,GP_NM_Sectors,0),10),IF(E5>=INDEX(GP_NM_T,MATCH($B5,GP_NM_Sectors,0),11),INDEX(GP_NM_T,MATCH($B5,GP_NM_Sectors,0),12),0)))))))) -> 88 | X5: =IF(OR($B5="",F5=""),"",IF(ISERROR(MATCH($B5,GP_RG_Sectors,0)),0,IF(F5>=INDEX(GP_RG_T,MATCH($B5,GP_RG_Sectors,0),1),INDEX(GP_RG_T,MATCH($B5,GP_RG_Sectors,0),2),IF(F5>=INDEX(GP_RG_T,MATCH($B5,GP_RG_Sectors,0),3),INDEX(GP_RG_T,MATCH($B5,GP_RG_Sectors,0),4),IF(F5>=INDEX(GP_RG_T,MATCH($B5,GP_RG_Sectors,0),5),INDEX(GP_RG_T,MATCH($B5,GP_RG_Sectors,0),6),IF(F5>=INDEX(GP_RG_T,MATCH($B5,GP_RG_Sectors,0),7),INDEX(GP_RG_T,MATCH($B5,GP_RG_Sectors,0),8),IF(F5>=INDEX(GP_RG_T,MATCH($B5,GP_RG_Sectors,0),9),INDEX(GP_RG_T,MATCH($B5,GP_RG_Sectors,0),10),IF(F5>=INDEX(GP_RG_T,MATCH($B5,GP_RG_Sectors,0),11),INDEX(GP_RG_T,MATCH($B5,GP_RG_Sectors,0),12),0)))))))) -> 35 | Y5: =IF(OR($B5="",G5=""),"",IF(ISERROR(MATCH($B5,GP_EG_Sectors,0)),0,IF(G5>=INDEX(GP_EG_T,MATCH($B5,GP_EG_Sectors,0),1),INDEX(GP_EG_T,MATCH($B5,GP_EG_Sectors,0),2),IF(G5>=INDEX(GP_EG_T,MATCH($B5,GP_EG_Sectors,0),3),INDEX(GP_EG_T,MATCH($B5,GP_EG_Sectors,0),4),IF(G5>=INDEX(GP_EG_T,MATCH($B5,GP_EG_Sectors,0),5),INDEX(GP_EG_T,MATCH($B5,GP_EG_Sectors,0),6),IF(G5>=INDEX(GP_EG_T,MATCH($B5,GP_EG_Sectors,0),7),INDEX(GP_EG_T,MATCH($B5,GP_EG_Sectors,0),8),IF(G5>=INDEX(GP_EG_T,MATCH($B5,GP_EG_Sectors,0),9),INDEX(GP_EG_T,MATCH($B5,GP_EG_Sectors,0),10),IF(G5>=INDEX(GP_EG_T,MATCH($B5,GP_EG_Sectors,0),11),INDEX(GP_EG_T,MATCH($B5,GP_EG_Sectors,0),12),0)))))))) -> 35 | Z5: =IF(OR($B5="",H5=""),"",IF(ISERROR(MATCH($B5,GP_OL_Sectors,0)),0,IF(H5>=INDEX(GP_OL_T,MATCH($B5,GP_OL_Sectors,0),1),INDEX(GP_OL_T,MATCH($B5,GP_OL_Sectors,0),2),IF(H5>=INDEX(GP_OL_T,MATCH($B5,GP_OL_Sectors,0),3),INDEX(GP_OL_T,MATCH($B5,GP_OL_Sectors,0),4),IF(H5>=INDEX(GP_OL_T,MATCH($B5,GP_OL_Sectors,0),5),INDEX(GP_OL_T,MATCH($B5,GP_OL_Sectors,0),6),IF(H5>=INDEX(GP_OL_T,MATCH($B5,GP_OL_Sectors,0),7),INDEX(GP_OL_T,MATCH($B5,GP_OL_Sectors,0),8),IF(H5>=INDEX(GP_OL_T,MATCH($B5,GP_OL_Sectors,0),9),INDEX(GP_OL_T,MATCH($B5,GP_OL_Sectors,0),10),IF(H5>=INDEX(GP_OL_T,MATCH($B5,GP_OL_Sectors,0),11),INDEX(GP_OL_T,MATCH($B5,GP_OL_Sectors,0),12),0)))))))) -> 52 | AA5: =IF(OR($B5="",I5=""),"",IF(ISERROR(MATCH($B5,GP_ND_Sectors,0)),0,IF(I5<=INDEX(GP_ND_T,MATCH($B5,GP_ND_Sectors,0),1),INDEX(GP_ND_T,MATCH($B5,GP_ND_Sectors,0),2),IF(I5<=INDEX(GP_ND_T,MATCH($B5,GP_ND_Sectors,0),3),INDEX(GP_ND_T,MATCH($B5,GP_ND_Sectors,0),4),IF(I5<=INDEX(GP_ND_T,MATCH($B5,GP_ND_Sectors,0),5),INDEX(GP_ND_T,MATCH($B5,GP_ND_Sectors,0),6),IF(I5<=INDEX(GP_ND_T,MATCH($B5,GP_ND_Sectors,0),7),INDEX(GP_ND_T,MATCH($B5,GP_ND_Sectors,0),8),IF(I5<=INDEX(GP_ND_T,MATCH($B5,GP_ND_Sectors,0),9),INDEX(GP_ND_T,MATCH($B5,GP_ND_Sectors,0),10),IF(I5<=INDEX(GP_ND_T,MATCH($B5,GP_ND_Sectors,0),11),INDEX(GP_ND_T,MATCH($B5,GP_ND_Sectors,0),12),0)))))))) -> 70 | AB5: =IF(OR($B5="",J5=""),"",IF(ISERROR(MATCH($B5,GP_CR_Sectors,0)),0,IF(J5>=INDEX(GP_CR_T,MATCH($B5,GP_CR_Sectors,0),1),INDEX(GP_CR_T,MATCH($B5,GP_CR_Sectors,0),2),IF(J5>=INDEX(GP_CR_T,MATCH($B5,GP_CR_Sectors,0),3),INDEX(GP_CR_T,MATCH($B5,GP_CR_Sectors,0),4),IF(J5>=INDEX(GP_CR_T,MATCH($B5,GP_CR_Sectors,0),5),INDEX(GP_CR_T,MATCH($B5,GP_CR_Sectors,0),6),IF(J5>=INDEX(GP_CR_T,MATCH($B5,GP_CR_Sectors,0),7),INDEX(GP_CR_T,MATCH($B5,GP_CR_Sectors,0),8),IF(J5>=INDEX(GP_CR_T,MATCH($B5,GP_CR_Sectors,0),9),INDEX(GP_CR_T,MATCH($B5,GP_CR_Sectors,0),10),IF(J5>=INDEX(GP_CR_T,MATCH($B5,GP_CR_Sectors,0),11),INDEX(GP_CR_T,MATCH($B5,GP_CR_Sectors,0),12),0)))))))) -> 52 | AC5: =IF(OR($B5="",K5=""),"",IF(ISERROR(MATCH($B5,GP_IC_Sectors,0)),0,IF(K5>=INDEX(GP_IC_T,MATCH($B5,GP_IC_Sectors,0),1),INDEX(GP_IC_T,MATCH($B5,GP_IC_Sectors,0),2),IF(K5>=INDEX(GP_IC_T,MATCH($B5,GP_IC_Sectors,0),3),INDEX(GP_IC_T,MATCH($B5,GP_IC_Sectors,0),4),IF(K5>=INDEX(GP_IC_T,MATCH($B5,GP_IC_Sectors,0),5),INDEX(GP_IC_T,MATCH($B5,GP_IC_Sectors,0),6),IF(K5>=INDEX(GP_IC_T,MATCH($B5,GP_IC_Sectors,0),7),INDEX(GP_IC_T,MATCH($B5,GP_IC_Sectors,0),8),IF(K5>=INDEX(GP_IC_T,MATCH($B5,GP_IC_Sectors,0),9),INDEX(GP_IC_T,MATCH($B5,GP_IC_Sectors,0),10),IF(K5>=INDEX(GP_IC_T,MATCH($B5,GP_IC_Sectors,0),11),INDEX(GP_IC_T,MATCH($B5,GP_IC_Sectors,0),12),0)))))))) -> 85 | AD5: =IF(OR($B5="",L5=""),"",IF(ISERROR(MATCH($B5,GP_FM_Sectors,0)),0,IF(L5>=INDEX(GP_FM_T,MATCH($B5,GP_FM_Sectors,0),1),INDEX(GP_FM_T,MATCH($B5,GP_FM_Sectors,0),2),IF(L5>=INDEX(GP_FM_T,MATCH($B5,GP_FM_Sectors,0),3),INDEX(GP_FM_T,MATCH($B5,GP_FM_Sectors,0),4),IF(L5>=INDEX(GP_FM_T,MATCH($B5,GP_FM_Sectors,0),5),INDEX(GP_FM_T,MATCH($B5,GP_FM_Sectors,0),6),IF(L5>=INDEX(GP_FM_T,MATCH($B5,GP_FM_Sectors,0),7),INDEX(GP_FM_T,MATCH($B5,GP_FM_Sectors,0),8),IF(L5>=INDEX(GP_FM_T,MATCH($B5,GP_FM_Sectors,0),9),INDEX(GP_FM_T,MATCH($B5,GP_FM_Sectors,0),10),IF(L5>=INDEX(GP_FM_T,MATCH($B5,GP_FM_Sectors,0),11),INDEX(GP_FM_T,MATCH($B5,GP_FM_Sectors,0),12),0)))))))) -> 85 | AE5: =IF(OR($B5="",M5=""),"",IF(ISERROR(MATCH($B5,GP_FN_Sectors,0)),0,IF(M5>=INDEX(GP_FN_T,MATCH($B5,GP_FN_Sectors,0),1),INDEX(GP_FN_T,MATCH($B5,GP_FN_Sectors,0),2),IF(M5>=INDEX(GP_FN_T,MATCH($B5,GP_FN_Sectors,0),3),INDEX(GP_FN_T,MATCH($B5,GP_FN_Sectors,0),4),IF(M5>=INDEX(GP_FN_T,MATCH($B5,GP_FN_Sectors,0),5),INDEX(GP_FN_T,MATCH($B5,GP_FN_Sectors,0),6),IF(M5>=INDEX(GP_FN_T,MATCH($B5,GP_FN_Sectors,0),7),INDEX(GP_FN_T,MATCH($B5,GP_FN_Sectors,0),8),IF(M5>=INDEX(GP_FN_T,MATCH($B5,GP_FN_Sectors,0),9),INDEX(GP_FN_T,MATCH($B5,GP_FN_Sectors,0),10),IF(M5>=INDEX(GP_FN_T,MATCH($B5,GP_FN_Sectors,0),11),INDEX(GP_FN_T,MATCH($B5,GP_FN_Sectors,0),12),0)))))))) -> 70 | AF5: =IF(OR($B5="",N5=""),"",IF(ISERROR(MATCH($B5,GP_CX_Sectors,0)),0,IF(N5<=INDEX(GP_CX_T,MATCH($B5,GP_CX_Sectors,0),1),INDEX(GP_CX_T,MATCH($B5,GP_CX_Sectors,0),2),IF(N5<=INDEX(GP_CX_T,MATCH($B5,GP_CX_Sectors,0),3),INDEX(GP_CX_T,MATCH($B5,GP_CX_Sectors,0),4),IF(N5<=INDEX(GP_CX_T,MATCH($B5,GP_CX_Sectors,0),5),INDEX(GP_CX_T,MATCH($B5,GP_CX_Sectors,0),6),IF(N5<=INDEX(GP_CX_T,MATCH($B5,GP_CX_Sectors,0),7),INDEX(GP_CX_T,MATCH($B5,GP_CX_Sectors,0),8),IF(N5<=INDEX(GP_CX_T,MATCH($B5,GP_CX_Sectors,0),9),INDEX(GP_CX_T,MATCH($B5,GP_CX_Sectors,0),10),IF(N5<=INDEX(GP_CX_T,MATCH($B5,GP_CX_Sectors,0),11),INDEX(GP_CX_T,MATCH($B5,GP_CX_Sectors,0),12),0)))))))) -> 85 | AG5: =IF(OR($B5="",O5=""),"",IF(ISERROR(MATCH($B5,GP_PE_Sectors,0)),0,IF(O5<=INDEX(GP_PE_T,MATCH($B5,GP_PE_Sectors,0),1),INDEX(GP_PE_T,MATCH($B5,GP_PE_Sectors,0),2),IF(O5<=INDEX(GP_PE_T,MATCH($B5,GP_PE_Sectors,0),3),INDEX(GP_PE_T,MATCH($B5,GP_PE_Sectors,0),4),IF(O5<=INDEX(GP_PE_T,MATCH($B5,GP_PE_Sectors,0),5),INDEX(GP_PE_T,MATCH($B5,GP_PE_Sectors,0),6),IF(O5<=INDEX(GP_PE_T,MATCH($B5,GP_PE_Sectors,0),7),INDEX(GP_PE_T,MATCH($B5,GP_PE_Sectors,0),8),IF(O5<=INDEX(GP_PE_T,MATCH($B5,GP_PE_Sectors,0),9),INDEX(GP_PE_T,MATCH($B5,GP_PE_Sectors,0),10),IF(O5<=INDEX(GP_PE_T,MATCH($B5,GP_PE_Sectors,0),11),INDEX(GP_PE_T,MATCH($B5,GP_PE_Sectors,0),12),0)))))))) -> 82 | AH5: =IF(OR($B5="",P5=""),"",IF(ISERROR(MATCH($B5,GP_EV_Sectors,0)),0,IF(P5<=INDEX(GP_EV_T,MATCH($B5,GP_EV_Sectors,0),1),INDEX(GP_EV_T,MATCH($B5,GP_EV_Sectors,0),2),IF(P5<=INDEX(GP_EV_T,MATCH($B5,GP_EV_Sectors,0),3),INDEX(GP_EV_T,MATCH($B5,GP_EV_Sectors,0),4),IF(P5<=INDEX(GP_EV_T,MATCH($B5,GP_EV_Sectors,0),5),INDEX(GP_EV_T,MATCH($B5,GP_EV_Sectors,0),6),IF(P5<=INDEX(GP_EV_T,MATCH($B5,GP_EV_Sectors,0),7),INDEX(GP_EV_T,MATCH($B5,GP_EV_Sectors,0),8),IF(P5<=INDEX(GP_EV_T,MATCH($B5,GP_EV_Sectors,0),9),INDEX(GP_EV_T,MATCH($B5,GP_EV_Sectors,0),10),IF(P5<=INDEX(GP_EV_T,MATCH($B5,GP_EV_Sectors,0),11),INDEX(GP_EV_T,MATCH($B5,GP_EV_Sectors,0),12),0)))))))) -> 82 | AI5: =IF(OR($B5="",Q5=""),"",IF(ISERROR(MATCH($B5,GP_PF_Sectors,0)),0,IF(Q5<=INDEX(GP_PF_T,MATCH($B5,GP_PF_Sectors,0),1),INDEX(GP_PF_T,MATCH($B5,GP_PF_Sectors,0),2),IF(Q5<=INDEX(GP_PF_T,MATCH($B5,GP_PF_Sectors,0),3),INDEX(GP_PF_T,MATCH($B5,GP_PF_Sectors,0),4),IF(Q5<=INDEX(GP_PF_T,MATCH($B5,GP_PF_Sectors,0),5),INDEX(GP_PF_T,MATCH($B5,GP_PF_Sectors,0),6),IF(Q5<=INDEX(GP_PF_T,MATCH($B5,GP_PF_Sectors,0),7),INDEX(GP_PF_T,MATCH($B5,GP_PF_Sectors,0),8),IF(Q5<=INDEX(GP_PF_T,MATCH($B5,GP_PF_Sectors,0),9),INDEX(GP_PF_T,MATCH($B5,GP_PF_Sectors,0),10),IF(Q5<=INDEX(GP_PF_T,MATCH($B5,GP_PF_Sectors,0),11),INDEX(GP_PF_T,MATCH($B5,GP_PF_Sectors,0),12),0)))))))) -> 82 | AJ5: =IF(OR($B5="",R5=""),"",IF(ISERROR(MATCH($B5,GP_DY_Sectors,0)),0,IF(R5>=INDEX(GP_DY_T,MATCH($B5,GP_DY_Sectors,0),1),INDEX(GP_DY_T,MATCH($B5,GP_DY_Sectors,0),2),IF(R5>=INDEX(GP_DY_T,MATCH($B5,GP_DY_Sectors,0),3),INDEX(GP_DY_T,MATCH($B5,GP_DY_Sectors,0),4),IF(R5>=INDEX(GP_DY_T,MATCH($B5,GP_DY_Sectors,0),5),INDEX(GP_DY_T,MATCH($B5,GP_DY_Sectors,0),6),IF(R5>=INDEX(GP_DY_T,MATCH($B5,GP_DY_Sectors,0),7),INDEX(GP_DY_T,MATCH($B5,GP_DY_Sectors,0),8),IF(R5>=INDEX(GP_DY_T,MATCH($B5,GP_DY_Sectors,0),9),INDEX(GP_DY_T,MATCH($B5,GP_DY_Sectors,0),10),IF(R5>=INDEX(GP_DY_T,MATCH($B5,GP_DY_Sectors,0),11),INDEX(GP_DY_T,MATCH($B5,GP_DY_Sectors,0),12),0)))))))) -> 100 | AK5: =IF(OR($B5="",S5=""),"",IF(ISERROR(MATCH($B5,GP_PR_Sectors,0)),0,IF(S5>=INDEX(GP_PR_T,MATCH($B5,GP_PR_Sectors,0),1),INDEX(GP_PR_T,MATCH($B5,GP_PR_Sectors,0),2),IF(S5>=INDEX(GP_PR_T,MATCH($B5,GP_PR_Sectors,0),3),INDEX(GP_PR_T,MATCH($B5,GP_PR_Sectors,0),4),IF(S5>=INDEX(GP_PR_T,MATCH($B5,GP_PR_Sectors,0),5),INDEX(GP_PR_T,MATCH($B5,GP_PR_Sectors,0),6),IF(S5>=INDEX(GP_PR_T,MATCH($B5,GP_PR_Sectors,0),7),INDEX(GP_PR_T,MATCH($B5,GP_PR_Sectors,0),8),IF(S5>=INDEX(GP_PR_T,MATCH($B5,GP_PR_Sectors,0),9),INDEX(GP_PR_T,MATCH($B5,GP_PR_Sectors,0),10),IF(S5>=INDEX(GP_PR_T,MATCH($B5,GP_PR_Sectors,0),11),INDEX(GP_PR_T,MATCH($B5,GP_PR_Sectors,0),12),0)))))))) -> 100 | AL5: =IF(OR($B5="",T5=""),"",IF(ISERROR(MATCH($B5,GP_BY_Sectors,0)),0,IF(T5>=INDEX(GP_BY_T,MATCH($B5,GP_BY_Sectors,0),1),INDEX(GP_BY_T,MATCH($B5,GP_BY_Sectors,0),2),IF(T5>=INDEX(GP_BY_T,MATCH($B5,GP_BY_Sectors,0),3),INDEX(GP_BY_T,MATCH($B5,GP_BY_Sectors,0),4),IF(T5>=INDEX(GP_BY_T,MATCH($B5,GP_BY_Sectors,0),5),INDEX(GP_BY_T,MATCH($B5,GP_BY_Sectors,0),6),IF(T5>=INDEX(GP_BY_T,MATCH($B5,GP_BY_Sectors,0),7),INDEX(GP_BY_T,MATCH($B5,GP_BY_Sectors,0),8),IF(T5>=INDEX(GP_BY_T,MATCH($B5,GP_BY_Sectors,0),9),INDEX(GP_BY_T,MATCH($B5,GP_BY_Sectors,0),10),IF(T5>=INDEX(GP_BY_T,MATCH($B5,GP_BY_Sectors,0),11),INDEX(GP_BY_T,MATCH($B5,GP_BY_Sectors,0),12),0)))))))) -> 68 | AM5: =IF($B5="","",U5*0.35+V5*0.35+W5*0.3) -> 88 | AN5: =IF($B5="","",X5*0.4+Y5*0.35+Z5*0.25) -> 39.25 | AO5: =IF($B5="","",AA5*0.35+AB5*0.3+AC5*0.35) -> 69.85 | AP5: =IF($B5="","",AD5*0.4+AE5*0.35+AF5*0.25) -> 79.75 | AQ5: =IF($B5="","",AG5*0.35+AH5*0.35+AI5*0.3) -> 82 | AR5: =IF($B5="","",AJ5*0.45+AK5*0.2+AL5*0.35) -> 88.8 | AS5: =IF($B5="","",MIN(100,MAX(0,ROUND(AM5*INDEX(GP_W_P1,MATCH($B5,GP_Weights_Sectors,0))+AN5*INDEX(GP_W_P2,MATCH($B5,GP_Weights_Sectors,0))+AO5*INDEX(GP_W_P3,MATCH($B5,GP_Weights_Sectors,0))+AP5*INDEX(GP_W_P4,MATCH($B5,GP_Weights_Sectors,0))+AQ5*INDEX(GP_W_P5,MATCH($B5,GP_Weights_Sectors,0))+AR5*INDEX(GP_W_P6,MATCH($B5,GP_Weights_Sectors,0)),0)))) -> 73 | AT5: 1 | AU5: 2 | AV5: 2 | AW5: =MAX(-10,MIN(10,AT5+AU5+AV5)) -> 5 | AX5: #VALUE! | AY5: {=_FV(AX5,"PRECIO")} -> 239.24 | AZ5: 182 | BA5: =IFERROR(INDEX('DCF Simplified'!$Y$4:$Y$38,MATCH(A5,'DCF Simplified'!$A$4:$A$38,0)),"") -> 154.33163 | BB5: =IF(OR(AY5="",AZ5=""),"",(AZ5-AY5)/AY5) -> -0.23925765 | BD5: -0.02 | BE5: 48 | BF5: -0.05 | BG5: =IF(BD5>0.1,100,IF(BD5>0.05,80,IF(BD5>0,65,IF(BD5>-0.05,45,IF(BD5>-0.1,25,10))))) -> 45 | BH5: =IF(AND(BE5>=40,BE5<=60),70,IF(AND(BE5>60,BE5<=70),85,IF(BE5>70,50,IF(AND(BE5>=30,BE5<40),55,40)))) -> 70 | BI5: =IF(BF5>0.2,100,IF(BF5>0.1,80,IF(BF5>0,65,IF(BF5>-0.1,45,IF(BF5>-0.2,25,10))))) -> 45 | BJ5: =ROUND(BG5*0.4+BH5*0.25+BI5*0.35,1) -> 51.3 | BK5: =IF(OR(AS5="",AQ5="",BJ5=""),"",ROUND(AS5*0.4+MAX(15,MIN(90,AQ5))*0.2+BJ5*0.25+MIN(100,MAX(0,AW5*10))*0.15,0)) -> 66 | BL5: =IF(BK5="","",IF(BK5>=85,"🟢 STRONG",IF(BK5>=70,"🟡 FAVORABLE",IF(BK5>=55,"⚪ NEUTRAL",IF(BK5>=40,"🟠 WEAK","🔴 AVOID"))))) -> ⚪ NEUTRAL | BM5: =IF(BK5="","",IF(AND(BK5>=75,BJ5>=70,AW5>=6),"🚀 STRONG BUY",IF(AND(BK5>=65,BJ5>=55),"✅ BUY",IF(BK5>=55,"⚠️ HOLD",IF(OR(BK5<45,AND(BJ5<35,AW5<3)),"🔴 SELL","🟠 UNDERWEIGHT"))))) -> ⚠️ HOLD
A6: Exxon Mobil Corp | B6: Energy | C6: 0.18 | D6: 0.12 | E6: 0.1 | F6: 0.08 | G6: 0.05 | H6: 1.4 | I6: 0.8 | J6: 1.4 | K6: 6 | L6: 0.08 | M6: 0.85 | N6: 0.15 | O6: 9 | P6: 6 | Q6: 10 | R6: 0.035 | S6: 0.4 | T6: 0.04 | U6: =IF(OR($B6="",C6=""),"",IF(ISERROR(MATCH($B6,GP_ROE_Sectors,0)),0,IF(C6>=INDEX(GP_ROE_T,MATCH($B6,GP_ROE_Sectors,0),1),INDEX(GP_ROE_T,MATCH($B6,GP_ROE_Sectors,0),2),IF(C6>=INDEX(GP_ROE_T,MATCH($B6,GP_ROE_Sectors,0),3),INDEX(GP_ROE_T,MATCH($B6,GP_ROE_Sectors,0),4),IF(C6>=INDEX(GP_ROE_T,MATCH($B6,GP_ROE_Sectors,0),5),INDEX(GP_ROE_T,MATCH($B6,GP_ROE_Sectors,0),6),IF(C6>=INDEX(GP_ROE_T,MATCH($B6,GP_ROE_Sectors,0),7),INDEX(GP_ROE_T,MATCH($B6,GP_ROE_Sectors,0),8),IF(C6>=INDEX(GP_ROE_T,MATCH($B6,GP_ROE_Sectors,0),9),INDEX(GP_ROE_T,MATCH($B6,GP_ROE_Sectors,0),10),IF(C6>=INDEX(GP_ROE_T,MATCH($B6,GP_ROE_Sectors,0),11),INDEX(GP_ROE_T,MATCH($B6,GP_ROE_Sectors,0),12),0)))))))) -> 85 | V6: =IF(OR($B6="",D6=""),"",IF(ISERROR(MATCH($B6,GP_ROIC_Sectors,0)),0,IF(D6>=INDEX(GP_ROIC_T,MATCH($B6,GP_ROIC_Sectors,0),1),INDEX(GP_ROIC_T,MATCH($B6,GP_ROIC_Sectors,0),2),IF(D6>=INDEX(GP_ROIC_T,MATCH($B6,GP_ROIC_Sectors,0),3),INDEX(GP_ROIC_T,MATCH($B6,GP_ROIC_Sectors,0),4),IF(D6>=INDEX(GP_ROIC_T,MATCH($B6,GP_ROIC_Sectors,0),5),INDEX(GP_ROIC_T,MATCH($B6,GP_ROIC_Sectors,0),6),IF(D6>=INDEX(GP_ROIC_T,MATCH($B6,GP_ROIC_Sectors,0),7),INDEX(GP_ROIC_T,MATCH($B6,GP_ROIC_Sectors,0),8),IF(D6>=INDEX(GP_ROIC_T,MATCH($B6,GP_ROIC_Sectors,0),9),INDEX(GP_ROIC_T,MATCH($B6,GP_ROIC_Sectors,0),10),IF(D6>=INDEX(GP_ROIC_T,MATCH($B6,GP_ROIC_Sectors,0),11),INDEX(GP_ROIC_T,MATCH($B6,GP_ROIC_Sectors,0),12),0)))))))) -> 82 | W6: =IF(OR($B6="",E6=""),"",IF(ISERROR(MATCH($B6,GP_NM_Sectors,0)),0,IF(E6>=INDEX(GP_NM_T,MATCH($B6,GP_NM_Sectors,0),1),INDEX(GP_NM_T,MATCH($B6,GP_NM_Sectors,0),2),IF(E6>=INDEX(GP_NM_T,MATCH($B6,GP_NM_Sectors,0),3),INDEX(GP_NM_T,MATCH($B6,GP_NM_Sectors,0),4),IF(E6>=INDEX(GP_NM_T,MATCH($B6,GP_NM_Sectors,0),5),INDEX(GP_NM_T,MATCH($B6,GP_NM_Sectors,0),6),IF(E6>=INDEX(GP_NM_T,MATCH($B6,GP_NM_Sectors,0),7),INDEX(GP_NM_T,MATCH($B6,GP_NM_Sectors,0),8),IF(E6>=INDEX(GP_NM_T,MATCH($B6,GP_NM_Sectors,0),9),INDEX(GP_NM_T,MATCH($B6,GP_NM_Sectors,0),10),IF(E6>=INDEX(GP_NM_T,MATCH($B6,GP_NM_Sectors,0),11),INDEX(GP_NM_T,MATCH($B6,GP_NM_Sectors,0),12),0)))))))) -> 82 | X6: =IF(OR($B6="",F6=""),"",IF(ISERROR(MATCH($B6,GP_RG_Sectors,0)),0,IF(F6>=INDEX(GP_RG_T,MATCH($B6,GP_RG_Sectors,0),1),INDEX(GP_RG_T,MATCH($B6,GP_RG_Sectors,0),2),IF(F6>=INDEX(GP_RG_T,MATCH($B6,GP_RG_Sectors,0),3),INDEX(GP_RG_T,MATCH($B6,GP_RG_Sectors,0),4),IF(F6>=INDEX(GP_RG_T,MATCH($B6,GP_RG_Sectors,0),5),INDEX(GP_RG_T,MATCH($B6,GP_RG_Sectors,0),6),IF(F6>=INDEX(GP_RG_T,MATCH($B6,GP_RG_Sectors,0),7),INDEX(GP_RG_T,MATCH($B6,GP_RG_Sectors,0),8),IF(F6>=INDEX(GP_RG_T,MATCH($B6,GP_RG_Sectors,0),9),INDEX(GP_RG_T,MATCH($B6,GP_RG_Sectors,0),10),IF(F6>=INDEX(GP_RG_T,MATCH($B6,GP_RG_Sectors,0),11),INDEX(GP_RG_T,MATCH($B6,GP_RG_Sectors,0),12),0)))))))) -> 65 | Y6: =IF(OR($B6="",G6=""),"",IF(ISERROR(MATCH($B6,GP_EG_Sectors,0)),0,IF(G6>=INDEX(GP_EG_T,MATCH($B6,GP_EG_Sectors,0),1),INDEX(GP_EG_T,MATCH($B6,GP_EG_Sectors,0),2),IF(G6>=INDEX(GP_EG_T,MATCH($B6,GP_EG_Sectors,0),3),INDEX(GP_EG_T,MATCH($B6,GP_EG_Sectors,0),4),IF(G6>=INDEX(GP_EG_T,MATCH($B6,GP_EG_Sectors,0),5),INDEX(GP_EG_T,MATCH($B6,GP_EG_Sectors,0),6),IF(G6>=INDEX(GP_EG_T,MATCH($B6,GP_EG_Sectors,0),7),INDEX(GP_EG_T,MATCH($B6,GP_EG_Sectors,0),8),IF(G6>=INDEX(GP_EG_T,MATCH($B6,GP_EG_Sectors,0),9),INDEX(GP_EG_T,MATCH($B6,GP_EG_Sectors,0),10),IF(G6>=INDEX(GP_EG_T,MATCH($B6,GP_EG_Sectors,0),11),INDEX(GP_EG_T,MATCH($B6,GP_EG_Sectors,0),12),0)))))))) -> 42 | Z6: =IF(OR($B6="",H6=""),"",IF(ISERROR(MATCH($B6,GP_OL_Sectors,0)),0,IF(H6>=INDEX(GP_OL_T,MATCH($B6,GP_OL_Sectors,0),1),INDEX(GP_OL_T,MATCH($B6,GP_OL_Sectors,0),2),IF(H6>=INDEX(GP_OL_T,MATCH($B6,GP_OL_Sectors,0),3),INDEX(GP_OL_T,MATCH($B6,GP_OL_Sectors,0),4),IF(H6>=INDEX(GP_OL_T,MATCH($B6,GP_OL_Sectors,0),5),INDEX(GP_OL_T,MATCH($B6,GP_OL_Sectors,0),6),IF(H6>=INDEX(GP_OL_T,MATCH($B6,GP_OL_Sectors,0),7),INDEX(GP_OL_T,MATCH($B6,GP_OL_Sectors,0),8),IF(H6>=INDEX(GP_OL_T,MATCH($B6,GP_OL_Sectors,0),9),INDEX(GP_OL_T,MATCH($B6,GP_OL_Sectors,0),10),IF(H6>=INDEX(GP_OL_T,MATCH($B6,GP_OL_Sectors,0),11),INDEX(GP_OL_T,MATCH($B6,GP_OL_Sectors,0),12),0)))))))) -> 65 | AA6: =IF(OR($B6="",I6=""),"",IF(ISERROR(MATCH($B6,GP_ND_Sectors,0)),0,IF(I6<=INDEX(GP_ND_T,MATCH($B6,GP_ND_Sectors,0),1),INDEX(GP_ND_T,MATCH($B6,GP_ND_Sectors,0),2),IF(I6<=INDEX(GP_ND_T,MATCH($B6,GP_ND_Sectors,0),3),INDEX(GP_ND_T,MATCH($B6,GP_ND_Sectors,0),4),IF(I6<=INDEX(GP_ND_T,MATCH($B6,GP_ND_Sectors,0),5),INDEX(GP_ND_T,MATCH($B6,GP_ND_Sectors,0),6),IF(I6<=INDEX(GP_ND_T,MATCH($B6,GP_ND_Sectors,0),7),INDEX(GP_ND_T,MATCH($B6,GP_ND_Sectors,0),8),IF(I6<=INDEX(GP_ND_T,MATCH($B6,GP_ND_Sectors,0),9),INDEX(GP_ND_T,MATCH($B6,GP_ND_Sectors,0),10),IF(I6<=INDEX(GP_ND_T,MATCH($B6,GP_ND_Sectors,0),11),INDEX(GP_ND_T,MATCH($B6,GP_ND_Sectors,0),12),0)))))))) -> 82 | AB6: =IF(OR($B6="",J6=""),"",IF(ISERROR(MATCH($B6,GP_CR_Sectors,0)),0,IF(J6>=INDEX(GP_CR_T,MATCH($B6,GP_CR_Sectors,0),1),INDEX(GP_CR_T,MATCH($B6,GP_CR_Sectors,0),2),IF(J6>=INDEX(GP_CR_T,MATCH($B6,GP_CR_Sectors,0),3),INDEX(GP_CR_T,MATCH($B6,GP_CR_Sectors,0),4),IF(J6>=INDEX(GP_CR_T,MATCH($B6,GP_CR_Sectors,0),5),INDEX(GP_CR_T,MATCH($B6,GP_CR_Sectors,0),6),IF(J6>=INDEX(GP_CR_T,MATCH($B6,GP_CR_Sectors,0),7),INDEX(GP_CR_T,MATCH($B6,GP_CR_Sectors,0),8),IF(J6>=INDEX(GP_CR_T,MATCH($B6,GP_CR_Sectors,0),9),INDEX(GP_CR_T,MATCH($B6,GP_CR_Sectors,0),10),IF(J6>=INDEX(GP_CR_T,MATCH($B6,GP_CR_Sectors,0),11),INDEX(GP_CR_T,MATCH($B6,GP_CR_Sectors,0),12),0)))))))) -> 65 | AC6: =IF(OR($B6="",K6=""),"",IF(ISERROR(MATCH($B6,GP_IC_Sectors,0)),0,IF(K6>=INDEX(GP_IC_T,MATCH($B6,GP_IC_Sectors,0),1),INDEX(GP_IC_T,MATCH($B6,GP_IC_Sectors,0),2),IF(K6>=INDEX(GP_IC_T,MATCH($B6,GP_IC_Sectors,0),3),INDEX(GP_IC_T,MATCH($B6,GP_IC_Sectors,0),4),IF(K6>=INDEX(GP_IC_T,MATCH($B6,GP_IC_Sectors,0),5),INDEX(GP_IC_T,MATCH($B6,GP_IC_Sectors,0),6),IF(K6>=INDEX(GP_IC_T,MATCH($B6,GP_IC_Sectors,0),7),INDEX(GP_IC_T,MATCH($B6,GP_IC_Sectors,0),8),IF(K6>=INDEX(GP_IC_T,MATCH($B6,GP_IC_Sectors,0),9),INDEX(GP_IC_T,MATCH($B6,GP_IC_Sectors,0),10),IF(K6>=INDEX(GP_IC_T,MATCH($B6,GP_IC_Sectors,0),11),INDEX(GP_IC_T,MATCH($B6,GP_IC_Sectors,0),12),0)))))))) -> 80 | AD6: =IF(OR($B6="",L6=""),"",IF(ISERROR(MATCH($B6,GP_FM_Sectors,0)),0,IF(L6>=INDEX(GP_FM_T,MATCH($B6,GP_FM_Sectors,0),1),INDEX(GP_FM_T,MATCH($B6,GP_FM_Sectors,0),2),IF(L6>=INDEX(GP_FM_T,MATCH($B6,GP_FM_Sectors,0),3),INDEX(GP_FM_T,MATCH($B6,GP_FM_Sectors,0),4),IF(L6>=INDEX(GP_FM_T,MATCH($B6,GP_FM_Sectors,0),5),INDEX(GP_FM_T,MATCH($B6,GP_FM_Sectors,0),6),IF(L6>=INDEX(GP_FM_T,MATCH($B6,GP_FM_Sectors,0),7),INDEX(GP_FM_T,MATCH($B6,GP_FM_Sectors,0),8),IF(L6>=INDEX(GP_FM_T,MATCH($B6,GP_FM_Sectors,0),9),INDEX(GP_FM_T,MATCH($B6,GP_FM_Sectors,0),10),IF(L6>=INDEX(GP_FM_T,MATCH($B6,GP_FM_Sectors,0),11),INDEX(GP_FM_T,MATCH($B6,GP_FM_Sectors,0),12),0)))))))) -> 80 | AE6: =IF(OR($B6="",M6=""),"",IF(ISERROR(MATCH($B6,GP_FN_Sectors,0)),0,IF(M6>=INDEX(GP_FN_T,MATCH($B6,GP_FN_Sectors,0),1),INDEX(GP_FN_T,MATCH($B6,GP_FN_Sectors,0),2),IF(M6>=INDEX(GP_FN_T,MATCH($B6,GP_FN_Sectors,0),3),INDEX(GP_FN_T,MATCH($B6,GP_FN_Sectors,0),4),IF(M6>=INDEX(GP_FN_T,MATCH($B6,GP_FN_Sectors,0),5),INDEX(GP_FN_T,MATCH($B6,GP_FN_Sectors,0),6),IF(M6>=INDEX(GP_FN_T,MATCH($B6,GP_FN_Sectors,0),7),INDEX(GP_FN_T,MATCH($B6,GP_FN_Sectors,0),8),IF(M6>=INDEX(GP_FN_T,MATCH($B6,GP_FN_Sectors,0),9),INDEX(GP_FN_T,MATCH($B6,GP_FN_Sectors,0),10),IF(M6>=INDEX(GP_FN_T,MATCH($B6,GP_FN_Sectors,0),11),INDEX(GP_FN_T,MATCH($B6,GP_FN_Sectors,0),12),0)))))))) -> 80 | AF6: =IF(OR($B6="",N6=""),"",IF(ISERROR(MATCH($B6,GP_CX_Sectors,0)),0,IF(N6<=INDEX(GP_CX_T,MATCH($B6,GP_CX_Sectors,0),1),INDEX(GP_CX_T,MATCH($B6,GP_CX_Sectors,0),2),IF(N6<=INDEX(GP_CX_T,MATCH($B6,GP_CX_Sectors,0),3),INDEX(GP_CX_T,MATCH($B6,GP_CX_Sectors,0),4),IF(N6<=INDEX(GP_CX_T,MATCH($B6,GP_CX_Sectors,0),5),INDEX(GP_CX_T,MATCH($B6,GP_CX_Sectors,0),6),IF(N6<=INDEX(GP_CX_T,MATCH($B6,GP_CX_Sectors,0),7),INDEX(GP_CX_T,MATCH($B6,GP_CX_Sectors,0),8),IF(N6<=INDEX(GP_CX_T,MATCH($B6,GP_CX_Sectors,0),9),INDEX(GP_CX_T,MATCH($B6,GP_CX_Sectors,0),10),IF(N6<=INDEX(GP_CX_T,MATCH($B6,GP_CX_Sectors,0),11),INDEX(GP_CX_T,MATCH($B6,GP_CX_Sectors,0),12),0)))))))) -> 62 | AG6: =IF(OR($B6="",O6=""),"",IF(ISERROR(MATCH($B6,GP_PE_Sectors,0)),0,IF(O6<=INDEX(GP_PE_T,MATCH($B6,GP_PE_Sectors,0),1),INDEX(GP_PE_T,MATCH($B6,GP_PE_Sectors,0),2),IF(O6<=INDEX(GP_PE_T,MATCH($B6,GP_PE_Sectors,0),3),INDEX(GP_PE_T,MATCH($B6,GP_PE_Sectors,0),4),IF(O6<=INDEX(GP_PE_T,MATCH($B6,GP_PE_Sectors,0),5),INDEX(GP_PE_T,MATCH($B6,GP_PE_Sectors,0),6),IF(O6<=INDEX(GP_PE_T,MATCH($B6,GP_PE_Sectors,0),7),INDEX(GP_PE_T,MATCH($B6,GP_PE_Sectors,0),8),IF(O6<=INDEX(GP_PE_T,MATCH($B6,GP_PE_Sectors,0),9),INDEX(GP_PE_T,MATCH($B6,GP_PE_Sectors,0),10),IF(O6<=INDEX(GP_PE_T,MATCH($B6,GP_PE_Sectors,0),11),INDEX(GP_PE_T,MATCH($B6,GP_PE_Sectors,0),12),0)))))))) -> 82 | AH6: =IF(OR($B6="",P6=""),"",IF(ISERROR(MATCH($B6,GP_EV_Sectors,0)),0,IF(P6<=INDEX(GP_EV_T,MATCH($B6,GP_EV_Sectors,0),1),INDEX(GP_EV_T,MATCH($B6,GP_EV_Sectors,0),2),IF(P6<=INDEX(GP_EV_T,MATCH($B6,GP_EV_Sectors,0),3),INDEX(GP_EV_T,MATCH($B6,GP_EV_Sectors,0),4),IF(P6<=INDEX(GP_EV_T,MATCH($B6,GP_EV_Sectors,0),5),INDEX(GP_EV_T,MATCH($B6,GP_EV_Sectors,0),6),IF(P6<=INDEX(GP_EV_T,MATCH($B6,GP_EV_Sectors,0),7),INDEX(GP_EV_T,MATCH($B6,GP_EV_Sectors,0),8),IF(P6<=INDEX(GP_EV_T,MATCH($B6,GP_EV_Sectors,0),9),INDEX(GP_EV_T,MATCH($B6,GP_EV_Sectors,0),10),IF(P6<=INDEX(GP_EV_T,MATCH($B6,GP_EV_Sectors,0),11),INDEX(GP_EV_T,MATCH($B6,GP_EV_Sectors,0),12),0)))))))) -> 82 | AI6: =IF(OR($B6="",Q6=""),"",IF(ISERROR(MATCH($B6,GP_PF_Sectors,0)),0,IF(Q6<=INDEX(GP_PF_T,MATCH($B6,GP_PF_Sectors,0),1),INDEX(GP_PF_T,MATCH($B6,GP_PF_Sectors,0),2),IF(Q6<=INDEX(GP_PF_T,MATCH($B6,GP_PF_Sectors,0),3),INDEX(GP_PF_T,MATCH($B6,GP_PF_Sectors,0),4),IF(Q6<=INDEX(GP_PF_T,MATCH($B6,GP_PF_Sectors,0),5),INDEX(GP_PF_T,MATCH($B6,GP_PF_Sectors,0),6),IF(Q6<=INDEX(GP_PF_T,MATCH($B6,GP_PF_Sectors,0),7),INDEX(GP_PF_T,MATCH($B6,GP_PF_Sectors,0),8),IF(Q6<=INDEX(GP_PF_T,MATCH($B6,GP_PF_Sectors,0),9),INDEX(GP_PF_T,MATCH($B6,GP_PF_Sectors,0),10),IF(Q6<=INDEX(GP_PF_T,MATCH($B6,GP_PF_Sectors,0),11),INDEX(GP_PF_T,MATCH($B6,GP_PF_Sectors,0),12),0)))))))) -> 80 | AJ6: =IF(OR($B6="",R6=""),"",IF(ISERROR(MATCH($B6,GP_DY_Sectors,0)),0,IF(R6>=INDEX(GP_DY_T,MATCH($B6,GP_DY_Sectors,0),1),INDEX(GP_DY_T,MATCH($B6,GP_DY_Sectors,0),2),IF(R6>=INDEX(GP_DY_T,MATCH($B6,GP_DY_Sectors,0),3),INDEX(GP_DY_T,MATCH($B6,GP_DY_Sectors,0),4),IF(R6>=INDEX(GP_DY_T,MATCH($B6,GP_DY_Sectors,0),5),INDEX(GP_DY_T,MATCH($B6,GP_DY_Sectors,0),6),IF(R6>=INDEX(GP_DY_T,MATCH($B6,GP_DY_Sectors,0),7),INDEX(GP_DY_T,MATCH($B6,GP_DY_Sectors,0),8),IF(R6>=INDEX(GP_DY_T,MATCH($B6,GP_DY_Sectors,0),9),INDEX(GP_DY_T,MATCH($B6,GP_DY_Sectors,0),10),IF(R6>=INDEX(GP_DY_T,MATCH($B6,GP_DY_Sectors,0),11),INDEX(GP_DY_T,MATCH($B6,GP_DY_Sectors,0),12),0)))))))) -> 68 | AK6: =IF(OR($B6="",S6=""),"",IF(ISERROR(MATCH($B6,GP_PR_Sectors,0)),0,IF(S6>=INDEX(GP_PR_T,MATCH($B6,GP_PR_Sectors,0),1),INDEX(GP_PR_T,MATCH($B6,GP_PR_Sectors,0),2),IF(S6>=INDEX(GP_PR_T,MATCH($B6,GP_PR_Sectors,0),3),INDEX(GP_PR_T,MATCH($B6,GP_PR_Sectors,0),4),IF(S6>=INDEX(GP_PR_T,MATCH($B6,GP_PR_Sectors,0),5),INDEX(GP_PR_T,MATCH($B6,GP_PR_Sectors,0),6),IF(S6>=INDEX(GP_PR_T,MATCH($B6,GP_PR_Sectors,0),7),INDEX(GP_PR_T,MATCH($B6,GP_PR_Sectors,0),8),IF(S6>=INDEX(GP_PR_T,MATCH($B6,GP_PR_Sectors,0),9),INDEX(GP_PR_T,MATCH($B6,GP_PR_Sectors,0),10),IF(S6>=INDEX(GP_PR_T,MATCH($B6,GP_PR_Sectors,0),11),INDEX(GP_PR_T,MATCH($B6,GP_PR_Sectors,0),12),0)))))))) -> 100 | AL6: =IF(OR($B6="",T6=""),"",IF(ISERROR(MATCH($B6,GP_BY_Sectors,0)),0,IF(T6>=INDEX(GP_BY_T,MATCH($B6,GP_BY_Sectors,0),1),INDEX(GP_BY_T,MATCH($B6,GP_BY_Sectors,0),2),IF(T6>=INDEX(GP_BY_T,MATCH($B6,GP_BY_Sectors,0),3),INDEX(GP_BY_T,MATCH($B6,GP_BY_Sectors,0),4),IF(T6>=INDEX(GP_BY_T,MATCH($B6,GP_BY_Sectors,0),5),INDEX(GP_BY_T,MATCH($B6,GP_BY_Sectors,0),6),IF(T6>=INDEX(GP_BY_T,MATCH($B6,GP_BY_Sectors,0),7),INDEX(GP_BY_T,MATCH($B6,GP_BY_Sectors,0),8),IF(T6>=INDEX(GP_BY_T,MATCH($B6,GP_BY_Sectors,0),9),INDEX(GP_BY_T,MATCH($B6,GP_BY_Sectors,0),10),IF(T6>=INDEX(GP_BY_T,MATCH($B6,GP_BY_Sectors,0),11),INDEX(GP_BY_T,MATCH($B6,GP_BY_Sectors,0),12),0)))))))) -> 80 | AM6: =IF($B6="","",U6*0.35+V6*0.35+W6*0.3) -> 83.05 | AN6: =IF($B6="","",X6*0.4+Y6*0.35+Z6*0.25) -> 56.95 | AO6: =IF($B6="","",AA6*0.35+AB6*0.3+AC6*0.35) -> 76.2 | AP6: =IF($B6="","",AD6*0.4+AE6*0.35+AF6*0.25) -> 75.5 | AQ6: =IF($B6="","",AG6*0.35+AH6*0.35+AI6*0.3) -> 81.4 | AR6: =IF($B6="","",AJ6*0.45+AK6*0.2+AL6*0.35) -> 78.6 | AS6: =IF($B6="","",MIN(100,MAX(0,ROUND(AM6*INDEX(GP_W_P1,MATCH($B6,GP_Weights_Sectors,0))+AN6*INDEX(GP_W_P2,MATCH($B6,GP_Weights_Sectors,0))+AO6*INDEX(GP_W_P3,MATCH($B6,GP_Weights_Sectors,0))+AP6*INDEX(GP_W_P4,MATCH($B6,GP_Weights_Sectors,0))+AQ6*INDEX(GP_W_P5,MATCH($B6,GP_Weights_Sectors,0))+AR6*INDEX(GP_W_P6,MATCH($B6,GP_Weights_Sectors,0)),0)))) -> 75 | AT6: 1 | AU6: 2 | AV6: 3 | AW6: =MAX(-10,MIN(10,AT6+AU6+AV6)) -> 6 | AX6: #VALUE! | AY6: {=_FV(AX6,"PRECIO")} -> 165.43 | AZ6: 142 | BA6: =IFERROR(INDEX('DCF Simplified'!$Y$4:$Y$38,MATCH(A6,'DCF Simplified'!$A$4:$A$38,0)),"") -> 128.95781 | BB6: =IF(OR(AY6="",AZ6=""),"",(AZ6-AY6)/AY6) -> -0.1416309 | BD6: -0.05 | BE6: 44 | BF6: -0.12 | BG6: =IF(BD6>0.1,100,IF(BD6>0.05,80,IF(BD6>0,65,IF(BD6>-0.05,45,IF(BD6>-0.1,25,10))))) -> 25 | BH6: =IF(AND(BE6>=40,BE6<=60),70,IF(AND(BE6>60,BE6<=70),85,IF(BE6>70,50,IF(AND(BE6>=30,BE6<40),55,40)))) -> 70 | BI6: =IF(BF6>0.2,100,IF(BF6>0.1,80,IF(BF6>0,65,IF(BF6>-0.1,45,IF(BF6>-0.2,25,10))))) -> 25 | BJ6: =ROUND(BG6*0.4+BH6*0.25+BI6*0.35,1) -> 36.3 | BK6: =IF(OR(AS6="",AQ6="",BJ6=""),"",ROUND(AS6*0.4+MAX(15,MIN(90,AQ6))*0.2+BJ6*0.25+MIN(100,MAX(0,AW6*10))*0.15,0)) -> 64 | BL6: =IF(BK6="","",IF(BK6>=85,"🟢 STRONG",IF(BK6>=70,"🟡 FAVORABLE",IF(BK6>=55,"⚪ NEUTRAL",IF(BK6>=40,"🟠 WEAK","🔴 AVOID"))))) -> ⚪ NEUTRAL | BM6: =IF(BK6="","",IF(AND(BK6>=75,BJ6>=70,AW6>=6),"🚀 STRONG BUY",IF(AND(BK6>=65,BJ6>=55),"✅ BUY",IF(BK6>=55,"⚠️ HOLD",IF(OR(BK6<45,AND(BJ6<35,AW6<3)),"🔴 SELL","🟠 UNDERWEIGHT"))))) -> ⚠️ HOLD
A7: Berkshire Hathaway | B7: Financials | C7: 0.16 | D7: 0.1 | E7: 0.2 | F7: 0.08 | G7: 0.1 | H7: 1.2 | I7: 0.5 | J7: 1 | K7: 5 | L7: 0.08 | M7: 0.8 | N7: 0.04 | O7: 12 | P7: 9 | Q7: 14 | R7: 0 | S7: 0 | T7: 0.03 | U7: =IF(OR($B7="",C7=""),"",IF(ISERROR(MATCH($B7,GP_ROE_Sectors,0)),0,IF(C7>=INDEX(GP_ROE_T,MATCH($B7,GP_ROE_Sectors,0),1),INDEX(GP_ROE_T,MATCH($B7,GP_ROE_Sectors,0),2),IF(C7>=INDEX(GP_ROE_T,MATCH($B7,GP_ROE_Sectors,0),3),INDEX(GP_ROE_T,MATCH($B7,GP_ROE_Sectors,0),4),IF(C7>=INDEX(GP_ROE_T,MATCH($B7,GP_ROE_Sectors,0),5),INDEX(GP_ROE_T,MATCH($B7,GP_ROE_Sectors,0),6),IF(C7>=INDEX(GP_ROE_T,MATCH($B7,GP_ROE_Sectors,0),7),INDEX(GP_ROE_T,MATCH($B7,GP_ROE_Sectors,0),8),IF(C7>=INDEX(GP_ROE_T,MATCH($B7,GP_ROE_Sectors,0),9),INDEX(GP_ROE_T,MATCH($B7,GP_ROE_Sectors,0),10),IF(C7>=INDEX(GP_ROE_T,MATCH($B7,GP_ROE_Sectors,0),11),INDEX(GP_ROE_T,MATCH($B7,GP_ROE_Sectors,0),12),0)))))))) -> 88 | V7: =IF(OR($B7="",D7=""),"",IF(ISERROR(MATCH($B7,GP_ROIC_Sectors,0)),0,IF(D7>=INDEX(GP_ROIC_T,MATCH($B7,GP_ROIC_Sectors,0),1),INDEX(GP_ROIC_T,MATCH($B7,GP_ROIC_Sectors,0),2),IF(D7>=INDEX(GP_ROIC_T,MATCH($B7,GP_ROIC_Sectors,0),3),INDEX(GP_ROIC_T,MATCH($B7,GP_ROIC_Sectors,0),4),IF(D7>=INDEX(GP_ROIC_T,MATCH($B7,GP_ROIC_Sectors,0),5),INDEX(GP_ROIC_T,MATCH($B7,GP_ROIC_Sectors,0),6),IF(D7>=INDEX(GP_ROIC_T,MATCH($B7,GP_ROIC_Sectors,0),7),INDEX(GP_ROIC_T,MATCH($B7,GP_ROIC_Sectors,0),8),IF(D7>=INDEX(GP_ROIC_T,MATCH($B7,GP_ROIC_Sectors,0),9),INDEX(GP_ROIC_T,MATCH($B7,GP_ROIC_Sectors,0),10),IF(D7>=INDEX(GP_ROIC_T,MATCH($B7,GP_ROIC_Sectors,0),11),INDEX(GP_ROIC_T,MATCH($B7,GP_ROIC_Sectors,0),12),0)))))))) -> 72 | W7: =IF(OR($B7="",E7=""),"",IF(ISERROR(MATCH($B7,GP_NM_Sectors,0)),0,IF(E7>=INDEX(GP_NM_T,MATCH($B7,GP_NM_Sectors,0),1),INDEX(GP_NM_T,MATCH($B7,GP_NM_Sectors,0),2),IF(E7>=INDEX(GP_NM_T,MATCH($B7,GP_NM_Sectors,0),3),INDEX(GP_NM_T,MATCH($B7,GP_NM_Sectors,0),4),IF(E7>=INDEX(GP_NM_T,MATCH($B7,GP_NM_Sectors,0),5),INDEX(GP_NM_T,MATCH($B7,GP_NM_Sectors,0),6),IF(E7>=INDEX(GP_NM_T,MATCH($B7,GP_NM_Sectors,0),7),INDEX(GP_NM_T,MATCH($B7,GP_NM_Sectors,0),8),IF(E7>=INDEX(GP_NM_T,MATCH($B7,GP_NM_Sectors,0),9),INDEX(GP_NM_T,MATCH($B7,GP_NM_Sectors,0),10),IF(E7>=INDEX(GP_NM_T,MATCH($B7,GP_NM_Sectors,0),11),INDEX(GP_NM_T,MATCH($B7,GP_NM_Sectors,0),12),0)))))))) -> 72 | X7: =IF(OR($B7="",F7=""),"",IF(ISERROR(MATCH($B7,GP_RG_Sectors,0)),0,IF(F7>=INDEX(GP_RG_T,MATCH($B7,GP_RG_Sectors,0),1),INDEX(GP_RG_T,MATCH($B7,GP_RG_Sectors,0),2),IF(F7>=INDEX(GP_RG_T,MATCH($B7,GP_RG_Sectors,0),3),INDEX(GP_RG_T,MATCH($B7,GP_RG_Sectors,0),4),IF(F7>=INDEX(GP_RG_T,MATCH($B7,GP_RG_Sectors,0),5),INDEX(GP_RG_T,MATCH($B7,GP_RG_Sectors,0),6),IF(F7>=INDEX(GP_RG_T,MATCH($B7,GP_RG_Sectors,0),7),INDEX(GP_RG_T,MATCH($B7,GP_RG_Sectors,0),8),IF(F7>=INDEX(GP_RG_T,MATCH($B7,GP_RG_Sectors,0),9),INDEX(GP_RG_T,MATCH($B7,GP_RG_Sectors,0),10),IF(F7>=INDEX(GP_RG_T,MATCH($B7,GP_RG_Sectors,0),11),INDEX(GP_RG_T,MATCH($B7,GP_RG_Sectors,0),12),0)))))))) -> 85 | Y7: =IF(OR($B7="",G7=""),"",IF(ISERROR(MATCH($B7,GP_EG_Sectors,0)),0,IF(G7>=INDEX(GP_EG_T,MATCH($B7,GP_EG_Sectors,0),1),INDEX(GP_EG_T,MATCH($B7,GP_EG_Sectors,0),2),IF(G7>=INDEX(GP_EG_T,MATCH($B7,GP_EG_Sectors,0),3),INDEX(GP_EG_T,MATCH($B7,GP_EG_Sectors,0),4),IF(G7>=INDEX(GP_EG_T,MATCH($B7,GP_EG_Sectors,0),5),INDEX(GP_EG_T,MATCH($B7,GP_EG_Sectors,0),6),IF(G7>=INDEX(GP_EG_T,MATCH($B7,GP_EG_Sectors,0),7),INDEX(GP_EG_T,MATCH($B7,GP_EG_Sectors,0),8),IF(G7>=INDEX(GP_EG_T,MATCH($B7,GP_EG_Sectors,0),9),INDEX(GP_EG_T,MATCH($B7,GP_EG_Sectors,0),10),IF(G7>=INDEX(GP_EG_T,MATCH($B7,GP_EG_Sectors,0),11),INDEX(GP_EG_T,MATCH($B7,GP_EG_Sectors,0),12),0)))))))) -> 85 | Z7: =IF(OR($B7="",H7=""),"",IF(ISERROR(MATCH($B7,GP_OL_Sectors,0)),0,IF(H7>=INDEX(GP_OL_T,MATCH($B7,GP_OL_Sectors,0),1),INDEX(GP_OL_T,MATCH($B7,GP_OL_Sectors,0),2),IF(H7>=INDEX(GP_OL_T,MATCH($B7,GP_OL_Sectors,0),3),INDEX(GP_OL_T,MATCH($B7,GP_OL_Sectors,0),4),IF(H7>=INDEX(GP_OL_T,MATCH($B7,GP_OL_Sectors,0),5),INDEX(GP_OL_T,MATCH($B7,GP_OL_Sectors,0),6),IF(H7>=INDEX(GP_OL_T,MATCH($B7,GP_OL_Sectors,0),7),INDEX(GP_OL_T,MATCH($B7,GP_OL_Sectors,0),8),IF(H7>=INDEX(GP_OL_T,MATCH($B7,GP_OL_Sectors,0),9),INDEX(GP_OL_T,MATCH($B7,GP_OL_Sectors,0),10),IF(H7>=INDEX(GP_OL_T,MATCH($B7,GP_OL_Sectors,0),11),INDEX(GP_OL_T,MATCH($B7,GP_OL_Sectors,0),12),0)))))))) -> 85 | AA7: =IF(OR($B7="",I7=""),"",IF(ISERROR(MATCH($B7,GP_ND_Sectors,0)),0,IF(I7<=INDEX(GP_ND_T,MATCH($B7,GP_ND_Sectors,0),1),INDEX(GP_ND_T,MATCH($B7,GP_ND_Sectors,0),2),IF(I7<=INDEX(GP_ND_T,MATCH($B7,GP_ND_Sectors,0),3),INDEX(GP_ND_T,MATCH($B7,GP_ND_Sectors,0),4),IF(I7<=INDEX(GP_ND_T,MATCH($B7,GP_ND_Sectors,0),5),INDEX(GP_ND_T,MATCH($B7,GP_ND_Sectors,0),6),IF(I7<=INDEX(GP_ND_T,MATCH($B7,GP_ND_Sectors,0),7),INDEX(GP_ND_T,MATCH($B7,GP_ND_Sectors,0),8),IF(I7<=INDEX(GP_ND_T,MATCH($B7,GP_ND_Sectors,0),9),INDEX(GP_ND_T,MATCH($B7,GP_ND_Sectors,0),10),IF(I7<=INDEX(GP_ND_T,MATCH($B7,GP_ND_Sectors,0),11),INDEX(GP_ND_T,MATCH($B7,GP_ND_Sectors,0),12),0)))))))) -> 85 | AB7: =IF(OR($B7="",J7=""),"",IF(ISERROR(MATCH($B7,GP_CR_Sectors,0)),0,IF(J7>=INDEX(GP_CR_T,MATCH($B7,GP_CR_Sectors,0),1),INDEX(GP_CR_T,MATCH($B7,GP_CR_Sectors,0),2),IF(J7>=INDEX(GP_CR_T,MATCH($B7,GP_CR_Sectors,0),3),INDEX(GP_CR_T,MATCH($B7,GP_CR_Sectors,0),4),IF(J7>=INDEX(GP_CR_T,MATCH($B7,GP_CR_Sectors,0),5),INDEX(GP_CR_T,MATCH($B7,GP_CR_Sectors,0),6),IF(J7>=INDEX(GP_CR_T,MATCH($B7,GP_CR_Sectors,0),7),INDEX(GP_CR_T,MATCH($B7,GP_CR_Sectors,0),8),IF(J7>=INDEX(GP_CR_T,MATCH($B7,GP_CR_Sectors,0),9),INDEX(GP_CR_T,MATCH($B7,GP_CR_Sectors,0),10),IF(J7>=INDEX(GP_CR_T,MATCH($B7,GP_CR_Sectors,0),11),INDEX(GP_CR_T,MATCH($B7,GP_CR_Sectors,0),12),0)))))))) -> 70 | AC7: =IF(OR($B7="",K7=""),"",IF(ISERROR(MATCH($B7,GP_IC_Sectors,0)),0,IF(K7>=INDEX(GP_IC_T,MATCH($B7,GP_IC_Sectors,0),1),INDEX(GP_IC_T,MATCH($B7,GP_IC_Sectors,0),2),IF(K7>=INDEX(GP_IC_T,MATCH($B7,GP_IC_Sectors,0),3),INDEX(GP_IC_T,MATCH($B7,GP_IC_Sectors,0),4),IF(K7>=INDEX(GP_IC_T,MATCH($B7,GP_IC_Sectors,0),5),INDEX(GP_IC_T,MATCH($B7,GP_IC_Sectors,0),6),IF(K7>=INDEX(GP_IC_T,MATCH($B7,GP_IC_Sectors,0),7),INDEX(GP_IC_T,MATCH($B7,GP_IC_Sectors,0),8),IF(K7>=INDEX(GP_IC_T,MATCH($B7,GP_IC_Sectors,0),9),INDEX(GP_IC_T,MATCH($B7,GP_IC_Sectors,0),10),IF(K7>=INDEX(GP_IC_T,MATCH($B7,GP_IC_Sectors,0),11),INDEX(GP_IC_T,MATCH($B7,GP_IC_Sectors,0),12),0)))))))) -> 85 | AD7: =IF(OR($B7="",L7=""),"",IF(ISERROR(MATCH($B7,GP_FM_Sectors,0)),0,IF(L7>=INDEX(GP_FM_T,MATCH($B7,GP_FM_Sectors,0),1),INDEX(GP_FM_T,MATCH($B7,GP_FM_Sectors,0),2),IF(L7>=INDEX(GP_FM_T,MATCH($B7,GP_FM_Sectors,0),3),INDEX(GP_FM_T,MATCH($B7,GP_FM_Sectors,0),4),IF(L7>=INDEX(GP_FM_T,MATCH($B7,GP_FM_Sectors,0),5),INDEX(GP_FM_T,MATCH($B7,GP_FM_Sectors,0),6),IF(L7>=INDEX(GP_FM_T,MATCH($B7,GP_FM_Sectors,0),7),INDEX(GP_FM_T,MATCH($B7,GP_FM_Sectors,0),8),IF(L7>=INDEX(GP_FM_T,MATCH($B7,GP_FM_Sectors,0),9),INDEX(GP_FM_T,MATCH($B7,GP_FM_Sectors,0),10),IF(L7>=INDEX(GP_FM_T,MATCH($B7,GP_FM_Sectors,0),11),INDEX(GP_FM_T,MATCH($B7,GP_FM_Sectors,0),12),0)))))))) -> 68 | AE7: =IF(OR($B7="",M7=""),"",IF(ISERROR(MATCH($B7,GP_FN_Sectors,0)),0,IF(M7>=INDEX(GP_FN_T,MATCH($B7,GP_FN_Sectors,0),1),INDEX(GP_FN_T,MATCH($B7,GP_FN_Sectors,0),2),IF(M7>=INDEX(GP_FN_T,MATCH($B7,GP_FN_Sectors,0),3),INDEX(GP_FN_T,MATCH($B7,GP_FN_Sectors,0),4),IF(M7>=INDEX(GP_FN_T,MATCH($B7,GP_FN_Sectors,0),5),INDEX(GP_FN_T,MATCH($B7,GP_FN_Sectors,0),6),IF(M7>=INDEX(GP_FN_T,MATCH($B7,GP_FN_Sectors,0),7),INDEX(GP_FN_T,MATCH($B7,GP_FN_Sectors,0),8),IF(M7>=INDEX(GP_FN_T,MATCH($B7,GP_FN_Sectors,0),9),INDEX(GP_FN_T,MATCH($B7,GP_FN_Sectors,0),10),IF(M7>=INDEX(GP_FN_T,MATCH($B7,GP_FN_Sectors,0),11),INDEX(GP_FN_T,MATCH($B7,GP_FN_Sectors,0),12),0)))))))) -> 70 | AF7: =IF(OR($B7="",N7=""),"",IF(ISERROR(MATCH($B7,GP_CX_Sectors,0)),0,IF(N7<=INDEX(GP_CX_T,MATCH($B7,GP_CX_Sectors,0),1),INDEX(GP_CX_T,MATCH($B7,GP_CX_Sectors,0),2),IF(N7<=INDEX(GP_CX_T,MATCH($B7,GP_CX_Sectors,0),3),INDEX(GP_CX_T,MATCH($B7,GP_CX_Sectors,0),4),IF(N7<=INDEX(GP_CX_T,MATCH($B7,GP_CX_Sectors,0),5),INDEX(GP_CX_T,MATCH($B7,GP_CX_Sectors,0),6),IF(N7<=INDEX(GP_CX_T,MATCH($B7,GP_CX_Sectors,0),7),INDEX(GP_CX_T,MATCH($B7,GP_CX_Sectors,0),8),IF(N7<=INDEX(GP_CX_T,MATCH($B7,GP_CX_Sectors,0),9),INDEX(GP_CX_T,MATCH($B7,GP_CX_Sectors,0),10),IF(N7<=INDEX(GP_CX_T,MATCH($B7,GP_CX_Sectors,0),11),INDEX(GP_CX_T,MATCH($B7,GP_CX_Sectors,0),12),0)))))))) -> 85 | AG7: =IF(OR($B7="",O7=""),"",IF(ISERROR(MATCH($B7,GP_PE_Sectors,0)),0,IF(O7<=INDEX(GP_PE_T,MATCH($B7,GP_PE_Sectors,0),1),INDEX(GP_PE_T,MATCH($B7,GP_PE_Sectors,0),2),IF(O7<=INDEX(GP_PE_T,MATCH($B7,GP_PE_Sectors,0),3),INDEX(GP_PE_T,MATCH($B7,GP_PE_Sectors,0),4),IF(O7<=INDEX(GP_PE_T,MATCH($B7,GP_PE_Sectors,0),5),INDEX(GP_PE_T,MATCH($B7,GP_PE_Sectors,0),6),IF(O7<=INDEX(GP_PE_T,MATCH($B7,GP_PE_Sectors,0),7),INDEX(GP_PE_T,MATCH($B7,GP_PE_Sectors,0),8),IF(O7<=INDEX(GP_PE_T,MATCH($B7,GP_PE_Sectors,0),9),INDEX(GP_PE_T,MATCH($B7,GP_PE_Sectors,0),10),IF(O7<=INDEX(GP_PE_T,MATCH($B7,GP_PE_Sectors,0),11),INDEX(GP_PE_T,MATCH($B7,GP_PE_Sectors,0),12),0)))))))) -> 85 | AH7: =IF(OR($B7="",P7=""),"",IF(ISERROR(MATCH($B7,GP_EV_Sectors,0)),0,IF(P7<=INDEX(GP_EV_T,MATCH($B7,GP_EV_Sectors,0),1),INDEX(GP_EV_T,MATCH($B7,GP_EV_Sectors,0),2),IF(P7<=INDEX(GP_EV_T,MATCH($B7,GP_EV_Sectors,0),3),INDEX(GP_EV_T,MATCH($B7,GP_EV_Sectors,0),4),IF(P7<=INDEX(GP_EV_T,MATCH($B7,GP_EV_Sectors,0),5),INDEX(GP_EV_T,MATCH($B7,GP_EV_Sectors,0),6),IF(P7<=INDEX(GP_EV_T,MATCH($B7,GP_EV_Sectors,0),7),INDEX(GP_EV_T,MATCH($B7,GP_EV_Sectors,0),8),IF(P7<=INDEX(GP_EV_T,MATCH($B7,GP_EV_Sectors,0),9),INDEX(GP_EV_T,MATCH($B7,GP_EV_Sectors,0),10),IF(P7<=INDEX(GP_EV_T,MATCH($B7,GP_EV_Sectors,0),11),INDEX(GP_EV_T,MATCH($B7,GP_EV_Sectors,0),12),0)))))))) -> 85 | AI7: =IF(OR($B7="",Q7=""),"",IF(ISERROR(MATCH($B7,GP_PF_Sectors,0)),0,IF(Q7<=INDEX(GP_PF_T,MATCH($B7,GP_PF_Sectors,0),1),INDEX(GP_PF_T,MATCH($B7,GP_PF_Sectors,0),2),IF(Q7<=INDEX(GP_PF_T,MATCH($B7,GP_PF_Sectors,0),3),INDEX(GP_PF_T,MATCH($B7,GP_PF_Sectors,0),4),IF(Q7<=INDEX(GP_PF_T,MATCH($B7,GP_PF_Sectors,0),5),INDEX(GP_PF_T,MATCH($B7,GP_PF_Sectors,0),6),IF(Q7<=INDEX(GP_PF_T,MATCH($B7,GP_PF_Sectors,0),7),INDEX(GP_PF_T,MATCH($B7,GP_PF_Sectors,0),8),IF(Q7<=INDEX(GP_PF_T,MATCH($B7,GP_PF_Sectors,0),9),INDEX(GP_PF_T,MATCH($B7,GP_PF_Sectors,0),10),IF(Q7<=INDEX(GP_PF_T,MATCH($B7,GP_PF_Sectors,0),11),INDEX(GP_PF_T,MATCH($B7,GP_PF_Sectors,0),12),0)))))))) -> 85 | AJ7: =IF(OR($B7="",R7=""),"",IF(ISERROR(MATCH($B7,GP_DY_Sectors,0)),0,IF(R7>=INDEX(GP_DY_T,MATCH($B7,GP_DY_Sectors,0),1),INDEX(GP_DY_T,MATCH($B7,GP_DY_Sectors,0),2),IF(R7>=INDEX(GP_DY_T,MATCH($B7,GP_DY_Sectors,0),3),INDEX(GP_DY_T,MATCH($B7,GP_DY_Sectors,0),4),IF(R7>=INDEX(GP_DY_T,MATCH($B7,GP_DY_Sectors,0),5),INDEX(GP_DY_T,MATCH($B7,GP_DY_Sectors,0),6),IF(R7>=INDEX(GP_DY_T,MATCH($B7,GP_DY_Sectors,0),7),INDEX(GP_DY_T,MATCH($B7,GP_DY_Sectors,0),8),IF(R7>=INDEX(GP_DY_T,MATCH($B7,GP_DY_Sectors,0),9),INDEX(GP_DY_T,MATCH($B7,GP_DY_Sectors,0),10),IF(R7>=INDEX(GP_DY_T,MATCH($B7,GP_DY_Sectors,0),11),INDEX(GP_DY_T,MATCH($B7,GP_DY_Sectors,0),12),0)))))))) -> 8 | AK7: =IF(OR($B7="",S7=""),"",IF(ISERROR(MATCH($B7,GP_PR_Sectors,0)),0,IF(S7>=INDEX(GP_PR_T,MATCH($B7,GP_PR_Sectors,0),1),INDEX(GP_PR_T,MATCH($B7,GP_PR_Sectors,0),2),IF(S7>=INDEX(GP_PR_T,MATCH($B7,GP_PR_Sectors,0),3),INDEX(GP_PR_T,MATCH($B7,GP_PR_Sectors,0),4),IF(S7>=INDEX(GP_PR_T,MATCH($B7,GP_PR_Sectors,0),5),INDEX(GP_PR_T,MATCH($B7,GP_PR_Sectors,0),6),IF(S7>=INDEX(GP_PR_T,MATCH($B7,GP_PR_Sectors,0),7),INDEX(GP_PR_T,MATCH($B7,GP_PR_Sectors,0),8),IF(S7>=INDEX(GP_PR_T,MATCH($B7,GP_PR_Sectors,0),9),INDEX(GP_PR_T,MATCH($B7,GP_PR_Sectors,0),10),IF(S7>=INDEX(GP_PR_T,MATCH($B7,GP_PR_Sectors,0),11),INDEX(GP_PR_T,MATCH($B7,GP_PR_Sectors,0),12),0)))))))) -> 0 | AL7: =IF(OR($B7="",T7=""),"",IF(ISERROR(MATCH($B7,GP_BY_Sectors,0)),0,IF(T7>=INDEX(GP_BY_T,MATCH($B7,GP_BY_Sectors,0),1),INDEX(GP_BY_T,MATCH($B7,GP_BY_Sectors,0),2),IF(T7>=INDEX(GP_BY_T,MATCH($B7,GP_BY_Sectors,0),3),INDEX(GP_BY_T,MATCH($B7,GP_BY_Sectors,0),4),IF(T7>=INDEX(GP_BY_T,MATCH($B7,GP_BY_Sectors,0),5),INDEX(GP_BY_T,MATCH($B7,GP_BY_Sectors,0),6),IF(T7>=INDEX(GP_BY_T,MATCH($B7,GP_BY_Sectors,0),7),INDEX(GP_BY_T,MATCH($B7,GP_BY_Sectors,0),8),IF(T7>=INDEX(GP_BY_T,MATCH($B7,GP_BY_Sectors,0),9),INDEX(GP_BY_T,MATCH($B7,GP_BY_Sectors,0),10),IF(T7>=INDEX(GP_BY_T,MATCH($B7,GP_BY_Sectors,0),11),INDEX(GP_BY_T,MATCH($B7,GP_BY_Sectors,0),12),0)))))))) -> 70 | AM7: =IF($B7="","",U7*0.35+V7*0.35+W7*0.3) -> 77.6 | AN7: =IF($B7="","",X7*0.4+Y7*0.35+Z7*0.25) -> 85 | AO7: =IF($B7="","",AA7*0.35+AB7*0.3+AC7*0.35) -> 80.5 | AP7: =IF($B7="","",AD7*0.4+AE7*0.35+AF7*0.25) -> 72.95 | AQ7: =IF($B7="","",AG7*0.35+AH7*0.35+AI7*0.3) -> 85 | AR7: =IF($B7="","",AJ7*0.45+AK7*0.2+AL7*0.35) -> 28.1 | AS7: =IF($B7="","",MIN(100,MAX(0,ROUND(AM7*INDEX(GP_W_P1,MATCH($B7,GP_Weights_Sectors,0))+AN7*INDEX(GP_W_P2,MATCH($B7,GP_Weights_Sectors,0))+AO7*INDEX(GP_W_P3,MATCH($B7,GP_Weights_Sectors,0))+AP7*INDEX(GP_W_P4,MATCH($B7,GP_Weights_Sectors,0))+AQ7*INDEX(GP_W_P5,MATCH($B7,GP_Weights_Sectors,0))+AR7*INDEX(GP_W_P6,MATCH($B7,GP_Weights_Sectors,0)),0)))) -> 75 | AT7: 2 | AU7: 3 | AV7: 3 | AW7: =MAX(-10,MIN(10,AT7+AU7+AV7)) -> 8 | AX7: #VALUE! | AY7: {=_FV(AX7,"PRECIO")} -> 475.27 | AZ7: 510 | BA7: =IFERROR(INDEX('DCF Simplified'!$Y$4:$Y$38,MATCH(A7,'DCF Simplified'!$A$4:$A$38,0)),"") -> 680.42848 | BB7: =IF(OR(AY7="",AZ7=""),"",(AZ7-AY7)/AY7) -> 0.073074253 | BD7: 0.08 | BE7: 55 | BF7: 0.15 | BG7: =IF(BD7>0.1,100,IF(BD7>0.05,80,IF(BD7>0,65,IF(BD7>-0.05,45,IF(BD7>-0.1,25,10))))) -> 80 | BH7: =IF(AND(BE7>=40,BE7<=60),70,IF(AND(BE7>60,BE7<=70),85,IF(BE7>70,50,IF(AND(BE7>=30,BE7<40),55,40)))) -> 70 | BI7: =IF(BF7>0.2,100,IF(BF7>0.1,80,IF(BF7>0,65,IF(BF7>-0.1,45,IF(BF7>-0.2,25,10))))) -> 80 | BJ7: =ROUND(BG7*0.4+BH7*0.25+BI7*0.35,1) -> 77.5 | BK7: =IF(OR(AS7="",AQ7="",BJ7=""),"",ROUND(AS7*0.4+MAX(15,MIN(90,AQ7))*0.2+BJ7*0.25+MIN(100,MAX(0,AW7*10))*0.15,0)) -> 78 | BL7: =IF(BK7="","",IF(BK7>=85,"🟢 STRONG",IF(BK7>=70,"🟡 FAVORABLE",IF(BK7>=55,"⚪ NEUTRAL",IF(BK7>=40,"🟠 WEAK","🔴 AVOID"))))) -> 🟡 FAVORABLE | BM7: =IF(BK7="","",IF(AND(BK7>=75,BJ7>=70,AW7>=6),"🚀 STRONG BUY",IF(AND(BK7>=65,BJ7>=55),"✅ BUY",IF(BK7>=55,"⚠️ HOLD",IF(OR(BK7<45,AND(BJ7<35,AW7<3)),"🔴 SELL","🟠 UNDERWEIGHT"))))) -> 🚀 STRONG BUY
A8: NextEra Energy | B8: Utilities | C8: 0.1 | D8: 0.06 | E8: 0.15 | F8: 0.1 | G8: 0.08 | H8: 0.9 | I8: 4.5 | J8: 0.7 | K8: 3 | L8: 0.04 | M8: 0.5 | N8: 0.25 | O8: 18 | P8: 14 | Q8: 25 | R8: 0.03 | S8: 0.6 | T8: 0.005 | U8: =IF(OR($B8="",C8=""),"",IF(ISERROR(MATCH($B8,GP_ROE_Sectors,0)),0,IF(C8>=INDEX(GP_ROE_T,MATCH($B8,GP_ROE_Sectors,0),1),INDEX(GP_ROE_T,MATCH($B8,GP_ROE_Sectors,0),2),IF(C8>=INDEX(GP_ROE_T,MATCH($B8,GP_ROE_Sectors,0),3),INDEX(GP_ROE_T,MATCH($B8,GP_ROE_Sectors,0),4),IF(C8>=INDEX(GP_ROE_T,MATCH($B8,GP_ROE_Sectors,0),5),INDEX(GP_ROE_T,MATCH($B8,GP_ROE_Sectors,0),6),IF(C8>=INDEX(GP_ROE_T,MATCH($B8,GP_ROE_Sectors,0),7),INDEX(GP_ROE_T,MATCH($B8,GP_ROE_Sectors,0),8),IF(C8>=INDEX(GP_ROE_T,MATCH($B8,GP_ROE_Sectors,0),9),INDEX(GP_ROE_T,MATCH($B8,GP_ROE_Sectors,0),10),IF(C8>=INDEX(GP_ROE_T,MATCH($B8,GP_ROE_Sectors,0),11),INDEX(GP_ROE_T,MATCH($B8,GP_ROE_Sectors,0),12),0)))))))) -> 85 | V8: =IF(OR($B8="",D8=""),"",IF(ISERROR(MATCH($B8,GP_ROIC_Sectors,0)),0,IF(D8>=INDEX(GP_ROIC_T,MATCH($B8,GP_ROIC_Sectors,0),1),INDEX(GP_ROIC_T,MATCH($B8,GP_ROIC_Sectors,0),2),IF(D8>=INDEX(GP_ROIC_T,MATCH($B8,GP_ROIC_Sectors,0),3),INDEX(GP_ROIC_T,MATCH($B8,GP_ROIC_Sectors,0),4),IF(D8>=INDEX(GP_ROIC_T,MATCH($B8,GP_ROIC_Sectors,0),5),INDEX(GP_ROIC_T,MATCH($B8,GP_ROIC_Sectors,0),6),IF(D8>=INDEX(GP_ROIC_T,MATCH($B8,GP_ROIC_Sectors,0),7),INDEX(GP_ROIC_T,MATCH($B8,GP_ROIC_Sectors,0),8),IF(D8>=INDEX(GP_ROIC_T,MATCH($B8,GP_ROIC_Sectors,0),9),INDEX(GP_ROIC_T,MATCH($B8,GP_ROIC_Sectors,0),10),IF(D8>=INDEX(GP_ROIC_T,MATCH($B8,GP_ROIC_Sectors,0),11),INDEX(GP_ROIC_T,MATCH($B8,GP_ROIC_Sectors,0),12),0)))))))) -> 65 | W8: =IF(OR($B8="",E8=""),"",IF(ISERROR(MATCH($B8,GP_NM_Sectors,0)),0,IF(E8>=INDEX(GP_NM_T,MATCH($B8,GP_NM_Sectors,0),1),INDEX(GP_NM_T,MATCH($B8,GP_NM_Sectors,0),2),IF(E8>=INDEX(GP_NM_T,MATCH($B8,GP_NM_Sectors,0),3),INDEX(GP_NM_T,MATCH($B8,GP_NM_Sectors,0),4),IF(E8>=INDEX(GP_NM_T,MATCH($B8,GP_NM_Sectors,0),5),INDEX(GP_NM_T,MATCH($B8,GP_NM_Sectors,0),6),IF(E8>=INDEX(GP_NM_T,MATCH($B8,GP_NM_Sectors,0),7),INDEX(GP_NM_T,MATCH($B8,GP_NM_Sectors,0),8),IF(E8>=INDEX(GP_NM_T,MATCH($B8,GP_NM_Sectors,0),9),INDEX(GP_NM_T,MATCH($B8,GP_NM_Sectors,0),10),IF(E8>=INDEX(GP_NM_T,MATCH($B8,GP_NM_Sectors,0),11),INDEX(GP_NM_T,MATCH($B8,GP_NM_Sectors,0),12),0)))))))) -> 100 | X8: =IF(OR($B8="",F8=""),"",IF(ISERROR(MATCH($B8,GP_RG_Sectors,0)),0,IF(F8>=INDEX(GP_RG_T,MATCH($B8,GP_RG_Sectors,0),1),INDEX(GP_RG_T,MATCH($B8,GP_RG_Sectors,0),2),IF(F8>=INDEX(GP_RG_T,MATCH($B8,GP_RG_Sectors,0),3),INDEX(GP_RG_T,MATCH($B8,GP_RG_Sectors,0),4),IF(F8>=INDEX(GP_RG_T,MATCH($B8,GP_RG_Sectors,0),5),INDEX(GP_RG_T,MATCH($B8,GP_RG_Sectors,0),6),IF(F8>=INDEX(GP_RG_T,MATCH($B8,GP_RG_Sectors,0),7),INDEX(GP_RG_T,MATCH($B8,GP_RG_Sectors,0),8),IF(F8>=INDEX(GP_RG_T,MATCH($B8,GP_RG_Sectors,0),9),INDEX(GP_RG_T,MATCH($B8,GP_RG_Sectors,0),10),IF(F8>=INDEX(GP_RG_T,MATCH($B8,GP_RG_Sectors,0),11),INDEX(GP_RG_T,MATCH($B8,GP_RG_Sectors,0),12),0)))))))) -> 100 | Y8: =IF(OR($B8="",G8=""),"",IF(ISERROR(MATCH($B8,GP_EG_Sectors,0)),0,IF(G8>=INDEX(GP_EG_T,MATCH($B8,GP_EG_Sectors,0),1),INDEX(GP_EG_T,MATCH($B8,GP_EG_Sectors,0),2),IF(G8>=INDEX(GP_EG_T,MATCH($B8,GP_EG_Sectors,0),3),INDEX(GP_EG_T,MATCH($B8,GP_EG_Sectors,0),4),IF(G8>=INDEX(GP_EG_T,MATCH($B8,GP_EG_Sectors,0),5),INDEX(GP_EG_T,MATCH($B8,GP_EG_Sectors,0),6),IF(G8>=INDEX(GP_EG_T,MATCH($B8,GP_EG_Sectors,0),7),INDEX(GP_EG_T,MATCH($B8,GP_EG_Sectors,0),8),IF(G8>=INDEX(GP_EG_T,MATCH($B8,GP_EG_Sectors,0),9),INDEX(GP_EG_T,MATCH($B8,GP_EG_Sectors,0),10),IF(G8>=INDEX(GP_EG_T,MATCH($B8,GP_EG_Sectors,0),11),INDEX(GP_EG_T,MATCH($B8,GP_EG_Sectors,0),12),0)))))))) -> 100 | Z8: =IF(OR($B8="",H8=""),"",IF(ISERROR(MATCH($B8,GP_OL_Sectors,0)),0,IF(H8>=INDEX(GP_OL_T,MATCH($B8,GP_OL_Sectors,0),1),INDEX(GP_OL_T,MATCH($B8,GP_OL_Sectors,0),2),IF(H8>=INDEX(GP_OL_T,MATCH($B8,GP_OL_Sectors,0),3),INDEX(GP_OL_T,MATCH($B8,GP_OL_Sectors,0),4),IF(H8>=INDEX(GP_OL_T,MATCH($B8,GP_OL_Sectors,0),5),INDEX(GP_OL_T,MATCH($B8,GP_OL_Sectors,0),6),IF(H8>=INDEX(GP_OL_T,MATCH($B8,GP_OL_Sectors,0),7),INDEX(GP_OL_T,MATCH($B8,GP_OL_Sectors,0),8),IF(H8>=INDEX(GP_OL_T,MATCH($B8,GP_OL_Sectors,0),9),INDEX(GP_OL_T,MATCH($B8,GP_OL_Sectors,0),10),IF(H8>=INDEX(GP_OL_T,MATCH($B8,GP_OL_Sectors,0),11),INDEX(GP_OL_T,MATCH($B8,GP_OL_Sectors,0),12),0)))))))) -> 65 | AA8: =IF(OR($B8="",I8=""),"",IF(ISERROR(MATCH($B8,GP_ND_Sectors,0)),0,IF(I8<=INDEX(GP_ND_T,MATCH($B8,GP_ND_Sectors,0),1),INDEX(GP_ND_T,MATCH($B8,GP_ND_Sectors,0),2),IF(I8<=INDEX(GP_ND_T,MATCH($B8,GP_ND_Sectors,0),3),INDEX(GP_ND_T,MATCH($B8,GP_ND_Sectors,0),4),IF(I8<=INDEX(GP_ND_T,MATCH($B8,GP_ND_Sectors,0),5),INDEX(GP_ND_T,MATCH($B8,GP_ND_Sectors,0),6),IF(I8<=INDEX(GP_ND_T,MATCH($B8,GP_ND_Sectors,0),7),INDEX(GP_ND_T,MATCH($B8,GP_ND_Sectors,0),8),IF(I8<=INDEX(GP_ND_T,MATCH($B8,GP_ND_Sectors,0),9),INDEX(GP_ND_T,MATCH($B8,GP_ND_Sectors,0),10),IF(I8<=INDEX(GP_ND_T,MATCH($B8,GP_ND_Sectors,0),11),INDEX(GP_ND_T,MATCH($B8,GP_ND_Sectors,0),12),0)))))))) -> 48 | AB8: =IF(OR($B8="",J8=""),"",IF(ISERROR(MATCH($B8,GP_CR_Sectors,0)),0,IF(J8>=INDEX(GP_CR_T,MATCH($B8,GP_CR_Sectors,0),1),INDEX(GP_CR_T,MATCH($B8,GP_CR_Sectors,0),2),IF(J8>=INDEX(GP_CR_T,MATCH($B8,GP_CR_Sectors,0),3),INDEX(GP_CR_T,MATCH($B8,GP_CR_Sectors,0),4),IF(J8>=INDEX(GP_CR_T,MATCH($B8,GP_CR_Sectors,0),5),INDEX(GP_CR_T,MATCH($B8,GP_CR_Sectors,0),6),IF(J8>=INDEX(GP_CR_T,MATCH($B8,GP_CR_Sectors,0),7),INDEX(GP_CR_T,MATCH($B8,GP_CR_Sectors,0),8),IF(J8>=INDEX(GP_CR_T,MATCH($B8,GP_CR_Sectors,0),9),INDEX(GP_CR_T,MATCH($B8,GP_CR_Sectors,0),10),IF(J8>=INDEX(GP_CR_T,MATCH($B8,GP_CR_Sectors,0),11),INDEX(GP_CR_T,MATCH($B8,GP_CR_Sectors,0),12),0)))))))) -> 48 | AC8: =IF(OR($B8="",K8=""),"",IF(ISERROR(MATCH($B8,GP_IC_Sectors,0)),0,IF(K8>=INDEX(GP_IC_T,MATCH($B8,GP_IC_Sectors,0),1),INDEX(GP_IC_T,MATCH($B8,GP_IC_Sectors,0),2),IF(K8>=INDEX(GP_IC_T,MATCH($B8,GP_IC_Sectors,0),3),INDEX(GP_IC_T,MATCH($B8,GP_IC_Sectors,0),4),IF(K8>=INDEX(GP_IC_T,MATCH($B8,GP_IC_Sectors,0),5),INDEX(GP_IC_T,MATCH($B8,GP_IC_Sectors,0),6),IF(K8>=INDEX(GP_IC_T,MATCH($B8,GP_IC_Sectors,0),7),INDEX(GP_IC_T,MATCH($B8,GP_IC_Sectors,0),8),IF(K8>=INDEX(GP_IC_T,MATCH($B8,GP_IC_Sectors,0),9),INDEX(GP_IC_T,MATCH($B8,GP_IC_Sectors,0),10),IF(K8>=INDEX(GP_IC_T,MATCH($B8,GP_IC_Sectors,0),11),INDEX(GP_IC_T,MATCH($B8,GP_IC_Sectors,0),12),0)))))))) -> 65 | AD8: =IF(OR($B8="",L8=""),"",IF(ISERROR(MATCH($B8,GP_FM_Sectors,0)),0,IF(L8>=INDEX(GP_FM_T,MATCH($B8,GP_FM_Sectors,0),1),INDEX(GP_FM_T,MATCH($B8,GP_FM_Sectors,0),2),IF(L8>=INDEX(GP_FM_T,MATCH($B8,GP_FM_Sectors,0),3),INDEX(GP_FM_T,MATCH($B8,GP_FM_Sectors,0),4),IF(L8>=INDEX(GP_FM_T,MATCH($B8,GP_FM_Sectors,0),5),INDEX(GP_FM_T,MATCH($B8,GP_FM_Sectors,0),6),IF(L8>=INDEX(GP_FM_T,MATCH($B8,GP_FM_Sectors,0),7),INDEX(GP_FM_T,MATCH($B8,GP_FM_Sectors,0),8),IF(L8>=INDEX(GP_FM_T,MATCH($B8,GP_FM_Sectors,0),9),INDEX(GP_FM_T,MATCH($B8,GP_FM_Sectors,0),10),IF(L8>=INDEX(GP_FM_T,MATCH($B8,GP_FM_Sectors,0),11),INDEX(GP_FM_T,MATCH($B8,GP_FM_Sectors,0),12),0)))))))) -> 60 | AE8: =IF(OR($B8="",M8=""),"",IF(ISERROR(MATCH($B8,GP_FN_Sectors,0)),0,IF(M8>=INDEX(GP_FN_T,MATCH($B8,GP_FN_Sectors,0),1),INDEX(GP_FN_T,MATCH($B8,GP_FN_Sectors,0),2),IF(M8>=INDEX(GP_FN_T,MATCH($B8,GP_FN_Sectors,0),3),INDEX(GP_FN_T,MATCH($B8,GP_FN_Sectors,0),4),IF(M8>=INDEX(GP_FN_T,MATCH($B8,GP_FN_Sectors,0),5),INDEX(GP_FN_T,MATCH($B8,GP_FN_Sectors,0),6),IF(M8>=INDEX(GP_FN_T,MATCH($B8,GP_FN_Sectors,0),7),INDEX(GP_FN_T,MATCH($B8,GP_FN_Sectors,0),8),IF(M8>=INDEX(GP_FN_T,MATCH($B8,GP_FN_Sectors,0),9),INDEX(GP_FN_T,MATCH($B8,GP_FN_Sectors,0),10),IF(M8>=INDEX(GP_FN_T,MATCH($B8,GP_FN_Sectors,0),11),INDEX(GP_FN_T,MATCH($B8,GP_FN_Sectors,0),12),0)))))))) -> 60 | AF8: =IF(OR($B8="",N8=""),"",IF(ISERROR(MATCH($B8,GP_CX_Sectors,0)),0,IF(N8<=INDEX(GP_CX_T,MATCH($B8,GP_CX_Sectors,0),1),INDEX(GP_CX_T,MATCH($B8,GP_CX_Sectors,0),2),IF(N8<=INDEX(GP_CX_T,MATCH($B8,GP_CX_Sectors,0),3),INDEX(GP_CX_T,MATCH($B8,GP_CX_Sectors,0),4),IF(N8<=INDEX(GP_CX_T,MATCH($B8,GP_CX_Sectors,0),5),INDEX(GP_CX_T,MATCH($B8,GP_CX_Sectors,0),6),IF(N8<=INDEX(GP_CX_T,MATCH($B8,GP_CX_Sectors,0),7),INDEX(GP_CX_T,MATCH($B8,GP_CX_Sectors,0),8),IF(N8<=INDEX(GP_CX_T,MATCH($B8,GP_CX_Sectors,0),9),INDEX(GP_CX_T,MATCH($B8,GP_CX_Sectors,0),10),IF(N8<=INDEX(GP_CX_T,MATCH($B8,GP_CX_Sectors,0),11),INDEX(GP_CX_T,MATCH($B8,GP_CX_Sectors,0),12),0)))))))) -> 42 | AG8: =IF(OR($B8="",O8=""),"",IF(ISERROR(MATCH($B8,GP_PE_Sectors,0)),0,IF(O8<=INDEX(GP_PE_T,MATCH($B8,GP_PE_Sectors,0),1),INDEX(GP_PE_T,MATCH($B8,GP_PE_Sectors,0),2),IF(O8<=INDEX(GP_PE_T,MATCH($B8,GP_PE_Sectors,0),3),INDEX(GP_PE_T,MATCH($B8,GP_PE_Sectors,0),4),IF(O8<=INDEX(GP_PE_T,MATCH($B8,GP_PE_Sectors,0),5),INDEX(GP_PE_T,MATCH($B8,GP_PE_Sectors,0),6),IF(O8<=INDEX(GP_PE_T,MATCH($B8,GP_PE_Sectors,0),7),INDEX(GP_PE_T,MATCH($B8,GP_PE_Sectors,0),8),IF(O8<=INDEX(GP_PE_T,MATCH($B8,GP_PE_Sectors,0),9),INDEX(GP_PE_T,MATCH($B8,GP_PE_Sectors,0),10),IF(O8<=INDEX(GP_PE_T,MATCH($B8,GP_PE_Sectors,0),11),INDEX(GP_PE_T,MATCH($B8,GP_PE_Sectors,0),12),0)))))))) -> 62 | AH8: =IF(OR($B8="",P8=""),"",IF(ISERROR(MATCH($B8,GP_EV_Sectors,0)),0,IF(P8<=INDEX(GP_EV_T,MATCH($B8,GP_EV_Sectors,0),1),INDEX(GP_EV_T,MATCH($B8,GP_EV_Sectors,0),2),IF(P8<=INDEX(GP_EV_T,MATCH($B8,GP_EV_Sectors,0),3),INDEX(GP_EV_T,MATCH($B8,GP_EV_Sectors,0),4),IF(P8<=INDEX(GP_EV_T,MATCH($B8,GP_EV_Sectors,0),5),INDEX(GP_EV_T,MATCH($B8,GP_EV_Sectors,0),6),IF(P8<=INDEX(GP_EV_T,MATCH($B8,GP_EV_Sectors,0),7),INDEX(GP_EV_T,MATCH($B8,GP_EV_Sectors,0),8),IF(P8<=INDEX(GP_EV_T,MATCH($B8,GP_EV_Sectors,0),9),INDEX(GP_EV_T,MATCH($B8,GP_EV_Sectors,0),10),IF(P8<=INDEX(GP_EV_T,MATCH($B8,GP_EV_Sectors,0),11),INDEX(GP_EV_T,MATCH($B8,GP_EV_Sectors,0),12),0)))))))) -> 45 | AI8: =IF(OR($B8="",Q8=""),"",IF(ISERROR(MATCH($B8,GP_PF_Sectors,0)),0,IF(Q8<=INDEX(GP_PF_T,MATCH($B8,GP_PF_Sectors,0),1),INDEX(GP_PF_T,MATCH($B8,GP_PF_Sectors,0),2),IF(Q8<=INDEX(GP_PF_T,MATCH($B8,GP_PF_Sectors,0),3),INDEX(GP_PF_T,MATCH($B8,GP_PF_Sectors,0),4),IF(Q8<=INDEX(GP_PF_T,MATCH($B8,GP_PF_Sectors,0),5),INDEX(GP_PF_T,MATCH($B8,GP_PF_Sectors,0),6),IF(Q8<=INDEX(GP_PF_T,MATCH($B8,GP_PF_Sectors,0),7),INDEX(GP_PF_T,MATCH($B8,GP_PF_Sectors,0),8),IF(Q8<=INDEX(GP_PF_T,MATCH($B8,GP_PF_Sectors,0),9),INDEX(GP_PF_T,MATCH($B8,GP_PF_Sectors,0),10),IF(Q8<=INDEX(GP_PF_T,MATCH($B8,GP_PF_Sectors,0),11),INDEX(GP_PF_T,MATCH($B8,GP_PF_Sectors,0),12),0)))))))) -> 60 | AJ8: =IF(OR($B8="",R8=""),"",IF(ISERROR(MATCH($B8,GP_DY_Sectors,0)),0,IF(R8>=INDEX(GP_DY_T,MATCH($B8,GP_DY_Sectors,0),1),INDEX(GP_DY_T,MATCH($B8,GP_DY_Sectors,0),2),IF(R8>=INDEX(GP_DY_T,MATCH($B8,GP_DY_Sectors,0),3),INDEX(GP_DY_T,MATCH($B8,GP_DY_Sectors,0),4),IF(R8>=INDEX(GP_DY_T,MATCH($B8,GP_DY_Sectors,0),5),INDEX(GP_DY_T,MATCH($B8,GP_DY_Sectors,0),6),IF(R8>=INDEX(GP_DY_T,MATCH($B8,GP_DY_Sectors,0),7),INDEX(GP_DY_T,MATCH($B8,GP_DY_Sectors,0),8),IF(R8>=INDEX(GP_DY_T,MATCH($B8,GP_DY_Sectors,0),9),INDEX(GP_DY_T,MATCH($B8,GP_DY_Sectors,0),10),IF(R8>=INDEX(GP_DY_T,MATCH($B8,GP_DY_Sectors,0),11),INDEX(GP_DY_T,MATCH($B8,GP_DY_Sectors,0),12),0)))))))) -> 72 | AK8: =IF(OR($B8="",S8=""),"",IF(ISERROR(MATCH($B8,GP_PR_Sectors,0)),0,IF(S8>=INDEX(GP_PR_T,MATCH($B8,GP_PR_Sectors,0),1),INDEX(GP_PR_T,MATCH($B8,GP_PR_Sectors,0),2),IF(S8>=INDEX(GP_PR_T,MATCH($B8,GP_PR_Sectors,0),3),INDEX(GP_PR_T,MATCH($B8,GP_PR_Sectors,0),4),IF(S8>=INDEX(GP_PR_T,MATCH($B8,GP_PR_Sectors,0),5),INDEX(GP_PR_T,MATCH($B8,GP_PR_Sectors,0),6),IF(S8>=INDEX(GP_PR_T,MATCH($B8,GP_PR_Sectors,0),7),INDEX(GP_PR_T,MATCH($B8,GP_PR_Sectors,0),8),IF(S8>=INDEX(GP_PR_T,MATCH($B8,GP_PR_Sectors,0),9),INDEX(GP_PR_T,MATCH($B8,GP_PR_Sectors,0),10),IF(S8>=INDEX(GP_PR_T,MATCH($B8,GP_PR_Sectors,0),11),INDEX(GP_PR_T,MATCH($B8,GP_PR_Sectors,0),12),0)))))))) -> 88 | AL8: =IF(OR($B8="",T8=""),"",IF(ISERROR(MATCH($B8,GP_BY_Sectors,0)),0,IF(T8>=INDEX(GP_BY_T,MATCH($B8,GP_BY_Sectors,0),1),INDEX(GP_BY_T,MATCH($B8,GP_BY_Sectors,0),2),IF(T8>=INDEX(GP_BY_T,MATCH($B8,GP_BY_Sectors,0),3),INDEX(GP_BY_T,MATCH($B8,GP_BY_Sectors,0),4),IF(T8>=INDEX(GP_BY_T,MATCH($B8,GP_BY_Sectors,0),5),INDEX(GP_BY_T,MATCH($B8,GP_BY_Sectors,0),6),IF(T8>=INDEX(GP_BY_T,MATCH($B8,GP_BY_Sectors,0),7),INDEX(GP_BY_T,MATCH($B8,GP_BY_Sectors,0),8),IF(T8>=INDEX(GP_BY_T,MATCH($B8,GP_BY_Sectors,0),9),INDEX(GP_BY_T,MATCH($B8,GP_BY_Sectors,0),10),IF(T8>=INDEX(GP_BY_T,MATCH($B8,GP_BY_Sectors,0),11),INDEX(GP_BY_T,MATCH($B8,GP_BY_Sectors,0),12),0)))))))) -> 40 | AM8: =IF($B8="","",U8*0.35+V8*0.35+W8*0.3) -> 82.5 | AN8: =IF($B8="","",X8*0.4+Y8*0.35+Z8*0.25) -> 91.25 | AO8: =IF($B8="","",AA8*0.35+AB8*0.3+AC8*0.35) -> 53.95 | AP8: =IF($B8="","",AD8*0.4+AE8*0.35+AF8*0.25) -> 55.5 | AQ8: =IF($B8="","",AG8*0.35+AH8*0.35+AI8*0.3) -> 55.45 | AR8: =IF($B8="","",AJ8*0.45+AK8*0.2+AL8*0.35) -> 64 | AS8: =IF($B8="","",MIN(100,MAX(0,ROUND(AM8*INDEX(GP_W_P1,MATCH($B8,GP_Weights_Sectors,0))+AN8*INDEX(GP_W_P2,MATCH($B8,GP_Weights_Sectors,0))+AO8*INDEX(GP_W_P3,MATCH($B8,GP_Weights_Sectors,0))+AP8*INDEX(GP_W_P4,MATCH($B8,GP_Weights_Sectors,0))+AQ8*INDEX(GP_W_P5,MATCH($B8,GP_Weights_Sectors,0))+AR8*INDEX(GP_W_P6,MATCH($B8,GP_Weights_Sectors,0)),0)))) -> 64 | AT8: -1 | AU8: 1 | AV8: 0 | AW8: =MAX(-10,MIN(10,AT8+AU8+AV8)) -> 0 | AX8: #VALUE! | AY8: {=_FV(AX8,"PRECIO")} -> 91.16 | AZ8: 77 | BA8: =IFERROR(INDEX('DCF Simplified'!$Y$4:$Y$38,MATCH(A8,'DCF Simplified'!$A$4:$A$38,0)),"") -> 3.7164874 | BB8: =IF(OR(AY8="",AZ8=""),"",(AZ8-AY8)/AY8) -> -0.15533129 | BD8: -0.03 | BE8: 42 | BF8: -0.08 | BG8: =IF(BD8>0.1,100,IF(BD8>0.05,80,IF(BD8>0,65,IF(BD8>-0.05,45,IF(BD8>-0.1,25,10))))) -> 45 | BH8: =IF(AND(BE8>=40,BE8<=60),70,IF(AND(BE8>60,BE8<=70),85,IF(BE8>70,50,IF(AND(BE8>=30,BE8<40),55,40)))) -> 70 | BI8: =IF(BF8>0.2,100,IF(BF8>0.1,80,IF(BF8>0,65,IF(BF8>-0.1,45,IF(BF8>-0.2,25,10))))) -> 45 | BJ8: =ROUND(BG8*0.4+BH8*0.25+BI8*0.35,1) -> 51.3 | BK8: =IF(OR(AS8="",AQ8="",BJ8=""),"",ROUND(AS8*0.4+MAX(15,MIN(90,AQ8))*0.2+BJ8*0.25+MIN(100,MAX(0,AW8*10))*0.15,0)) -> 50 | BL8: =IF(BK8="","",IF(BK8>=85,"🟢 STRONG",IF(BK8>=70,"🟡 FAVORABLE",IF(BK8>=55,"⚪ NEUTRAL",IF(BK8>=40,"🟠 WEAK","🔴 AVOID"))))) -> 🟠 WEAK | BM8: =IF(BK8="","",IF(AND(BK8>=75,BJ8>=70,AW8>=6),"🚀 STRONG BUY",IF(AND(BK8>=65,BJ8>=55),"✅ BUY",IF(BK8>=55,"⚠️ HOLD",IF(OR(BK8<45,AND(BJ8<35,AW8<3)),"🔴 SELL","🟠 UNDERWEIGHT"))))) -> 🟠 UNDERWEIGHT
A9: Apple Inc | B9: Information Technology | C9: 1.52 | D9: 0.485 | E9: 0.267 | F9: 0.05 | G9: 0.1 | H9: 1.6 | I9: -0.5 | J9: 1 | K9: 40 | L9: 0.27 | M9: 1.05 | N9: 0.05 | O9: 33 | P9: 27 | Q9: 38 | R9: 0.005 | S9: 0.15 | T9: 0.035 | U9: =IF(OR($B9="",C9=""),"",IF(ISERROR(MATCH($B9,GP_ROE_Sectors,0)),0,IF(C9>=INDEX(GP_ROE_T,MATCH($B9,GP_ROE_Sectors,0),1),INDEX(GP_ROE_T,MATCH($B9,GP_ROE_Sectors,0),2),IF(C9>=INDEX(GP_ROE_T,MATCH($B9,GP_ROE_Sectors,0),3),INDEX(GP_ROE_T,MATCH($B9,GP_ROE_Sectors,0),4),IF(C9>=INDEX(GP_ROE_T,MATCH($B9,GP_ROE_Sectors,0),5),INDEX(GP_ROE_T,MATCH($B9,GP_ROE_Sectors,0),6),IF(C9>=INDEX(GP_ROE_T,MATCH($B9,GP_ROE_Sectors,0),7),INDEX(GP_ROE_T,MATCH($B9,GP_ROE_Sectors,0),8),IF(C9>=INDEX(GP_ROE_T,MATCH($B9,GP_ROE_Sectors,0),9),INDEX(GP_ROE_T,MATCH($B9,GP_ROE_Sectors,0),10),IF(C9>=INDEX(GP_ROE_T,MATCH($B9,GP_ROE_Sectors,0),11),INDEX(GP_ROE_T,MATCH($B9,GP_ROE_Sectors,0),12),0)))))))) -> 100 | V9: =IF(OR($B9="",D9=""),"",IF(ISERROR(MATCH($B9,GP_ROIC_Sectors,0)),0,IF(D9>=INDEX(GP_ROIC_T,MATCH($B9,GP_ROIC_Sectors,0),1),INDEX(GP_ROIC_T,MATCH($B9,GP_ROIC_Sectors,0),2),IF(D9>=INDEX(GP_ROIC_T,MATCH($B9,GP_ROIC_Sectors,0),3),INDEX(GP_ROIC_T,MATCH($B9,GP_ROIC_Sectors,0),4),IF(D9>=INDEX(GP_ROIC_T,MATCH($B9,GP_ROIC_Sectors,0),5),INDEX(GP_ROIC_T,MATCH($B9,GP_ROIC_Sectors,0),6),IF(D9>=INDEX(GP_ROIC_T,MATCH($B9,GP_ROIC_Sectors,0),7),INDEX(GP_ROIC_T,MATCH($B9,GP_ROIC_Sectors,0),8),IF(D9>=INDEX(GP_ROIC_T,MATCH($B9,GP_ROIC_Sectors,0),9),INDEX(GP_ROIC_T,MATCH($B9,GP_ROIC_Sectors,0),10),IF(D9>=INDEX(GP_ROIC_T,MATCH($B9,GP_ROIC_Sectors,0),11),INDEX(GP_ROIC_T,MATCH($B9,GP_ROIC_Sectors,0),12),0)))))))) -> 100 | W9: =IF(OR($B9="",E9=""),"",IF(ISERROR(MATCH($B9,GP_NM_Sectors,0)),0,IF(E9>=INDEX(GP_NM_T,MATCH($B9,GP_NM_Sectors,0),1),INDEX(GP_NM_T,MATCH($B9,GP_NM_Sectors,0),2),IF(E9>=INDEX(GP_NM_T,MATCH($B9,GP_NM_Sectors,0),3),INDEX(GP_NM_T,MATCH($B9,GP_NM_Sectors,0),4),IF(E9>=INDEX(GP_NM_T,MATCH($B9,GP_NM_Sectors,0),5),INDEX(GP_NM_T,MATCH($B9,GP_NM_Sectors,0),6),IF(E9>=INDEX(GP_NM_T,MATCH($B9,GP_NM_Sectors,0),7),INDEX(GP_NM_T,MATCH($B9,GP_NM_Sectors,0),8),IF(E9>=INDEX(GP_NM_T,MATCH($B9,GP_NM_Sectors,0),9),INDEX(GP_NM_T,MATCH($B9,GP_NM_Sectors,0),10),IF(E9>=INDEX(GP_NM_T,MATCH($B9,GP_NM_Sectors,0),11),INDEX(GP_NM_T,MATCH($B9,GP_NM_Sectors,0),12),0)))))))) -> 100 | X9: =IF(OR($B9="",F9=""),"",IF(ISERROR(MATCH($B9,GP_RG_Sectors,0)),0,IF(F9>=INDEX(GP_RG_T,MATCH($B9,GP_RG_Sectors,0),1),INDEX(GP_RG_T,MATCH($B9,GP_RG_Sectors,0),2),IF(F9>=INDEX(GP_RG_T,MATCH($B9,GP_RG_Sectors,0),3),INDEX(GP_RG_T,MATCH($B9,GP_RG_Sectors,0),4),IF(F9>=INDEX(GP_RG_T,MATCH($B9,GP_RG_Sectors,0),5),INDEX(GP_RG_T,MATCH($B9,GP_RG_Sectors,0),6),IF(F9>=INDEX(GP_RG_T,MATCH($B9,GP_RG_Sectors,0),7),INDEX(GP_RG_T,MATCH($B9,GP_RG_Sectors,0),8),IF(F9>=INDEX(GP_RG_T,MATCH($B9,GP_RG_Sectors,0),9),INDEX(GP_RG_T,MATCH($B9,GP_RG_Sectors,0),10),IF(F9>=INDEX(GP_RG_T,MATCH($B9,GP_RG_Sectors,0),11),INDEX(GP_RG_T,MATCH($B9,GP_RG_Sectors,0),12),0)))))))) -> 35 | Y9: =IF(OR($B9="",G9=""),"",IF(ISERROR(MATCH($B9,GP_EG_Sectors,0)),0,IF(G9>=INDEX(GP_EG_T,MATCH($B9,GP_EG_Sectors,0),1),INDEX(GP_EG_T,MATCH($B9,GP_EG_Sectors,0),2),IF(G9>=INDEX(GP_EG_T,MATCH($B9,GP_EG_Sectors,0),3),INDEX(GP_EG_T,MATCH($B9,GP_EG_Sectors,0),4),IF(G9>=INDEX(GP_EG_T,MATCH($B9,GP_EG_Sectors,0),5),INDEX(GP_EG_T,MATCH($B9,GP_EG_Sectors,0),6),IF(G9>=INDEX(GP_EG_T,MATCH($B9,GP_EG_Sectors,0),7),INDEX(GP_EG_T,MATCH($B9,GP_EG_Sectors,0),8),IF(G9>=INDEX(GP_EG_T,MATCH($B9,GP_EG_Sectors,0),9),INDEX(GP_EG_T,MATCH($B9,GP_EG_Sectors,0),10),IF(G9>=INDEX(GP_EG_T,MATCH($B9,GP_EG_Sectors,0),11),INDEX(GP_EG_T,MATCH($B9,GP_EG_Sectors,0),12),0)))))))) -> 55 | Z9: =IF(OR($B9="",H9=""),"",IF(ISERROR(MATCH($B9,GP_OL_Sectors,0)),0,IF(H9>=INDEX(GP_OL_T,MATCH($B9,GP_OL_Sectors,0),1),INDEX(GP_OL_T,MATCH($B9,GP_OL_Sectors,0),2),IF(H9>=INDEX(GP_OL_T,MATCH($B9,GP_OL_Sectors,0),3),INDEX(GP_OL_T,MATCH($B9,GP_OL_Sectors,0),4),IF(H9>=INDEX(GP_OL_T,MATCH($B9,GP_OL_Sectors,0),5),INDEX(GP_OL_T,MATCH($B9,GP_OL_Sectors,0),6),IF(H9>=INDEX(GP_OL_T,MATCH($B9,GP_OL_Sectors,0),7),INDEX(GP_OL_T,MATCH($B9,GP_OL_Sectors,0),8),IF(H9>=INDEX(GP_OL_T,MATCH($B9,GP_OL_Sectors,0),9),INDEX(GP_OL_T,MATCH($B9,GP_OL_Sectors,0),10),IF(H9>=INDEX(GP_OL_T,MATCH($B9,GP_OL_Sectors,0),11),INDEX(GP_OL_T,MATCH($B9,GP_OL_Sectors,0),12),0)))))))) -> 85 | AA9: =IF(OR($B9="",I9=""),"",IF(ISERROR(MATCH($B9,GP_ND_Sectors,0)),0,IF(I9<=INDEX(GP_ND_T,MATCH($B9,GP_ND_Sectors,0),1),INDEX(GP_ND_T,MATCH($B9,GP_ND_Sectors,0),2),IF(I9<=INDEX(GP_ND_T,MATCH($B9,GP_ND_Sectors,0),3),INDEX(GP_ND_T,MATCH($B9,GP_ND_Sectors,0),4),IF(I9<=INDEX(GP_ND_T,MATCH($B9,GP_ND_Sectors,0),5),INDEX(GP_ND_T,MATCH($B9,GP_ND_Sectors,0),6),IF(I9<=INDEX(GP_ND_T,MATCH($B9,GP_ND_Sectors,0),7),INDEX(GP_ND_T,MATCH($B9,GP_ND_Sectors,0),8),IF(I9<=INDEX(GP_ND_T,MATCH($B9,GP_ND_Sectors,0),9),INDEX(GP_ND_T,MATCH($B9,GP_ND_Sectors,0),10),IF(I9<=INDEX(GP_ND_T,MATCH($B9,GP_ND_Sectors,0),11),INDEX(GP_ND_T,MATCH($B9,GP_ND_Sectors,0),12),0)))))))) -> 100 | AB9: =IF(OR($B9="",J9=""),"",IF(ISERROR(MATCH($B9,GP_CR_Sectors,0)),0,IF(J9>=INDEX(GP_CR_T,MATCH($B9,GP_CR_Sectors,0),1),INDEX(GP_CR_T,MATCH($B9,GP_CR_Sectors,0),2),IF(J9>=INDEX(GP_CR_T,MATCH($B9,GP_CR_Sectors,0),3),INDEX(GP_CR_T,MATCH($B9,GP_CR_Sectors,0),4),IF(J9>=INDEX(GP_CR_T,MATCH($B9,GP_CR_Sectors,0),5),INDEX(GP_CR_T,MATCH($B9,GP_CR_Sectors,0),6),IF(J9>=INDEX(GP_CR_T,MATCH($B9,GP_CR_Sectors,0),7),INDEX(GP_CR_T,MATCH($B9,GP_CR_Sectors,0),8),IF(J9>=INDEX(GP_CR_T,MATCH($B9,GP_CR_Sectors,0),9),INDEX(GP_CR_T,MATCH($B9,GP_CR_Sectors,0),10),IF(J9>=INDEX(GP_CR_T,MATCH($B9,GP_CR_Sectors,0),11),INDEX(GP_CR_T,MATCH($B9,GP_CR_Sectors,0),12),0)))))))) -> 35 | AC9: =IF(OR($B9="",K9=""),"",IF(ISERROR(MATCH($B9,GP_IC_Sectors,0)),0,IF(K9>=INDEX(GP_IC_T,MATCH($B9,GP_IC_Sectors,0),1),INDEX(GP_IC_T,MATCH($B9,GP_IC_Sectors,0),2),IF(K9>=INDEX(GP_IC_T,MATCH($B9,GP_IC_Sectors,0),3),INDEX(GP_IC_T,MATCH($B9,GP_IC_Sectors,0),4),IF(K9>=INDEX(GP_IC_T,MATCH($B9,GP_IC_Sectors,0),5),INDEX(GP_IC_T,MATCH($B9,GP_IC_Sectors,0),6),IF(K9>=INDEX(GP_IC_T,MATCH($B9,GP_IC_Sectors,0),7),INDEX(GP_IC_T,MATCH($B9,GP_IC_Sectors,0),8),IF(K9>=INDEX(GP_IC_T,MATCH($B9,GP_IC_Sectors,0),9),INDEX(GP_IC_T,MATCH($B9,GP_IC_Sectors,0),10),IF(K9>=INDEX(GP_IC_T,MATCH($B9,GP_IC_Sectors,0),11),INDEX(GP_IC_T,MATCH($B9,GP_IC_Sectors,0),12),0)))))))) -> 100 | AD9: =IF(OR($B9="",L9=""),"",IF(ISERROR(MATCH($B9,GP_FM_Sectors,0)),0,IF(L9>=INDEX(GP_FM_T,MATCH($B9,GP_FM_Sectors,0),1),INDEX(GP_FM_T,MATCH($B9,GP_FM_Sectors,0),2),IF(L9>=INDEX(GP_FM_T,MATCH($B9,GP_FM_Sectors,0),3),INDEX(GP_FM_T,MATCH($B9,GP_FM_Sectors,0),4),IF(L9>=INDEX(GP_FM_T,MATCH($B9,GP_FM_Sectors,0),5),INDEX(GP_FM_T,MATCH($B9,GP_FM_Sectors,0),6),IF(L9>=INDEX(GP_FM_T,MATCH($B9,GP_FM_Sectors,0),7),INDEX(GP_FM_T,MATCH($B9,GP_FM_Sectors,0),8),IF(L9>=INDEX(GP_FM_T,MATCH($B9,GP_FM_Sectors,0),9),INDEX(GP_FM_T,MATCH($B9,GP_FM_Sectors,0),10),IF(L9>=INDEX(GP_FM_T,MATCH($B9,GP_FM_Sectors,0),11),INDEX(GP_FM_T,MATCH($B9,GP_FM_Sectors,0),12),0)))))))) -> 100 | AE9: =IF(OR($B9="",M9=""),"",IF(ISERROR(MATCH($B9,GP_FN_Sectors,0)),0,IF(M9>=INDEX(GP_FN_T,MATCH($B9,GP_FN_Sectors,0),1),INDEX(GP_FN_T,MATCH($B9,GP_FN_Sectors,0),2),IF(M9>=INDEX(GP_FN_T,MATCH($B9,GP_FN_Sectors,0),3),INDEX(GP_FN_T,MATCH($B9,GP_FN_Sectors,0),4),IF(M9>=INDEX(GP_FN_T,MATCH($B9,GP_FN_Sectors,0),5),INDEX(GP_FN_T,MATCH($B9,GP_FN_Sectors,0),6),IF(M9>=INDEX(GP_FN_T,MATCH($B9,GP_FN_Sectors,0),7),INDEX(GP_FN_T,MATCH($B9,GP_FN_Sectors,0),8),IF(M9>=INDEX(GP_FN_T,MATCH($B9,GP_FN_Sectors,0),9),INDEX(GP_FN_T,MATCH($B9,GP_FN_Sectors,0),10),IF(M9>=INDEX(GP_FN_T,MATCH($B9,GP_FN_Sectors,0),11),INDEX(GP_FN_T,MATCH($B9,GP_FN_Sectors,0),12),0)))))))) -> 72 | AF9: =IF(OR($B9="",N9=""),"",IF(ISERROR(MATCH($B9,GP_CX_Sectors,0)),0,IF(N9<=INDEX(GP_CX_T,MATCH($B9,GP_CX_Sectors,0),1),INDEX(GP_CX_T,MATCH($B9,GP_CX_Sectors,0),2),IF(N9<=INDEX(GP_CX_T,MATCH($B9,GP_CX_Sectors,0),3),INDEX(GP_CX_T,MATCH($B9,GP_CX_Sectors,0),4),IF(N9<=INDEX(GP_CX_T,MATCH($B9,GP_CX_Sectors,0),5),INDEX(GP_CX_T,MATCH($B9,GP_CX_Sectors,0),6),IF(N9<=INDEX(GP_CX_T,MATCH($B9,GP_CX_Sectors,0),7),INDEX(GP_CX_T,MATCH($B9,GP_CX_Sectors,0),8),IF(N9<=INDEX(GP_CX_T,MATCH($B9,GP_CX_Sectors,0),9),INDEX(GP_CX_T,MATCH($B9,GP_CX_Sectors,0),10),IF(N9<=INDEX(GP_CX_T,MATCH($B9,GP_CX_Sectors,0),11),INDEX(GP_CX_T,MATCH($B9,GP_CX_Sectors,0),12),0)))))))) -> 85 | AG9: =IF(OR($B9="",O9=""),"",IF(ISERROR(MATCH($B9,GP_PE_Sectors,0)),0,IF(O9<=INDEX(GP_PE_T,MATCH($B9,GP_PE_Sectors,0),1),INDEX(GP_PE_T,MATCH($B9,GP_PE_Sectors,0),2),IF(O9<=INDEX(GP_PE_T,MATCH($B9,GP_PE_Sectors,0),3),INDEX(GP_PE_T,MATCH($B9,GP_PE_Sectors,0),4),IF(O9<=INDEX(GP_PE_T,MATCH($B9,GP_PE_Sectors,0),5),INDEX(GP_PE_T,MATCH($B9,GP_PE_Sectors,0),6),IF(O9<=INDEX(GP_PE_T,MATCH($B9,GP_PE_Sectors,0),7),INDEX(GP_PE_T,MATCH($B9,GP_PE_Sectors,0),8),IF(O9<=INDEX(GP_PE_T,MATCH($B9,GP_PE_Sectors,0),9),INDEX(GP_PE_T,MATCH($B9,GP_PE_Sectors,0),10),IF(O9<=INDEX(GP_PE_T,MATCH($B9,GP_PE_Sectors,0),11),INDEX(GP_PE_T,MATCH($B9,GP_PE_Sectors,0),12),0)))))))) -> 30 | AH9: =IF(OR($B9="",P9=""),"",IF(ISERROR(MATCH($B9,GP_EV_Sectors,0)),0,IF(P9<=INDEX(GP_EV_T,MATCH($B9,GP_EV_Sectors,0),1),INDEX(GP_EV_T,MATCH($B9,GP_EV_Sectors,0),2),IF(P9<=INDEX(GP_EV_T,MATCH($B9,GP_EV_Sectors,0),3),INDEX(GP_EV_T,MATCH($B9,GP_EV_Sectors,0),4),IF(P9<=INDEX(GP_EV_T,MATCH($B9,GP_EV_Sectors,0),5),INDEX(GP_EV_T,MATCH($B9,GP_EV_Sectors,0),6),IF(P9<=INDEX(GP_EV_T,MATCH($B9,GP_EV_Sectors,0),7),INDEX(GP_EV_T,MATCH($B9,GP_EV_Sectors,0),8),IF(P9<=INDEX(GP_EV_T,MATCH($B9,GP_EV_Sectors,0),9),INDEX(GP_EV_T,MATCH($B9,GP_EV_Sectors,0),10),IF(P9<=INDEX(GP_EV_T,MATCH($B9,GP_EV_Sectors,0),11),INDEX(GP_EV_T,MATCH($B9,GP_EV_Sectors,0),12),0)))))))) -> 48 | AI9: =IF(OR($B9="",Q9=""),"",IF(ISERROR(MATCH($B9,GP_PF_Sectors,0)),0,IF(Q9<=INDEX(GP_PF_T,MATCH($B9,GP_PF_Sectors,0),1),INDEX(GP_PF_T,MATCH($B9,GP_PF_Sectors,0),2),IF(Q9<=INDEX(GP_PF_T,MATCH($B9,GP_PF_Sectors,0),3),INDEX(GP_PF_T,MATCH($B9,GP_PF_Sectors,0),4),IF(Q9<=INDEX(GP_PF_T,MATCH($B9,GP_PF_Sectors,0),5),INDEX(GP_PF_T,MATCH($B9,GP_PF_Sectors,0),6),IF(Q9<=INDEX(GP_PF_T,MATCH($B9,GP_PF_Sectors,0),7),INDEX(GP_PF_T,MATCH($B9,GP_PF_Sectors,0),8),IF(Q9<=INDEX(GP_PF_T,MATCH($B9,GP_PF_Sectors,0),9),INDEX(GP_PF_T,MATCH($B9,GP_PF_Sectors,0),10),IF(Q9<=INDEX(GP_PF_T,MATCH($B9,GP_PF_Sectors,0),11),INDEX(GP_PF_T,MATCH($B9,GP_PF_Sectors,0),12),0)))))))) -> 48 | AJ9: =IF(OR($B9="",R9=""),"",IF(ISERROR(MATCH($B9,GP_DY_Sectors,0)),0,IF(R9>=INDEX(GP_DY_T,MATCH($B9,GP_DY_Sectors,0),1),INDEX(GP_DY_T,MATCH($B9,GP_DY_Sectors,0),2),IF(R9>=INDEX(GP_DY_T,MATCH($B9,GP_DY_Sectors,0),3),INDEX(GP_DY_T,MATCH($B9,GP_DY_Sectors,0),4),IF(R9>=INDEX(GP_DY_T,MATCH($B9,GP_DY_Sectors,0),5),INDEX(GP_DY_T,MATCH($B9,GP_DY_Sectors,0),6),IF(R9>=INDEX(GP_DY_T,MATCH($B9,GP_DY_Sectors,0),7),INDEX(GP_DY_T,MATCH($B9,GP_DY_Sectors,0),8),IF(R9>=INDEX(GP_DY_T,MATCH($B9,GP_DY_Sectors,0),9),INDEX(GP_DY_T,MATCH($B9,GP_DY_Sectors,0),10),IF(R9>=INDEX(GP_DY_T,MATCH($B9,GP_DY_Sectors,0),11),INDEX(GP_DY_T,MATCH($B9,GP_DY_Sectors,0),12),0)))))))) -> 42 | AK9: =IF(OR($B9="",S9=""),"",IF(ISERROR(MATCH($B9,GP_PR_Sectors,0)),0,IF(S9>=INDEX(GP_PR_T,MATCH($B9,GP_PR_Sectors,0),1),INDEX(GP_PR_T,MATCH($B9,GP_PR_Sectors,0),2),IF(S9>=INDEX(GP_PR_T,MATCH($B9,GP_PR_Sectors,0),3),INDEX(GP_PR_T,MATCH($B9,GP_PR_Sectors,0),4),IF(S9>=INDEX(GP_PR_T,MATCH($B9,GP_PR_Sectors,0),5),INDEX(GP_PR_T,MATCH($B9,GP_PR_Sectors,0),6),IF(S9>=INDEX(GP_PR_T,MATCH($B9,GP_PR_Sectors,0),7),INDEX(GP_PR_T,MATCH($B9,GP_PR_Sectors,0),8),IF(S9>=INDEX(GP_PR_T,MATCH($B9,GP_PR_Sectors,0),9),INDEX(GP_PR_T,MATCH($B9,GP_PR_Sectors,0),10),IF(S9>=INDEX(GP_PR_T,MATCH($B9,GP_PR_Sectors,0),11),INDEX(GP_PR_T,MATCH($B9,GP_PR_Sectors,0),12),0)))))))) -> 0 | AL9: =IF(OR($B9="",T9=""),"",IF(ISERROR(MATCH($B9,GP_BY_Sectors,0)),0,IF(T9>=INDEX(GP_BY_T,MATCH($B9,GP_BY_Sectors,0),1),INDEX(GP_BY_T,MATCH($B9,GP_BY_Sectors,0),2),IF(T9>=INDEX(GP_BY_T,MATCH($B9,GP_BY_Sectors,0),3),INDEX(GP_BY_T,MATCH($B9,GP_BY_Sectors,0),4),IF(T9>=INDEX(GP_BY_T,MATCH($B9,GP_BY_Sectors,0),5),INDEX(GP_BY_T,MATCH($B9,GP_BY_Sectors,0),6),IF(T9>=INDEX(GP_BY_T,MATCH($B9,GP_BY_Sectors,0),7),INDEX(GP_BY_T,MATCH($B9,GP_BY_Sectors,0),8),IF(T9>=INDEX(GP_BY_T,MATCH($B9,GP_BY_Sectors,0),9),INDEX(GP_BY_T,MATCH($B9,GP_BY_Sectors,0),10),IF(T9>=INDEX(GP_BY_T,MATCH($B9,GP_BY_Sectors,0),11),INDEX(GP_BY_T,MATCH($B9,GP_BY_Sectors,0),12),0)))))))) -> 85 | AM9: =IF($B9="","",U9*0.35+V9*0.35+W9*0.3) -> 100 | AN9: =IF($B9="","",X9*0.4+Y9*0.35+Z9*0.25) -> 54.5 | AO9: =IF($B9="","",AA9*0.35+AB9*0.3+AC9*0.35) -> 80.5 | AP9: =IF($B9="","",AD9*0.4+AE9*0.35+AF9*0.25) -> 86.45 | AQ9: =IF($B9="","",AG9*0.35+AH9*0.35+AI9*0.3) -> 41.7 | AR9: =IF($B9="","",AJ9*0.45+AK9*0.2+AL9*0.35) -> 48.65 | AS9: =IF($B9="","",MIN(100,MAX(0,ROUND(AM9*INDEX(GP_W_P1,MATCH($B9,GP_Weights_Sectors,0))+AN9*INDEX(GP_W_P2,MATCH($B9,GP_Weights_Sectors,0))+AO9*INDEX(GP_W_P3,MATCH($B9,GP_Weights_Sectors,0))+AP9*INDEX(GP_W_P4,MATCH($B9,GP_Weights_Sectors,0))+AQ9*INDEX(GP_W_P5,MATCH($B9,GP_Weights_Sectors,0))+AR9*INDEX(GP_W_P6,MATCH($B9,GP_Weights_Sectors,0)),0)))) -> 72 | AT9: 2 | AU9: 2 | AV9: 3 | AW9: =MAX(-10,MIN(10,AT9+AU9+AV9)) -> 7 | AX9: #VALUE! | AY9: {=_FV(AX9,"PRECIO")} -> 252.89 | AZ9: 260 | BA9: =IFERROR(INDEX('DCF Simplified'!$Y$4:$Y$38,MATCH(A9,'DCF Simplified'!$A$4:$A$38,0)),"") -> 205.02859 | BB9: =IF(OR(AY9="",AZ9=""),"",(AZ9-AY9)/AY9) -> 0.028114991 | BD9: 0.04 | BE9: 52 | BF9: 0.08 | BG9: =IF(BD9>0.1,100,IF(BD9>0.05,80,IF(BD9>0,65,IF(BD9>-0.05,45,IF(BD9>-0.1,25,10))))) -> 65 | BH9: =IF(AND(BE9>=40,BE9<=60),70,IF(AND(BE9>60,BE9<=70),85,IF(BE9>70,50,IF(AND(BE9>=30,BE9<40),55,40)))) -> 70 | BI9: =IF(BF9>0.2,100,IF(BF9>0.1,80,IF(BF9>0,65,IF(BF9>-0.1,45,IF(BF9>-0.2,25,10))))) -> 65 | BJ9: =ROUND(BG9*0.4+BH9*0.25+BI9*0.35,1) -> 66.3 | BK9: =IF(OR(AS9="",AQ9="",BJ9=""),"",ROUND(AS9*0.4+MAX(15,MIN(90,AQ9))*0.2+BJ9*0.25+MIN(100,MAX(0,AW9*10))*0.15,0)) -> 64 | BL9: =IF(BK9="","",IF(BK9>=85,"🟢 STRONG",IF(BK9>=70,"🟡 FAVORABLE",IF(BK9>=55,"⚪ NEUTRAL",IF(BK9>=40,"🟠 WEAK","🔴 AVOID"))))) -> ⚪ NEUTRAL | BM9: =IF(BK9="","",IF(AND(BK9>=75,BJ9>=70,AW9>=6),"🚀 STRONG BUY",IF(AND(BK9>=65,BJ9>=55),"✅ BUY",IF(BK9>=55,"⚠️ HOLD",IF(OR(BK9<45,AND(BJ9<35,AW9<3)),"🔴 SELL","🟠 UNDERWEIGHT"))))) -> ⚠️ HOLD
A10: Amazon.com Inc | B10: Consumer Discretionary | C10: 0.207 | D10: 0.21 | E10: 0.093 | F10: 0.11 | G10: 0.92 | H10: 2.8 | I10: 0.3 | J10: 1.1 | K10: 15 | L10: 0.05 | M10: 0.55 | N10: 0.13 | O10: 35 | P10: 20 | Q10: 45 | R10: 0 | S10: 0 | T10: 0.015 | U10: =IF(OR($B10="",C10=""),"",IF(ISERROR(MATCH($B10,GP_ROE_Sectors,0)),0,IF(C10>=INDEX(GP_ROE_T,MATCH($B10,GP_ROE_Sectors,0),1),INDEX(GP_ROE_T,MATCH($B10,GP_ROE_Sectors,0),2),IF(C10>=INDEX(GP_ROE_T,MATCH($B10,GP_ROE_Sectors,0),3),INDEX(GP_ROE_T,MATCH($B10,GP_ROE_Sectors,0),4),IF(C10>=INDEX(GP_ROE_T,MATCH($B10,GP_ROE_Sectors,0),5),INDEX(GP_ROE_T,MATCH($B10,GP_ROE_Sectors,0),6),IF(C10>=INDEX(GP_ROE_T,MATCH($B10,GP_ROE_Sectors,0),7),INDEX(GP_ROE_T,MATCH($B10,GP_ROE_Sectors,0),8),IF(C10>=INDEX(GP_ROE_T,MATCH($B10,GP_ROE_Sectors,0),9),INDEX(GP_ROE_T,MATCH($B10,GP_ROE_Sectors,0),10),IF(C10>=INDEX(GP_ROE_T,MATCH($B10,GP_ROE_Sectors,0),11),INDEX(GP_ROE_T,MATCH($B10,GP_ROE_Sectors,0),12),0)))))))) -> 88 | V10: =IF(OR($B10="",D10=""),"",IF(ISERROR(MATCH($B10,GP_ROIC_Sectors,0)),0,IF(D10>=INDEX(GP_ROIC_T,MATCH($B10,GP_ROIC_Sectors,0),1),INDEX(GP_ROIC_T,MATCH($B10,GP_ROIC_Sectors,0),2),IF(D10>=INDEX(GP_ROIC_T,MATCH($B10,GP_ROIC_Sectors,0),3),INDEX(GP_ROIC_T,MATCH($B10,GP_ROIC_Sectors,0),4),IF(D10>=INDEX(GP_ROIC_T,MATCH($B10,GP_ROIC_Sectors,0),5),INDEX(GP_ROIC_T,MATCH($B10,GP_ROIC_Sectors,0),6),IF(D10>=INDEX(GP_ROIC_T,MATCH($B10,GP_ROIC_Sectors,0),7),INDEX(GP_ROIC_T,MATCH($B10,GP_ROIC_Sectors,0),8),IF(D10>=INDEX(GP_ROIC_T,MATCH($B10,GP_ROIC_Sectors,0),9),INDEX(GP_ROIC_T,MATCH($B10,GP_ROIC_Sectors,0),10),IF(D10>=INDEX(GP_ROIC_T,MATCH($B10,GP_ROIC_Sectors,0),11),INDEX(GP_ROIC_T,MATCH($B10,GP_ROIC_Sectors,0),12),0)))))))) -> 100 | W10: =IF(OR($B10="",E10=""),"",IF(ISERROR(MATCH($B10,GP_NM_Sectors,0)),0,IF(E10>=INDEX(GP_NM_T,MATCH($B10,GP_NM_Sectors,0),1),INDEX(GP_NM_T,MATCH($B10,GP_NM_Sectors,0),2),IF(E10>=INDEX(GP_NM_T,MATCH($B10,GP_NM_Sectors,0),3),INDEX(GP_NM_T,MATCH($B10,GP_NM_Sectors,0),4),IF(E10>=INDEX(GP_NM_T,MATCH($B10,GP_NM_Sectors,0),5),INDEX(GP_NM_T,MATCH($B10,GP_NM_Sectors,0),6),IF(E10>=INDEX(GP_NM_T,MATCH($B10,GP_NM_Sectors,0),7),INDEX(GP_NM_T,MATCH($B10,GP_NM_Sectors,0),8),IF(E10>=INDEX(GP_NM_T,MATCH($B10,GP_NM_Sectors,0),9),INDEX(GP_NM_T,MATCH($B10,GP_NM_Sectors,0),10),IF(E10>=INDEX(GP_NM_T,MATCH($B10,GP_NM_Sectors,0),11),INDEX(GP_NM_T,MATCH($B10,GP_NM_Sectors,0),12),0)))))))) -> 85 | X10: =IF(OR($B10="",F10=""),"",IF(ISERROR(MATCH($B10,GP_RG_Sectors,0)),0,IF(F10>=INDEX(GP_RG_T,MATCH($B10,GP_RG_Sectors,0),1),INDEX(GP_RG_T,MATCH($B10,GP_RG_Sectors,0),2),IF(F10>=INDEX(GP_RG_T,MATCH($B10,GP_RG_Sectors,0),3),INDEX(GP_RG_T,MATCH($B10,GP_RG_Sectors,0),4),IF(F10>=INDEX(GP_RG_T,MATCH($B10,GP_RG_Sectors,0),5),INDEX(GP_RG_T,MATCH($B10,GP_RG_Sectors,0),6),IF(F10>=INDEX(GP_RG_T,MATCH($B10,GP_RG_Sectors,0),7),INDEX(GP_RG_T,MATCH($B10,GP_RG_Sectors,0),8),IF(F10>=INDEX(GP_RG_T,MATCH($B10,GP_RG_Sectors,0),9),INDEX(GP_RG_T,MATCH($B10,GP_RG_Sectors,0),10),IF(F10>=INDEX(GP_RG_T,MATCH($B10,GP_RG_Sectors,0),11),INDEX(GP_RG_T,MATCH($B10,GP_RG_Sectors,0),12),0)))))))) -> 85 | Y10: =IF(OR($B10="",G10=""),"",IF(ISERROR(MATCH($B10,GP_EG_Sectors,0)),0,IF(G10>=INDEX(GP_EG_T,MATCH($B10,GP_EG_Sectors,0),1),INDEX(GP_EG_T,MATCH($B10,GP_EG_Sectors,0),2),IF(G10>=INDEX(GP_EG_T,MATCH($B10,GP_EG_Sectors,0),3),INDEX(GP_EG_T,MATCH($B10,GP_EG_Sectors,0),4),IF(G10>=INDEX(GP_EG_T,MATCH($B10,GP_EG_Sectors,0),5),INDEX(GP_EG_T,MATCH($B10,GP_EG_Sectors,0),6),IF(G10>=INDEX(GP_EG_T,MATCH($B10,GP_EG_Sectors,0),7),INDEX(GP_EG_T,MATCH($B10,GP_EG_Sectors,0),8),IF(G10>=INDEX(GP_EG_T,MATCH($B10,GP_EG_Sectors,0),9),INDEX(GP_EG_T,MATCH($B10,GP_EG_Sectors,0),10),IF(G10>=INDEX(GP_EG_T,MATCH($B10,GP_EG_Sectors,0),11),INDEX(GP_EG_T,MATCH($B10,GP_EG_Sectors,0),12),0)))))))) -> 100 | Z10: =IF(OR($B10="",H10=""),"",IF(ISERROR(MATCH($B10,GP_OL_Sectors,0)),0,IF(H10>=INDEX(GP_OL_T,MATCH($B10,GP_OL_Sectors,0),1),INDEX(GP_OL_T,MATCH($B10,GP_OL_Sectors,0),2),IF(H10>=INDEX(GP_OL_T,MATCH($B10,GP_OL_Sectors,0),3),INDEX(GP_OL_T,MATCH($B10,GP_OL_Sectors,0),4),IF(H10>=INDEX(GP_OL_T,MATCH($B10,GP_OL_Sectors,0),5),INDEX(GP_OL_T,MATCH($B10,GP_OL_Sectors,0),6),IF(H10>=INDEX(GP_OL_T,MATCH($B10,GP_OL_Sectors,0),7),INDEX(GP_OL_T,MATCH($B10,GP_OL_Sectors,0),8),IF(H10>=INDEX(GP_OL_T,MATCH($B10,GP_OL_Sectors,0),9),INDEX(GP_OL_T,MATCH($B10,GP_OL_Sectors,0),10),IF(H10>=INDEX(GP_OL_T,MATCH($B10,GP_OL_Sectors,0),11),INDEX(GP_OL_T,MATCH($B10,GP_OL_Sectors,0),12),0)))))))) -> 100 | AA10: =IF(OR($B10="",I10=""),"",IF(ISERROR(MATCH($B10,GP_ND_Sectors,0)),0,IF(I10<=INDEX(GP_ND_T,MATCH($B10,GP_ND_Sectors,0),1),INDEX(GP_ND_T,MATCH($B10,GP_ND_Sectors,0),2),IF(I10<=INDEX(GP_ND_T,MATCH($B10,GP_ND_Sectors,0),3),INDEX(GP_ND_T,MATCH($B10,GP_ND_Sectors,0),4),IF(I10<=INDEX(GP_ND_T,MATCH($B10,GP_ND_Sectors,0),5),INDEX(GP_ND_T,MATCH($B10,GP_ND_Sectors,0),6),IF(I10<=INDEX(GP_ND_T,MATCH($B10,GP_ND_Sectors,0),7),INDEX(GP_ND_T,MATCH($B10,GP_ND_Sectors,0),8),IF(I10<=INDEX(GP_ND_T,MATCH($B10,GP_ND_Sectors,0),9),INDEX(GP_ND_T,MATCH($B10,GP_ND_Sectors,0),10),IF(I10<=INDEX(GP_ND_T,MATCH($B10,GP_ND_Sectors,0),11),INDEX(GP_ND_T,MATCH($B10,GP_ND_Sectors,0),12),0)))))))) -> 85 | AB10: =IF(OR($B10="",J10=""),"",IF(ISERROR(MATCH($B10,GP_CR_Sectors,0)),0,IF(J10>=INDEX(GP_CR_T,MATCH($B10,GP_CR_Sectors,0),1),INDEX(GP_CR_T,MATCH($B10,GP_CR_Sectors,0),2),IF(J10>=INDEX(GP_CR_T,MATCH($B10,GP_CR_Sectors,0),3),INDEX(GP_CR_T,MATCH($B10,GP_CR_Sectors,0),4),IF(J10>=INDEX(GP_CR_T,MATCH($B10,GP_CR_Sectors,0),5),INDEX(GP_CR_T,MATCH($B10,GP_CR_Sectors,0),6),IF(J10>=INDEX(GP_CR_T,MATCH($B10,GP_CR_Sectors,0),7),INDEX(GP_CR_T,MATCH($B10,GP_CR_Sectors,0),8),IF(J10>=INDEX(GP_CR_T,MATCH($B10,GP_CR_Sectors,0),9),INDEX(GP_CR_T,MATCH($B10,GP_CR_Sectors,0),10),IF(J10>=INDEX(GP_CR_T,MATCH($B10,GP_CR_Sectors,0),11),INDEX(GP_CR_T,MATCH($B10,GP_CR_Sectors,0),12),0)))))))) -> 52 | AC10: =IF(OR($B10="",K10=""),"",IF(ISERROR(MATCH($B10,GP_IC_Sectors,0)),0,IF(K10>=INDEX(GP_IC_T,MATCH($B10,GP_IC_Sectors,0),1),INDEX(GP_IC_T,MATCH($B10,GP_IC_Sectors,0),2),IF(K10>=INDEX(GP_IC_T,MATCH($B10,GP_IC_Sectors,0),3),INDEX(GP_IC_T,MATCH($B10,GP_IC_Sectors,0),4),IF(K10>=INDEX(GP_IC_T,MATCH($B10,GP_IC_Sectors,0),5),INDEX(GP_IC_T,MATCH($B10,GP_IC_Sectors,0),6),IF(K10>=INDEX(GP_IC_T,MATCH($B10,GP_IC_Sectors,0),7),INDEX(GP_IC_T,MATCH($B10,GP_IC_Sectors,0),8),IF(K10>=INDEX(GP_IC_T,MATCH($B10,GP_IC_Sectors,0),9),INDEX(GP_IC_T,MATCH($B10,GP_IC_Sectors,0),10),IF(K10>=INDEX(GP_IC_T,MATCH($B10,GP_IC_Sectors,0),11),INDEX(GP_IC_T,MATCH($B10,GP_IC_Sectors,0),12),0)))))))) -> 100 | AD10: =IF(OR($B10="",L10=""),"",IF(ISERROR(MATCH($B10,GP_FM_Sectors,0)),0,IF(L10>=INDEX(GP_FM_T,MATCH($B10,GP_FM_Sectors,0),1),INDEX(GP_FM_T,MATCH($B10,GP_FM_Sectors,0),2),IF(L10>=INDEX(GP_FM_T,MATCH($B10,GP_FM_Sectors,0),3),INDEX(GP_FM_T,MATCH($B10,GP_FM_Sectors,0),4),IF(L10>=INDEX(GP_FM_T,MATCH($B10,GP_FM_Sectors,0),5),INDEX(GP_FM_T,MATCH($B10,GP_FM_Sectors,0),6),IF(L10>=INDEX(GP_FM_T,MATCH($B10,GP_FM_Sectors,0),7),INDEX(GP_FM_T,MATCH($B10,GP_FM_Sectors,0),8),IF(L10>=INDEX(GP_FM_T,MATCH($B10,GP_FM_Sectors,0),9),INDEX(GP_FM_T,MATCH($B10,GP_FM_Sectors,0),10),IF(L10>=INDEX(GP_FM_T,MATCH($B10,GP_FM_Sectors,0),11),INDEX(GP_FM_T,MATCH($B10,GP_FM_Sectors,0),12),0)))))))) -> 68 | AE10: =IF(OR($B10="",M10=""),"",IF(ISERROR(MATCH($B10,GP_FN_Sectors,0)),0,IF(M10>=INDEX(GP_FN_T,MATCH($B10,GP_FN_Sectors,0),1),INDEX(GP_FN_T,MATCH($B10,GP_FN_Sectors,0),2),IF(M10>=INDEX(GP_FN_T,MATCH($B10,GP_FN_Sectors,0),3),INDEX(GP_FN_T,MATCH($B10,GP_FN_Sectors,0),4),IF(M10>=INDEX(GP_FN_T,MATCH($B10,GP_FN_Sectors,0),5),INDEX(GP_FN_T,MATCH($B10,GP_FN_Sectors,0),6),IF(M10>=INDEX(GP_FN_T,MATCH($B10,GP_FN_Sectors,0),7),INDEX(GP_FN_T,MATCH($B10,GP_FN_Sectors,0),8),IF(M10>=INDEX(GP_FN_T,MATCH($B10,GP_FN_Sectors,0),9),INDEX(GP_FN_T,MATCH($B10,GP_FN_Sectors,0),10),IF(M10>=INDEX(GP_FN_T,MATCH($B10,GP_FN_Sectors,0),11),INDEX(GP_FN_T,MATCH($B10,GP_FN_Sectors,0),12),0)))))))) -> 32 | AF10: =IF(OR($B10="",N10=""),"",IF(ISERROR(MATCH($B10,GP_CX_Sectors,0)),0,IF(N10<=INDEX(GP_CX_T,MATCH($B10,GP_CX_Sectors,0),1),INDEX(GP_CX_T,MATCH($B10,GP_CX_Sectors,0),2),IF(N10<=INDEX(GP_CX_T,MATCH($B10,GP_CX_Sectors,0),3),INDEX(GP_CX_T,MATCH($B10,GP_CX_Sectors,0),4),IF(N10<=INDEX(GP_CX_T,MATCH($B10,GP_CX_Sectors,0),5),INDEX(GP_CX_T,MATCH($B10,GP_CX_Sectors,0),6),IF(N10<=INDEX(GP_CX_T,MATCH($B10,GP_CX_Sectors,0),7),INDEX(GP_CX_T,MATCH($B10,GP_CX_Sectors,0),8),IF(N10<=INDEX(GP_CX_T,MATCH($B10,GP_CX_Sectors,0),9),INDEX(GP_CX_T,MATCH($B10,GP_CX_Sectors,0),10),IF(N10<=INDEX(GP_CX_T,MATCH($B10,GP_CX_Sectors,0),11),INDEX(GP_CX_T,MATCH($B10,GP_CX_Sectors,0),12),0)))))))) -> 52 | AG10: =IF(OR($B10="",O10=""),"",IF(ISERROR(MATCH($B10,GP_PE_Sectors,0)),0,IF(O10<=INDEX(GP_PE_T,MATCH($B10,GP_PE_Sectors,0),1),INDEX(GP_PE_T,MATCH($B10,GP_PE_Sectors,0),2),IF(O10<=INDEX(GP_PE_T,MATCH($B10,GP_PE_Sectors,0),3),INDEX(GP_PE_T,MATCH($B10,GP_PE_Sectors,0),4),IF(O10<=INDEX(GP_PE_T,MATCH($B10,GP_PE_Sectors,0),5),INDEX(GP_PE_T,MATCH($B10,GP_PE_Sectors,0),6),IF(O10<=INDEX(GP_PE_T,MATCH($B10,GP_PE_Sectors,0),7),INDEX(GP_PE_T,MATCH($B10,GP_PE_Sectors,0),8),IF(O10<=INDEX(GP_PE_T,MATCH($B10,GP_PE_Sectors,0),9),INDEX(GP_PE_T,MATCH($B10,GP_PE_Sectors,0),10),IF(O10<=INDEX(GP_PE_T,MATCH($B10,GP_PE_Sectors,0),11),INDEX(GP_PE_T,MATCH($B10,GP_PE_Sectors,0),12),0)))))))) -> 30 | AH10: =IF(OR($B10="",P10=""),"",IF(ISERROR(MATCH($B10,GP_EV_Sectors,0)),0,IF(P10<=INDEX(GP_EV_T,MATCH($B10,GP_EV_Sectors,0),1),INDEX(GP_EV_T,MATCH($B10,GP_EV_Sectors,0),2),IF(P10<=INDEX(GP_EV_T,MATCH($B10,GP_EV_Sectors,0),3),INDEX(GP_EV_T,MATCH($B10,GP_EV_Sectors,0),4),IF(P10<=INDEX(GP_EV_T,MATCH($B10,GP_EV_Sectors,0),5),INDEX(GP_EV_T,MATCH($B10,GP_EV_Sectors,0),6),IF(P10<=INDEX(GP_EV_T,MATCH($B10,GP_EV_Sectors,0),7),INDEX(GP_EV_T,MATCH($B10,GP_EV_Sectors,0),8),IF(P10<=INDEX(GP_EV_T,MATCH($B10,GP_EV_Sectors,0),9),INDEX(GP_EV_T,MATCH($B10,GP_EV_Sectors,0),10),IF(P10<=INDEX(GP_EV_T,MATCH($B10,GP_EV_Sectors,0),11),INDEX(GP_EV_T,MATCH($B10,GP_EV_Sectors,0),12),0)))))))) -> 48 | AI10: =IF(OR($B10="",Q10=""),"",IF(ISERROR(MATCH($B10,GP_PF_Sectors,0)),0,IF(Q10<=INDEX(GP_PF_T,MATCH($B10,GP_PF_Sectors,0),1),INDEX(GP_PF_T,MATCH($B10,GP_PF_Sectors,0),2),IF(Q10<=INDEX(GP_PF_T,MATCH($B10,GP_PF_Sectors,0),3),INDEX(GP_PF_T,MATCH($B10,GP_PF_Sectors,0),4),IF(Q10<=INDEX(GP_PF_T,MATCH($B10,GP_PF_Sectors,0),5),INDEX(GP_PF_T,MATCH($B10,GP_PF_Sectors,0),6),IF(Q10<=INDEX(GP_PF_T,MATCH($B10,GP_PF_Sectors,0),7),INDEX(GP_PF_T,MATCH($B10,GP_PF_Sectors,0),8),IF(Q10<=INDEX(GP_PF_T,MATCH($B10,GP_PF_Sectors,0),9),INDEX(GP_PF_T,MATCH($B10,GP_PF_Sectors,0),10),IF(Q10<=INDEX(GP_PF_T,MATCH($B10,GP_PF_Sectors,0),11),INDEX(GP_PF_T,MATCH($B10,GP_PF_Sectors,0),12),0)))))))) -> 28 | AJ10: =IF(OR($B10="",R10=""),"",IF(ISERROR(MATCH($B10,GP_DY_Sectors,0)),0,IF(R10>=INDEX(GP_DY_T,MATCH($B10,GP_DY_Sectors,0),1),INDEX(GP_DY_T,MATCH($B10,GP_DY_Sectors,0),2),IF(R10>=INDEX(GP_DY_T,MATCH($B10,GP_DY_Sectors,0),3),INDEX(GP_DY_T,MATCH($B10,GP_DY_Sectors,0),4),IF(R10>=INDEX(GP_DY_T,MATCH($B10,GP_DY_Sectors,0),5),INDEX(GP_DY_T,MATCH($B10,GP_DY_Sectors,0),6),IF(R10>=INDEX(GP_DY_T,MATCH($B10,GP_DY_Sectors,0),7),INDEX(GP_DY_T,MATCH($B10,GP_DY_Sectors,0),8),IF(R10>=INDEX(GP_DY_T,MATCH($B10,GP_DY_Sectors,0),9),INDEX(GP_DY_T,MATCH($B10,GP_DY_Sectors,0),10),IF(R10>=INDEX(GP_DY_T,MATCH($B10,GP_DY_Sectors,0),11),INDEX(GP_DY_T,MATCH($B10,GP_DY_Sectors,0),12),0)))))))) -> 5 | AK10: =IF(OR($B10="",S10=""),"",IF(ISERROR(MATCH($B10,GP_PR_Sectors,0)),0,IF(S10>=INDEX(GP_PR_T,MATCH($B10,GP_PR_Sectors,0),1),INDEX(GP_PR_T,MATCH($B10,GP_PR_Sectors,0),2),IF(S10>=INDEX(GP_PR_T,MATCH($B10,GP_PR_Sectors,0),3),INDEX(GP_PR_T,MATCH($B10,GP_PR_Sectors,0),4),IF(S10>=INDEX(GP_PR_T,MATCH($B10,GP_PR_Sectors,0),5),INDEX(GP_PR_T,MATCH($B10,GP_PR_Sectors,0),6),IF(S10>=INDEX(GP_PR_T,MATCH($B10,GP_PR_Sectors,0),7),INDEX(GP_PR_T,MATCH($B10,GP_PR_Sectors,0),8),IF(S10>=INDEX(GP_PR_T,MATCH($B10,GP_PR_Sectors,0),9),INDEX(GP_PR_T,MATCH($B10,GP_PR_Sectors,0),10),IF(S10>=INDEX(GP_PR_T,MATCH($B10,GP_PR_Sectors,0),11),INDEX(GP_PR_T,MATCH($B10,GP_PR_Sectors,0),12),0)))))))) -> 0 | AL10: =IF(OR($B10="",T10=""),"",IF(ISERROR(MATCH($B10,GP_BY_Sectors,0)),0,IF(T10>=INDEX(GP_BY_T,MATCH($B10,GP_BY_Sectors,0),1),INDEX(GP_BY_T,MATCH($B10,GP_BY_Sectors,0),2),IF(T10>=INDEX(GP_BY_T,MATCH($B10,GP_BY_Sectors,0),3),INDEX(GP_BY_T,MATCH($B10,GP_BY_Sectors,0),4),IF(T10>=INDEX(GP_BY_T,MATCH($B10,GP_BY_Sectors,0),5),INDEX(GP_BY_T,MATCH($B10,GP_BY_Sectors,0),6),IF(T10>=INDEX(GP_BY_T,MATCH($B10,GP_BY_Sectors,0),7),INDEX(GP_BY_T,MATCH($B10,GP_BY_Sectors,0),8),IF(T10>=INDEX(GP_BY_T,MATCH($B10,GP_BY_Sectors,0),9),INDEX(GP_BY_T,MATCH($B10,GP_BY_Sectors,0),10),IF(T10>=INDEX(GP_BY_T,MATCH($B10,GP_BY_Sectors,0),11),INDEX(GP_BY_T,MATCH($B10,GP_BY_Sectors,0),12),0)))))))) -> 50 | AM10: =IF($B10="","",U10*0.35+V10*0.35+W10*0.3) -> 91.3 | AN10: =IF($B10="","",X10*0.4+Y10*0.35+Z10*0.25) -> 94 | AO10: =IF($B10="","",AA10*0.35+AB10*0.3+AC10*0.35) -> 80.35 | AP10: =IF($B10="","",AD10*0.4+AE10*0.35+AF10*0.25) -> 51.4 | AQ10: =IF($B10="","",AG10*0.35+AH10*0.35+AI10*0.3) -> 35.7 | AR10: =IF($B10="","",AJ10*0.45+AK10*0.2+AL10*0.35) -> 19.75 | AS10: =IF($B10="","",MIN(100,MAX(0,ROUND(AM10*INDEX(GP_W_P1,MATCH($B10,GP_Weights_Sectors,0))+AN10*INDEX(GP_W_P2,MATCH($B10,GP_Weights_Sectors,0))+AO10*INDEX(GP_W_P3,MATCH($B10,GP_Weights_Sectors,0))+AP10*INDEX(GP_W_P4,MATCH($B10,GP_Weights_Sectors,0))+AQ10*INDEX(GP_W_P5,MATCH($B10,GP_Weights_Sectors,0))+AR10*INDEX(GP_W_P6,MATCH($B10,GP_Weights_Sectors,0)),0)))) -> 69 | AT10: 3 | AU10: 2 | AV10: 3 | AW10: =MAX(-10,MIN(10,AT10+AU10+AV10)) -> 8 | AX10: #VALUE! | AY10: {=_FV(AX10,"PRECIO")} -> 207.54 | AZ10: 260 | BA10: =IFERROR(INDEX('DCF Simplified'!$Y$4:$Y$38,MATCH(A10,'DCF Simplified'!$A$4:$A$38,0)),"") -> 153.11256 | BB10: =IF(OR(AY10="",AZ10=""),"",(AZ10-AY10)/AY10) -> 0.25277055 | BD10: 0.1 | BE10: 58 | BF10: 0.22 | BG10: =IF(BD10>0.1,100,IF(BD10>0.05,80,IF(BD10>0,65,IF(BD10>-0.05,45,IF(BD10>-0.1,25,10))))) -> 80 | BH10: =IF(AND(BE10>=40,BE10<=60),70,IF(AND(BE10>60,BE10<=70),85,IF(BE10>70,50,IF(AND(BE10>=30,BE10<40),55,40)))) -> 70 | BI10: =IF(BF10>0.2,100,IF(BF10>0.1,80,IF(BF10>0,65,IF(BF10>-0.1,45,IF(BF10>-0.2,25,10))))) -> 100 | BJ10: =ROUND(BG10*0.4+BH10*0.25+BI10*0.35,1) -> 84.5 | BK10: =IF(OR(AS10="",AQ10="",BJ10=""),"",ROUND(AS10*0.4+MAX(15,MIN(90,AQ10))*0.2+BJ10*0.25+MIN(100,MAX(0,AW10*10))*0.15,0)) -> 68 | BL10: =IF(BK10="","",IF(BK10>=85,"🟢 STRONG",IF(BK10>=70,"🟡 FAVORABLE",IF(BK10>=55,"⚪ NEUTRAL",IF(BK10>=40,"🟠 WEAK","🔴 AVOID"))))) -> ⚪ NEUTRAL | BM10: =IF(BK10="","",IF(AND(BK10>=75,BJ10>=70,AW10>=6),"🚀 STRONG BUY",IF(AND(BK10>=65,BJ10>=55),"✅ BUY",IF(BK10>=55,"⚠️ HOLD",IF(OR(BK10<45,AND(BJ10<35,AW10<3)),"🔴 SELL","🟠 UNDERWEIGHT"))))) -> ✅ BUY
A11: Alphabet Inc | B11: Communication Services | C11: 0.308 | D11: 0.218 | E11: 0.29 | F11: 0.13 | G11: 0.31 | H11: 1.5 | I11: -1.2 | J11: 2 | K11: 30 | L11: 0.25 | M11: 0.9 | N11: 0.11 | O11: 21 | P11: 16 | Q11: 28 | R11: 0.005 | S11: 0.05 | T11: 0.05 | U11: =IF(OR($B11="",C11=""),"",IF(ISERROR(MATCH($B11,GP_ROE_Sectors,0)),0,IF(C11>=INDEX(GP_ROE_T,MATCH($B11,GP_ROE_Sectors,0),1),INDEX(GP_ROE_T,MATCH($B11,GP_ROE_Sectors,0),2),IF(C11>=INDEX(GP_ROE_T,MATCH($B11,GP_ROE_Sectors,0),3),INDEX(GP_ROE_T,MATCH($B11,GP_ROE_Sectors,0),4),IF(C11>=INDEX(GP_ROE_T,MATCH($B11,GP_ROE_Sectors,0),5),INDEX(GP_ROE_T,MATCH($B11,GP_ROE_Sectors,0),6),IF(C11>=INDEX(GP_ROE_T,MATCH($B11,GP_ROE_Sectors,0),7),INDEX(GP_ROE_T,MATCH($B11,GP_ROE_Sectors,0),8),IF(C11>=INDEX(GP_ROE_T,MATCH($B11,GP_ROE_Sectors,0),9),INDEX(GP_ROE_T,MATCH($B11,GP_ROE_Sectors,0),10),IF(C11>=INDEX(GP_ROE_T,MATCH($B11,GP_ROE_Sectors,0),11),INDEX(GP_ROE_T,MATCH($B11,GP_ROE_Sectors,0),12),0)))))))) -> 100 | V11: =IF(OR($B11="",D11=""),"",IF(ISERROR(MATCH($B11,GP_ROIC_Sectors,0)),0,IF(D11>=INDEX(GP_ROIC_T,MATCH($B11,GP_ROIC_Sectors,0),1),INDEX(GP_ROIC_T,MATCH($B11,GP_ROIC_Sectors,0),2),IF(D11>=INDEX(GP_ROIC_T,MATCH($B11,GP_ROIC_Sectors,0),3),INDEX(GP_ROIC_T,MATCH($B11,GP_ROIC_Sectors,0),4),IF(D11>=INDEX(GP_ROIC_T,MATCH($B11,GP_ROIC_Sectors,0),5),INDEX(GP_ROIC_T,MATCH($B11,GP_ROIC_Sectors,0),6),IF(D11>=INDEX(GP_ROIC_T,MATCH($B11,GP_ROIC_Sectors,0),7),INDEX(GP_ROIC_T,MATCH($B11,GP_ROIC_Sectors,0),8),IF(D11>=INDEX(GP_ROIC_T,MATCH($B11,GP_ROIC_Sectors,0),9),INDEX(GP_ROIC_T,MATCH($B11,GP_ROIC_Sectors,0),10),IF(D11>=INDEX(GP_ROIC_T,MATCH($B11,GP_ROIC_Sectors,0),11),INDEX(GP_ROIC_T,MATCH($B11,GP_ROIC_Sectors,0),12),0)))))))) -> 88 | W11: =IF(OR($B11="",E11=""),"",IF(ISERROR(MATCH($B11,GP_NM_Sectors,0)),0,IF(E11>=INDEX(GP_NM_T,MATCH($B11,GP_NM_Sectors,0),1),INDEX(GP_NM_T,MATCH($B11,GP_NM_Sectors,0),2),IF(E11>=INDEX(GP_NM_T,MATCH($B11,GP_NM_Sectors,0),3),INDEX(GP_NM_T,MATCH($B11,GP_NM_Sectors,0),4),IF(E11>=INDEX(GP_NM_T,MATCH($B11,GP_NM_Sectors,0),5),INDEX(GP_NM_T,MATCH($B11,GP_NM_Sectors,0),6),IF(E11>=INDEX(GP_NM_T,MATCH($B11,GP_NM_Sectors,0),7),INDEX(GP_NM_T,MATCH($B11,GP_NM_Sectors,0),8),IF(E11>=INDEX(GP_NM_T,MATCH($B11,GP_NM_Sectors,0),9),INDEX(GP_NM_T,MATCH($B11,GP_NM_Sectors,0),10),IF(E11>=INDEX(GP_NM_T,MATCH($B11,GP_NM_Sectors,0),11),INDEX(GP_NM_T,MATCH($B11,GP_NM_Sectors,0),12),0)))))))) -> 100 | X11: =IF(OR($B11="",F11=""),"",IF(ISERROR(MATCH($B11,GP_RG_Sectors,0)),0,IF(F11>=INDEX(GP_RG_T,MATCH($B11,GP_RG_Sectors,0),1),INDEX(GP_RG_T,MATCH($B11,GP_RG_Sectors,0),2),IF(F11>=INDEX(GP_RG_T,MATCH($B11,GP_RG_Sectors,0),3),INDEX(GP_RG_T,MATCH($B11,GP_RG_Sectors,0),4),IF(F11>=INDEX(GP_RG_T,MATCH($B11,GP_RG_Sectors,0),5),INDEX(GP_RG_T,MATCH($B11,GP_RG_Sectors,0),6),IF(F11>=INDEX(GP_RG_T,MATCH($B11,GP_RG_Sectors,0),7),INDEX(GP_RG_T,MATCH($B11,GP_RG_Sectors,0),8),IF(F11>=INDEX(GP_RG_T,MATCH($B11,GP_RG_Sectors,0),9),INDEX(GP_RG_T,MATCH($B11,GP_RG_Sectors,0),10),IF(F11>=INDEX(GP_RG_T,MATCH($B11,GP_RG_Sectors,0),11),INDEX(GP_RG_T,MATCH($B11,GP_RG_Sectors,0),12),0)))))))) -> 85 | Y11: =IF(OR($B11="",G11=""),"",IF(ISERROR(MATCH($B11,GP_EG_Sectors,0)),0,IF(G11>=INDEX(GP_EG_T,MATCH($B11,GP_EG_Sectors,0),1),INDEX(GP_EG_T,MATCH($B11,GP_EG_Sectors,0),2),IF(G11>=INDEX(GP_EG_T,MATCH($B11,GP_EG_Sectors,0),3),INDEX(GP_EG_T,MATCH($B11,GP_EG_Sectors,0),4),IF(G11>=INDEX(GP_EG_T,MATCH($B11,GP_EG_Sectors,0),5),INDEX(GP_EG_T,MATCH($B11,GP_EG_Sectors,0),6),IF(G11>=INDEX(GP_EG_T,MATCH($B11,GP_EG_Sectors,0),7),INDEX(GP_EG_T,MATCH($B11,GP_EG_Sectors,0),8),IF(G11>=INDEX(GP_EG_T,MATCH($B11,GP_EG_Sectors,0),9),INDEX(GP_EG_T,MATCH($B11,GP_EG_Sectors,0),10),IF(G11>=INDEX(GP_EG_T,MATCH($B11,GP_EG_Sectors,0),11),INDEX(GP_EG_T,MATCH($B11,GP_EG_Sectors,0),12),0)))))))) -> 100 | Z11: =IF(OR($B11="",H11=""),"",IF(ISERROR(MATCH($B11,GP_OL_Sectors,0)),0,IF(H11>=INDEX(GP_OL_T,MATCH($B11,GP_OL_Sectors,0),1),INDEX(GP_OL_T,MATCH($B11,GP_OL_Sectors,0),2),IF(H11>=INDEX(GP_OL_T,MATCH($B11,GP_OL_Sectors,0),3),INDEX(GP_OL_T,MATCH($B11,GP_OL_Sectors,0),4),IF(H11>=INDEX(GP_OL_T,MATCH($B11,GP_OL_Sectors,0),5),INDEX(GP_OL_T,MATCH($B11,GP_OL_Sectors,0),6),IF(H11>=INDEX(GP_OL_T,MATCH($B11,GP_OL_Sectors,0),7),INDEX(GP_OL_T,MATCH($B11,GP_OL_Sectors,0),8),IF(H11>=INDEX(GP_OL_T,MATCH($B11,GP_OL_Sectors,0),9),INDEX(GP_OL_T,MATCH($B11,GP_OL_Sectors,0),10),IF(H11>=INDEX(GP_OL_T,MATCH($B11,GP_OL_Sectors,0),11),INDEX(GP_OL_T,MATCH($B11,GP_OL_Sectors,0),12),0)))))))) -> 85 | AA11: =IF(OR($B11="",I11=""),"",IF(ISERROR(MATCH($B11,GP_ND_Sectors,0)),0,IF(I11<=INDEX(GP_ND_T,MATCH($B11,GP_ND_Sectors,0),1),INDEX(GP_ND_T,MATCH($B11,GP_ND_Sectors,0),2),IF(I11<=INDEX(GP_ND_T,MATCH($B11,GP_ND_Sectors,0),3),INDEX(GP_ND_T,MATCH($B11,GP_ND_Sectors,0),4),IF(I11<=INDEX(GP_ND_T,MATCH($B11,GP_ND_Sectors,0),5),INDEX(GP_ND_T,MATCH($B11,GP_ND_Sectors,0),6),IF(I11<=INDEX(GP_ND_T,MATCH($B11,GP_ND_Sectors,0),7),INDEX(GP_ND_T,MATCH($B11,GP_ND_Sectors,0),8),IF(I11<=INDEX(GP_ND_T,MATCH($B11,GP_ND_Sectors,0),9),INDEX(GP_ND_T,MATCH($B11,GP_ND_Sectors,0),10),IF(I11<=INDEX(GP_ND_T,MATCH($B11,GP_ND_Sectors,0),11),INDEX(GP_ND_T,MATCH($B11,GP_ND_Sectors,0),12),0)))))))) -> 100 | AB11: =IF(OR($B11="",J11=""),"",IF(ISERROR(MATCH($B11,GP_CR_Sectors,0)),0,IF(J11>=INDEX(GP_CR_T,MATCH($B11,GP_CR_Sectors,0),1),INDEX(GP_CR_T,MATCH($B11,GP_CR_Sectors,0),2),IF(J11>=INDEX(GP_CR_T,MATCH($B11,GP_CR_Sectors,0),3),INDEX(GP_CR_T,MATCH($B11,GP_CR_Sectors,0),4),IF(J11>=INDEX(GP_CR_T,MATCH($B11,GP_CR_Sectors,0),5),INDEX(GP_CR_T,MATCH($B11,GP_CR_Sectors,0),6),IF(J11>=INDEX(GP_CR_T,MATCH($B11,GP_CR_Sectors,0),7),INDEX(GP_CR_T,MATCH($B11,GP_CR_Sectors,0),8),IF(J11>=INDEX(GP_CR_T,MATCH($B11,GP_CR_Sectors,0),9),INDEX(GP_CR_T,MATCH($B11,GP_CR_Sectors,0),10),IF(J11>=INDEX(GP_CR_T,MATCH($B11,GP_CR_Sectors,0),11),INDEX(GP_CR_T,MATCH($B11,GP_CR_Sectors,0),12),0)))))))) -> 100 | AC11: =IF(OR($B11="",K11=""),"",IF(ISERROR(MATCH($B11,GP_IC_Sectors,0)),0,IF(K11>=INDEX(GP_IC_T,MATCH($B11,GP_IC_Sectors,0),1),INDEX(GP_IC_T,MATCH($B11,GP_IC_Sectors,0),2),IF(K11>=INDEX(GP_IC_T,MATCH($B11,GP_IC_Sectors,0),3),INDEX(GP_IC_T,MATCH($B11,GP_IC_Sectors,0),4),IF(K11>=INDEX(GP_IC_T,MATCH($B11,GP_IC_Sectors,0),5),INDEX(GP_IC_T,MATCH($B11,GP_IC_Sectors,0),6),IF(K11>=INDEX(GP_IC_T,MATCH($B11,GP_IC_Sectors,0),7),INDEX(GP_IC_T,MATCH($B11,GP_IC_Sectors,0),8),IF(K11>=INDEX(GP_IC_T,MATCH($B11,GP_IC_Sectors,0),9),INDEX(GP_IC_T,MATCH($B11,GP_IC_Sectors,0),10),IF(K11>=INDEX(GP_IC_T,MATCH($B11,GP_IC_Sectors,0),11),INDEX(GP_IC_T,MATCH($B11,GP_IC_Sectors,0),12),0)))))))) -> 100 | AD11: =IF(OR($B11="",L11=""),"",IF(ISERROR(MATCH($B11,GP_FM_Sectors,0)),0,IF(L11>=INDEX(GP_FM_T,MATCH($B11,GP_FM_Sectors,0),1),INDEX(GP_FM_T,MATCH($B11,GP_FM_Sectors,0),2),IF(L11>=INDEX(GP_FM_T,MATCH($B11,GP_FM_Sectors,0),3),INDEX(GP_FM_T,MATCH($B11,GP_FM_Sectors,0),4),IF(L11>=INDEX(GP_FM_T,MATCH($B11,GP_FM_Sectors,0),5),INDEX(GP_FM_T,MATCH($B11,GP_FM_Sectors,0),6),IF(L11>=INDEX(GP_FM_T,MATCH($B11,GP_FM_Sectors,0),7),INDEX(GP_FM_T,MATCH($B11,GP_FM_Sectors,0),8),IF(L11>=INDEX(GP_FM_T,MATCH($B11,GP_FM_Sectors,0),9),INDEX(GP_FM_T,MATCH($B11,GP_FM_Sectors,0),10),IF(L11>=INDEX(GP_FM_T,MATCH($B11,GP_FM_Sectors,0),11),INDEX(GP_FM_T,MATCH($B11,GP_FM_Sectors,0),12),0)))))))) -> 100 | AE11: =IF(OR($B11="",M11=""),"",IF(ISERROR(MATCH($B11,GP_FN_Sectors,0)),0,IF(M11>=INDEX(GP_FN_T,MATCH($B11,GP_FN_Sectors,0),1),INDEX(GP_FN_T,MATCH($B11,GP_FN_Sectors,0),2),IF(M11>=INDEX(GP_FN_T,MATCH($B11,GP_FN_Sectors,0),3),INDEX(GP_FN_T,MATCH($B11,GP_FN_Sectors,0),4),IF(M11>=INDEX(GP_FN_T,MATCH($B11,GP_FN_Sectors,0),5),INDEX(GP_FN_T,MATCH($B11,GP_FN_Sectors,0),6),IF(M11>=INDEX(GP_FN_T,MATCH($B11,GP_FN_Sectors,0),7),INDEX(GP_FN_T,MATCH($B11,GP_FN_Sectors,0),8),IF(M11>=INDEX(GP_FN_T,MATCH($B11,GP_FN_Sectors,0),9),INDEX(GP_FN_T,MATCH($B11,GP_FN_Sectors,0),10),IF(M11>=INDEX(GP_FN_T,MATCH($B11,GP_FN_Sectors,0),11),INDEX(GP_FN_T,MATCH($B11,GP_FN_Sectors,0),12),0)))))))) -> 70 | AF11: =IF(OR($B11="",N11=""),"",IF(ISERROR(MATCH($B11,GP_CX_Sectors,0)),0,IF(N11<=INDEX(GP_CX_T,MATCH($B11,GP_CX_Sectors,0),1),INDEX(GP_CX_T,MATCH($B11,GP_CX_Sectors,0),2),IF(N11<=INDEX(GP_CX_T,MATCH($B11,GP_CX_Sectors,0),3),INDEX(GP_CX_T,MATCH($B11,GP_CX_Sectors,0),4),IF(N11<=INDEX(GP_CX_T,MATCH($B11,GP_CX_Sectors,0),5),INDEX(GP_CX_T,MATCH($B11,GP_CX_Sectors,0),6),IF(N11<=INDEX(GP_CX_T,MATCH($B11,GP_CX_Sectors,0),7),INDEX(GP_CX_T,MATCH($B11,GP_CX_Sectors,0),8),IF(N11<=INDEX(GP_CX_T,MATCH($B11,GP_CX_Sectors,0),9),INDEX(GP_CX_T,MATCH($B11,GP_CX_Sectors,0),10),IF(N11<=INDEX(GP_CX_T,MATCH($B11,GP_CX_Sectors,0),11),INDEX(GP_CX_T,MATCH($B11,GP_CX_Sectors,0),12),0)))))))) -> 70 | AG11: =IF(OR($B11="",O11=""),"",IF(ISERROR(MATCH($B11,GP_PE_Sectors,0)),0,IF(O11<=INDEX(GP_PE_T,MATCH($B11,GP_PE_Sectors,0),1),INDEX(GP_PE_T,MATCH($B11,GP_PE_Sectors,0),2),IF(O11<=INDEX(GP_PE_T,MATCH($B11,GP_PE_Sectors,0),3),INDEX(GP_PE_T,MATCH($B11,GP_PE_Sectors,0),4),IF(O11<=INDEX(GP_PE_T,MATCH($B11,GP_PE_Sectors,0),5),INDEX(GP_PE_T,MATCH($B11,GP_PE_Sectors,0),6),IF(O11<=INDEX(GP_PE_T,MATCH($B11,GP_PE_Sectors,0),7),INDEX(GP_PE_T,MATCH($B11,GP_PE_Sectors,0),8),IF(O11<=INDEX(GP_PE_T,MATCH($B11,GP_PE_Sectors,0),9),INDEX(GP_PE_T,MATCH($B11,GP_PE_Sectors,0),10),IF(O11<=INDEX(GP_PE_T,MATCH($B11,GP_PE_Sectors,0),11),INDEX(GP_PE_T,MATCH($B11,GP_PE_Sectors,0),12),0)))))))) -> 65 | AH11: =IF(OR($B11="",P11=""),"",IF(ISERROR(MATCH($B11,GP_EV_Sectors,0)),0,IF(P11<=INDEX(GP_EV_T,MATCH($B11,GP_EV_Sectors,0),1),INDEX(GP_EV_T,MATCH($B11,GP_EV_Sectors,0),2),IF(P11<=INDEX(GP_EV_T,MATCH($B11,GP_EV_Sectors,0),3),INDEX(GP_EV_T,MATCH($B11,GP_EV_Sectors,0),4),IF(P11<=INDEX(GP_EV_T,MATCH($B11,GP_EV_Sectors,0),5),INDEX(GP_EV_T,MATCH($B11,GP_EV_Sectors,0),6),IF(P11<=INDEX(GP_EV_T,MATCH($B11,GP_EV_Sectors,0),7),INDEX(GP_EV_T,MATCH($B11,GP_EV_Sectors,0),8),IF(P11<=INDEX(GP_EV_T,MATCH($B11,GP_EV_Sectors,0),9),INDEX(GP_EV_T,MATCH($B11,GP_EV_Sectors,0),10),IF(P11<=INDEX(GP_EV_T,MATCH($B11,GP_EV_Sectors,0),11),INDEX(GP_EV_T,MATCH($B11,GP_EV_Sectors,0),12),0)))))))) -> 65 | AI11: =IF(OR($B11="",Q11=""),"",IF(ISERROR(MATCH($B11,GP_PF_Sectors,0)),0,IF(Q11<=INDEX(GP_PF_T,MATCH($B11,GP_PF_Sectors,0),1),INDEX(GP_PF_T,MATCH($B11,GP_PF_Sectors,0),2),IF(Q11<=INDEX(GP_PF_T,MATCH($B11,GP_PF_Sectors,0),3),INDEX(GP_PF_T,MATCH($B11,GP_PF_Sectors,0),4),IF(Q11<=INDEX(GP_PF_T,MATCH($B11,GP_PF_Sectors,0),5),INDEX(GP_PF_T,MATCH($B11,GP_PF_Sectors,0),6),IF(Q11<=INDEX(GP_PF_T,MATCH($B11,GP_PF_Sectors,0),7),INDEX(GP_PF_T,MATCH($B11,GP_PF_Sectors,0),8),IF(Q11<=INDEX(GP_PF_T,MATCH($B11,GP_PF_Sectors,0),9),INDEX(GP_PF_T,MATCH($B11,GP_PF_Sectors,0),10),IF(Q11<=INDEX(GP_PF_T,MATCH($B11,GP_PF_Sectors,0),11),INDEX(GP_PF_T,MATCH($B11,GP_PF_Sectors,0),12),0)))))))) -> 65 | AJ11: =IF(OR($B11="",R11=""),"",IF(ISERROR(MATCH($B11,GP_DY_Sectors,0)),0,IF(R11>=INDEX(GP_DY_T,MATCH($B11,GP_DY_Sectors,0),1),INDEX(GP_DY_T,MATCH($B11,GP_DY_Sectors,0),2),IF(R11>=INDEX(GP_DY_T,MATCH($B11,GP_DY_Sectors,0),3),INDEX(GP_DY_T,MATCH($B11,GP_DY_Sectors,0),4),IF(R11>=INDEX(GP_DY_T,MATCH($B11,GP_DY_Sectors,0),5),INDEX(GP_DY_T,MATCH($B11,GP_DY_Sectors,0),6),IF(R11>=INDEX(GP_DY_T,MATCH($B11,GP_DY_Sectors,0),7),INDEX(GP_DY_T,MATCH($B11,GP_DY_Sectors,0),8),IF(R11>=INDEX(GP_DY_T,MATCH($B11,GP_DY_Sectors,0),9),INDEX(GP_DY_T,MATCH($B11,GP_DY_Sectors,0),10),IF(R11>=INDEX(GP_DY_T,MATCH($B11,GP_DY_Sectors,0),11),INDEX(GP_DY_T,MATCH($B11,GP_DY_Sectors,0),12),0)))))))) -> 22 | AK11: =IF(OR($B11="",S11=""),"",IF(ISERROR(MATCH($B11,GP_PR_Sectors,0)),0,IF(S11>=INDEX(GP_PR_T,MATCH($B11,GP_PR_Sectors,0),1),INDEX(GP_PR_T,MATCH($B11,GP_PR_Sectors,0),2),IF(S11>=INDEX(GP_PR_T,MATCH($B11,GP_PR_Sectors,0),3),INDEX(GP_PR_T,MATCH($B11,GP_PR_Sectors,0),4),IF(S11>=INDEX(GP_PR_T,MATCH($B11,GP_PR_Sectors,0),5),INDEX(GP_PR_T,MATCH($B11,GP_PR_Sectors,0),6),IF(S11>=INDEX(GP_PR_T,MATCH($B11,GP_PR_Sectors,0),7),INDEX(GP_PR_T,MATCH($B11,GP_PR_Sectors,0),8),IF(S11>=INDEX(GP_PR_T,MATCH($B11,GP_PR_Sectors,0),9),INDEX(GP_PR_T,MATCH($B11,GP_PR_Sectors,0),10),IF(S11>=INDEX(GP_PR_T,MATCH($B11,GP_PR_Sectors,0),11),INDEX(GP_PR_T,MATCH($B11,GP_PR_Sectors,0),12),0)))))))) -> 0 | AL11: =IF(OR($B11="",T11=""),"",IF(ISERROR(MATCH($B11,GP_BY_Sectors,0)),0,IF(T11>=INDEX(GP_BY_T,MATCH($B11,GP_BY_Sectors,0),1),INDEX(GP_BY_T,MATCH($B11,GP_BY_Sectors,0),2),IF(T11>=INDEX(GP_BY_T,MATCH($B11,GP_BY_Sectors,0),3),INDEX(GP_BY_T,MATCH($B11,GP_BY_Sectors,0),4),IF(T11>=INDEX(GP_BY_T,MATCH($B11,GP_BY_Sectors,0),5),INDEX(GP_BY_T,MATCH($B11,GP_BY_Sectors,0),6),IF(T11>=INDEX(GP_BY_T,MATCH($B11,GP_BY_Sectors,0),7),INDEX(GP_BY_T,MATCH($B11,GP_BY_Sectors,0),8),IF(T11>=INDEX(GP_BY_T,MATCH($B11,GP_BY_Sectors,0),9),INDEX(GP_BY_T,MATCH($B11,GP_BY_Sectors,0),10),IF(T11>=INDEX(GP_BY_T,MATCH($B11,GP_BY_Sectors,0),11),INDEX(GP_BY_T,MATCH($B11,GP_BY_Sectors,0),12),0)))))))) -> 100 | AM11: =IF($B11="","",U11*0.35+V11*0.35+W11*0.3) -> 95.8 | AN11: =IF($B11="","",X11*0.4+Y11*0.35+Z11*0.25) -> 90.25 | AO11: =IF($B11="","",AA11*0.35+AB11*0.3+AC11*0.35) -> 100 | AP11: =IF($B11="","",AD11*0.4+AE11*0.35+AF11*0.25) -> 82 | AQ11: =IF($B11="","",AG11*0.35+AH11*0.35+AI11*0.3) -> 65 | AR11: =IF($B11="","",AJ11*0.45+AK11*0.2+AL11*0.35) -> 44.9 | AS11: =IF($B11="","",MIN(100,MAX(0,ROUND(AM11*INDEX(GP_W_P1,MATCH($B11,GP_Weights_Sectors,0))+AN11*INDEX(GP_W_P2,MATCH($B11,GP_Weights_Sectors,0))+AO11*INDEX(GP_W_P3,MATCH($B11,GP_Weights_Sectors,0))+AP11*INDEX(GP_W_P4,MATCH($B11,GP_Weights_Sectors,0))+AQ11*INDEX(GP_W_P5,MATCH($B11,GP_Weights_Sectors,0))+AR11*INDEX(GP_W_P6,MATCH($B11,GP_Weights_Sectors,0)),0)))) -> 84 | AT11: 2 | AU11: 3 | AV11: 3 | AW11: =MAX(-10,MIN(10,AT11+AU11+AV11)) -> 8 | AX11: #VALUE! | AY11: {=_FV(AX11,"PRECIO")} -> 280.92 | AZ11: 340 | BA11: =IFERROR(INDEX('DCF Simplified'!$Y$4:$Y$38,MATCH(A11,'DCF Simplified'!$A$4:$A$38,0)),"") -> 270.4372 | BB11: =IF(OR(AY11="",AZ11=""),"",(AZ11-AY11)/AY11) -> 0.21030898 | BD11: 0.03 | BE11: 50 | BF11: 0.05 | BG11: =IF(BD11>0.1,100,IF(BD11>0.05,80,IF(BD11>0,65,IF(BD11>-0.05,45,IF(BD11>-0.1,25,10))))) -> 65 | BH11: =IF(AND(BE11>=40,BE11<=60),70,IF(AND(BE11>60,BE11<=70),85,IF(BE11>70,50,IF(AND(BE11>=30,BE11<40),55,40)))) -> 70 | BI11: =IF(BF11>0.2,100,IF(BF11>0.1,80,IF(BF11>0,65,IF(BF11>-0.1,45,IF(BF11>-0.2,25,10))))) -> 65 | BJ11: =ROUND(BG11*0.4+BH11*0.25+BI11*0.35,1) -> 66.3 | BK11: =IF(OR(AS11="",AQ11="",BJ11=""),"",ROUND(AS11*0.4+MAX(15,MIN(90,AQ11))*0.2+BJ11*0.25+MIN(100,MAX(0,AW11*10))*0.15,0)) -> 75 | BL11: =IF(BK11="","",IF(BK11>=85,"🟢 STRONG",IF(BK11>=70,"🟡 FAVORABLE",IF(BK11>=55,"⚪ NEUTRAL",IF(BK11>=40,"🟠 WEAK","🔴 AVOID"))))) -> 🟡 FAVORABLE | BM11: =IF(BK11="","",IF(AND(BK11>=75,BJ11>=70,AW11>=6),"🚀 STRONG BUY",IF(AND(BK11>=65,BJ11>=55),"✅ BUY",IF(BK11>=55,"⚠️ HOLD",IF(OR(BK11<45,AND(BJ11<35,AW11<3)),"🔴 SELL","🟠 UNDERWEIGHT"))))) -> ✅ BUY
A12: Procter & Gamble | B12: Consumer Staples | C12: 0.296 | D12: 0.175 | E12: 0.177 | F12: 0.04 | G12: 0.06 | H12: 1.1 | I12: 1.3 | J12: 0.75 | K12: 25 | L12: 0.18 | M12: 0.9 | N12: 0.05 | O12: 24 | P12: 18 | Q12: 27 | R12: 0.024 | S12: 0.6 | T12: 0.03 | U12: =IF(OR($B12="",C12=""),"",IF(ISERROR(MATCH($B12,GP_ROE_Sectors,0)),0,IF(C12>=INDEX(GP_ROE_T,MATCH($B12,GP_ROE_Sectors,0),1),INDEX(GP_ROE_T,MATCH($B12,GP_ROE_Sectors,0),2),IF(C12>=INDEX(GP_ROE_T,MATCH($B12,GP_ROE_Sectors,0),3),INDEX(GP_ROE_T,MATCH($B12,GP_ROE_Sectors,0),4),IF(C12>=INDEX(GP_ROE_T,MATCH($B12,GP_ROE_Sectors,0),5),INDEX(GP_ROE_T,MATCH($B12,GP_ROE_Sectors,0),6),IF(C12>=INDEX(GP_ROE_T,MATCH($B12,GP_ROE_Sectors,0),7),INDEX(GP_ROE_T,MATCH($B12,GP_ROE_Sectors,0),8),IF(C12>=INDEX(GP_ROE_T,MATCH($B12,GP_ROE_Sectors,0),9),INDEX(GP_ROE_T,MATCH($B12,GP_ROE_Sectors,0),10),IF(C12>=INDEX(GP_ROE_T,MATCH($B12,GP_ROE_Sectors,0),11),INDEX(GP_ROE_T,MATCH($B12,GP_ROE_Sectors,0),12),0)))))))) -> 100 | V12: =IF(OR($B12="",D12=""),"",IF(ISERROR(MATCH($B12,GP_ROIC_Sectors,0)),0,IF(D12>=INDEX(GP_ROIC_T,MATCH($B12,GP_ROIC_Sectors,0),1),INDEX(GP_ROIC_T,MATCH($B12,GP_ROIC_Sectors,0),2),IF(D12>=INDEX(GP_ROIC_T,MATCH($B12,GP_ROIC_Sectors,0),3),INDEX(GP_ROIC_T,MATCH($B12,GP_ROIC_Sectors,0),4),IF(D12>=INDEX(GP_ROIC_T,MATCH($B12,GP_ROIC_Sectors,0),5),INDEX(GP_ROIC_T,MATCH($B12,GP_ROIC_Sectors,0),6),IF(D12>=INDEX(GP_ROIC_T,MATCH($B12,GP_ROIC_Sectors,0),7),INDEX(GP_ROIC_T,MATCH($B12,GP_ROIC_Sectors,0),8),IF(D12>=INDEX(GP_ROIC_T,MATCH($B12,GP_ROIC_Sectors,0),9),INDEX(GP_ROIC_T,MATCH($B12,GP_ROIC_Sectors,0),10),IF(D12>=INDEX(GP_ROIC_T,MATCH($B12,GP_ROIC_Sectors,0),11),INDEX(GP_ROIC_T,MATCH($B12,GP_ROIC_Sectors,0),12),0)))))))) -> 85 | W12: =IF(OR($B12="",E12=""),"",IF(ISERROR(MATCH($B12,GP_NM_Sectors,0)),0,IF(E12>=INDEX(GP_NM_T,MATCH($B12,GP_NM_Sectors,0),1),INDEX(GP_NM_T,MATCH($B12,GP_NM_Sectors,0),2),IF(E12>=INDEX(GP_NM_T,MATCH($B12,GP_NM_Sectors,0),3),INDEX(GP_NM_T,MATCH($B12,GP_NM_Sectors,0),4),IF(E12>=INDEX(GP_NM_T,MATCH($B12,GP_NM_Sectors,0),5),INDEX(GP_NM_T,MATCH($B12,GP_NM_Sectors,0),6),IF(E12>=INDEX(GP_NM_T,MATCH($B12,GP_NM_Sectors,0),7),INDEX(GP_NM_T,MATCH($B12,GP_NM_Sectors,0),8),IF(E12>=INDEX(GP_NM_T,MATCH($B12,GP_NM_Sectors,0),9),INDEX(GP_NM_T,MATCH($B12,GP_NM_Sectors,0),10),IF(E12>=INDEX(GP_NM_T,MATCH($B12,GP_NM_Sectors,0),11),INDEX(GP_NM_T,MATCH($B12,GP_NM_Sectors,0),12),0)))))))) -> 100 | X12: =IF(OR($B12="",F12=""),"",IF(ISERROR(MATCH($B12,GP_RG_Sectors,0)),0,IF(F12>=INDEX(GP_RG_T,MATCH($B12,GP_RG_Sectors,0),1),INDEX(GP_RG_T,MATCH($B12,GP_RG_Sectors,0),2),IF(F12>=INDEX(GP_RG_T,MATCH($B12,GP_RG_Sectors,0),3),INDEX(GP_RG_T,MATCH($B12,GP_RG_Sectors,0),4),IF(F12>=INDEX(GP_RG_T,MATCH($B12,GP_RG_Sectors,0),5),INDEX(GP_RG_T,MATCH($B12,GP_RG_Sectors,0),6),IF(F12>=INDEX(GP_RG_T,MATCH($B12,GP_RG_Sectors,0),7),INDEX(GP_RG_T,MATCH($B12,GP_RG_Sectors,0),8),IF(F12>=INDEX(GP_RG_T,MATCH($B12,GP_RG_Sectors,0),9),INDEX(GP_RG_T,MATCH($B12,GP_RG_Sectors,0),10),IF(F12>=INDEX(GP_RG_T,MATCH($B12,GP_RG_Sectors,0),11),INDEX(GP_RG_T,MATCH($B12,GP_RG_Sectors,0),12),0)))))))) -> 68 | Y12: =IF(OR($B12="",G12=""),"",IF(ISERROR(MATCH($B12,GP_EG_Sectors,0)),0,IF(G12>=INDEX(GP_EG_T,MATCH($B12,GP_EG_Sectors,0),1),INDEX(GP_EG_T,MATCH($B12,GP_EG_Sectors,0),2),IF(G12>=INDEX(GP_EG_T,MATCH($B12,GP_EG_Sectors,0),3),INDEX(GP_EG_T,MATCH($B12,GP_EG_Sectors,0),4),IF(G12>=INDEX(GP_EG_T,MATCH($B12,GP_EG_Sectors,0),5),INDEX(GP_EG_T,MATCH($B12,GP_EG_Sectors,0),6),IF(G12>=INDEX(GP_EG_T,MATCH($B12,GP_EG_Sectors,0),7),INDEX(GP_EG_T,MATCH($B12,GP_EG_Sectors,0),8),IF(G12>=INDEX(GP_EG_T,MATCH($B12,GP_EG_Sectors,0),9),INDEX(GP_EG_T,MATCH($B12,GP_EG_Sectors,0),10),IF(G12>=INDEX(GP_EG_T,MATCH($B12,GP_EG_Sectors,0),11),INDEX(GP_EG_T,MATCH($B12,GP_EG_Sectors,0),12),0)))))))) -> 85 | Z12: =IF(OR($B12="",H12=""),"",IF(ISERROR(MATCH($B12,GP_OL_Sectors,0)),0,IF(H12>=INDEX(GP_OL_T,MATCH($B12,GP_OL_Sectors,0),1),INDEX(GP_OL_T,MATCH($B12,GP_OL_Sectors,0),2),IF(H12>=INDEX(GP_OL_T,MATCH($B12,GP_OL_Sectors,0),3),INDEX(GP_OL_T,MATCH($B12,GP_OL_Sectors,0),4),IF(H12>=INDEX(GP_OL_T,MATCH($B12,GP_OL_Sectors,0),5),INDEX(GP_OL_T,MATCH($B12,GP_OL_Sectors,0),6),IF(H12>=INDEX(GP_OL_T,MATCH($B12,GP_OL_Sectors,0),7),INDEX(GP_OL_T,MATCH($B12,GP_OL_Sectors,0),8),IF(H12>=INDEX(GP_OL_T,MATCH($B12,GP_OL_Sectors,0),9),INDEX(GP_OL_T,MATCH($B12,GP_OL_Sectors,0),10),IF(H12>=INDEX(GP_OL_T,MATCH($B12,GP_OL_Sectors,0),11),INDEX(GP_OL_T,MATCH($B12,GP_OL_Sectors,0),12),0)))))))) -> 68 | AA12: =IF(OR($B12="",I12=""),"",IF(ISERROR(MATCH($B12,GP_ND_Sectors,0)),0,IF(I12<=INDEX(GP_ND_T,MATCH($B12,GP_ND_Sectors,0),1),INDEX(GP_ND_T,MATCH($B12,GP_ND_Sectors,0),2),IF(I12<=INDEX(GP_ND_T,MATCH($B12,GP_ND_Sectors,0),3),INDEX(GP_ND_T,MATCH($B12,GP_ND_Sectors,0),4),IF(I12<=INDEX(GP_ND_T,MATCH($B12,GP_ND_Sectors,0),5),INDEX(GP_ND_T,MATCH($B12,GP_ND_Sectors,0),6),IF(I12<=INDEX(GP_ND_T,MATCH($B12,GP_ND_Sectors,0),7),INDEX(GP_ND_T,MATCH($B12,GP_ND_Sectors,0),8),IF(I12<=INDEX(GP_ND_T,MATCH($B12,GP_ND_Sectors,0),9),INDEX(GP_ND_T,MATCH($B12,GP_ND_Sectors,0),10),IF(I12<=INDEX(GP_ND_T,MATCH($B12,GP_ND_Sectors,0),11),INDEX(GP_ND_T,MATCH($B12,GP_ND_Sectors,0),12),0)))))))) -> 68 | AB12: =IF(OR($B12="",J12=""),"",IF(ISERROR(MATCH($B12,GP_CR_Sectors,0)),0,IF(J12>=INDEX(GP_CR_T,MATCH($B12,GP_CR_Sectors,0),1),INDEX(GP_CR_T,MATCH($B12,GP_CR_Sectors,0),2),IF(J12>=INDEX(GP_CR_T,MATCH($B12,GP_CR_Sectors,0),3),INDEX(GP_CR_T,MATCH($B12,GP_CR_Sectors,0),4),IF(J12>=INDEX(GP_CR_T,MATCH($B12,GP_CR_Sectors,0),5),INDEX(GP_CR_T,MATCH($B12,GP_CR_Sectors,0),6),IF(J12>=INDEX(GP_CR_T,MATCH($B12,GP_CR_Sectors,0),7),INDEX(GP_CR_T,MATCH($B12,GP_CR_Sectors,0),8),IF(J12>=INDEX(GP_CR_T,MATCH($B12,GP_CR_Sectors,0),9),INDEX(GP_CR_T,MATCH($B12,GP_CR_Sectors,0),10),IF(J12>=INDEX(GP_CR_T,MATCH($B12,GP_CR_Sectors,0),11),INDEX(GP_CR_T,MATCH($B12,GP_CR_Sectors,0),12),0)))))))) -> 30 | AC12: =IF(OR($B12="",K12=""),"",IF(ISERROR(MATCH($B12,GP_IC_Sectors,0)),0,IF(K12>=INDEX(GP_IC_T,MATCH($B12,GP_IC_Sectors,0),1),INDEX(GP_IC_T,MATCH($B12,GP_IC_Sectors,0),2),IF(K12>=INDEX(GP_IC_T,MATCH($B12,GP_IC_Sectors,0),3),INDEX(GP_IC_T,MATCH($B12,GP_IC_Sectors,0),4),IF(K12>=INDEX(GP_IC_T,MATCH($B12,GP_IC_Sectors,0),5),INDEX(GP_IC_T,MATCH($B12,GP_IC_Sectors,0),6),IF(K12>=INDEX(GP_IC_T,MATCH($B12,GP_IC_Sectors,0),7),INDEX(GP_IC_T,MATCH($B12,GP_IC_Sectors,0),8),IF(K12>=INDEX(GP_IC_T,MATCH($B12,GP_IC_Sectors,0),9),INDEX(GP_IC_T,MATCH($B12,GP_IC_Sectors,0),10),IF(K12>=INDEX(GP_IC_T,MATCH($B12,GP_IC_Sectors,0),11),INDEX(GP_IC_T,MATCH($B12,GP_IC_Sectors,0),12),0)))))))) -> 100 | AD12: =IF(OR($B12="",L12=""),"",IF(ISERROR(MATCH($B12,GP_FM_Sectors,0)),0,IF(L12>=INDEX(GP_FM_T,MATCH($B12,GP_FM_Sectors,0),1),INDEX(GP_FM_T,MATCH($B12,GP_FM_Sectors,0),2),IF(L12>=INDEX(GP_FM_T,MATCH($B12,GP_FM_Sectors,0),3),INDEX(GP_FM_T,MATCH($B12,GP_FM_Sectors,0),4),IF(L12>=INDEX(GP_FM_T,MATCH($B12,GP_FM_Sectors,0),5),INDEX(GP_FM_T,MATCH($B12,GP_FM_Sectors,0),6),IF(L12>=INDEX(GP_FM_T,MATCH($B12,GP_FM_Sectors,0),7),INDEX(GP_FM_T,MATCH($B12,GP_FM_Sectors,0),8),IF(L12>=INDEX(GP_FM_T,MATCH($B12,GP_FM_Sectors,0),9),INDEX(GP_FM_T,MATCH($B12,GP_FM_Sectors,0),10),IF(L12>=INDEX(GP_FM_T,MATCH($B12,GP_FM_Sectors,0),11),INDEX(GP_FM_T,MATCH($B12,GP_FM_Sectors,0),12),0)))))))) -> 100 | AE12: =IF(OR($B12="",M12=""),"",IF(ISERROR(MATCH($B12,GP_FN_Sectors,0)),0,IF(M12>=INDEX(GP_FN_T,MATCH($B12,GP_FN_Sectors,0),1),INDEX(GP_FN_T,MATCH($B12,GP_FN_Sectors,0),2),IF(M12>=INDEX(GP_FN_T,MATCH($B12,GP_FN_Sectors,0),3),INDEX(GP_FN_T,MATCH($B12,GP_FN_Sectors,0),4),IF(M12>=INDEX(GP_FN_T,MATCH($B12,GP_FN_Sectors,0),5),INDEX(GP_FN_T,MATCH($B12,GP_FN_Sectors,0),6),IF(M12>=INDEX(GP_FN_T,MATCH($B12,GP_FN_Sectors,0),7),INDEX(GP_FN_T,MATCH($B12,GP_FN_Sectors,0),8),IF(M12>=INDEX(GP_FN_T,MATCH($B12,GP_FN_Sectors,0),9),INDEX(GP_FN_T,MATCH($B12,GP_FN_Sectors,0),10),IF(M12>=INDEX(GP_FN_T,MATCH($B12,GP_FN_Sectors,0),11),INDEX(GP_FN_T,MATCH($B12,GP_FN_Sectors,0),12),0)))))))) -> 82 | AF12: =IF(OR($B12="",N12=""),"",IF(ISERROR(MATCH($B12,GP_CX_Sectors,0)),0,IF(N12<=INDEX(GP_CX_T,MATCH($B12,GP_CX_Sectors,0),1),INDEX(GP_CX_T,MATCH($B12,GP_CX_Sectors,0),2),IF(N12<=INDEX(GP_CX_T,MATCH($B12,GP_CX_Sectors,0),3),INDEX(GP_CX_T,MATCH($B12,GP_CX_Sectors,0),4),IF(N12<=INDEX(GP_CX_T,MATCH($B12,GP_CX_Sectors,0),5),INDEX(GP_CX_T,MATCH($B12,GP_CX_Sectors,0),6),IF(N12<=INDEX(GP_CX_T,MATCH($B12,GP_CX_Sectors,0),7),INDEX(GP_CX_T,MATCH($B12,GP_CX_Sectors,0),8),IF(N12<=INDEX(GP_CX_T,MATCH($B12,GP_CX_Sectors,0),9),INDEX(GP_CX_T,MATCH($B12,GP_CX_Sectors,0),10),IF(N12<=INDEX(GP_CX_T,MATCH($B12,GP_CX_Sectors,0),11),INDEX(GP_CX_T,MATCH($B12,GP_CX_Sectors,0),12),0)))))))) -> 82 | AG12: =IF(OR($B12="",O12=""),"",IF(ISERROR(MATCH($B12,GP_PE_Sectors,0)),0,IF(O12<=INDEX(GP_PE_T,MATCH($B12,GP_PE_Sectors,0),1),INDEX(GP_PE_T,MATCH($B12,GP_PE_Sectors,0),2),IF(O12<=INDEX(GP_PE_T,MATCH($B12,GP_PE_Sectors,0),3),INDEX(GP_PE_T,MATCH($B12,GP_PE_Sectors,0),4),IF(O12<=INDEX(GP_PE_T,MATCH($B12,GP_PE_Sectors,0),5),INDEX(GP_PE_T,MATCH($B12,GP_PE_Sectors,0),6),IF(O12<=INDEX(GP_PE_T,MATCH($B12,GP_PE_Sectors,0),7),INDEX(GP_PE_T,MATCH($B12,GP_PE_Sectors,0),8),IF(O12<=INDEX(GP_PE_T,MATCH($B12,GP_PE_Sectors,0),9),INDEX(GP_PE_T,MATCH($B12,GP_PE_Sectors,0),10),IF(O12<=INDEX(GP_PE_T,MATCH($B12,GP_PE_Sectors,0),11),INDEX(GP_PE_T,MATCH($B12,GP_PE_Sectors,0),12),0)))))))) -> 48 | AH12: =IF(OR($B12="",P12=""),"",IF(ISERROR(MATCH($B12,GP_EV_Sectors,0)),0,IF(P12<=INDEX(GP_EV_T,MATCH($B12,GP_EV_Sectors,0),1),INDEX(GP_EV_T,MATCH($B12,GP_EV_Sectors,0),2),IF(P12<=INDEX(GP_EV_T,MATCH($B12,GP_EV_Sectors,0),3),INDEX(GP_EV_T,MATCH($B12,GP_EV_Sectors,0),4),IF(P12<=INDEX(GP_EV_T,MATCH($B12,GP_EV_Sectors,0),5),INDEX(GP_EV_T,MATCH($B12,GP_EV_Sectors,0),6),IF(P12<=INDEX(GP_EV_T,MATCH($B12,GP_EV_Sectors,0),7),INDEX(GP_EV_T,MATCH($B12,GP_EV_Sectors,0),8),IF(P12<=INDEX(GP_EV_T,MATCH($B12,GP_EV_Sectors,0),9),INDEX(GP_EV_T,MATCH($B12,GP_EV_Sectors,0),10),IF(P12<=INDEX(GP_EV_T,MATCH($B12,GP_EV_Sectors,0),11),INDEX(GP_EV_T,MATCH($B12,GP_EV_Sectors,0),12),0)))))))) -> 48 | AI12: =IF(OR($B12="",Q12=""),"",IF(ISERROR(MATCH($B12,GP_PF_Sectors,0)),0,IF(Q12<=INDEX(GP_PF_T,MATCH($B12,GP_PF_Sectors,0),1),INDEX(GP_PF_T,MATCH($B12,GP_PF_Sectors,0),2),IF(Q12<=INDEX(GP_PF_T,MATCH($B12,GP_PF_Sectors,0),3),INDEX(GP_PF_T,MATCH($B12,GP_PF_Sectors,0),4),IF(Q12<=INDEX(GP_PF_T,MATCH($B12,GP_PF_Sectors,0),5),INDEX(GP_PF_T,MATCH($B12,GP_PF_Sectors,0),6),IF(Q12<=INDEX(GP_PF_T,MATCH($B12,GP_PF_Sectors,0),7),INDEX(GP_PF_T,MATCH($B12,GP_PF_Sectors,0),8),IF(Q12<=INDEX(GP_PF_T,MATCH($B12,GP_PF_Sectors,0),9),INDEX(GP_PF_T,MATCH($B12,GP_PF_Sectors,0),10),IF(Q12<=INDEX(GP_PF_T,MATCH($B12,GP_PF_Sectors,0),11),INDEX(GP_PF_T,MATCH($B12,GP_PF_Sectors,0),12),0)))))))) -> 65 | AJ12: =IF(OR($B12="",R12=""),"",IF(ISERROR(MATCH($B12,GP_DY_Sectors,0)),0,IF(R12>=INDEX(GP_DY_T,MATCH($B12,GP_DY_Sectors,0),1),INDEX(GP_DY_T,MATCH($B12,GP_DY_Sectors,0),2),IF(R12>=INDEX(GP_DY_T,MATCH($B12,GP_DY_Sectors,0),3),INDEX(GP_DY_T,MATCH($B12,GP_DY_Sectors,0),4),IF(R12>=INDEX(GP_DY_T,MATCH($B12,GP_DY_Sectors,0),5),INDEX(GP_DY_T,MATCH($B12,GP_DY_Sectors,0),6),IF(R12>=INDEX(GP_DY_T,MATCH($B12,GP_DY_Sectors,0),7),INDEX(GP_DY_T,MATCH($B12,GP_DY_Sectors,0),8),IF(R12>=INDEX(GP_DY_T,MATCH($B12,GP_DY_Sectors,0),9),INDEX(GP_DY_T,MATCH($B12,GP_DY_Sectors,0),10),IF(R12>=INDEX(GP_DY_T,MATCH($B12,GP_DY_Sectors,0),11),INDEX(GP_DY_T,MATCH($B12,GP_DY_Sectors,0),12),0)))))))) -> 68 | AK12: =IF(OR($B12="",S12=""),"",IF(ISERROR(MATCH($B12,GP_PR_Sectors,0)),0,IF(S12>=INDEX(GP_PR_T,MATCH($B12,GP_PR_Sectors,0),1),INDEX(GP_PR_T,MATCH($B12,GP_PR_Sectors,0),2),IF(S12>=INDEX(GP_PR_T,MATCH($B12,GP_PR_Sectors,0),3),INDEX(GP_PR_T,MATCH($B12,GP_PR_Sectors,0),4),IF(S12>=INDEX(GP_PR_T,MATCH($B12,GP_PR_Sectors,0),5),INDEX(GP_PR_T,MATCH($B12,GP_PR_Sectors,0),6),IF(S12>=INDEX(GP_PR_T,MATCH($B12,GP_PR_Sectors,0),7),INDEX(GP_PR_T,MATCH($B12,GP_PR_Sectors,0),8),IF(S12>=INDEX(GP_PR_T,MATCH($B12,GP_PR_Sectors,0),9),INDEX(GP_PR_T,MATCH($B12,GP_PR_Sectors,0),10),IF(S12>=INDEX(GP_PR_T,MATCH($B12,GP_PR_Sectors,0),11),INDEX(GP_PR_T,MATCH($B12,GP_PR_Sectors,0),12),0)))))))) -> 100 | AL12: =IF(OR($B12="",T12=""),"",IF(ISERROR(MATCH($B12,GP_BY_Sectors,0)),0,IF(T12>=INDEX(GP_BY_T,MATCH($B12,GP_BY_Sectors,0),1),INDEX(GP_BY_T,MATCH($B12,GP_BY_Sectors,0),2),IF(T12>=INDEX(GP_BY_T,MATCH($B12,GP_BY_Sectors,0),3),INDEX(GP_BY_T,MATCH($B12,GP_BY_Sectors,0),4),IF(T12>=INDEX(GP_BY_T,MATCH($B12,GP_BY_Sectors,0),5),INDEX(GP_BY_T,MATCH($B12,GP_BY_Sectors,0),6),IF(T12>=INDEX(GP_BY_T,MATCH($B12,GP_BY_Sectors,0),7),INDEX(GP_BY_T,MATCH($B12,GP_BY_Sectors,0),8),IF(T12>=INDEX(GP_BY_T,MATCH($B12,GP_BY_Sectors,0),9),INDEX(GP_BY_T,MATCH($B12,GP_BY_Sectors,0),10),IF(T12>=INDEX(GP_BY_T,MATCH($B12,GP_BY_Sectors,0),11),INDEX(GP_BY_T,MATCH($B12,GP_BY_Sectors,0),12),0)))))))) -> 100 | AM12: =IF($B12="","",U12*0.35+V12*0.35+W12*0.3) -> 94.75 | AN12: =IF($B12="","",X12*0.4+Y12*0.35+Z12*0.25) -> 73.95 | AO12: =IF($B12="","",AA12*0.35+AB12*0.3+AC12*0.35) -> 67.8 | AP12: =IF($B12="","",AD12*0.4+AE12*0.35+AF12*0.25) -> 89.2 | AQ12: =IF($B12="","",AG12*0.35+AH12*0.35+AI12*0.3) -> 53.1 | AR12: =IF($B12="","",AJ12*0.45+AK12*0.2+AL12*0.35) -> 85.6 | AS12: =IF($B12="","",MIN(100,MAX(0,ROUND(AM12*INDEX(GP_W_P1,MATCH($B12,GP_Weights_Sectors,0))+AN12*INDEX(GP_W_P2,MATCH($B12,GP_Weights_Sectors,0))+AO12*INDEX(GP_W_P3,MATCH($B12,GP_Weights_Sectors,0))+AP12*INDEX(GP_W_P4,MATCH($B12,GP_Weights_Sectors,0))+AQ12*INDEX(GP_W_P5,MATCH($B12,GP_Weights_Sectors,0))+AR12*INDEX(GP_W_P6,MATCH($B12,GP_Weights_Sectors,0)),0)))) -> 78 | AT12: 1 | AU12: 2 | AV12: 2 | AW12: =MAX(-10,MIN(10,AT12+AU12+AV12)) -> 5 | AX12: #VALUE! | AY12: {=_FV(AX12,"PRECIO")} -> 142.42 | AZ12: 148 | BA12: =IFERROR(INDEX('DCF Simplified'!$Y$4:$Y$38,MATCH(A12,'DCF Simplified'!$A$4:$A$38,0)),"") -> 165.86976 | BB12: =IF(OR(AY12="",AZ12=""),"",(AZ12-AY12)/AY12) -> 0.03917989 | BD12: -0.04 | BE12: 45 | BF12: -0.06 | BG12: =IF(BD12>0.1,100,IF(BD12>0.05,80,IF(BD12>0,65,IF(BD12>-0.05,45,IF(BD12>-0.1,25,10))))) -> 45 | BH12: =IF(AND(BE12>=40,BE12<=60),70,IF(AND(BE12>60,BE12<=70),85,IF(BE12>70,50,IF(AND(BE12>=30,BE12<40),55,40)))) -> 70 | BI12: =IF(BF12>0.2,100,IF(BF12>0.1,80,IF(BF12>0,65,IF(BF12>-0.1,45,IF(BF12>-0.2,25,10))))) -> 45 | BJ12: =ROUND(BG12*0.4+BH12*0.25+BI12*0.35,1) -> 51.3 | BK12: =IF(OR(AS12="",AQ12="",BJ12=""),"",ROUND(AS12*0.4+MAX(15,MIN(90,AQ12))*0.2+BJ12*0.25+MIN(100,MAX(0,AW12*10))*0.15,0)) -> 62 | BL12: =IF(BK12="","",IF(BK12>=85,"🟢 STRONG",IF(BK12>=70,"🟡 FAVORABLE",IF(BK12>=55,"⚪ NEUTRAL",IF(BK12>=40,"🟠 WEAK","🔴 AVOID"))))) -> ⚪ NEUTRAL | BM12: =IF(BK12="","",IF(AND(BK12>=75,BJ12>=70,AW12>=6),"🚀 STRONG BUY",IF(AND(BK12>=65,BJ12>=55),"✅ BUY",IF(BK12>=55,"⚠️ HOLD",IF(OR(BK12<45,AND(BJ12<35,AW12<3)),"🔴 SELL","🟠 UNDERWEIGHT"))))) -> ⚠️ HOLD
A13: Caterpillar Inc | B13: Industrials | C13: 0.554 | D13: 0.155 | E13: 0.166 | F13: 0.08 | G13: 0.18 | H13: 1.4 | I13: 1.5 | J13: 1.4 | K13: 20 | L13: 0.14 | M13: 1 | N13: 0.06 | O13: 17 | P13: 13 | Q13: 20 | R13: 0.015 | S13: 0.25 | T13: 0.06 | U13: =IF(OR($B13="",C13=""),"",IF(ISERROR(MATCH($B13,GP_ROE_Sectors,0)),0,IF(C13>=INDEX(GP_ROE_T,MATCH($B13,GP_ROE_Sectors,0),1),INDEX(GP_ROE_T,MATCH($B13,GP_ROE_Sectors,0),2),IF(C13>=INDEX(GP_ROE_T,MATCH($B13,GP_ROE_Sectors,0),3),INDEX(GP_ROE_T,MATCH($B13,GP_ROE_Sectors,0),4),IF(C13>=INDEX(GP_ROE_T,MATCH($B13,GP_ROE_Sectors,0),5),INDEX(GP_ROE_T,MATCH($B13,GP_ROE_Sectors,0),6),IF(C13>=INDEX(GP_ROE_T,MATCH($B13,GP_ROE_Sectors,0),7),INDEX(GP_ROE_T,MATCH($B13,GP_ROE_Sectors,0),8),IF(C13>=INDEX(GP_ROE_T,MATCH($B13,GP_ROE_Sectors,0),9),INDEX(GP_ROE_T,MATCH($B13,GP_ROE_Sectors,0),10),IF(C13>=INDEX(GP_ROE_T,MATCH($B13,GP_ROE_Sectors,0),11),INDEX(GP_ROE_T,MATCH($B13,GP_ROE_Sectors,0),12),0)))))))) -> 100 | V13: =IF(OR($B13="",D13=""),"",IF(ISERROR(MATCH($B13,GP_ROIC_Sectors,0)),0,IF(D13>=INDEX(GP_ROIC_T,MATCH($B13,GP_ROIC_Sectors,0),1),INDEX(GP_ROIC_T,MATCH($B13,GP_ROIC_Sectors,0),2),IF(D13>=INDEX(GP_ROIC_T,MATCH($B13,GP_ROIC_Sectors,0),3),INDEX(GP_ROIC_T,MATCH($B13,GP_ROIC_Sectors,0),4),IF(D13>=INDEX(GP_ROIC_T,MATCH($B13,GP_ROIC_Sectors,0),5),INDEX(GP_ROIC_T,MATCH($B13,GP_ROIC_Sectors,0),6),IF(D13>=INDEX(GP_ROIC_T,MATCH($B13,GP_ROIC_Sectors,0),7),INDEX(GP_ROIC_T,MATCH($B13,GP_ROIC_Sectors,0),8),IF(D13>=INDEX(GP_ROIC_T,MATCH($B13,GP_ROIC_Sectors,0),9),INDEX(GP_ROIC_T,MATCH($B13,GP_ROIC_Sectors,0),10),IF(D13>=INDEX(GP_ROIC_T,MATCH($B13,GP_ROIC_Sectors,0),11),INDEX(GP_ROIC_T,MATCH($B13,GP_ROIC_Sectors,0),12),0)))))))) -> 85 | W13: =IF(OR($B13="",E13=""),"",IF(ISERROR(MATCH($B13,GP_NM_Sectors,0)),0,IF(E13>=INDEX(GP_NM_T,MATCH($B13,GP_NM_Sectors,0),1),INDEX(GP_NM_T,MATCH($B13,GP_NM_Sectors,0),2),IF(E13>=INDEX(GP_NM_T,MATCH($B13,GP_NM_Sectors,0),3),INDEX(GP_NM_T,MATCH($B13,GP_NM_Sectors,0),4),IF(E13>=INDEX(GP_NM_T,MATCH($B13,GP_NM_Sectors,0),5),INDEX(GP_NM_T,MATCH($B13,GP_NM_Sectors,0),6),IF(E13>=INDEX(GP_NM_T,MATCH($B13,GP_NM_Sectors,0),7),INDEX(GP_NM_T,MATCH($B13,GP_NM_Sectors,0),8),IF(E13>=INDEX(GP_NM_T,MATCH($B13,GP_NM_Sectors,0),9),INDEX(GP_NM_T,MATCH($B13,GP_NM_Sectors,0),10),IF(E13>=INDEX(GP_NM_T,MATCH($B13,GP_NM_Sectors,0),11),INDEX(GP_NM_T,MATCH($B13,GP_NM_Sectors,0),12),0)))))))) -> 100 | X13: =IF(OR($B13="",F13=""),"",IF(ISERROR(MATCH($B13,GP_RG_Sectors,0)),0,IF(F13>=INDEX(GP_RG_T,MATCH($B13,GP_RG_Sectors,0),1),INDEX(GP_RG_T,MATCH($B13,GP_RG_Sectors,0),2),IF(F13>=INDEX(GP_RG_T,MATCH($B13,GP_RG_Sectors,0),3),INDEX(GP_RG_T,MATCH($B13,GP_RG_Sectors,0),4),IF(F13>=INDEX(GP_RG_T,MATCH($B13,GP_RG_Sectors,0),5),INDEX(GP_RG_T,MATCH($B13,GP_RG_Sectors,0),6),IF(F13>=INDEX(GP_RG_T,MATCH($B13,GP_RG_Sectors,0),7),INDEX(GP_RG_T,MATCH($B13,GP_RG_Sectors,0),8),IF(F13>=INDEX(GP_RG_T,MATCH($B13,GP_RG_Sectors,0),9),INDEX(GP_RG_T,MATCH($B13,GP_RG_Sectors,0),10),IF(F13>=INDEX(GP_RG_T,MATCH($B13,GP_RG_Sectors,0),11),INDEX(GP_RG_T,MATCH($B13,GP_RG_Sectors,0),12),0)))))))) -> 85 | Y13: =IF(OR($B13="",G13=""),"",IF(ISERROR(MATCH($B13,GP_EG_Sectors,0)),0,IF(G13>=INDEX(GP_EG_T,MATCH($B13,GP_EG_Sectors,0),1),INDEX(GP_EG_T,MATCH($B13,GP_EG_Sectors,0),2),IF(G13>=INDEX(GP_EG_T,MATCH($B13,GP_EG_Sectors,0),3),INDEX(GP_EG_T,MATCH($B13,GP_EG_Sectors,0),4),IF(G13>=INDEX(GP_EG_T,MATCH($B13,GP_EG_Sectors,0),5),INDEX(GP_EG_T,MATCH($B13,GP_EG_Sectors,0),6),IF(G13>=INDEX(GP_EG_T,MATCH($B13,GP_EG_Sectors,0),7),INDEX(GP_EG_T,MATCH($B13,GP_EG_Sectors,0),8),IF(G13>=INDEX(GP_EG_T,MATCH($B13,GP_EG_Sectors,0),9),INDEX(GP_EG_T,MATCH($B13,GP_EG_Sectors,0),10),IF(G13>=INDEX(GP_EG_T,MATCH($B13,GP_EG_Sectors,0),11),INDEX(GP_EG_T,MATCH($B13,GP_EG_Sectors,0),12),0)))))))) -> 100 | Z13: =IF(OR($B13="",H13=""),"",IF(ISERROR(MATCH($B13,GP_OL_Sectors,0)),0,IF(H13>=INDEX(GP_OL_T,MATCH($B13,GP_OL_Sectors,0),1),INDEX(GP_OL_T,MATCH($B13,GP_OL_Sectors,0),2),IF(H13>=INDEX(GP_OL_T,MATCH($B13,GP_OL_Sectors,0),3),INDEX(GP_OL_T,MATCH($B13,GP_OL_Sectors,0),4),IF(H13>=INDEX(GP_OL_T,MATCH($B13,GP_OL_Sectors,0),5),INDEX(GP_OL_T,MATCH($B13,GP_OL_Sectors,0),6),IF(H13>=INDEX(GP_OL_T,MATCH($B13,GP_OL_Sectors,0),7),INDEX(GP_OL_T,MATCH($B13,GP_OL_Sectors,0),8),IF(H13>=INDEX(GP_OL_T,MATCH($B13,GP_OL_Sectors,0),9),INDEX(GP_OL_T,MATCH($B13,GP_OL_Sectors,0),10),IF(H13>=INDEX(GP_OL_T,MATCH($B13,GP_OL_Sectors,0),11),INDEX(GP_OL_T,MATCH($B13,GP_OL_Sectors,0),12),0)))))))) -> 82 | AA13: =IF(OR($B13="",I13=""),"",IF(ISERROR(MATCH($B13,GP_ND_Sectors,0)),0,IF(I13<=INDEX(GP_ND_T,MATCH($B13,GP_ND_Sectors,0),1),INDEX(GP_ND_T,MATCH($B13,GP_ND_Sectors,0),2),IF(I13<=INDEX(GP_ND_T,MATCH($B13,GP_ND_Sectors,0),3),INDEX(GP_ND_T,MATCH($B13,GP_ND_Sectors,0),4),IF(I13<=INDEX(GP_ND_T,MATCH($B13,GP_ND_Sectors,0),5),INDEX(GP_ND_T,MATCH($B13,GP_ND_Sectors,0),6),IF(I13<=INDEX(GP_ND_T,MATCH($B13,GP_ND_Sectors,0),7),INDEX(GP_ND_T,MATCH($B13,GP_ND_Sectors,0),8),IF(I13<=INDEX(GP_ND_T,MATCH($B13,GP_ND_Sectors,0),9),INDEX(GP_ND_T,MATCH($B13,GP_ND_Sectors,0),10),IF(I13<=INDEX(GP_ND_T,MATCH($B13,GP_ND_Sectors,0),11),INDEX(GP_ND_T,MATCH($B13,GP_ND_Sectors,0),12),0)))))))) -> 68 | AB13: =IF(OR($B13="",J13=""),"",IF(ISERROR(MATCH($B13,GP_CR_Sectors,0)),0,IF(J13>=INDEX(GP_CR_T,MATCH($B13,GP_CR_Sectors,0),1),INDEX(GP_CR_T,MATCH($B13,GP_CR_Sectors,0),2),IF(J13>=INDEX(GP_CR_T,MATCH($B13,GP_CR_Sectors,0),3),INDEX(GP_CR_T,MATCH($B13,GP_CR_Sectors,0),4),IF(J13>=INDEX(GP_CR_T,MATCH($B13,GP_CR_Sectors,0),5),INDEX(GP_CR_T,MATCH($B13,GP_CR_Sectors,0),6),IF(J13>=INDEX(GP_CR_T,MATCH($B13,GP_CR_Sectors,0),7),INDEX(GP_CR_T,MATCH($B13,GP_CR_Sectors,0),8),IF(J13>=INDEX(GP_CR_T,MATCH($B13,GP_CR_Sectors,0),9),INDEX(GP_CR_T,MATCH($B13,GP_CR_Sectors,0),10),IF(J13>=INDEX(GP_CR_T,MATCH($B13,GP_CR_Sectors,0),11),INDEX(GP_CR_T,MATCH($B13,GP_CR_Sectors,0),12),0)))))))) -> 68 | AC13: =IF(OR($B13="",K13=""),"",IF(ISERROR(MATCH($B13,GP_IC_Sectors,0)),0,IF(K13>=INDEX(GP_IC_T,MATCH($B13,GP_IC_Sectors,0),1),INDEX(GP_IC_T,MATCH($B13,GP_IC_Sectors,0),2),IF(K13>=INDEX(GP_IC_T,MATCH($B13,GP_IC_Sectors,0),3),INDEX(GP_IC_T,MATCH($B13,GP_IC_Sectors,0),4),IF(K13>=INDEX(GP_IC_T,MATCH($B13,GP_IC_Sectors,0),5),INDEX(GP_IC_T,MATCH($B13,GP_IC_Sectors,0),6),IF(K13>=INDEX(GP_IC_T,MATCH($B13,GP_IC_Sectors,0),7),INDEX(GP_IC_T,MATCH($B13,GP_IC_Sectors,0),8),IF(K13>=INDEX(GP_IC_T,MATCH($B13,GP_IC_Sectors,0),9),INDEX(GP_IC_T,MATCH($B13,GP_IC_Sectors,0),10),IF(K13>=INDEX(GP_IC_T,MATCH($B13,GP_IC_Sectors,0),11),INDEX(GP_IC_T,MATCH($B13,GP_IC_Sectors,0),12),0)))))))) -> 100 | AD13: =IF(OR($B13="",L13=""),"",IF(ISERROR(MATCH($B13,GP_FM_Sectors,0)),0,IF(L13>=INDEX(GP_FM_T,MATCH($B13,GP_FM_Sectors,0),1),INDEX(GP_FM_T,MATCH($B13,GP_FM_Sectors,0),2),IF(L13>=INDEX(GP_FM_T,MATCH($B13,GP_FM_Sectors,0),3),INDEX(GP_FM_T,MATCH($B13,GP_FM_Sectors,0),4),IF(L13>=INDEX(GP_FM_T,MATCH($B13,GP_FM_Sectors,0),5),INDEX(GP_FM_T,MATCH($B13,GP_FM_Sectors,0),6),IF(L13>=INDEX(GP_FM_T,MATCH($B13,GP_FM_Sectors,0),7),INDEX(GP_FM_T,MATCH($B13,GP_FM_Sectors,0),8),IF(L13>=INDEX(GP_FM_T,MATCH($B13,GP_FM_Sectors,0),9),INDEX(GP_FM_T,MATCH($B13,GP_FM_Sectors,0),10),IF(L13>=INDEX(GP_FM_T,MATCH($B13,GP_FM_Sectors,0),11),INDEX(GP_FM_T,MATCH($B13,GP_FM_Sectors,0),12),0)))))))) -> 100 | AE13: =IF(OR($B13="",M13=""),"",IF(ISERROR(MATCH($B13,GP_FN_Sectors,0)),0,IF(M13>=INDEX(GP_FN_T,MATCH($B13,GP_FN_Sectors,0),1),INDEX(GP_FN_T,MATCH($B13,GP_FN_Sectors,0),2),IF(M13>=INDEX(GP_FN_T,MATCH($B13,GP_FN_Sectors,0),3),INDEX(GP_FN_T,MATCH($B13,GP_FN_Sectors,0),4),IF(M13>=INDEX(GP_FN_T,MATCH($B13,GP_FN_Sectors,0),5),INDEX(GP_FN_T,MATCH($B13,GP_FN_Sectors,0),6),IF(M13>=INDEX(GP_FN_T,MATCH($B13,GP_FN_Sectors,0),7),INDEX(GP_FN_T,MATCH($B13,GP_FN_Sectors,0),8),IF(M13>=INDEX(GP_FN_T,MATCH($B13,GP_FN_Sectors,0),9),INDEX(GP_FN_T,MATCH($B13,GP_FN_Sectors,0),10),IF(M13>=INDEX(GP_FN_T,MATCH($B13,GP_FN_Sectors,0),11),INDEX(GP_FN_T,MATCH($B13,GP_FN_Sectors,0),12),0)))))))) -> 82 | AF13: =IF(OR($B13="",N13=""),"",IF(ISERROR(MATCH($B13,GP_CX_Sectors,0)),0,IF(N13<=INDEX(GP_CX_T,MATCH($B13,GP_CX_Sectors,0),1),INDEX(GP_CX_T,MATCH($B13,GP_CX_Sectors,0),2),IF(N13<=INDEX(GP_CX_T,MATCH($B13,GP_CX_Sectors,0),3),INDEX(GP_CX_T,MATCH($B13,GP_CX_Sectors,0),4),IF(N13<=INDEX(GP_CX_T,MATCH($B13,GP_CX_Sectors,0),5),INDEX(GP_CX_T,MATCH($B13,GP_CX_Sectors,0),6),IF(N13<=INDEX(GP_CX_T,MATCH($B13,GP_CX_Sectors,0),7),INDEX(GP_CX_T,MATCH($B13,GP_CX_Sectors,0),8),IF(N13<=INDEX(GP_CX_T,MATCH($B13,GP_CX_Sectors,0),9),INDEX(GP_CX_T,MATCH($B13,GP_CX_Sectors,0),10),IF(N13<=INDEX(GP_CX_T,MATCH($B13,GP_CX_Sectors,0),11),INDEX(GP_CX_T,MATCH($B13,GP_CX_Sectors,0),12),0)))))))) -> 82 | AG13: =IF(OR($B13="",O13=""),"",IF(ISERROR(MATCH($B13,GP_PE_Sectors,0)),0,IF(O13<=INDEX(GP_PE_T,MATCH($B13,GP_PE_Sectors,0),1),INDEX(GP_PE_T,MATCH($B13,GP_PE_Sectors,0),2),IF(O13<=INDEX(GP_PE_T,MATCH($B13,GP_PE_Sectors,0),3),INDEX(GP_PE_T,MATCH($B13,GP_PE_Sectors,0),4),IF(O13<=INDEX(GP_PE_T,MATCH($B13,GP_PE_Sectors,0),5),INDEX(GP_PE_T,MATCH($B13,GP_PE_Sectors,0),6),IF(O13<=INDEX(GP_PE_T,MATCH($B13,GP_PE_Sectors,0),7),INDEX(GP_PE_T,MATCH($B13,GP_PE_Sectors,0),8),IF(O13<=INDEX(GP_PE_T,MATCH($B13,GP_PE_Sectors,0),9),INDEX(GP_PE_T,MATCH($B13,GP_PE_Sectors,0),10),IF(O13<=INDEX(GP_PE_T,MATCH($B13,GP_PE_Sectors,0),11),INDEX(GP_PE_T,MATCH($B13,GP_PE_Sectors,0),12),0)))))))) -> 65 | AH13: =IF(OR($B13="",P13=""),"",IF(ISERROR(MATCH($B13,GP_EV_Sectors,0)),0,IF(P13<=INDEX(GP_EV_T,MATCH($B13,GP_EV_Sectors,0),1),INDEX(GP_EV_T,MATCH($B13,GP_EV_Sectors,0),2),IF(P13<=INDEX(GP_EV_T,MATCH($B13,GP_EV_Sectors,0),3),INDEX(GP_EV_T,MATCH($B13,GP_EV_Sectors,0),4),IF(P13<=INDEX(GP_EV_T,MATCH($B13,GP_EV_Sectors,0),5),INDEX(GP_EV_T,MATCH($B13,GP_EV_Sectors,0),6),IF(P13<=INDEX(GP_EV_T,MATCH($B13,GP_EV_Sectors,0),7),INDEX(GP_EV_T,MATCH($B13,GP_EV_Sectors,0),8),IF(P13<=INDEX(GP_EV_T,MATCH($B13,GP_EV_Sectors,0),9),INDEX(GP_EV_T,MATCH($B13,GP_EV_Sectors,0),10),IF(P13<=INDEX(GP_EV_T,MATCH($B13,GP_EV_Sectors,0),11),INDEX(GP_EV_T,MATCH($B13,GP_EV_Sectors,0),12),0)))))))) -> 65 | AI13: =IF(OR($B13="",Q13=""),"",IF(ISERROR(MATCH($B13,GP_PF_Sectors,0)),0,IF(Q13<=INDEX(GP_PF_T,MATCH($B13,GP_PF_Sectors,0),1),INDEX(GP_PF_T,MATCH($B13,GP_PF_Sectors,0),2),IF(Q13<=INDEX(GP_PF_T,MATCH($B13,GP_PF_Sectors,0),3),INDEX(GP_PF_T,MATCH($B13,GP_PF_Sectors,0),4),IF(Q13<=INDEX(GP_PF_T,MATCH($B13,GP_PF_Sectors,0),5),INDEX(GP_PF_T,MATCH($B13,GP_PF_Sectors,0),6),IF(Q13<=INDEX(GP_PF_T,MATCH($B13,GP_PF_Sectors,0),7),INDEX(GP_PF_T,MATCH($B13,GP_PF_Sectors,0),8),IF(Q13<=INDEX(GP_PF_T,MATCH($B13,GP_PF_Sectors,0),9),INDEX(GP_PF_T,MATCH($B13,GP_PF_Sectors,0),10),IF(Q13<=INDEX(GP_PF_T,MATCH($B13,GP_PF_Sectors,0),11),INDEX(GP_PF_T,MATCH($B13,GP_PF_Sectors,0),12),0)))))))) -> 82 | AJ13: =IF(OR($B13="",R13=""),"",IF(ISERROR(MATCH($B13,GP_DY_Sectors,0)),0,IF(R13>=INDEX(GP_DY_T,MATCH($B13,GP_DY_Sectors,0),1),INDEX(GP_DY_T,MATCH($B13,GP_DY_Sectors,0),2),IF(R13>=INDEX(GP_DY_T,MATCH($B13,GP_DY_Sectors,0),3),INDEX(GP_DY_T,MATCH($B13,GP_DY_Sectors,0),4),IF(R13>=INDEX(GP_DY_T,MATCH($B13,GP_DY_Sectors,0),5),INDEX(GP_DY_T,MATCH($B13,GP_DY_Sectors,0),6),IF(R13>=INDEX(GP_DY_T,MATCH($B13,GP_DY_Sectors,0),7),INDEX(GP_DY_T,MATCH($B13,GP_DY_Sectors,0),8),IF(R13>=INDEX(GP_DY_T,MATCH($B13,GP_DY_Sectors,0),9),INDEX(GP_DY_T,MATCH($B13,GP_DY_Sectors,0),10),IF(R13>=INDEX(GP_DY_T,MATCH($B13,GP_DY_Sectors,0),11),INDEX(GP_DY_T,MATCH($B13,GP_DY_Sectors,0),12),0)))))))) -> 65 | AK13: =IF(OR($B13="",S13=""),"",IF(ISERROR(MATCH($B13,GP_PR_Sectors,0)),0,IF(S13>=INDEX(GP_PR_T,MATCH($B13,GP_PR_Sectors,0),1),INDEX(GP_PR_T,MATCH($B13,GP_PR_Sectors,0),2),IF(S13>=INDEX(GP_PR_T,MATCH($B13,GP_PR_Sectors,0),3),INDEX(GP_PR_T,MATCH($B13,GP_PR_Sectors,0),4),IF(S13>=INDEX(GP_PR_T,MATCH($B13,GP_PR_Sectors,0),5),INDEX(GP_PR_T,MATCH($B13,GP_PR_Sectors,0),6),IF(S13>=INDEX(GP_PR_T,MATCH($B13,GP_PR_Sectors,0),7),INDEX(GP_PR_T,MATCH($B13,GP_PR_Sectors,0),8),IF(S13>=INDEX(GP_PR_T,MATCH($B13,GP_PR_Sectors,0),9),INDEX(GP_PR_T,MATCH($B13,GP_PR_Sectors,0),10),IF(S13>=INDEX(GP_PR_T,MATCH($B13,GP_PR_Sectors,0),11),INDEX(GP_PR_T,MATCH($B13,GP_PR_Sectors,0),12),0)))))))) -> 50 | AL13: =IF(OR($B13="",T13=""),"",IF(ISERROR(MATCH($B13,GP_BY_Sectors,0)),0,IF(T13>=INDEX(GP_BY_T,MATCH($B13,GP_BY_Sectors,0),1),INDEX(GP_BY_T,MATCH($B13,GP_BY_Sectors,0),2),IF(T13>=INDEX(GP_BY_T,MATCH($B13,GP_BY_Sectors,0),3),INDEX(GP_BY_T,MATCH($B13,GP_BY_Sectors,0),4),IF(T13>=INDEX(GP_BY_T,MATCH($B13,GP_BY_Sectors,0),5),INDEX(GP_BY_T,MATCH($B13,GP_BY_Sectors,0),6),IF(T13>=INDEX(GP_BY_T,MATCH($B13,GP_BY_Sectors,0),7),INDEX(GP_BY_T,MATCH($B13,GP_BY_Sectors,0),8),IF(T13>=INDEX(GP_BY_T,MATCH($B13,GP_BY_Sectors,0),9),INDEX(GP_BY_T,MATCH($B13,GP_BY_Sectors,0),10),IF(T13>=INDEX(GP_BY_T,MATCH($B13,GP_BY_Sectors,0),11),INDEX(GP_BY_T,MATCH($B13,GP_BY_Sectors,0),12),0)))))))) -> 100 | AM13: =IF($B13="","",U13*0.35+V13*0.35+W13*0.3) -> 94.75 | AN13: =IF($B13="","",X13*0.4+Y13*0.35+Z13*0.25) -> 89.5 | AO13: =IF($B13="","",AA13*0.35+AB13*0.3+AC13*0.35) -> 79.2 | AP13: =IF($B13="","",AD13*0.4+AE13*0.35+AF13*0.25) -> 89.2 | AQ13: =IF($B13="","",AG13*0.35+AH13*0.35+AI13*0.3) -> 70.1 | AR13: =IF($B13="","",AJ13*0.45+AK13*0.2+AL13*0.35) -> 74.25 | AS13: =IF($B13="","",MIN(100,MAX(0,ROUND(AM13*INDEX(GP_W_P1,MATCH($B13,GP_Weights_Sectors,0))+AN13*INDEX(GP_W_P2,MATCH($B13,GP_Weights_Sectors,0))+AO13*INDEX(GP_W_P3,MATCH($B13,GP_Weights_Sectors,0))+AP13*INDEX(GP_W_P4,MATCH($B13,GP_Weights_Sectors,0))+AQ13*INDEX(GP_W_P5,MATCH($B13,GP_Weights_Sectors,0))+AR13*INDEX(GP_W_P6,MATCH($B13,GP_Weights_Sectors,0)),0)))) -> 83 | AT13: 2 | AU13: 2 | AV13: 2 | AW13: =MAX(-10,MIN(10,AT13+AU13+AV13)) -> 6 | AX13: #VALUE! | AY13: {=_FV(AX13,"PRECIO")} -> 0.01 | AZ13: 620 | BA13: =IFERROR(INDEX('DCF Simplified'!$Y$4:$Y$38,MATCH(A13,'DCF Simplified'!$A$4:$A$38,0)),"") -> 396.82578 | BB13: =IF(OR(AY13="",AZ13=""),"",(AZ13-AY13)/AY13) -> 61999 | BD13: 0.06 | BE13: 54 | BF13: 0.1 | BG13: =IF(BD13>0.1,100,IF(BD13>0.05,80,IF(BD13>0,65,IF(BD13>-0.05,45,IF(BD13>-0.1,25,10))))) -> 80 | BH13: =IF(AND(BE13>=40,BE13<=60),70,IF(AND(BE13>60,BE13<=70),85,IF(BE13>70,50,IF(AND(BE13>=30,BE13<40),55,40)))) -> 70 | BI13: =IF(BF13>0.2,100,IF(BF13>0.1,80,IF(BF13>0,65,IF(BF13>-0.1,45,IF(BF13>-0.2,25,10))))) -> 65 | BJ13: =ROUND(BG13*0.4+BH13*0.25+BI13*0.35,1) -> 72.3 | BK13: =IF(OR(AS13="",AQ13="",BJ13=""),"",ROUND(AS13*0.4+MAX(15,MIN(90,AQ13))*0.2+BJ13*0.25+MIN(100,MAX(0,AW13*10))*0.15,0)) -> 74 | BL13: =IF(BK13="","",IF(BK13>=85,"🟢 STRONG",IF(BK13>=70,"🟡 FAVORABLE",IF(BK13>=55,"⚪ NEUTRAL",IF(BK13>=40,"🟠 WEAK","🔴 AVOID"))))) -> 🟡 FAVORABLE | BM13: =IF(BK13="","",IF(AND(BK13>=75,BJ13>=70,AW13>=6),"🚀 STRONG BUY",IF(AND(BK13>=65,BJ13>=55),"✅ BUY",IF(BK13>=55,"⚠️ HOLD",IF(OR(BK13<45,AND(BJ13<35,AW13<3)),"🔴 SELL","🟠 UNDERWEIGHT"))))) -> ✅ BUY
A14: Linde plc | B14: Materials | C14: 0.185 | D14: 0.096 | E14: 0.204 | F14: 0.02 | G14: 0.08 | H14: 1.2 | I14: 1.8 | J14: 0.85 | K14: 18 | L14: 0.15 | M14: 0.7 | N14: 0.14 | O14: 28 | P14: 19 | Q14: 32 | R14: 0.013 | S14: 0.4 | T14: 0.03 | U14: =IF(OR($B14="",C14=""),"",IF(ISERROR(MATCH($B14,GP_ROE_Sectors,0)),0,IF(C14>=INDEX(GP_ROE_T,MATCH($B14,GP_ROE_Sectors,0),1),INDEX(GP_ROE_T,MATCH($B14,GP_ROE_Sectors,0),2),IF(C14>=INDEX(GP_ROE_T,MATCH($B14,GP_ROE_Sectors,0),3),INDEX(GP_ROE_T,MATCH($B14,GP_ROE_Sectors,0),4),IF(C14>=INDEX(GP_ROE_T,MATCH($B14,GP_ROE_Sectors,0),5),INDEX(GP_ROE_T,MATCH($B14,GP_ROE_Sectors,0),6),IF(C14>=INDEX(GP_ROE_T,MATCH($B14,GP_ROE_Sectors,0),7),INDEX(GP_ROE_T,MATCH($B14,GP_ROE_Sectors,0),8),IF(C14>=INDEX(GP_ROE_T,MATCH($B14,GP_ROE_Sectors,0),9),INDEX(GP_ROE_T,MATCH($B14,GP_ROE_Sectors,0),10),IF(C14>=INDEX(GP_ROE_T,MATCH($B14,GP_ROE_Sectors,0),11),INDEX(GP_ROE_T,MATCH($B14,GP_ROE_Sectors,0),12),0)))))))) -> 100 | V14: =IF(OR($B14="",D14=""),"",IF(ISERROR(MATCH($B14,GP_ROIC_Sectors,0)),0,IF(D14>=INDEX(GP_ROIC_T,MATCH($B14,GP_ROIC_Sectors,0),1),INDEX(GP_ROIC_T,MATCH($B14,GP_ROIC_Sectors,0),2),IF(D14>=INDEX(GP_ROIC_T,MATCH($B14,GP_ROIC_Sectors,0),3),INDEX(GP_ROIC_T,MATCH($B14,GP_ROIC_Sectors,0),4),IF(D14>=INDEX(GP_ROIC_T,MATCH($B14,GP_ROIC_Sectors,0),5),INDEX(GP_ROIC_T,MATCH($B14,GP_ROIC_Sectors,0),6),IF(D14>=INDEX(GP_ROIC_T,MATCH($B14,GP_ROIC_Sectors,0),7),INDEX(GP_ROIC_T,MATCH($B14,GP_ROIC_Sectors,0),8),IF(D14>=INDEX(GP_ROIC_T,MATCH($B14,GP_ROIC_Sectors,0),9),INDEX(GP_ROIC_T,MATCH($B14,GP_ROIC_Sectors,0),10),IF(D14>=INDEX(GP_ROIC_T,MATCH($B14,GP_ROIC_Sectors,0),11),INDEX(GP_ROIC_T,MATCH($B14,GP_ROIC_Sectors,0),12),0)))))))) -> 65 | W14: =IF(OR($B14="",E14=""),"",IF(ISERROR(MATCH($B14,GP_NM_Sectors,0)),0,IF(E14>=INDEX(GP_NM_T,MATCH($B14,GP_NM_Sectors,0),1),INDEX(GP_NM_T,MATCH($B14,GP_NM_Sectors,0),2),IF(E14>=INDEX(GP_NM_T,MATCH($B14,GP_NM_Sectors,0),3),INDEX(GP_NM_T,MATCH($B14,GP_NM_Sectors,0),4),IF(E14>=INDEX(GP_NM_T,MATCH($B14,GP_NM_Sectors,0),5),INDEX(GP_NM_T,MATCH($B14,GP_NM_Sectors,0),6),IF(E14>=INDEX(GP_NM_T,MATCH($B14,GP_NM_Sectors,0),7),INDEX(GP_NM_T,MATCH($B14,GP_NM_Sectors,0),8),IF(E14>=INDEX(GP_NM_T,MATCH($B14,GP_NM_Sectors,0),9),INDEX(GP_NM_T,MATCH($B14,GP_NM_Sectors,0),10),IF(E14>=INDEX(GP_NM_T,MATCH($B14,GP_NM_Sectors,0),11),INDEX(GP_NM_T,MATCH($B14,GP_NM_Sectors,0),12),0)))))))) -> 100 | X14: =IF(OR($B14="",F14=""),"",IF(ISERROR(MATCH($B14,GP_RG_Sectors,0)),0,IF(F14>=INDEX(GP_RG_T,MATCH($B14,GP_RG_Sectors,0),1),INDEX(GP_RG_T,MATCH($B14,GP_RG_Sectors,0),2),IF(F14>=INDEX(GP_RG_T,MATCH($B14,GP_RG_Sectors,0),3),INDEX(GP_RG_T,MATCH($B14,GP_RG_Sectors,0),4),IF(F14>=INDEX(GP_RG_T,MATCH($B14,GP_RG_Sectors,0),5),INDEX(GP_RG_T,MATCH($B14,GP_RG_Sectors,0),6),IF(F14>=INDEX(GP_RG_T,MATCH($B14,GP_RG_Sectors,0),7),INDEX(GP_RG_T,MATCH($B14,GP_RG_Sectors,0),8),IF(F14>=INDEX(GP_RG_T,MATCH($B14,GP_RG_Sectors,0),9),INDEX(GP_RG_T,MATCH($B14,GP_RG_Sectors,0),10),IF(F14>=INDEX(GP_RG_T,MATCH($B14,GP_RG_Sectors,0),11),INDEX(GP_RG_T,MATCH($B14,GP_RG_Sectors,0),12),0)))))))) -> 45 | Y14: =IF(OR($B14="",G14=""),"",IF(ISERROR(MATCH($B14,GP_EG_Sectors,0)),0,IF(G14>=INDEX(GP_EG_T,MATCH($B14,GP_EG_Sectors,0),1),INDEX(GP_EG_T,MATCH($B14,GP_EG_Sectors,0),2),IF(G14>=INDEX(GP_EG_T,MATCH($B14,GP_EG_Sectors,0),3),INDEX(GP_EG_T,MATCH($B14,GP_EG_Sectors,0),4),IF(G14>=INDEX(GP_EG_T,MATCH($B14,GP_EG_Sectors,0),5),INDEX(GP_EG_T,MATCH($B14,GP_EG_Sectors,0),6),IF(G14>=INDEX(GP_EG_T,MATCH($B14,GP_EG_Sectors,0),7),INDEX(GP_EG_T,MATCH($B14,GP_EG_Sectors,0),8),IF(G14>=INDEX(GP_EG_T,MATCH($B14,GP_EG_Sectors,0),9),INDEX(GP_EG_T,MATCH($B14,GP_EG_Sectors,0),10),IF(G14>=INDEX(GP_EG_T,MATCH($B14,GP_EG_Sectors,0),11),INDEX(GP_EG_T,MATCH($B14,GP_EG_Sectors,0),12),0)))))))) -> 62 | Z14: =IF(OR($B14="",H14=""),"",IF(ISERROR(MATCH($B14,GP_OL_Sectors,0)),0,IF(H14>=INDEX(GP_OL_T,MATCH($B14,GP_OL_Sectors,0),1),INDEX(GP_OL_T,MATCH($B14,GP_OL_Sectors,0),2),IF(H14>=INDEX(GP_OL_T,MATCH($B14,GP_OL_Sectors,0),3),INDEX(GP_OL_T,MATCH($B14,GP_OL_Sectors,0),4),IF(H14>=INDEX(GP_OL_T,MATCH($B14,GP_OL_Sectors,0),5),INDEX(GP_OL_T,MATCH($B14,GP_OL_Sectors,0),6),IF(H14>=INDEX(GP_OL_T,MATCH($B14,GP_OL_Sectors,0),7),INDEX(GP_OL_T,MATCH($B14,GP_OL_Sectors,0),8),IF(H14>=INDEX(GP_OL_T,MATCH($B14,GP_OL_Sectors,0),9),INDEX(GP_OL_T,MATCH($B14,GP_OL_Sectors,0),10),IF(H14>=INDEX(GP_OL_T,MATCH($B14,GP_OL_Sectors,0),11),INDEX(GP_OL_T,MATCH($B14,GP_OL_Sectors,0),12),0)))))))) -> 65 | AA14: =IF(OR($B14="",I14=""),"",IF(ISERROR(MATCH($B14,GP_ND_Sectors,0)),0,IF(I14<=INDEX(GP_ND_T,MATCH($B14,GP_ND_Sectors,0),1),INDEX(GP_ND_T,MATCH($B14,GP_ND_Sectors,0),2),IF(I14<=INDEX(GP_ND_T,MATCH($B14,GP_ND_Sectors,0),3),INDEX(GP_ND_T,MATCH($B14,GP_ND_Sectors,0),4),IF(I14<=INDEX(GP_ND_T,MATCH($B14,GP_ND_Sectors,0),5),INDEX(GP_ND_T,MATCH($B14,GP_ND_Sectors,0),6),IF(I14<=INDEX(GP_ND_T,MATCH($B14,GP_ND_Sectors,0),7),INDEX(GP_ND_T,MATCH($B14,GP_ND_Sectors,0),8),IF(I14<=INDEX(GP_ND_T,MATCH($B14,GP_ND_Sectors,0),9),INDEX(GP_ND_T,MATCH($B14,GP_ND_Sectors,0),10),IF(I14<=INDEX(GP_ND_T,MATCH($B14,GP_ND_Sectors,0),11),INDEX(GP_ND_T,MATCH($B14,GP_ND_Sectors,0),12),0)))))))) -> 65 | AB14: =IF(OR($B14="",J14=""),"",IF(ISERROR(MATCH($B14,GP_CR_Sectors,0)),0,IF(J14>=INDEX(GP_CR_T,MATCH($B14,GP_CR_Sectors,0),1),INDEX(GP_CR_T,MATCH($B14,GP_CR_Sectors,0),2),IF(J14>=INDEX(GP_CR_T,MATCH($B14,GP_CR_Sectors,0),3),INDEX(GP_CR_T,MATCH($B14,GP_CR_Sectors,0),4),IF(J14>=INDEX(GP_CR_T,MATCH($B14,GP_CR_Sectors,0),5),INDEX(GP_CR_T,MATCH($B14,GP_CR_Sectors,0),6),IF(J14>=INDEX(GP_CR_T,MATCH($B14,GP_CR_Sectors,0),7),INDEX(GP_CR_T,MATCH($B14,GP_CR_Sectors,0),8),IF(J14>=INDEX(GP_CR_T,MATCH($B14,GP_CR_Sectors,0),9),INDEX(GP_CR_T,MATCH($B14,GP_CR_Sectors,0),10),IF(J14>=INDEX(GP_CR_T,MATCH($B14,GP_CR_Sectors,0),11),INDEX(GP_CR_T,MATCH($B14,GP_CR_Sectors,0),12),0)))))))) -> 28 | AC14: =IF(OR($B14="",K14=""),"",IF(ISERROR(MATCH($B14,GP_IC_Sectors,0)),0,IF(K14>=INDEX(GP_IC_T,MATCH($B14,GP_IC_Sectors,0),1),INDEX(GP_IC_T,MATCH($B14,GP_IC_Sectors,0),2),IF(K14>=INDEX(GP_IC_T,MATCH($B14,GP_IC_Sectors,0),3),INDEX(GP_IC_T,MATCH($B14,GP_IC_Sectors,0),4),IF(K14>=INDEX(GP_IC_T,MATCH($B14,GP_IC_Sectors,0),5),INDEX(GP_IC_T,MATCH($B14,GP_IC_Sectors,0),6),IF(K14>=INDEX(GP_IC_T,MATCH($B14,GP_IC_Sectors,0),7),INDEX(GP_IC_T,MATCH($B14,GP_IC_Sectors,0),8),IF(K14>=INDEX(GP_IC_T,MATCH($B14,GP_IC_Sectors,0),9),INDEX(GP_IC_T,MATCH($B14,GP_IC_Sectors,0),10),IF(K14>=INDEX(GP_IC_T,MATCH($B14,GP_IC_Sectors,0),11),INDEX(GP_IC_T,MATCH($B14,GP_IC_Sectors,0),12),0)))))))) -> 100 | AD14: =IF(OR($B14="",L14=""),"",IF(ISERROR(MATCH($B14,GP_FM_Sectors,0)),0,IF(L14>=INDEX(GP_FM_T,MATCH($B14,GP_FM_Sectors,0),1),INDEX(GP_FM_T,MATCH($B14,GP_FM_Sectors,0),2),IF(L14>=INDEX(GP_FM_T,MATCH($B14,GP_FM_Sectors,0),3),INDEX(GP_FM_T,MATCH($B14,GP_FM_Sectors,0),4),IF(L14>=INDEX(GP_FM_T,MATCH($B14,GP_FM_Sectors,0),5),INDEX(GP_FM_T,MATCH($B14,GP_FM_Sectors,0),6),IF(L14>=INDEX(GP_FM_T,MATCH($B14,GP_FM_Sectors,0),7),INDEX(GP_FM_T,MATCH($B14,GP_FM_Sectors,0),8),IF(L14>=INDEX(GP_FM_T,MATCH($B14,GP_FM_Sectors,0),9),INDEX(GP_FM_T,MATCH($B14,GP_FM_Sectors,0),10),IF(L14>=INDEX(GP_FM_T,MATCH($B14,GP_FM_Sectors,0),11),INDEX(GP_FM_T,MATCH($B14,GP_FM_Sectors,0),12),0)))))))) -> 100 | AE14: =IF(OR($B14="",M14=""),"",IF(ISERROR(MATCH($B14,GP_FN_Sectors,0)),0,IF(M14>=INDEX(GP_FN_T,MATCH($B14,GP_FN_Sectors,0),1),INDEX(GP_FN_T,MATCH($B14,GP_FN_Sectors,0),2),IF(M14>=INDEX(GP_FN_T,MATCH($B14,GP_FN_Sectors,0),3),INDEX(GP_FN_T,MATCH($B14,GP_FN_Sectors,0),4),IF(M14>=INDEX(GP_FN_T,MATCH($B14,GP_FN_Sectors,0),5),INDEX(GP_FN_T,MATCH($B14,GP_FN_Sectors,0),6),IF(M14>=INDEX(GP_FN_T,MATCH($B14,GP_FN_Sectors,0),7),INDEX(GP_FN_T,MATCH($B14,GP_FN_Sectors,0),8),IF(M14>=INDEX(GP_FN_T,MATCH($B14,GP_FN_Sectors,0),9),INDEX(GP_FN_T,MATCH($B14,GP_FN_Sectors,0),10),IF(M14>=INDEX(GP_FN_T,MATCH($B14,GP_FN_Sectors,0),11),INDEX(GP_FN_T,MATCH($B14,GP_FN_Sectors,0),12),0)))))))) -> 62 | AF14: =IF(OR($B14="",N14=""),"",IF(ISERROR(MATCH($B14,GP_CX_Sectors,0)),0,IF(N14<=INDEX(GP_CX_T,MATCH($B14,GP_CX_Sectors,0),1),INDEX(GP_CX_T,MATCH($B14,GP_CX_Sectors,0),2),IF(N14<=INDEX(GP_CX_T,MATCH($B14,GP_CX_Sectors,0),3),INDEX(GP_CX_T,MATCH($B14,GP_CX_Sectors,0),4),IF(N14<=INDEX(GP_CX_T,MATCH($B14,GP_CX_Sectors,0),5),INDEX(GP_CX_T,MATCH($B14,GP_CX_Sectors,0),6),IF(N14<=INDEX(GP_CX_T,MATCH($B14,GP_CX_Sectors,0),7),INDEX(GP_CX_T,MATCH($B14,GP_CX_Sectors,0),8),IF(N14<=INDEX(GP_CX_T,MATCH($B14,GP_CX_Sectors,0),9),INDEX(GP_CX_T,MATCH($B14,GP_CX_Sectors,0),10),IF(N14<=INDEX(GP_CX_T,MATCH($B14,GP_CX_Sectors,0),11),INDEX(GP_CX_T,MATCH($B14,GP_CX_Sectors,0),12),0)))))))) -> 45 | AG14: =IF(OR($B14="",O14=""),"",IF(ISERROR(MATCH($B14,GP_PE_Sectors,0)),0,IF(O14<=INDEX(GP_PE_T,MATCH($B14,GP_PE_Sectors,0),1),INDEX(GP_PE_T,MATCH($B14,GP_PE_Sectors,0),2),IF(O14<=INDEX(GP_PE_T,MATCH($B14,GP_PE_Sectors,0),3),INDEX(GP_PE_T,MATCH($B14,GP_PE_Sectors,0),4),IF(O14<=INDEX(GP_PE_T,MATCH($B14,GP_PE_Sectors,0),5),INDEX(GP_PE_T,MATCH($B14,GP_PE_Sectors,0),6),IF(O14<=INDEX(GP_PE_T,MATCH($B14,GP_PE_Sectors,0),7),INDEX(GP_PE_T,MATCH($B14,GP_PE_Sectors,0),8),IF(O14<=INDEX(GP_PE_T,MATCH($B14,GP_PE_Sectors,0),9),INDEX(GP_PE_T,MATCH($B14,GP_PE_Sectors,0),10),IF(O14<=INDEX(GP_PE_T,MATCH($B14,GP_PE_Sectors,0),11),INDEX(GP_PE_T,MATCH($B14,GP_PE_Sectors,0),12),0)))))))) -> 28 | AH14: =IF(OR($B14="",P14=""),"",IF(ISERROR(MATCH($B14,GP_EV_Sectors,0)),0,IF(P14<=INDEX(GP_EV_T,MATCH($B14,GP_EV_Sectors,0),1),INDEX(GP_EV_T,MATCH($B14,GP_EV_Sectors,0),2),IF(P14<=INDEX(GP_EV_T,MATCH($B14,GP_EV_Sectors,0),3),INDEX(GP_EV_T,MATCH($B14,GP_EV_Sectors,0),4),IF(P14<=INDEX(GP_EV_T,MATCH($B14,GP_EV_Sectors,0),5),INDEX(GP_EV_T,MATCH($B14,GP_EV_Sectors,0),6),IF(P14<=INDEX(GP_EV_T,MATCH($B14,GP_EV_Sectors,0),7),INDEX(GP_EV_T,MATCH($B14,GP_EV_Sectors,0),8),IF(P14<=INDEX(GP_EV_T,MATCH($B14,GP_EV_Sectors,0),9),INDEX(GP_EV_T,MATCH($B14,GP_EV_Sectors,0),10),IF(P14<=INDEX(GP_EV_T,MATCH($B14,GP_EV_Sectors,0),11),INDEX(GP_EV_T,MATCH($B14,GP_EV_Sectors,0),12),0)))))))) -> 8 | AI14: =IF(OR($B14="",Q14=""),"",IF(ISERROR(MATCH($B14,GP_PF_Sectors,0)),0,IF(Q14<=INDEX(GP_PF_T,MATCH($B14,GP_PF_Sectors,0),1),INDEX(GP_PF_T,MATCH($B14,GP_PF_Sectors,0),2),IF(Q14<=INDEX(GP_PF_T,MATCH($B14,GP_PF_Sectors,0),3),INDEX(GP_PF_T,MATCH($B14,GP_PF_Sectors,0),4),IF(Q14<=INDEX(GP_PF_T,MATCH($B14,GP_PF_Sectors,0),5),INDEX(GP_PF_T,MATCH($B14,GP_PF_Sectors,0),6),IF(Q14<=INDEX(GP_PF_T,MATCH($B14,GP_PF_Sectors,0),7),INDEX(GP_PF_T,MATCH($B14,GP_PF_Sectors,0),8),IF(Q14<=INDEX(GP_PF_T,MATCH($B14,GP_PF_Sectors,0),9),INDEX(GP_PF_T,MATCH($B14,GP_PF_Sectors,0),10),IF(Q14<=INDEX(GP_PF_T,MATCH($B14,GP_PF_Sectors,0),11),INDEX(GP_PF_T,MATCH($B14,GP_PF_Sectors,0),12),0)))))))) -> 25 | AJ14: =IF(OR($B14="",R14=""),"",IF(ISERROR(MATCH($B14,GP_DY_Sectors,0)),0,IF(R14>=INDEX(GP_DY_T,MATCH($B14,GP_DY_Sectors,0),1),INDEX(GP_DY_T,MATCH($B14,GP_DY_Sectors,0),2),IF(R14>=INDEX(GP_DY_T,MATCH($B14,GP_DY_Sectors,0),3),INDEX(GP_DY_T,MATCH($B14,GP_DY_Sectors,0),4),IF(R14>=INDEX(GP_DY_T,MATCH($B14,GP_DY_Sectors,0),5),INDEX(GP_DY_T,MATCH($B14,GP_DY_Sectors,0),6),IF(R14>=INDEX(GP_DY_T,MATCH($B14,GP_DY_Sectors,0),7),INDEX(GP_DY_T,MATCH($B14,GP_DY_Sectors,0),8),IF(R14>=INDEX(GP_DY_T,MATCH($B14,GP_DY_Sectors,0),9),INDEX(GP_DY_T,MATCH($B14,GP_DY_Sectors,0),10),IF(R14>=INDEX(GP_DY_T,MATCH($B14,GP_DY_Sectors,0),11),INDEX(GP_DY_T,MATCH($B14,GP_DY_Sectors,0),12),0)))))))) -> 48 | AK14: =IF(OR($B14="",S14=""),"",IF(ISERROR(MATCH($B14,GP_PR_Sectors,0)),0,IF(S14>=INDEX(GP_PR_T,MATCH($B14,GP_PR_Sectors,0),1),INDEX(GP_PR_T,MATCH($B14,GP_PR_Sectors,0),2),IF(S14>=INDEX(GP_PR_T,MATCH($B14,GP_PR_Sectors,0),3),INDEX(GP_PR_T,MATCH($B14,GP_PR_Sectors,0),4),IF(S14>=INDEX(GP_PR_T,MATCH($B14,GP_PR_Sectors,0),5),INDEX(GP_PR_T,MATCH($B14,GP_PR_Sectors,0),6),IF(S14>=INDEX(GP_PR_T,MATCH($B14,GP_PR_Sectors,0),7),INDEX(GP_PR_T,MATCH($B14,GP_PR_Sectors,0),8),IF(S14>=INDEX(GP_PR_T,MATCH($B14,GP_PR_Sectors,0),9),INDEX(GP_PR_T,MATCH($B14,GP_PR_Sectors,0),10),IF(S14>=INDEX(GP_PR_T,MATCH($B14,GP_PR_Sectors,0),11),INDEX(GP_PR_T,MATCH($B14,GP_PR_Sectors,0),12),0)))))))) -> 100 | AL14: =IF(OR($B14="",T14=""),"",IF(ISERROR(MATCH($B14,GP_BY_Sectors,0)),0,IF(T14>=INDEX(GP_BY_T,MATCH($B14,GP_BY_Sectors,0),1),INDEX(GP_BY_T,MATCH($B14,GP_BY_Sectors,0),2),IF(T14>=INDEX(GP_BY_T,MATCH($B14,GP_BY_Sectors,0),3),INDEX(GP_BY_T,MATCH($B14,GP_BY_Sectors,0),4),IF(T14>=INDEX(GP_BY_T,MATCH($B14,GP_BY_Sectors,0),5),INDEX(GP_BY_T,MATCH($B14,GP_BY_Sectors,0),6),IF(T14>=INDEX(GP_BY_T,MATCH($B14,GP_BY_Sectors,0),7),INDEX(GP_BY_T,MATCH($B14,GP_BY_Sectors,0),8),IF(T14>=INDEX(GP_BY_T,MATCH($B14,GP_BY_Sectors,0),9),INDEX(GP_BY_T,MATCH($B14,GP_BY_Sectors,0),10),IF(T14>=INDEX(GP_BY_T,MATCH($B14,GP_BY_Sectors,0),11),INDEX(GP_BY_T,MATCH($B14,GP_BY_Sectors,0),12),0)))))))) -> 100 | AM14: =IF($B14="","",U14*0.35+V14*0.35+W14*0.3) -> 87.75 | AN14: =IF($B14="","",X14*0.4+Y14*0.35+Z14*0.25) -> 55.95 | AO14: =IF($B14="","",AA14*0.35+AB14*0.3+AC14*0.35) -> 66.15 | AP14: =IF($B14="","",AD14*0.4+AE14*0.35+AF14*0.25) -> 72.95 | AQ14: =IF($B14="","",AG14*0.35+AH14*0.35+AI14*0.3) -> 20.1 | AR14: =IF($B14="","",AJ14*0.45+AK14*0.2+AL14*0.35) -> 76.6 | AS14: =IF($B14="","",MIN(100,MAX(0,ROUND(AM14*INDEX(GP_W_P1,MATCH($B14,GP_Weights_Sectors,0))+AN14*INDEX(GP_W_P2,MATCH($B14,GP_Weights_Sectors,0))+AO14*INDEX(GP_W_P3,MATCH($B14,GP_Weights_Sectors,0))+AP14*INDEX(GP_W_P4,MATCH($B14,GP_Weights_Sectors,0))+AQ14*INDEX(GP_W_P5,MATCH($B14,GP_Weights_Sectors,0))+AR14*INDEX(GP_W_P6,MATCH($B14,GP_Weights_Sectors,0)),0)))) -> 67 | AT14: 1 | AU14: 2 | AV14: 1 | AW14: =MAX(-10,MIN(10,AT14+AU14+AV14)) -> 4 | AX14: #VALUE! | AY14: {=_FV(AX14,"PRECIO")} -> 495.49 | AZ14: 550 | BA14: =IFERROR(INDEX('DCF Simplified'!$Y$4:$Y$38,MATCH(A14,'DCF Simplified'!$A$4:$A$38,0)),"") -> 241.33414 | BB14: =IF(OR(AY14="",AZ14=""),"",(AZ14-AY14)/AY14) -> 0.11001231 | BD14: -0.02 | BE14: 47 | BF14: -0.03 | BG14: =IF(BD14>0.1,100,IF(BD14>0.05,80,IF(BD14>0,65,IF(BD14>-0.05,45,IF(BD14>-0.1,25,10))))) -> 45 | BH14: =IF(AND(BE14>=40,BE14<=60),70,IF(AND(BE14>60,BE14<=70),85,IF(BE14>70,50,IF(AND(BE14>=30,BE14<40),55,40)))) -> 70 | BI14: =IF(BF14>0.2,100,IF(BF14>0.1,80,IF(BF14>0,65,IF(BF14>-0.1,45,IF(BF14>-0.2,25,10))))) -> 45 | BJ14: =ROUND(BG14*0.4+BH14*0.25+BI14*0.35,1) -> 51.3 | BK14: =IF(OR(AS14="",AQ14="",BJ14=""),"",ROUND(AS14*0.4+MAX(15,MIN(90,AQ14))*0.2+BJ14*0.25+MIN(100,MAX(0,AW14*10))*0.15,0)) -> 50 | BL14: =IF(BK14="","",IF(BK14>=85,"🟢 STRONG",IF(BK14>=70,"🟡 FAVORABLE",IF(BK14>=55,"⚪ NEUTRAL",IF(BK14>=40,"🟠 WEAK","🔴 AVOID"))))) -> 🟠 WEAK | BM14: =IF(BK14="","",IF(AND(BK14>=75,BJ14>=70,AW14>=6),"🚀 STRONG BUY",IF(AND(BK14>=65,BJ14>=55),"✅ BUY",IF(BK14>=55,"⚠️ HOLD",IF(OR(BK14<45,AND(BJ14<35,AW14<3)),"🔴 SELL","🟠 UNDERWEIGHT"))))) -> 🟠 UNDERWEIGHT
A15: Prologis Inc | B15: Real Estate | C15: 0.06 | D15: 0.035 | E15: 0.27 | F15: 0.1 | G15: -0.1 | H15: 0.8 | I15: 6 | J15: 0.3 | K15: 5 | L15: 0.5 | M15: 0.6 | N15: 0.04 | O15: 35 | P15: 22 | Q15: 30 | R15: 0.033 | S15: 0.75 | T15: 0 | U15: =IF(OR($B15="",C15=""),"",IF(ISERROR(MATCH($B15,GP_ROE_Sectors,0)),0,IF(C15>=INDEX(GP_ROE_T,MATCH($B15,GP_ROE_Sectors,0),1),INDEX(GP_ROE_T,MATCH($B15,GP_ROE_Sectors,0),2),IF(C15>=INDEX(GP_ROE_T,MATCH($B15,GP_ROE_Sectors,0),3),INDEX(GP_ROE_T,MATCH($B15,GP_ROE_Sectors,0),4),IF(C15>=INDEX(GP_ROE_T,MATCH($B15,GP_ROE_Sectors,0),5),INDEX(GP_ROE_T,MATCH($B15,GP_ROE_Sectors,0),6),IF(C15>=INDEX(GP_ROE_T,MATCH($B15,GP_ROE_Sectors,0),7),INDEX(GP_ROE_T,MATCH($B15,GP_ROE_Sectors,0),8),IF(C15>=INDEX(GP_ROE_T,MATCH($B15,GP_ROE_Sectors,0),9),INDEX(GP_ROE_T,MATCH($B15,GP_ROE_Sectors,0),10),IF(C15>=INDEX(GP_ROE_T,MATCH($B15,GP_ROE_Sectors,0),11),INDEX(GP_ROE_T,MATCH($B15,GP_ROE_Sectors,0),12),0)))))))) -> 50 | V15: =IF(OR($B15="",D15=""),"",IF(ISERROR(MATCH($B15,GP_ROIC_Sectors,0)),0,IF(D15>=INDEX(GP_ROIC_T,MATCH($B15,GP_ROIC_Sectors,0),1),INDEX(GP_ROIC_T,MATCH($B15,GP_ROIC_Sectors,0),2),IF(D15>=INDEX(GP_ROIC_T,MATCH($B15,GP_ROIC_Sectors,0),3),INDEX(GP_ROIC_T,MATCH($B15,GP_ROIC_Sectors,0),4),IF(D15>=INDEX(GP_ROIC_T,MATCH($B15,GP_ROIC_Sectors,0),5),INDEX(GP_ROIC_T,MATCH($B15,GP_ROIC_Sectors,0),6),IF(D15>=INDEX(GP_ROIC_T,MATCH($B15,GP_ROIC_Sectors,0),7),INDEX(GP_ROIC_T,MATCH($B15,GP_ROIC_Sectors,0),8),IF(D15>=INDEX(GP_ROIC_T,MATCH($B15,GP_ROIC_Sectors,0),9),INDEX(GP_ROIC_T,MATCH($B15,GP_ROIC_Sectors,0),10),IF(D15>=INDEX(GP_ROIC_T,MATCH($B15,GP_ROIC_Sectors,0),11),INDEX(GP_ROIC_T,MATCH($B15,GP_ROIC_Sectors,0),12),0)))))))) -> 48 | W15: =IF(OR($B15="",E15=""),"",IF(ISERROR(MATCH($B15,GP_NM_Sectors,0)),0,IF(E15>=INDEX(GP_NM_T,MATCH($B15,GP_NM_Sectors,0),1),INDEX(GP_NM_T,MATCH($B15,GP_NM_Sectors,0),2),IF(E15>=INDEX(GP_NM_T,MATCH($B15,GP_NM_Sectors,0),3),INDEX(GP_NM_T,MATCH($B15,GP_NM_Sectors,0),4),IF(E15>=INDEX(GP_NM_T,MATCH($B15,GP_NM_Sectors,0),5),INDEX(GP_NM_T,MATCH($B15,GP_NM_Sectors,0),6),IF(E15>=INDEX(GP_NM_T,MATCH($B15,GP_NM_Sectors,0),7),INDEX(GP_NM_T,MATCH($B15,GP_NM_Sectors,0),8),IF(E15>=INDEX(GP_NM_T,MATCH($B15,GP_NM_Sectors,0),9),INDEX(GP_NM_T,MATCH($B15,GP_NM_Sectors,0),10),IF(E15>=INDEX(GP_NM_T,MATCH($B15,GP_NM_Sectors,0),11),INDEX(GP_NM_T,MATCH($B15,GP_NM_Sectors,0),12),0)))))))) -> 100 | X15: =IF(OR($B15="",F15=""),"",IF(ISERROR(MATCH($B15,GP_RG_Sectors,0)),0,IF(F15>=INDEX(GP_RG_T,MATCH($B15,GP_RG_Sectors,0),1),INDEX(GP_RG_T,MATCH($B15,GP_RG_Sectors,0),2),IF(F15>=INDEX(GP_RG_T,MATCH($B15,GP_RG_Sectors,0),3),INDEX(GP_RG_T,MATCH($B15,GP_RG_Sectors,0),4),IF(F15>=INDEX(GP_RG_T,MATCH($B15,GP_RG_Sectors,0),5),INDEX(GP_RG_T,MATCH($B15,GP_RG_Sectors,0),6),IF(F15>=INDEX(GP_RG_T,MATCH($B15,GP_RG_Sectors,0),7),INDEX(GP_RG_T,MATCH($B15,GP_RG_Sectors,0),8),IF(F15>=INDEX(GP_RG_T,MATCH($B15,GP_RG_Sectors,0),9),INDEX(GP_RG_T,MATCH($B15,GP_RG_Sectors,0),10),IF(F15>=INDEX(GP_RG_T,MATCH($B15,GP_RG_Sectors,0),11),INDEX(GP_RG_T,MATCH($B15,GP_RG_Sectors,0),12),0)))))))) -> 100 | Y15: =IF(OR($B15="",G15=""),"",IF(ISERROR(MATCH($B15,GP_EG_Sectors,0)),0,IF(G15>=INDEX(GP_EG_T,MATCH($B15,GP_EG_Sectors,0),1),INDEX(GP_EG_T,MATCH($B15,GP_EG_Sectors,0),2),IF(G15>=INDEX(GP_EG_T,MATCH($B15,GP_EG_Sectors,0),3),INDEX(GP_EG_T,MATCH($B15,GP_EG_Sectors,0),4),IF(G15>=INDEX(GP_EG_T,MATCH($B15,GP_EG_Sectors,0),5),INDEX(GP_EG_T,MATCH($B15,GP_EG_Sectors,0),6),IF(G15>=INDEX(GP_EG_T,MATCH($B15,GP_EG_Sectors,0),7),INDEX(GP_EG_T,MATCH($B15,GP_EG_Sectors,0),8),IF(G15>=INDEX(GP_EG_T,MATCH($B15,GP_EG_Sectors,0),9),INDEX(GP_EG_T,MATCH($B15,GP_EG_Sectors,0),10),IF(G15>=INDEX(GP_EG_T,MATCH($B15,GP_EG_Sectors,0),11),INDEX(GP_EG_T,MATCH($B15,GP_EG_Sectors,0),12),0)))))))) -> 0 | Z15: =IF(OR($B15="",H15=""),"",IF(ISERROR(MATCH($B15,GP_OL_Sectors,0)),0,IF(H15>=INDEX(GP_OL_T,MATCH($B15,GP_OL_Sectors,0),1),INDEX(GP_OL_T,MATCH($B15,GP_OL_Sectors,0),2),IF(H15>=INDEX(GP_OL_T,MATCH($B15,GP_OL_Sectors,0),3),INDEX(GP_OL_T,MATCH($B15,GP_OL_Sectors,0),4),IF(H15>=INDEX(GP_OL_T,MATCH($B15,GP_OL_Sectors,0),5),INDEX(GP_OL_T,MATCH($B15,GP_OL_Sectors,0),6),IF(H15>=INDEX(GP_OL_T,MATCH($B15,GP_OL_Sectors,0),7),INDEX(GP_OL_T,MATCH($B15,GP_OL_Sectors,0),8),IF(H15>=INDEX(GP_OL_T,MATCH($B15,GP_OL_Sectors,0),9),INDEX(GP_OL_T,MATCH($B15,GP_OL_Sectors,0),10),IF(H15>=INDEX(GP_OL_T,MATCH($B15,GP_OL_Sectors,0),11),INDEX(GP_OL_T,MATCH($B15,GP_OL_Sectors,0),12),0)))))))) -> 48 | AA15: =IF(OR($B15="",I15=""),"",IF(ISERROR(MATCH($B15,GP_ND_Sectors,0)),0,IF(I15<=INDEX(GP_ND_T,MATCH($B15,GP_ND_Sectors,0),1),INDEX(GP_ND_T,MATCH($B15,GP_ND_Sectors,0),2),IF(I15<=INDEX(GP_ND_T,MATCH($B15,GP_ND_Sectors,0),3),INDEX(GP_ND_T,MATCH($B15,GP_ND_Sectors,0),4),IF(I15<=INDEX(GP_ND_T,MATCH($B15,GP_ND_Sectors,0),5),INDEX(GP_ND_T,MATCH($B15,GP_ND_Sectors,0),6),IF(I15<=INDEX(GP_ND_T,MATCH($B15,GP_ND_Sectors,0),7),INDEX(GP_ND_T,MATCH($B15,GP_ND_Sectors,0),8),IF(I15<=INDEX(GP_ND_T,MATCH($B15,GP_ND_Sectors,0),9),INDEX(GP_ND_T,MATCH($B15,GP_ND_Sectors,0),10),IF(I15<=INDEX(GP_ND_T,MATCH($B15,GP_ND_Sectors,0),11),INDEX(GP_ND_T,MATCH($B15,GP_ND_Sectors,0),12),0)))))))) -> 48 | AB15: =IF(OR($B15="",J15=""),"",IF(ISERROR(MATCH($B15,GP_CR_Sectors,0)),0,IF(J15>=INDEX(GP_CR_T,MATCH($B15,GP_CR_Sectors,0),1),INDEX(GP_CR_T,MATCH($B15,GP_CR_Sectors,0),2),IF(J15>=INDEX(GP_CR_T,MATCH($B15,GP_CR_Sectors,0),3),INDEX(GP_CR_T,MATCH($B15,GP_CR_Sectors,0),4),IF(J15>=INDEX(GP_CR_T,MATCH($B15,GP_CR_Sectors,0),5),INDEX(GP_CR_T,MATCH($B15,GP_CR_Sectors,0),6),IF(J15>=INDEX(GP_CR_T,MATCH($B15,GP_CR_Sectors,0),7),INDEX(GP_CR_T,MATCH($B15,GP_CR_Sectors,0),8),IF(J15>=INDEX(GP_CR_T,MATCH($B15,GP_CR_Sectors,0),9),INDEX(GP_CR_T,MATCH($B15,GP_CR_Sectors,0),10),IF(J15>=INDEX(GP_CR_T,MATCH($B15,GP_CR_Sectors,0),11),INDEX(GP_CR_T,MATCH($B15,GP_CR_Sectors,0),12),0)))))))) -> 10 | AC15: =IF(OR($B15="",K15=""),"",IF(ISERROR(MATCH($B15,GP_IC_Sectors,0)),0,IF(K15>=INDEX(GP_IC_T,MATCH($B15,GP_IC_Sectors,0),1),INDEX(GP_IC_T,MATCH($B15,GP_IC_Sectors,0),2),IF(K15>=INDEX(GP_IC_T,MATCH($B15,GP_IC_Sectors,0),3),INDEX(GP_IC_T,MATCH($B15,GP_IC_Sectors,0),4),IF(K15>=INDEX(GP_IC_T,MATCH($B15,GP_IC_Sectors,0),5),INDEX(GP_IC_T,MATCH($B15,GP_IC_Sectors,0),6),IF(K15>=INDEX(GP_IC_T,MATCH($B15,GP_IC_Sectors,0),7),INDEX(GP_IC_T,MATCH($B15,GP_IC_Sectors,0),8),IF(K15>=INDEX(GP_IC_T,MATCH($B15,GP_IC_Sectors,0),9),INDEX(GP_IC_T,MATCH($B15,GP_IC_Sectors,0),10),IF(K15>=INDEX(GP_IC_T,MATCH($B15,GP_IC_Sectors,0),11),INDEX(GP_IC_T,MATCH($B15,GP_IC_Sectors,0),12),0)))))))) -> 100 | AD15: =IF(OR($B15="",L15=""),"",IF(ISERROR(MATCH($B15,GP_FM_Sectors,0)),0,IF(L15>=INDEX(GP_FM_T,MATCH($B15,GP_FM_Sectors,0),1),INDEX(GP_FM_T,MATCH($B15,GP_FM_Sectors,0),2),IF(L15>=INDEX(GP_FM_T,MATCH($B15,GP_FM_Sectors,0),3),INDEX(GP_FM_T,MATCH($B15,GP_FM_Sectors,0),4),IF(L15>=INDEX(GP_FM_T,MATCH($B15,GP_FM_Sectors,0),5),INDEX(GP_FM_T,MATCH($B15,GP_FM_Sectors,0),6),IF(L15>=INDEX(GP_FM_T,MATCH($B15,GP_FM_Sectors,0),7),INDEX(GP_FM_T,MATCH($B15,GP_FM_Sectors,0),8),IF(L15>=INDEX(GP_FM_T,MATCH($B15,GP_FM_Sectors,0),9),INDEX(GP_FM_T,MATCH($B15,GP_FM_Sectors,0),10),IF(L15>=INDEX(GP_FM_T,MATCH($B15,GP_FM_Sectors,0),11),INDEX(GP_FM_T,MATCH($B15,GP_FM_Sectors,0),12),0)))))))) -> 100 | AE15: =IF(OR($B15="",M15=""),"",IF(ISERROR(MATCH($B15,GP_FN_Sectors,0)),0,IF(M15>=INDEX(GP_FN_T,MATCH($B15,GP_FN_Sectors,0),1),INDEX(GP_FN_T,MATCH($B15,GP_FN_Sectors,0),2),IF(M15>=INDEX(GP_FN_T,MATCH($B15,GP_FN_Sectors,0),3),INDEX(GP_FN_T,MATCH($B15,GP_FN_Sectors,0),4),IF(M15>=INDEX(GP_FN_T,MATCH($B15,GP_FN_Sectors,0),5),INDEX(GP_FN_T,MATCH($B15,GP_FN_Sectors,0),6),IF(M15>=INDEX(GP_FN_T,MATCH($B15,GP_FN_Sectors,0),7),INDEX(GP_FN_T,MATCH($B15,GP_FN_Sectors,0),8),IF(M15>=INDEX(GP_FN_T,MATCH($B15,GP_FN_Sectors,0),9),INDEX(GP_FN_T,MATCH($B15,GP_FN_Sectors,0),10),IF(M15>=INDEX(GP_FN_T,MATCH($B15,GP_FN_Sectors,0),11),INDEX(GP_FN_T,MATCH($B15,GP_FN_Sectors,0),12),0)))))))) -> 78 | AF15: =IF(OR($B15="",N15=""),"",IF(ISERROR(MATCH($B15,GP_CX_Sectors,0)),0,IF(N15<=INDEX(GP_CX_T,MATCH($B15,GP_CX_Sectors,0),1),INDEX(GP_CX_T,MATCH($B15,GP_CX_Sectors,0),2),IF(N15<=INDEX(GP_CX_T,MATCH($B15,GP_CX_Sectors,0),3),INDEX(GP_CX_T,MATCH($B15,GP_CX_Sectors,0),4),IF(N15<=INDEX(GP_CX_T,MATCH($B15,GP_CX_Sectors,0),5),INDEX(GP_CX_T,MATCH($B15,GP_CX_Sectors,0),6),IF(N15<=INDEX(GP_CX_T,MATCH($B15,GP_CX_Sectors,0),7),INDEX(GP_CX_T,MATCH($B15,GP_CX_Sectors,0),8),IF(N15<=INDEX(GP_CX_T,MATCH($B15,GP_CX_Sectors,0),9),INDEX(GP_CX_T,MATCH($B15,GP_CX_Sectors,0),10),IF(N15<=INDEX(GP_CX_T,MATCH($B15,GP_CX_Sectors,0),11),INDEX(GP_CX_T,MATCH($B15,GP_CX_Sectors,0),12),0)))))))) -> 100 | AG15: =IF(OR($B15="",O15=""),"",IF(ISERROR(MATCH($B15,GP_PE_Sectors,0)),0,IF(O15<=INDEX(GP_PE_T,MATCH($B15,GP_PE_Sectors,0),1),INDEX(GP_PE_T,MATCH($B15,GP_PE_Sectors,0),2),IF(O15<=INDEX(GP_PE_T,MATCH($B15,GP_PE_Sectors,0),3),INDEX(GP_PE_T,MATCH($B15,GP_PE_Sectors,0),4),IF(O15<=INDEX(GP_PE_T,MATCH($B15,GP_PE_Sectors,0),5),INDEX(GP_PE_T,MATCH($B15,GP_PE_Sectors,0),6),IF(O15<=INDEX(GP_PE_T,MATCH($B15,GP_PE_Sectors,0),7),INDEX(GP_PE_T,MATCH($B15,GP_PE_Sectors,0),8),IF(O15<=INDEX(GP_PE_T,MATCH($B15,GP_PE_Sectors,0),9),INDEX(GP_PE_T,MATCH($B15,GP_PE_Sectors,0),10),IF(O15<=INDEX(GP_PE_T,MATCH($B15,GP_PE_Sectors,0),11),INDEX(GP_PE_T,MATCH($B15,GP_PE_Sectors,0),12),0)))))))) -> 25 | AH15: =IF(OR($B15="",P15=""),"",IF(ISERROR(MATCH($B15,GP_EV_Sectors,0)),0,IF(P15<=INDEX(GP_EV_T,MATCH($B15,GP_EV_Sectors,0),1),INDEX(GP_EV_T,MATCH($B15,GP_EV_Sectors,0),2),IF(P15<=INDEX(GP_EV_T,MATCH($B15,GP_EV_Sectors,0),3),INDEX(GP_EV_T,MATCH($B15,GP_EV_Sectors,0),4),IF(P15<=INDEX(GP_EV_T,MATCH($B15,GP_EV_Sectors,0),5),INDEX(GP_EV_T,MATCH($B15,GP_EV_Sectors,0),6),IF(P15<=INDEX(GP_EV_T,MATCH($B15,GP_EV_Sectors,0),7),INDEX(GP_EV_T,MATCH($B15,GP_EV_Sectors,0),8),IF(P15<=INDEX(GP_EV_T,MATCH($B15,GP_EV_Sectors,0),9),INDEX(GP_EV_T,MATCH($B15,GP_EV_Sectors,0),10),IF(P15<=INDEX(GP_EV_T,MATCH($B15,GP_EV_Sectors,0),11),INDEX(GP_EV_T,MATCH($B15,GP_EV_Sectors,0),12),0)))))))) -> 45 | AI15: =IF(OR($B15="",Q15=""),"",IF(ISERROR(MATCH($B15,GP_PF_Sectors,0)),0,IF(Q15<=INDEX(GP_PF_T,MATCH($B15,GP_PF_Sectors,0),1),INDEX(GP_PF_T,MATCH($B15,GP_PF_Sectors,0),2),IF(Q15<=INDEX(GP_PF_T,MATCH($B15,GP_PF_Sectors,0),3),INDEX(GP_PF_T,MATCH($B15,GP_PF_Sectors,0),4),IF(Q15<=INDEX(GP_PF_T,MATCH($B15,GP_PF_Sectors,0),5),INDEX(GP_PF_T,MATCH($B15,GP_PF_Sectors,0),6),IF(Q15<=INDEX(GP_PF_T,MATCH($B15,GP_PF_Sectors,0),7),INDEX(GP_PF_T,MATCH($B15,GP_PF_Sectors,0),8),IF(Q15<=INDEX(GP_PF_T,MATCH($B15,GP_PF_Sectors,0),9),INDEX(GP_PF_T,MATCH($B15,GP_PF_Sectors,0),10),IF(Q15<=INDEX(GP_PF_T,MATCH($B15,GP_PF_Sectors,0),11),INDEX(GP_PF_T,MATCH($B15,GP_PF_Sectors,0),12),0)))))))) -> 42 | AJ15: =IF(OR($B15="",R15=""),"",IF(ISERROR(MATCH($B15,GP_DY_Sectors,0)),0,IF(R15>=INDEX(GP_DY_T,MATCH($B15,GP_DY_Sectors,0),1),INDEX(GP_DY_T,MATCH($B15,GP_DY_Sectors,0),2),IF(R15>=INDEX(GP_DY_T,MATCH($B15,GP_DY_Sectors,0),3),INDEX(GP_DY_T,MATCH($B15,GP_DY_Sectors,0),4),IF(R15>=INDEX(GP_DY_T,MATCH($B15,GP_DY_Sectors,0),5),INDEX(GP_DY_T,MATCH($B15,GP_DY_Sectors,0),6),IF(R15>=INDEX(GP_DY_T,MATCH($B15,GP_DY_Sectors,0),7),INDEX(GP_DY_T,MATCH($B15,GP_DY_Sectors,0),8),IF(R15>=INDEX(GP_DY_T,MATCH($B15,GP_DY_Sectors,0),9),INDEX(GP_DY_T,MATCH($B15,GP_DY_Sectors,0),10),IF(R15>=INDEX(GP_DY_T,MATCH($B15,GP_DY_Sectors,0),11),INDEX(GP_DY_T,MATCH($B15,GP_DY_Sectors,0),12),0)))))))) -> 55 | AK15: =IF(OR($B15="",S15=""),"",IF(ISERROR(MATCH($B15,GP_PR_Sectors,0)),0,IF(S15>=INDEX(GP_PR_T,MATCH($B15,GP_PR_Sectors,0),1),INDEX(GP_PR_T,MATCH($B15,GP_PR_Sectors,0),2),IF(S15>=INDEX(GP_PR_T,MATCH($B15,GP_PR_Sectors,0),3),INDEX(GP_PR_T,MATCH($B15,GP_PR_Sectors,0),4),IF(S15>=INDEX(GP_PR_T,MATCH($B15,GP_PR_Sectors,0),5),INDEX(GP_PR_T,MATCH($B15,GP_PR_Sectors,0),6),IF(S15>=INDEX(GP_PR_T,MATCH($B15,GP_PR_Sectors,0),7),INDEX(GP_PR_T,MATCH($B15,GP_PR_Sectors,0),8),IF(S15>=INDEX(GP_PR_T,MATCH($B15,GP_PR_Sectors,0),9),INDEX(GP_PR_T,MATCH($B15,GP_PR_Sectors,0),10),IF(S15>=INDEX(GP_PR_T,MATCH($B15,GP_PR_Sectors,0),11),INDEX(GP_PR_T,MATCH($B15,GP_PR_Sectors,0),12),0)))))))) -> 100 | AL15: =IF(OR($B15="",T15=""),"",IF(ISERROR(MATCH($B15,GP_BY_Sectors,0)),0,IF(T15>=INDEX(GP_BY_T,MATCH($B15,GP_BY_Sectors,0),1),INDEX(GP_BY_T,MATCH($B15,GP_BY_Sectors,0),2),IF(T15>=INDEX(GP_BY_T,MATCH($B15,GP_BY_Sectors,0),3),INDEX(GP_BY_T,MATCH($B15,GP_BY_Sectors,0),4),IF(T15>=INDEX(GP_BY_T,MATCH($B15,GP_BY_Sectors,0),5),INDEX(GP_BY_T,MATCH($B15,GP_BY_Sectors,0),6),IF(T15>=INDEX(GP_BY_T,MATCH($B15,GP_BY_Sectors,0),7),INDEX(GP_BY_T,MATCH($B15,GP_BY_Sectors,0),8),IF(T15>=INDEX(GP_BY_T,MATCH($B15,GP_BY_Sectors,0),9),INDEX(GP_BY_T,MATCH($B15,GP_BY_Sectors,0),10),IF(T15>=INDEX(GP_BY_T,MATCH($B15,GP_BY_Sectors,0),11),INDEX(GP_BY_T,MATCH($B15,GP_BY_Sectors,0),12),0)))))))) -> 5 | AM15: =IF($B15="","",U15*0.35+V15*0.35+W15*0.3) -> 64.3 | AN15: =IF($B15="","",X15*0.4+Y15*0.35+Z15*0.25) -> 52 | AO15: =IF($B15="","",AA15*0.35+AB15*0.3+AC15*0.35) -> 54.8 | AP15: =IF($B15="","",AD15*0.4+AE15*0.35+AF15*0.25) -> 92.3 | AQ15: =IF($B15="","",AG15*0.35+AH15*0.35+AI15*0.3) -> 37.1 | AR15: =IF($B15="","",AJ15*0.45+AK15*0.2+AL15*0.35) -> 46.5 | AS15: =IF($B15="","",MIN(100,MAX(0,ROUND(AM15*INDEX(GP_W_P1,MATCH($B15,GP_Weights_Sectors,0))+AN15*INDEX(GP_W_P2,MATCH($B15,GP_Weights_Sectors,0))+AO15*INDEX(GP_W_P3,MATCH($B15,GP_Weights_Sectors,0))+AP15*INDEX(GP_W_P4,MATCH($B15,GP_Weights_Sectors,0))+AQ15*INDEX(GP_W_P5,MATCH($B15,GP_Weights_Sectors,0))+AR15*INDEX(GP_W_P6,MATCH($B15,GP_Weights_Sectors,0)),0)))) -> 58 | AT15: -1 | AU15: 1 | AV15: 1 | AW15: =MAX(-10,MIN(10,AT15+AU15+AV15)) -> 1 | AX15: #VALUE! | AY15: {=_FV(AX15,"PRECIO")} -> 129.74 | AZ15: 130 | BA15: =IFERROR(INDEX('DCF Simplified'!$Y$4:$Y$38,MATCH(A15,'DCF Simplified'!$A$4:$A$38,0)),"") -> 129.12987 | BB15: =IF(OR(AY15="",AZ15=""),"",(AZ15-AY15)/AY15) -> 0.002004008 | BD15: -0.08 | BE15: 38 | BF15: -0.15 | BG15: =IF(BD15>0.1,100,IF(BD15>0.05,80,IF(BD15>0,65,IF(BD15>-0.05,45,IF(BD15>-0.1,25,10))))) -> 25 | BH15: =IF(AND(BE15>=40,BE15<=60),70,IF(AND(BE15>60,BE15<=70),85,IF(BE15>70,50,IF(AND(BE15>=30,BE15<40),55,40)))) -> 55 | BI15: =IF(BF15>0.2,100,IF(BF15>0.1,80,IF(BF15>0,65,IF(BF15>-0.1,45,IF(BF15>-0.2,25,10))))) -> 25 | BJ15: =ROUND(BG15*0.4+BH15*0.25+BI15*0.35,1) -> 32.5 | BK15: =IF(OR(AS15="",AQ15="",BJ15=""),"",ROUND(AS15*0.4+MAX(15,MIN(90,AQ15))*0.2+BJ15*0.25+MIN(100,MAX(0,AW15*10))*0.15,0)) -> 40 | BL15: =IF(BK15="","",IF(BK15>=85,"🟢 STRONG",IF(BK15>=70,"🟡 FAVORABLE",IF(BK15>=55,"⚪ NEUTRAL",IF(BK15>=40,"🟠 WEAK","🔴 AVOID"))))) -> 🟠 WEAK | BM15: =IF(BK15="","",IF(AND(BK15>=75,BJ15>=70,AW15>=6),"🚀 STRONG BUY",IF(AND(BK15>=65,BJ15>=55),"✅ BUY",IF(BK15>=55,"⚠️ HOLD",IF(OR(BK15<45,AND(BJ15<35,AW15<3)),"🔴 SELL","🟠 UNDERWEIGHT"))))) -> 🔴 SELL
... A27: Freeport-McMoRan | B27: Materials | C27: 0.22 | D27: 0.12 | E27: 0.14 | F27: 0.12 | G27: 0.15 | H27: 1.8 | I27: 0.8 | J27: 2.2 | K27: 10 | L27: 0.1 | M27: 0.75 | N27: 0.18 | O27: 18 | P27: 8 | Q27: 16 | R27: 0.008 | S27: 0.15 | T27: 0.04 | U27: =IF(OR($B27="",C27=""),"",IF(ISERROR(MATCH($B27,GP_ROE_Sectors,0)),0,IF(C27>=INDEX(GP_ROE_T,MATCH($B27,GP_ROE_Sectors,0),1),INDEX(GP_ROE_T,MATCH($B27,GP_ROE_Sectors,0),2),IF(C27>=INDEX(GP_ROE_T,MATCH($B27,GP_ROE_Sectors,0),3),INDEX(GP_ROE_T,MATCH($B27,GP_ROE_Sectors,0),4),IF(C27>=INDEX(GP_ROE_T,MATCH($B27,GP_ROE_Sectors,0),5),INDEX(GP_ROE_T,MATCH($B27,GP_ROE_Sectors,0),6),IF(C27>=INDEX(GP_ROE_T,MATCH($B27,GP_ROE_Sectors,0),7),INDEX(GP_ROE_T,MATCH($B27,GP_ROE_Sectors,0),8),IF(C27>=INDEX(GP_ROE_T,MATCH($B27,GP_ROE_Sectors,0),9),INDEX(GP_ROE_T,MATCH($B27,GP_ROE_Sectors,0),10),IF(C27>=INDEX(GP_ROE_T,MATCH($B27,GP_ROE_Sectors,0),11),INDEX(GP_ROE_T,MATCH($B27,GP_ROE_Sectors,0),12),0)))))))) -> 100 | V27: =IF(OR($B27="",D27=""),"",IF(ISERROR(MATCH($B27,GP_ROIC_Sectors,0)),0,IF(D27>=INDEX(GP_ROIC_T,MATCH($B27,GP_ROIC_Sectors,0),1),INDEX(GP_ROIC_T,MATCH($B27,GP_ROIC_Sectors,0),2),IF(D27>=INDEX(GP_ROIC_T,MATCH($B27,GP_ROIC_Sectors,0),3),INDEX(GP_ROIC_T,MATCH($B27,GP_ROIC_Sectors,0),4),IF(D27>=INDEX(GP_ROIC_T,MATCH($B27,GP_ROIC_Sectors,0),5),INDEX(GP_ROIC_T,MATCH($B27,GP_ROIC_Sectors,0),6),IF(D27>=INDEX(GP_ROIC_T,MATCH($B27,GP_ROIC_Sectors,0),7),INDEX(GP_ROIC_T,MATCH($B27,GP_ROIC_Sectors,0),8),IF(D27>=INDEX(GP_ROIC_T,MATCH($B27,GP_ROIC_Sectors,0),9),INDEX(GP_ROIC_T,MATCH($B27,GP_ROIC_Sectors,0),10),IF(D27>=INDEX(GP_ROIC_T,MATCH($B27,GP_ROIC_Sectors,0),11),INDEX(GP_ROIC_T,MATCH($B27,GP_ROIC_Sectors,0),12),0)))))))) -> 82 | W27: =IF(OR($B27="",E27=""),"",IF(ISERROR(MATCH($B27,GP_NM_Sectors,0)),0,IF(E27>=INDEX(GP_NM_T,MATCH($B27,GP_NM_Sectors,0),1),INDEX(GP_NM_T,MATCH($B27,GP_NM_Sectors,0),2),IF(E27>=INDEX(GP_NM_T,MATCH($B27,GP_NM_Sectors,0),3),INDEX(GP_NM_T,MATCH($B27,GP_NM_Sectors,0),4),IF(E27>=INDEX(GP_NM_T,MATCH($B27,GP_NM_Sectors,0),5),INDEX(GP_NM_T,MATCH($B27,GP_NM_Sectors,0),6),IF(E27>=INDEX(GP_NM_T,MATCH($B27,GP_NM_Sectors,0),7),INDEX(GP_NM_T,MATCH($B27,GP_NM_Sectors,0),8),IF(E27>=INDEX(GP_NM_T,MATCH($B27,GP_NM_Sectors,0),9),INDEX(GP_NM_T,MATCH($B27,GP_NM_Sectors,0),10),IF(E27>=INDEX(GP_NM_T,MATCH($B27,GP_NM_Sectors,0),11),INDEX(GP_NM_T,MATCH($B27,GP_NM_Sectors,0),12),0)))))))) -> 100 | X27: =IF(OR($B27="",F27=""),"",IF(ISERROR(MATCH($B27,GP_RG_Sectors,0)),0,IF(F27>=INDEX(GP_RG_T,MATCH($B27,GP_RG_Sectors,0),1),INDEX(GP_RG_T,MATCH($B27,GP_RG_Sectors,0),2),IF(F27>=INDEX(GP_RG_T,MATCH($B27,GP_RG_Sectors,0),3),INDEX(GP_RG_T,MATCH($B27,GP_RG_Sectors,0),4),IF(F27>=INDEX(GP_RG_T,MATCH($B27,GP_RG_Sectors,0),5),INDEX(GP_RG_T,MATCH($B27,GP_RG_Sectors,0),6),IF(F27>=INDEX(GP_RG_T,MATCH($B27,GP_RG_Sectors,0),7),INDEX(GP_RG_T,MATCH($B27,GP_RG_Sectors,0),8),IF(F27>=INDEX(GP_RG_T,MATCH($B27,GP_RG_Sectors,0),9),INDEX(GP_RG_T,MATCH($B27,GP_RG_Sectors,0),10),IF(F27>=INDEX(GP_RG_T,MATCH($B27,GP_RG_Sectors,0),11),INDEX(GP_RG_T,MATCH($B27,GP_RG_Sectors,0),12),0)))))))) -> 100 | Y27: =IF(OR($B27="",G27=""),"",IF(ISERROR(MATCH($B27,GP_EG_Sectors,0)),0,IF(G27>=INDEX(GP_EG_T,MATCH($B27,GP_EG_Sectors,0),1),INDEX(GP_EG_T,MATCH($B27,GP_EG_Sectors,0),2),IF(G27>=INDEX(GP_EG_T,MATCH($B27,GP_EG_Sectors,0),3),INDEX(GP_EG_T,MATCH($B27,GP_EG_Sectors,0),4),IF(G27>=INDEX(GP_EG_T,MATCH($B27,GP_EG_Sectors,0),5),INDEX(GP_EG_T,MATCH($B27,GP_EG_Sectors,0),6),IF(G27>=INDEX(GP_EG_T,MATCH($B27,GP_EG_Sectors,0),7),INDEX(GP_EG_T,MATCH($B27,GP_EG_Sectors,0),8),IF(G27>=INDEX(GP_EG_T,MATCH($B27,GP_EG_Sectors,0),9),INDEX(GP_EG_T,MATCH($B27,GP_EG_Sectors,0),10),IF(G27>=INDEX(GP_EG_T,MATCH($B27,GP_EG_Sectors,0),11),INDEX(GP_EG_T,MATCH($B27,GP_EG_Sectors,0),12),0)))))))) -> 82 | Z27: =IF(OR($B27="",H27=""),"",IF(ISERROR(MATCH($B27,GP_OL_Sectors,0)),0,IF(H27>=INDEX(GP_OL_T,MATCH($B27,GP_OL_Sectors,0),1),INDEX(GP_OL_T,MATCH($B27,GP_OL_Sectors,0),2),IF(H27>=INDEX(GP_OL_T,MATCH($B27,GP_OL_Sectors,0),3),INDEX(GP_OL_T,MATCH($B27,GP_OL_Sectors,0),4),IF(H27>=INDEX(GP_OL_T,MATCH($B27,GP_OL_Sectors,0),5),INDEX(GP_OL_T,MATCH($B27,GP_OL_Sectors,0),6),IF(H27>=INDEX(GP_OL_T,MATCH($B27,GP_OL_Sectors,0),7),INDEX(GP_OL_T,MATCH($B27,GP_OL_Sectors,0),8),IF(H27>=INDEX(GP_OL_T,MATCH($B27,GP_OL_Sectors,0),9),INDEX(GP_OL_T,MATCH($B27,GP_OL_Sectors,0),10),IF(H27>=INDEX(GP_OL_T,MATCH($B27,GP_OL_Sectors,0),11),INDEX(GP_OL_T,MATCH($B27,GP_OL_Sectors,0),12),0)))))))) -> 100 | AA27: =IF(OR($B27="",I27=""),"",IF(ISERROR(MATCH($B27,GP_ND_Sectors,0)),0,IF(I27<=INDEX(GP_ND_T,MATCH($B27,GP_ND_Sectors,0),1),INDEX(GP_ND_T,MATCH($B27,GP_ND_Sectors,0),2),IF(I27<=INDEX(GP_ND_T,MATCH($B27,GP_ND_Sectors,0),3),INDEX(GP_ND_T,MATCH($B27,GP_ND_Sectors,0),4),IF(I27<=INDEX(GP_ND_T,MATCH($B27,GP_ND_Sectors,0),5),INDEX(GP_ND_T,MATCH($B27,GP_ND_Sectors,0),6),IF(I27<=INDEX(GP_ND_T,MATCH($B27,GP_ND_Sectors,0),7),INDEX(GP_ND_T,MATCH($B27,GP_ND_Sectors,0),8),IF(I27<=INDEX(GP_ND_T,MATCH($B27,GP_ND_Sectors,0),9),INDEX(GP_ND_T,MATCH($B27,GP_ND_Sectors,0),10),IF(I27<=INDEX(GP_ND_T,MATCH($B27,GP_ND_Sectors,0),11),INDEX(GP_ND_T,MATCH($B27,GP_ND_Sectors,0),12),0)))))))) -> 82 | AB27: =IF(OR($B27="",J27=""),"",IF(ISERROR(MATCH($B27,GP_CR_Sectors,0)),0,IF(J27>=INDEX(GP_CR_T,MATCH($B27,GP_CR_Sectors,0),1),INDEX(GP_CR_T,MATCH($B27,GP_CR_Sectors,0),2),IF(J27>=INDEX(GP_CR_T,MATCH($B27,GP_CR_Sectors,0),3),INDEX(GP_CR_T,MATCH($B27,GP_CR_Sectors,0),4),IF(J27>=INDEX(GP_CR_T,MATCH($B27,GP_CR_Sectors,0),5),INDEX(GP_CR_T,MATCH($B27,GP_CR_Sectors,0),6),IF(J27>=INDEX(GP_CR_T,MATCH($B27,GP_CR_Sectors,0),7),INDEX(GP_CR_T,MATCH($B27,GP_CR_Sectors,0),8),IF(J27>=INDEX(GP_CR_T,MATCH($B27,GP_CR_Sectors,0),9),INDEX(GP_CR_T,MATCH($B27,GP_CR_Sectors,0),10),IF(J27>=INDEX(GP_CR_T,MATCH($B27,GP_CR_Sectors,0),11),INDEX(GP_CR_T,MATCH($B27,GP_CR_Sectors,0),12),0)))))))) -> 100 | AC27: =IF(OR($B27="",K27=""),"",IF(ISERROR(MATCH($B27,GP_IC_Sectors,0)),0,IF(K27>=INDEX(GP_IC_T,MATCH($B27,GP_IC_Sectors,0),1),INDEX(GP_IC_T,MATCH($B27,GP_IC_Sectors,0),2),IF(K27>=INDEX(GP_IC_T,MATCH($B27,GP_IC_Sectors,0),3),INDEX(GP_IC_T,MATCH($B27,GP_IC_Sectors,0),4),IF(K27>=INDEX(GP_IC_T,MATCH($B27,GP_IC_Sectors,0),5),INDEX(GP_IC_T,MATCH($B27,GP_IC_Sectors,0),6),IF(K27>=INDEX(GP_IC_T,MATCH($B27,GP_IC_Sectors,0),7),INDEX(GP_IC_T,MATCH($B27,GP_IC_Sectors,0),8),IF(K27>=INDEX(GP_IC_T,MATCH($B27,GP_IC_Sectors,0),9),INDEX(GP_IC_T,MATCH($B27,GP_IC_Sectors,0),10),IF(K27>=INDEX(GP_IC_T,MATCH($B27,GP_IC_Sectors,0),11),INDEX(GP_IC_T,MATCH($B27,GP_IC_Sectors,0),12),0)))))))) -> 100 | AD27: =IF(OR($B27="",L27=""),"",IF(ISERROR(MATCH($B27,GP_FM_Sectors,0)),0,IF(L27>=INDEX(GP_FM_T,MATCH($B27,GP_FM_Sectors,0),1),INDEX(GP_FM_T,MATCH($B27,GP_FM_Sectors,0),2),IF(L27>=INDEX(GP_FM_T,MATCH($B27,GP_FM_Sectors,0),3),INDEX(GP_FM_T,MATCH($B27,GP_FM_Sectors,0),4),IF(L27>=INDEX(GP_FM_T,MATCH($B27,GP_FM_Sectors,0),5),INDEX(GP_FM_T,MATCH($B27,GP_FM_Sectors,0),6),IF(L27>=INDEX(GP_FM_T,MATCH($B27,GP_FM_Sectors,0),7),INDEX(GP_FM_T,MATCH($B27,GP_FM_Sectors,0),8),IF(L27>=INDEX(GP_FM_T,MATCH($B27,GP_FM_Sectors,0),9),INDEX(GP_FM_T,MATCH($B27,GP_FM_Sectors,0),10),IF(L27>=INDEX(GP_FM_T,MATCH($B27,GP_FM_Sectors,0),11),INDEX(GP_FM_T,MATCH($B27,GP_FM_Sectors,0),12),0)))))))) -> 100 | AE27: =IF(OR($B27="",M27=""),"",IF(ISERROR(MATCH($B27,GP_FN_Sectors,0)),0,IF(M27>=INDEX(GP_FN_T,MATCH($B27,GP_FN_Sectors,0),1),INDEX(GP_FN_T,MATCH($B27,GP_FN_Sectors,0),2),IF(M27>=INDEX(GP_FN_T,MATCH($B27,GP_FN_Sectors,0),3),INDEX(GP_FN_T,MATCH($B27,GP_FN_Sectors,0),4),IF(M27>=INDEX(GP_FN_T,MATCH($B27,GP_FN_Sectors,0),5),INDEX(GP_FN_T,MATCH($B27,GP_FN_Sectors,0),6),IF(M27>=INDEX(GP_FN_T,MATCH($B27,GP_FN_Sectors,0),7),INDEX(GP_FN_T,MATCH($B27,GP_FN_Sectors,0),8),IF(M27>=INDEX(GP_FN_T,MATCH($B27,GP_FN_Sectors,0),9),INDEX(GP_FN_T,MATCH($B27,GP_FN_Sectors,0),10),IF(M27>=INDEX(GP_FN_T,MATCH($B27,GP_FN_Sectors,0),11),INDEX(GP_FN_T,MATCH($B27,GP_FN_Sectors,0),12),0)))))))) -> 62 | AF27: =IF(OR($B27="",N27=""),"",IF(ISERROR(MATCH($B27,GP_CX_Sectors,0)),0,IF(N27<=INDEX(GP_CX_T,MATCH($B27,GP_CX_Sectors,0),1),INDEX(GP_CX_T,MATCH($B27,GP_CX_Sectors,0),2),IF(N27<=INDEX(GP_CX_T,MATCH($B27,GP_CX_Sectors,0),3),INDEX(GP_CX_T,MATCH($B27,GP_CX_Sectors,0),4),IF(N27<=INDEX(GP_CX_T,MATCH($B27,GP_CX_Sectors,0),5),INDEX(GP_CX_T,MATCH($B27,GP_CX_Sectors,0),6),IF(N27<=INDEX(GP_CX_T,MATCH($B27,GP_CX_Sectors,0),7),INDEX(GP_CX_T,MATCH($B27,GP_CX_Sectors,0),8),IF(N27<=INDEX(GP_CX_T,MATCH($B27,GP_CX_Sectors,0),9),INDEX(GP_CX_T,MATCH($B27,GP_CX_Sectors,0),10),IF(N27<=INDEX(GP_CX_T,MATCH($B27,GP_CX_Sectors,0),11),INDEX(GP_CX_T,MATCH($B27,GP_CX_Sectors,0),12),0)))))))) -> 45 | AG27: =IF(OR($B27="",O27=""),"",IF(ISERROR(MATCH($B27,GP_PE_Sectors,0)),0,IF(O27<=INDEX(GP_PE_T,MATCH($B27,GP_PE_Sectors,0),1),INDEX(GP_PE_T,MATCH($B27,GP_PE_Sectors,0),2),IF(O27<=INDEX(GP_PE_T,MATCH($B27,GP_PE_Sectors,0),3),INDEX(GP_PE_T,MATCH($B27,GP_PE_Sectors,0),4),IF(O27<=INDEX(GP_PE_T,MATCH($B27,GP_PE_Sectors,0),5),INDEX(GP_PE_T,MATCH($B27,GP_PE_Sectors,0),6),IF(O27<=INDEX(GP_PE_T,MATCH($B27,GP_PE_Sectors,0),7),INDEX(GP_PE_T,MATCH($B27,GP_PE_Sectors,0),8),IF(O27<=INDEX(GP_PE_T,MATCH($B27,GP_PE_Sectors,0),9),INDEX(GP_PE_T,MATCH($B27,GP_PE_Sectors,0),10),IF(O27<=INDEX(GP_PE_T,MATCH($B27,GP_PE_Sectors,0),11),INDEX(GP_PE_T,MATCH($B27,GP_PE_Sectors,0),12),0)))))))) -> 48 | AH27: =IF(OR($B27="",P27=""),"",IF(ISERROR(MATCH($B27,GP_EV_Sectors,0)),0,IF(P27<=INDEX(GP_EV_T,MATCH($B27,GP_EV_Sectors,0),1),INDEX(GP_EV_T,MATCH($B27,GP_EV_Sectors,0),2),IF(P27<=INDEX(GP_EV_T,MATCH($B27,GP_EV_Sectors,0),3),INDEX(GP_EV_T,MATCH($B27,GP_EV_Sectors,0),4),IF(P27<=INDEX(GP_EV_T,MATCH($B27,GP_EV_Sectors,0),5),INDEX(GP_EV_T,MATCH($B27,GP_EV_Sectors,0),6),IF(P27<=INDEX(GP_EV_T,MATCH($B27,GP_EV_Sectors,0),7),INDEX(GP_EV_T,MATCH($B27,GP_EV_Sectors,0),8),IF(P27<=INDEX(GP_EV_T,MATCH($B27,GP_EV_Sectors,0),9),INDEX(GP_EV_T,MATCH($B27,GP_EV_Sectors,0),10),IF(P27<=INDEX(GP_EV_T,MATCH($B27,GP_EV_Sectors,0),11),INDEX(GP_EV_T,MATCH($B27,GP_EV_Sectors,0),12),0)))))))) -> 82 | AI27: =IF(OR($B27="",Q27=""),"",IF(ISERROR(MATCH($B27,GP_PF_Sectors,0)),0,IF(Q27<=INDEX(GP_PF_T,MATCH($B27,GP_PF_Sectors,0),1),INDEX(GP_PF_T,MATCH($B27,GP_PF_Sectors,0),2),IF(Q27<=INDEX(GP_PF_T,MATCH($B27,GP_PF_Sectors,0),3),INDEX(GP_PF_T,MATCH($B27,GP_PF_Sectors,0),4),IF(Q27<=INDEX(GP_PF_T,MATCH($B27,GP_PF_Sectors,0),5),INDEX(GP_PF_T,MATCH($B27,GP_PF_Sectors,0),6),IF(Q27<=INDEX(GP_PF_T,MATCH($B27,GP_PF_Sectors,0),7),INDEX(GP_PF_T,MATCH($B27,GP_PF_Sectors,0),8),IF(Q27<=INDEX(GP_PF_T,MATCH($B27,GP_PF_Sectors,0),9),INDEX(GP_PF_T,MATCH($B27,GP_PF_Sectors,0),10),IF(Q27<=INDEX(GP_PF_T,MATCH($B27,GP_PF_Sectors,0),11),INDEX(GP_PF_T,MATCH($B27,GP_PF_Sectors,0),12),0)))))))) -> 62 | AJ27: =IF(OR($B27="",R27=""),"",IF(ISERROR(MATCH($B27,GP_DY_Sectors,0)),0,IF(R27>=INDEX(GP_DY_T,MATCH($B27,GP_DY_Sectors,0),1),INDEX(GP_DY_T,MATCH($B27,GP_DY_Sectors,0),2),IF(R27>=INDEX(GP_DY_T,MATCH($B27,GP_DY_Sectors,0),3),INDEX(GP_DY_T,MATCH($B27,GP_DY_Sectors,0),4),IF(R27>=INDEX(GP_DY_T,MATCH($B27,GP_DY_Sectors,0),5),INDEX(GP_DY_T,MATCH($B27,GP_DY_Sectors,0),6),IF(R27>=INDEX(GP_DY_T,MATCH($B27,GP_DY_Sectors,0),7),INDEX(GP_DY_T,MATCH($B27,GP_DY_Sectors,0),8),IF(R27>=INDEX(GP_DY_T,MATCH($B27,GP_DY_Sectors,0),9),INDEX(GP_DY_T,MATCH($B27,GP_DY_Sectors,0),10),IF(R27>=INDEX(GP_DY_T,MATCH($B27,GP_DY_Sectors,0),11),INDEX(GP_DY_T,MATCH($B27,GP_DY_Sectors,0),12),0)))))))) -> 28 | AK27: =IF(OR($B27="",S27=""),"",IF(ISERROR(MATCH($B27,GP_PR_Sectors,0)),0,IF(S27>=INDEX(GP_PR_T,MATCH($B27,GP_PR_Sectors,0),1),INDEX(GP_PR_T,MATCH($B27,GP_PR_Sectors,0),2),IF(S27>=INDEX(GP_PR_T,MATCH($B27,GP_PR_Sectors,0),3),INDEX(GP_PR_T,MATCH($B27,GP_PR_Sectors,0),4),IF(S27>=INDEX(GP_PR_T,MATCH($B27,GP_PR_Sectors,0),5),INDEX(GP_PR_T,MATCH($B27,GP_PR_Sectors,0),6),IF(S27>=INDEX(GP_PR_T,MATCH($B27,GP_PR_Sectors,0),7),INDEX(GP_PR_T,MATCH($B27,GP_PR_Sectors,0),8),IF(S27>=INDEX(GP_PR_T,MATCH($B27,GP_PR_Sectors,0),9),INDEX(GP_PR_T,MATCH($B27,GP_PR_Sectors,0),10),IF(S27>=INDEX(GP_PR_T,MATCH($B27,GP_PR_Sectors,0),11),INDEX(GP_PR_T,MATCH($B27,GP_PR_Sectors,0),12),0)))))))) -> 0 | AL27: =IF(OR($B27="",T27=""),"",IF(ISERROR(MATCH($B27,GP_BY_Sectors,0)),0,IF(T27>=INDEX(GP_BY_T,MATCH($B27,GP_BY_Sectors,0),1),INDEX(GP_BY_T,MATCH($B27,GP_BY_Sectors,0),2),IF(T27>=INDEX(GP_BY_T,MATCH($B27,GP_BY_Sectors,0),3),INDEX(GP_BY_T,MATCH($B27,GP_BY_Sectors,0),4),IF(T27>=INDEX(GP_BY_T,MATCH($B27,GP_BY_Sectors,0),5),INDEX(GP_BY_T,MATCH($B27,GP_BY_Sectors,0),6),IF(T27>=INDEX(GP_BY_T,MATCH($B27,GP_BY_Sectors,0),7),INDEX(GP_BY_T,MATCH($B27,GP_BY_Sectors,0),8),IF(T27>=INDEX(GP_BY_T,MATCH($B27,GP_BY_Sectors,0),9),INDEX(GP_BY_T,MATCH($B27,GP_BY_Sectors,0),10),IF(T27>=INDEX(GP_BY_T,MATCH($B27,GP_BY_Sectors,0),11),INDEX(GP_BY_T,MATCH($B27,GP_BY_Sectors,0),12),0)))))))) -> 100 | AM27: =IF($B27="","",U27*0.35+V27*0.35+W27*0.3) -> 93.7 | AN27: =IF($B27="","",X27*0.4+Y27*0.35+Z27*0.25) -> 93.7 | AO27: =IF($B27="","",AA27*0.35+AB27*0.3+AC27*0.35) -> 93.7 | AP27: =IF($B27="","",AD27*0.4+AE27*0.35+AF27*0.25) -> 72.95 | AQ27: =IF($B27="","",AG27*0.35+AH27*0.35+AI27*0.3) -> 64.1 | AR27: =IF($B27="","",AJ27*0.45+AK27*0.2+AL27*0.35) -> 47.6 | AS27: =IF($B27="","",MIN(100,MAX(0,ROUND(AM27*INDEX(GP_W_P1,MATCH($B27,GP_Weights_Sectors,0))+AN27*INDEX(GP_W_P2,MATCH($B27,GP_Weights_Sectors,0))+AO27*INDEX(GP_W_P3,MATCH($B27,GP_Weights_Sectors,0))+AP27*INDEX(GP_W_P4,MATCH($B27,GP_Weights_Sectors,0))+AQ27*INDEX(GP_W_P5,MATCH($B27,GP_Weights_Sectors,0))+AR27*INDEX(GP_W_P6,MATCH($B27,GP_Weights_Sectors,0)),0)))) -> 81 | AT27: 2 | AU27: 2 | AV27: 2 | AW27: =MAX(-10,MIN(10,AT27+AU27+AV27)) -> 6 | AX27: #VALUE! | AY27: {=_FV(AX27,"PRECIO")} -> 55.83 | AZ27: 30 | BA27: =IFERROR(INDEX('DCF Simplified'!$Y$4:$Y$38,MATCH(A27,'DCF Simplified'!$A$4:$A$38,0)),"") -> 36.90024 | BB27: =IF(OR(AY27="",AZ27=""),"",(AZ27-AY27)/AY27) -> -0.46265449 | BD27: 0.1 | BE27: 58 | BF27: 0.18 | BG27: =IF(BD27>0.1,100,IF(BD27>0.05,80,IF(BD27>0,65,IF(BD27>-0.05,45,IF(BD27>-0.1,25,10))))) -> 80 | BH27: =IF(AND(BE27>=40,BE27<=60),70,IF(AND(BE27>60,BE27<=70),85,IF(BE27>70,50,IF(AND(BE27>=30,BE27<40),55,40)))) -> 70 | BI27: =IF(BF27>0.2,100,IF(BF27>0.1,80,IF(BF27>0,65,IF(BF27>-0.1,45,IF(BF27>-0.2,25,10))))) -> 80 | BJ27: =ROUND(BG27*0.4+BH27*0.25+BI27*0.35,1) -> 77.5 | BK27: =IF(OR(AS27="",AQ27="",BJ27=""),"",ROUND(AS27*0.4+MAX(15,MIN(90,AQ27))*0.2+BJ27*0.25+MIN(100,MAX(0,AW27*10))*0.15,0)) -> 74 | BL27: =IF(BK27="","",IF(BK27>=85,"🟢 STRONG",IF(BK27>=70,"🟡 FAVORABLE",IF(BK27>=55,"⚪ NEUTRAL",IF(BK27>=40,"🟠 WEAK","🔴 AVOID"))))) -> 🟡 FAVORABLE | BM27: =IF(BK27="","",IF(AND(BK27>=75,BJ27>=70,AW27>=6),"🚀 STRONG BUY",IF(AND(BK27>=65,BJ27>=55),"✅ BUY",IF(BK27>=55,"⚠️ HOLD",IF(OR(BK27<45,AND(BJ27<35,AW27<3)),"🔴 SELL","🟠 UNDERWEIGHT"))))) -> ✅ BUY
